Workbook
Name _1: #REF!
Name _1: #REF!
Name _1: #REF!
Name _10: #REF!
Name _10: #REF!
Name _10: #REF!
Name _11: #REF!
Name _11: #REF!
Name _11: #REF!
Name _12: #REF!
Name _12: #REF!
Name _12: #REF!
Name _13: #REF!
Name _13: #REF!
Name _13: #REF!
Name _14: #REF!
Name _14: #REF!
Name _14: #REF!
Name _15: #REF!
Name _15: #REF!
Name _15: #REF!
Name _16: #REF!
Name _16: #REF!
Name _16: #REF!
Name _17: #REF!
Name _17: #REF!
Name _17: #REF!
Name _18: #REF!
Name _18: #REF!
Name _18: #REF!
Name _19: #REF!
Name _19: #REF!
Name _19: #REF!
Name _1Excel_BuiltIn__FilterDatabase_10_9_1: NA()
Name _2: #REF!
Name _2: #REF!
Name _2: #REF!
Name _20: #REF!
Name _20: #REF!
Name _20: #REF!
Name _21: #REF!
Name _21: #REF!
Name _21: #REF!
Name _22: #REF!
Name _22: #REF!
Name _22: #REF!
Name _23: #REF!
Name _23: #REF!
Name _23: #REF!
Name _24: #REF!
Name _24: #REF!
Name _24: #REF!
Name _25: #REF!
Name _25: #REF!
Name _25: #REF!
Name _26: #REF!
Name _26: #REF!
Name _26: #REF!
Name _27: #REF!
Name _27: #REF!

Sheet COVER
B6: Tactical Media Plan | I6: CONFIDENCIAL
B8: CLIENT: | C8: SABESP
B9: CAMPAING | C9: ESCASSEZ HIDRICA - CRÍTICO
B10: TARGET: | C10: AS ABCDE 25+
B14: VERSION | C14: UPDATE DATE | D14: UPDATES:
B15: v1 | C15: 46038 | D15: AJUSTE NO VALOR DE RADIO E JORNAL + INCLUSÃO DE tv + INCLUSÃO DO ABCD JORNAL
B18: V5 | C18: 45677 | D18: Inclusão da veiculação de TV aberta e fechada
B19: V6 | C19: 45679 | D19: Ajuste conforme inserções de TV encaixadas
B20: V7 | C20: 46058 | D20: Atualização do plano conforme o veiculado de janeiro.
B21: V8 | C21: 46076 | D21: Atualização conforme realizado de fevereiro.

Sheet RESUMO DE MEIOS - SP1
B5: CLIENT: SABESP
B6: CAMPAING: ESCASSEZ HIDRICA - CRÍTICO
B8: RESUMO DE MEIOS - SÃO PAULO CAPITAL
B10: PRAÇA | C10: MEIO | D10: VEÍCULO | F10: JANEIRO | G10: FEVEREIRO | H10: TOTAL BRUTO | I10: VALOR DESEMBOLSO TT | J10: PART GERAL %
N12: UTILIZAÇÃO DE SALDO DE PACOTES
B13: SÃO PAULO CAPITAL | C13: TV ABERTA | D13: GLOBO | F13: ='TV ABERTA - SP1'!CC33*1.25 -> 1799646.8 | G13: ='TV ABERTA - SP1'!CE33*1.25 -> 543961 | H13: =SUM(F13:G13) -> 2343607.8 | I13: =H13*0.8 -> 1874886.2 | J13: =I13/$I$21 -> 0.58930842 | N13: SBT | O13: =I16 -> 409671.65
B14: SÃO PAULO CAPITAL | C14: TV ABERTA | D14: BANDEIRANTES | F14: ='TV ABERTA - SP1'!CC45*1.25 -> 66842.4 | G14: ='TV ABERTA - SP1'!CE45*1.25 -> 43587.6 | H14: =SUM(F14:G14) -> 110430 | I14: =H14*0.8 -> 88344 | J14: =I14/$I$21 -> 0.027768012 | N14: REDE TV | O14: =I17 -> 80635.56
B15: SÃO PAULO CAPITAL | C15: TV ABERTA | D15: RECORD | F15: ='TV ABERTA - SP1'!CC58*1.25 -> 471401.6 | G15: ='TV ABERTA - SP1'!CE58*1.25 -> 377926.6 | H15: =SUM(F15:G15) -> 849328.2 | I15: =H15*0.8 -> 679462.56 | J15: =I15/$I$21 -> 0.21356656 | N15: GLOBO | O15: =G13*0.8 -> 435168.8
B16: SÃO PAULO CAPITAL | C16: TV ABERTA | D16: SBT | F16: ='TV ABERTA - SP1'!CC83*1.25 -> 272575 | G16: ='TV ABERTA - SP1'!CE83*1.25 -> 239514.56 | H16: =SUM(F16:G16) -> 512089.56 | I16: =H16*0.8 -> 409671.65 | J16: =I16/$I$21 -> 0.12876672
B17: SÃO PAULO CAPITAL | C17: TV ABERTA | D17: REDE TV | F17: ='TV ABERTA - SP1'!CC90*1.25 -> 49699.95 | G17: ='TV ABERTA - SP1'!CE90*1.25 -> 51094.5 | H17: =SUM(F17:G17) -> 100794.45 | I17: =H17*0.8 -> 80635.56 | J17: =I17/$I$21 -> 0.025345119
B18: SÃO PAULO CAPITAL | C18: TV ABERTA | D18: CULTURA | F18: ='TV ABERTA - SP1'!CC100*1.25 -> 17112 | G18: ='TV ABERTA - SP1'!CE100*1.25 -> 15960 | H18: =SUM(F18:G18) -> 33072 | I18: =H18*0.8 -> 26457.6 | J18: =I18/$I$21 -> 0.0083160706
B19: SÃO PAULO CAPITAL | C19: TV ABERTA | D19: GAZETA | F19: ='TV ABERTA - SP1'!CC106*1.25 -> 16102.8 | G19: ='TV ABERTA - SP1'!CE106*1.25 -> 11453.4 | H19: =SUM(F19:G19) -> 27556.2 | I19: =H19*0.8 -> 22044.96 | J19: =I19/$I$21 -> 0.0069291033
B21: TT TV ABERTA | F21: =SUM(F13:F19) -> 2693380.5 | G21: =SUM(G13:G19) -> 1283497.7 | H21: =SUM(H13:H19) -> 3976878.2 | I21: =SUM(I13:I19) -> 3181502.6 | J21: =SUM(J13:J19) -> 1 | K21: =I21/I67 -> 0.57276866 | L21: =I21=SUM('TV ABERTA - SP1'!BU108) -> TRUE
B23: SÃO PAULO ESTADO | C23: TV PAGA | D23: GLOBONEWS | H23: =SUM(F23:G23) -> 0 | I23: =H23*0.8 -> 0 | J23: =IFERROR(I23/$I$28,0) -> 0
B24: SÃO PAULO ESTADO | C24: TV PAGA | D24: CNN BRASIL | H24: =SUM(F24:G24) -> 0 | I24: =H24*0.8 -> 0 | J24: =IFERROR(I24/$I$28,0) -> 0
B25: SÃO PAULO ESTADO | C25: TV PAGA | D25: RECORD NEWS | H25: =SUM(F25:G25) -> 0 | I25: =H25*0.8 -> 0 | J25: =IFERROR(I25/$I$28,0) -> 0
B26: SÃO PAULO ESTADO | C26: TV PAGA | D26: BAND NEWS | H26: =SUM(F26:G26) -> 0 | I26: =H26*0.8 -> 0 | J26: =IFERROR(I26/$I$28,0) -> 0
B28: TT TV PAGA | F28: =SUM(F23:F27) -> 0 | G28: =SUM(G23:G27) -> 0 | H28: =SUM(H23:H27) -> 0 | I28: =SUM(I23:I27) -> 0 | J28: =SUM(J23:J27) -> 0 | K28: =I28/I67 -> 0 | L28: =I28='TV PAGA - COLCHÃO REP - SP1'!BU28 -> FALSE
B30: SÃO PAULO CAPITAL | C30: JORNAL | D30: =JORNAL!C14 -> FOLHA DE SP | F30: =SUM(JORNAL!CN14:CN16)*1.25 -> 205409.91 | G30: {=SUM(JORNAL!CP14:CP16*1.25)} -> 0 | H30: =SUM(F30:G30) -> 205409.91 | I30: =H30*0.8 -> 164327.93 | J30: =I30/$I$36 -> 0.30990317
B31: SÃO PAULO CAPITAL | C31: JORNAL | D31: =JORNAL!C19 -> O ESTADO DE SP | F31: =SUM(JORNAL!CN19:CN21)*1.25 -> 232919.51 | G31: =SUM(JORNAL!CP19:CP21)*1.25 -> 0 | H31: =SUM(F31:G31) -> 232919.51 | I31: =H31*0.8 -> 186335.61 | J31: =I31/$I$36 -> 0.35140706
B32: SÃO PAULO CAPITAL | C32: JORNAL | D32: =JORNAL!C23 -> VALOR | F32: =SUM(JORNAL!CN23:CN25)*1.25 -> 138378.24 | G32: =SUM(JORNAL!CP23:CP25)*1.25 -> 0 | H32: =SUM(F32:G32) -> 138378.24 | I32: =H32*0.8 -> 110702.59 | J32: =I32/$I$36 -> 0.20877208
B33: SÃO PAULO CAPITAL | C33: JORNAL | D33: =JORNAL!C27 -> GAZETA DE SP | F33: =SUM(JORNAL!CN27:CN28)*1.25 -> 0 | G33: =SUM(JORNAL!CP27:CP29)*1.25 -> 0 | H33: =SUM(F33:G33) -> 0 | I33: =H33*0.8 -> 0 | J33: =I33/$I$36 -> 0
B34: =JORNAL!B31 -> ABC | C34: JORNAL | D34: =JORNAL!C31 -> DIÁRIO DO GRANDE ABC | F34: =SUM(JORNAL!CN31:CN34)*1.25 -> 86112 | G34: =SUM(JORNAL!CP31:CP34)*1.25 -> 0 | H34: =SUM(F34:G34) -> 86112 | I34: =H34*0.8 -> 68889.6 | J34: =I34/$I$36 -> 0.12991769
B36: TT JORNAL | F36: =SUM(F30:F34) -> 662819.66 | G36: =SUM(G30:G34) -> 0 | H36: =SUM(H30:H34) -> 662819.66 | I36: =SUM(I30:I34) -> 530255.73 | J36: =SUM(J30:J34) -> 1 | K36: =I36/I67 -> 0.095462398 | L36: =I36=JORNAL!CN39 -> TRUE
B38: SÃO PAULO CAPITAL | C38: RADIO | D38: JOVEM PAN FM | F38: =SUM(RÁDIO!CH14:CH15)*1.25 -> 94517.28 | G38: =SUM(RÁDIO!CJ14:CJ15)*1.25 -> 89266.32 | H38: =SUM(F38:G38) -> 183783.6 | I38: =H38*0.8 -> 147026.88 | J38: =I38/$I$58 -> 0.082231879
B39: SÃO PAULO CAPITAL | C39: RADIO | D39: BAND NEWS FM | F39: =SUM(RÁDIO!CH18:CH19)*1.25 -> 83832 | G39: =SUM(RÁDIO!CJ18:CJ19)*1.25 -> 55888 | H39: =SUM(F39:G39) -> 139720 | I39: =H39*0.8 -> 111776 | J39: =I39/$I$58 -> 0.062516123
B40: SÃO PAULO CAPITAL | C40: RADIO | D40: BANDEIRANTES | F40: =SUM(RÁDIO!CH22:CH23)*1.25 -> 59052 | G40: =SUM(RÁDIO!CJ22:CJ23)*1.25 -> 59052 | H40: =SUM(F40:G40) -> 118104 | I40: =H40*0.8 -> 94483.2 | J40: =I40/$I$58 -> 0.05284429
B41: SÃO PAULO CAPITAL | C41: RADIO | D41: CBN | F41: =SUM(RÁDIO!CH26:CH27)*1.25 -> 104319 | G41: =SUM(RÁDIO!CJ26:CJ27)*1.25 -> 48682.2 | H41: =SUM(F41:G41) -> 153001.2 | I41: =H41*0.8 -> 122400.96 | J41: =I41/$I$58 -> 0.068458645
B42: SÃO PAULO CAPITAL | C42: RADIO | D42: NATIVA FM | F42: =SUM(RÁDIO!CH35:CH36)*1.25 -> 60773.24 | G42: =SUM(RÁDIO!CJ35:CJ36)*1.25 -> 53867.19 | H42: =SUM(F42:G42) -> 114640.43 | I42: =H42*0.8 -> 91712.344 | J42: =I42/$I$58 -> 0.051294555
B43: SÃO PAULO CAPITAL | C43: RADIO | D43: BAND FM | F43: =SUM(RÁDIO!CH39:CH40)*1.25 -> 77714 | G43: =SUM(RÁDIO!CJ39:CJ40)*1.25 -> 77714 | H43: =SUM(F43:G43) -> 155428 | I43: =H43*0.8 -> 124342.4 | J43: =I43/$I$58 -> 0.069544489
B44: SÃO PAULO CAPITAL | C44: RADIO | D44: 89 ROCK FM | F44: =SUM(RÁDIO!CH43:CH44)*1.25 -> 72852 | G44: =SUM(RÁDIO!CJ43:CJ44)*1.25 -> 72852 | H44: =SUM(F44:G44) -> 145704 | I44: =H44*0.8 -> 116563.2 | J44: =I44/$I$58 -> 0.065193596
B45: SÃO PAULO CAPITAL | C45: RADIO | D45: ALPHA FM | F45: =SUM(RÁDIO!CH47:CH48)*1.25 -> 91929.6 | G45: =SUM(RÁDIO!CJ47:CJ48)*1.25 -> 94348.8 | H45: =SUM(F45:G45) -> 186278.4 | I45: =H45*0.8 -> 149022.72 | J45: =I45/$I$58 -> 0.083348149
B46: SÃO PAULO CAPITAL | C46: RADIO | D46: DISNEY FM | F46: =SUM(RÁDIO!CH51:CH52)*1.25 -> 60762 | G46: =SUM(RÁDIO!CJ51:CJ52)*1.25 -> 62361 | H46: =SUM(F46:G46) -> 123123 | I46: =H46*0.8 -> 98498.4 | J46: =I46/$I$58 -> 0.055089984
B47: SÃO PAULO CAPITAL | C47: RADIO | D47: ENERGIA 97 FM | F47: =SUM(RÁDIO!CH55:CH56)*1.25 -> 25766 | G47: =SUM(RÁDIO!CJ55:CJ56)*1.25 -> 25766 | H47: =SUM(F47:G47) -> 51532 | I47: =H47*0.8 -> 41225.6 | J47: =I47/$I$58 -> 0.023057407
B48: SÃO PAULO CAPITAL | C48: RADIO | D48: KISS FM | F48: =SUM(RÁDIO!CH59:CH60)*1.25 -> 0 | G48: =SUM(RÁDIO!CJ59:CJ60)*1.25 -> 0 | H48: =SUM(F48:G48) -> 0 | I48: =H48*0.8 -> 0 | J48: =I48/$I$58 -> 0
B49: SÃO PAULO CAPITAL | C49: RADIO | D49: GAZETA FM | F49: =SUM(RÁDIO!CH63:CH64)*1.25 -> 67184 | G49: =SUM(RÁDIO!CJ63:CJ64)*1.25 -> 67184 | H49: =SUM(F49:G49) -> 134368 | I49: =H49*0.8 -> 107494.4 | J49: =I49/$I$58 -> 0.060121431
B50: SÃO PAULO CAPITAL | C50: RADIO | D50: 105 FM | F50: =SUM(RÁDIO!CH67:CH68)*1.25 -> 40716 | G50: =SUM(RÁDIO!CJ67:CJ68)*1.25 -> 40716 | H50: =SUM(F50:G50) -> 81432 | I50: =H50*0.8 -> 65145.6 | J50: =I50/$I$58 -> 0.036435821
B51: SÃO PAULO CAPITAL | C51: RADIO | D51: RÁDIO MIX | F51: =SUM(RÁDIO!CH71+RÁDIO!CH72)*1.25 -> 60115 | G51: =SUM(RÁDIO!CJ71+RÁDIO!CJ72)*1.25 -> 53283.75 | H51: =SUM(F51:G51) -> 113398.75 | I51: =H51*0.8 -> 90719 | J51: =I51/$I$58 -> 0.050738979
B52: SÃO PAULO CAPITAL | C52: RADIO | D52: TRANSAMÉRICA FM | F52: =SUM(RÁDIO!CH75:CH76)*1.25 -> 53911.2 | G52: =SUM(RÁDIO!CJ75:CJ76)*1.25 -> 50060.4 | H52: =SUM(F52:G52) -> 103971.6 | I52: =H52*0.8 -> 83177.28 | J52: =I52/$I$58 -> 0.046520908
B53: SÃO PAULO CAPITAL | C53: RADIO | D53: MASSA FM | F53: =SUM(RÁDIO!CH79:CH80)*1.25 -> 30410.64 | G53: =SUM(RÁDIO!CJ79:CJ80)*1.25 -> 30410.64 | H53: =SUM(F53:G53) -> 60821.28 | I53: =H53*0.8 -> 48657.024 | J53: =I53/$I$58 -> 0.027213789
B54: SÃO PAULO CAPITAL | C54: RADIO | D54: ANTENA 1 FM | F54: =SUM(RÁDIO!CH83:CH84)*1.25 -> 43110.6 | G54: =SUM(RÁDIO!CJ83:CJ84)*1.25 -> 43110.6 | H54: =SUM(F54:G54) -> 86221.2 | I54: =H54*0.8 -> 68976.96 | J54: =I54/$I$58 -> 0.038578694
B55: SÃO PAULO CAPITAL | C55: RADIO | D55: NOVABRASIL | F55: =SUM(RÁDIO!CH87:CH88)*1.25 -> 58708 | G55: =SUM(RÁDIO!CJ87:CJ88)*1.25 -> 58708 | H55: =SUM(F55:G55) -> 117416 | I55: =H55*0.8 -> 93932.8 | J55: =I55/$I$58 -> 0.052536452
B56: SÃO PAULO CAPITAL | C56: RADIO | D56: TRANSCONTINENTAL | F56: =SUM(RÁDIO!CH91:CH92)*1.25 -> 88000 | G56: =SUM(RÁDIO!CJ91:CJ92)*1.25 -> 78000 | H56: =SUM(F56:G56) -> 166000 | I56: =H56*0.8 -> 132800 | J56: =I56/$I$58 -> 0.07427481
B58: TT RÁDIO | F58: =SUM(F38:F56) -> 1173672.6 | G58: =SUM(G38:G56) -> 1061270.9 | H58: =SUM(H38:H56) -> 2234943.5 | I58: =SUM(I38:I56) -> 1787954.8 | J58: =SUM(J38:J56) -> 1 | K58: =I58/I67 -> 0.32188705 | L58: =I58=RÁDIO!BR197 -> TRUE
B60: SÃO BERNARDO DO CAMPO | C60: DIGITAL | D60: JORNAL ABCD | F60: =DIGITAL!J8*1.25 -> 62500 | G60: {=SUM(JORNAL!CP47:CP49*1.25)} -> 0 | H60: =SUM(F60:G60) -> 62500 | I60: =H60*0.8 -> 50000 | J60: =I60/$I$63 -> 1
B61: SÃO PAULO | C61: DIGITAL | D61: SBT DIGITAL | F61: 0 | G61: =DIGITAL!K9*1.25 -> 0 | H61: =SUM(F61:G61) -> 0 | I61: =H61*0.8 -> 0 | J61: =I61/$I$63 -> 0
B63: TT DIGITAL | F63: {=F60:F61} -> 62500 | G63: {=G60:G61} -> 0 | H63: {=H60:H61} -> 62500 | I63: {=I60:I61} -> 50000 | J63: {=J60:J61} -> 1 | K63: =I63/I67 -> 0.0090015433 | L63: =I63=SUM(DIGITAL!K8:K9) -> TRUE
F64: 0 | G64: 0 | H64: 0 | I64: 0 | J64: 0
B65: TT GERAÇÃO | F65: ='CUSTO GERAÇÃO SP1'!I40*1.25 -> 6112.5 | G65: 0 | H65: =SUM(F65:G65) -> 6112.5 | I65: =H65*0.8 -> 4890 | J65: 1 | K65: =I65/I67 -> 0.00088035094
B67: TOTAL GERAL CAMPANHA ESCASSEZ HIDRICA - CRÍTICO | SP1 | F67: =SUM(F21,F28,F36,F58,F63,F65) -> 4598485.3 | G67: =SUM(G21,G28,G36,G58,G63,G65) -> 2344768.6 | H67: =SUM(H21,H28,H36,H58,H63,H65) -> 6943253.8 | I67: =SUM(I21,I28,I36,I58,I63,I65) -> 5554603.1 | K67: =SUM(K10:K66) -> 1
F68: =F67/H67 -> 0.66229543 | G68: =G67/H67 -> 0.33770457 | I68: =SUM('TV ABERTA - SP1'!BU108,RÁDIO!BR197,JORNAL!CK37,DIGITAL!K8,'CUSTO GERAÇÃO SP1'!I40)=I67 -> TRUE

Sheet RESUMO DE MEIOS - SPE
B5: CLIENT: SABESP
B6: CAMPAING: ESCASSEZ HIDRICA - CRÍTICO
B8: RESUMO DE MEIOS - SÃO PAULO ESTADO
B10: PRAÇA | C10: MEIO | D10: VEÍCULO | F10: JANEIRO | G10: FEVEREIRO | H10: TOTAL BRUTO | I10: VALOR DESEMBOLSO TT | J10: PART GERAL %
N12: UTILIZAÇÃO DE SALDO DE PACOTES | P12: SALDO PACOTE | Q12: TOTAL A SER FATURADO
B13: SÃO PAULO ESTADO | C13: TV ABERTA | D13: GLOBO | F13: ='TV ABERTA - SPE'!CC32*1.25 -> 3234841.4 | G13: ='TV ABERTA - SPE'!CE32*1.25 -> 1220562 | H13: =SUM(F13:G13) -> 4455403.4 | I13: =H13*0.8 -> 3564322.8 | J13: =I13/$I$23 -> 0.45681236 | N13: SBT | O13: =I16+I21 -> 1109489.6 | P13: 567311.6 | Q13: =O13-P13 -> 542178
B14: SÃO PAULO ESTADO | C14: TV ABERTA | D14: BANDEIRANTES | F14: ='TV ABERTA - SPE'!CC44*1.25 -> 118538.85 | G14: ='TV ABERTA - SPE'!CE44*1.25 -> 77298.6 | H14: =SUM(F14:G14) -> 195837.45 | I14: =H14*0.8 -> 156669.96 | J14: =I14/$I$23 -> 0.020079207
B15: SÃO PAULO ESTADO | C15: TV ABERTA | D15: RECORD | F15: ='TV ABERTA - SPE'!CC57*1.25 -> 602332.6 | G15: ='TV ABERTA - SPE'!CE57*1.25 -> 574113.2 | H15: =SUM(F15:G15) -> 1176445.8 | I15: =H15*0.8 -> 941156.64 | J15: =I15/$I$23 -> 0.12062095
B16: SÃO PAULO ESTADO | C16: TV ABERTA | D16: SBT | F16: ='TV ABERTA - SPE'!CC70*1.25 -> 510641.5 | G16: ='TV ABERTA - SPE'!CE70*1.25 -> 573264 | H16: =SUM(F16:G16) -> 1083905.5 | I16: =H16*0.8 -> 867124.4 | J16: =I16/$I$23 -> 0.11113279
B18: SÃO PAULO ESTADO | C18: TV ABERTA | D18: GLOBO | F18: ='TV ABERTA - COLCHÃO REP - SPE'!CC17*1.25 -> 830408.4 | G18: ='TV ABERTA - COLCHÃO REP - SPE'!CE17*1.25 -> 830408.4 | H18: =SUM(F18:G18) -> 1660816.8 | I18: =H18*0.8 -> 1328653.4 | J18: =I18/$I$23 -> 0.17028349
B19: SÃO PAULO ESTADO | C19: TV ABERTA | D19: BANDEIRANTES | F19: ='TV ABERTA - COLCHÃO REP - SPE'!CC20*1.25 -> 114500.4 | G19: ='TV ABERTA - COLCHÃO REP - SPE'!CE20*1.25 -> 114500.4 | H19: =SUM(F19:G19) -> 229000.8 | I19: =H19*0.8 -> 183200.64 | J19: =I19/$I$23 -> 0.023479444
B20: SÃO PAULO ESTADO | C20: TV ABERTA | D20: RECORD | F20: ='TV ABERTA - COLCHÃO REP - SPE'!CC23*1.25 -> 324440 | G20: ='TV ABERTA - COLCHÃO REP - SPE'!CE23*1.25 -> 324440 | H20: =SUM(F20:G20) -> 648880 | I20: =H20*0.8 -> 519104 | J20: =I20/$I$23 -> 0.066529644
B21: SÃO PAULO ESTADO | C21: TV ABERTA | D21: SBT | F21: ='TV ABERTA - COLCHÃO REP - SPE'!CC25*1.25 -> 100985.5 | G21: ='TV ABERTA - COLCHÃO REP - SPE'!CE25*1.25 -> 201971 | H21: =SUM(F21:G21) -> 302956.5 | I21: =H21*0.8 -> 242365.2 | J21: =I21/$I$23 -> 0.031062119
B23: TT TV ABERTA | F23: =SUM(F13:F21) -> 5836688.7 | G23: =SUM(G13:G21) -> 3916557.6 | H23: =SUM(H13:H21) -> 9753246.3 | I23: =SUM(I13:I21) -> 7802597 | J23: =SUM(J13:J21) -> 1 | K23: =I23/I68 -> 0.75373272 | L23: =I23=SUM('TV ABERTA - SPE'!BU72,'TV ABERTA - COLCHÃO REP - SPE'!BU27) -> TRUE
B25: SÃO PAULO ESTADO | C25: TV PAGA | D25: GLOBONEWS | F25: ='TV PAGA - COLCHÃO REP - SPE'!CC37*1.25 -> 38904 | G25: ='TV PAGA - COLCHÃO REP - SPE'!CE37*1.25 -> 38904 | H25: =SUM(F25:G25) -> 77808 | I25: =H25*0.8 -> 62246.4 | J25: =I25/$I$30 -> 0.41072115
B26: SÃO PAULO ESTADO | C26: TV PAGA | D26: CNN BRASIL | F26: ='TV PAGA - COLCHÃO REP - SPE'!CC40*1.25 -> 22260 | G26: ='TV PAGA - COLCHÃO REP - SPE'!CE40*1.25 -> 22260 | H26: =SUM(F26:G26) -> 44520 | I26: =H26*0.8 -> 35616 | J26: =I26/$I$30 -> 0.23500547
B27: SÃO PAULO ESTADO | C27: TV PAGA | D27: RECORD NEWS | F27: ='TV PAGA - COLCHÃO REP - SPE'!CC43*1.25 -> 22000 | G27: ='TV PAGA - COLCHÃO REP - SPE'!CE43*1.25 -> 22000 | H27: =SUM(F27:G27) -> 44000 | I27: =H27*0.8 -> 35200 | J27: =I27/$I$30 -> 0.23226057
B28: SÃO PAULO ESTADO | C28: TV PAGA | D28: BAND NEWS | F28: ='TV PAGA - COLCHÃO REP - SPE'!CC46*1.25 -> 11557.2 | G28: ='TV PAGA - COLCHÃO REP - SPE'!CE46*1.25 -> 11557.2 | H28: =SUM(F28:G28) -> 23114.4 | I28: =H28*0.8 -> 18491.52 | J28: =I28/$I$30 -> 0.12201281
B30: TT TV PAGA | F30: =SUM(F25:F29) -> 94721.2 | G30: =SUM(G25:G29) -> 94721.2 | H30: =SUM(H25:H29) -> 189442.4 | I30: =SUM(I25:I29) -> 151553.92 | J30: =SUM(J25:J29) -> 1 | K30: =I30/I68 -> 0.014640145 | L30: =I30='TV PAGA - COLCHÃO REP - SPE'!BU48 -> TRUE
B32: SÃO PAULO | C32: JORNAL | D32: =JORNAL!C14 -> FOLHA DE SP | F32: =SUM(JORNAL!CN14:CN16)*1.25 -> 205409.91 | G32: {=SUM(JORNAL!CP14:CP16*1.25)} -> 0 | H32: =SUM(F32:G32) -> 205409.91 | I32: =H32*0.8 -> 164327.93 | J32: =I32/$I$38 -> 0.30990317
B33: SÃO PAULO | C33: JORNAL | D33: =JORNAL!C19 -> O ESTADO DE SP | F33: =SUM(JORNAL!CN19:CN21)*1.25 -> 232919.51 | G33: =SUM(JORNAL!CP19:CP21)*1.25 -> 0 | H33: =SUM(F33:G33) -> 232919.51 | I33: =H33*0.8 -> 186335.61 | J33: =I33/$I$38 -> 0.35140706
B34: SÃO PAULO | C34: JORNAL | D34: =JORNAL!C23 -> VALOR | F34: =SUM(JORNAL!CN23:CN25)*1.25 -> 138378.24 | G34: =SUM(JORNAL!CP23:CP25)*1.25 -> 0 | H34: =SUM(F34:G34) -> 138378.24 | I34: =H34*0.8 -> 110702.59 | J34: =I34/$I$38 -> 0.20877208
B35: SÃO PAULO | C35: JORNAL | D35: =JORNAL!C27 -> GAZETA DE SP | F35: =SUM(JORNAL!CN27:CN28)*1.25 -> 0 | G35: =SUM(JORNAL!CP27:CP29)*1.25 -> 0 | H35: =SUM(F35:G35) -> 0 | I35: =H35*0.8 -> 0 | J35: =I35/$I$38 -> 0
B36: =JORNAL!B31 -> ABC | C36: JORNAL | D36: =JORNAL!C31 -> DIÁRIO DO GRANDE ABC | F36: =SUM(JORNAL!CN31:CN34)*1.25 -> 86112 | G36: =SUM(JORNAL!CP31:CP34)*1.25 -> 0 | H36: =SUM(F36:G36) -> 86112 | I36: =H36*0.8 -> 68889.6 | J36: =I36/$I$38 -> 0.12991769
B38: TT JORNAL | F38: =SUM(F32:F36) -> 662819.66 | G38: =SUM(G32:G36) -> 0 | H38: =SUM(H32:H36) -> 662819.66 | I38: =SUM(I32:I36) -> 530255.73 | J38: =SUM(J32:J36) -> 1 | K38: =I38/I68 -> 0.051222829 | L38: =I38=JORNAL!CN39 -> TRUE
B40: SÃO PAULO | C40: RADIO | D40: JOVEM PAN FM | F40: =SUM(RÁDIO!CH14:CH15)*1.25 -> 94517.28 | G40: =SUM(RÁDIO!CJ14:CJ15)*1.25 -> 89266.32 | H40: =SUM(F40:G40) -> 183783.6 | I40: =H40*0.8 -> 147026.88 | J40: =I40/$I$60 -> 0.082231879
B41: SÃO PAULO | C41: RADIO | D41: BAND NEWS FM | F41: =SUM(RÁDIO!CH18:CH19)*1.25 -> 83832 | G41: =SUM(RÁDIO!CJ18:CJ19)*1.25 -> 55888 | H41: =SUM(F41:G41) -> 139720 | I41: =H41*0.8 -> 111776 | J41: =I41/$I$60 -> 0.062516123
B42: SÃO PAULO | C42: RADIO | D42: BANDEIRANTES | F42: =SUM(RÁDIO!CH22:CH23)*1.25 -> 59052 | G42: =SUM(RÁDIO!CJ22:CJ23)*1.25 -> 59052 | H42: =SUM(F42:G42) -> 118104 | I42: =H42*0.8 -> 94483.2 | J42: =I42/$I$60 -> 0.05284429
B43: SÃO PAULO | C43: RADIO | D43: CBN | F43: =SUM(RÁDIO!CH26:CH27)*1.25 -> 104319 | G43: =SUM(RÁDIO!CJ26:CJ27)*1.25 -> 48682.2 | H43: =SUM(F43:G43) -> 153001.2 | I43: =H43*0.8 -> 122400.96 | J43: =I43/$I$60 -> 0.068458645
B44: SÃO PAULO | C44: RADIO | D44: NATIVA FM | F44: =SUM(RÁDIO!CH35:CH36)*1.25 -> 60773.24 | G44: =SUM(RÁDIO!CJ35:CJ36)*1.25 -> 53867.19 | H44: =SUM(F44:G44) -> 114640.43 | I44: =H44*0.8 -> 91712.344 | J44: =I44/$I$60 -> 0.051294555
B45: SÃO PAULO | C45: RADIO | D45: BAND FM | F45: =SUM(RÁDIO!CH39:CH40)*1.25 -> 77714 | G45: =SUM(RÁDIO!CJ39:CJ40)*1.25 -> 77714 | H45: =SUM(F45:G45) -> 155428 | I45: =H45*0.8 -> 124342.4 | J45: =I45/$I$60 -> 0.069544489
B46: SÃO PAULO | C46: RADIO | D46: 89 ROCK FM | F46: =SUM(RÁDIO!CH43:CH44)*1.25 -> 72852 | G46: =SUM(RÁDIO!CJ43:CJ44)*1.25 -> 72852 | H46: =SUM(F46:G46) -> 145704 | I46: =H46*0.8 -> 116563.2 | J46: =I46/$I$60 -> 0.065193596
B47: SÃO PAULO | C47: RADIO | D47: ALPHA FM | F47: =SUM(RÁDIO!CH47:CH48)*1.25 -> 91929.6 | G47: =SUM(RÁDIO!CJ47:CJ48)*1.25 -> 94348.8 | H47: =SUM(F47:G47) -> 186278.4 | I47: =H47*0.8 -> 149022.72 | J47: =I47/$I$60 -> 0.083348149
B48: SÃO PAULO | C48: RADIO | D48: DISNEY FM | F48: =SUM(RÁDIO!CH51:CH52)*1.25 -> 60762 | G48: =SUM(RÁDIO!CJ51:CJ52)*1.25 -> 62361 | H48: =SUM(F48:G48) -> 123123 | I48: =H48*0.8 -> 98498.4 | J48: =I48/$I$60 -> 0.055089984
B49: SÃO PAULO | C49: RADIO | D49: ENERGIA 97 FM | F49: =SUM(RÁDIO!CH55:CH56)*1.25 -> 25766 | G49: =SUM(RÁDIO!CJ55:CJ56)*1.25 -> 25766 | H49: =SUM(F49:G49) -> 51532 | I49: =H49*0.8 -> 41225.6 | J49: =I49/$I$60 -> 0.023057407
B50: SÃO PAULO | C50: RADIO | D50: KISS FM | F50: =SUM(RÁDIO!CH59:CH60)*1.25 -> 0 | G50: =SUM(RÁDIO!CJ59:CJ60)*1.25 -> 0 | H50: =SUM(F50:G50) -> 0 | I50: =H50*0.8 -> 0 | J50: =I50/$I$60 -> 0
B51: SÃO PAULO | C51: RADIO | D51: GAZETA FM | F51: =SUM(RÁDIO!CH63:CH64)*1.25 -> 67184 | G51: =SUM(RÁDIO!CJ63:CJ64)*1.25 -> 67184 | H51: =SUM(F51:G51) -> 134368 | I51: =H51*0.8 -> 107494.4 | J51: =I51/$I$60 -> 0.060121431
B52: SÃO PAULO | C52: RADIO | D52: 105 FM | F52: =SUM(RÁDIO!CH67:CH68)*1.25 -> 40716 | G52: =SUM(RÁDIO!CJ67:CJ68)*1.25 -> 40716 | H52: =SUM(F52:G52) -> 81432 | I52: =H52*0.8 -> 65145.6 | J52: =I52/$I$60 -> 0.036435821
B53: SÃO PAULO | C53: RADIO | D53: RÁDIO MIX | F53: =SUM(RÁDIO!CH71+RÁDIO!CH72)*1.25 -> 60115 | G53: =SUM(RÁDIO!CJ71+RÁDIO!CJ72)*1.25 -> 53283.75 | H53: =SUM(F53:G53) -> 113398.75 | I53: =H53*0.8 -> 90719 | J53: =I53/$I$60 -> 0.050738979
B54: SÃO PAULO | C54: RADIO | D54: TRANSAMÉRICA FM | F54: =SUM(RÁDIO!CH75:CH76)*1.25 -> 53911.2 | G54: =SUM(RÁDIO!CJ75:CJ76)*1.25 -> 50060.4 | H54: =SUM(F54:G54) -> 103971.6 | I54: =H54*0.8 -> 83177.28 | J54: =I54/$I$60 -> 0.046520908
B55: SÃO PAULO | C55: RADIO | D55: MASSA FM | F55: =SUM(RÁDIO!CH79:CH80)*1.25 -> 30410.64 | G55: =SUM(RÁDIO!CJ79:CJ80)*1.25 -> 30410.64 | H55: =SUM(F55:G55) -> 60821.28 | I55: =H55*0.8 -> 48657.024 | J55: =I55/$I$60 -> 0.027213789
B56: SÃO PAULO | C56: RADIO | D56: ANTENA 1 FM | F56: =SUM(RÁDIO!CH83:CH84)*1.25 -> 43110.6 | G56: =SUM(RÁDIO!CJ83:CJ84)*1.25 -> 43110.6 | H56: =SUM(F56:G56) -> 86221.2 | I56: =H56*0.8 -> 68976.96 | J56: =I56/$I$60 -> 0.038578694
B57: SÃO PAULO | C57: RADIO | D57: NOVABRASIL | F57: =SUM(RÁDIO!CH87:CH88)*1.25 -> 58708 | G57: =SUM(RÁDIO!CJ87:CJ88)*1.25 -> 58708 | H57: =SUM(F57:G57) -> 117416 | I57: =H57*0.8 -> 93932.8 | J57: =I57/$I$60 -> 0.052536452
B58: SÃO PAULO | C58: RADIO | D58: TRANSCONTINENTAL | F58: =SUM(RÁDIO!CH91:CH92)*1.25 -> 88000 | G58: =SUM(RÁDIO!CJ91:CJ92)*1.25 -> 78000 | H58: =SUM(F58:G58) -> 166000 | I58: =H58*0.8 -> 132800 | J58: =I58/$I$60 -> 0.07427481
B60: TT RÁDIO | F60: =SUM(F40:F58) -> 1173672.6 | G60: =SUM(G40:G58) -> 1061270.9 | H60: =SUM(H40:H58) -> 2234943.5 | I60: =SUM(I40:I58) -> 1787954.8 | J60: =SUM(J40:J58) -> 1 | K60: =I60/I68 -> 0.17271685 | L60: =I60=RÁDIO!BR197 -> TRUE
B62: ABCD | C62: DIGITAL | F62: =SUM(DIGITAL!K8)*1.25 -> 62500 | G62: {=SUM(JORNAL!CP48:CP50*1.25)} -> 0 | H62: =SUM(F62:G62) -> 62500 | I62: =H62*0.8 -> 50000 | J62: 1
B64: TT DIGITAL | F64: =F62 -> 62500 | G64: =G62 -> 0 | H64: =H62 -> 62500 | I64: =I62 -> 50000 | J64: =J62 -> 1 | K64: =I64/I68 -> 0.0048300119
B66: TT GERAÇÃO | F66: ='CUSTO GERAÇÃO SPE'!I93*1.25 -> 36975 | G66: 0 | H66: =SUM(F66:G66) -> 36975 | I66: =H66*0.8 -> 29580 | J66: 1 | K66: =I66/I68 -> 0.002857435
B68: TOTAL GERAL CAMPANHA ESCASSEZ HIDRICA - CRÍTICO | SPE | F68: =SUM(F23,F30,F38,F60,F64,F66) -> 7867377.1 | G68: =SUM(G23,G30,G38,G60,G64,G66) -> 5072549.7 | H68: =SUM(H23,H30,H38,H60,H64,H66) -> 12939927 | I68: =SUM(I23,I30,I38,I60,I64,I66) -> 10351941 | K68: =SUM(K10:K67) -> 1
F69: =F68/H68 -> 0.6079924 | G69: =G68/H68 -> 0.3920076 | I69: =SUM('TV ABERTA - SPE'!BU72,'TV PAGA - COLCHÃO REP - SPE'!BU48,'TV ABERTA - COLCHÃO REP - SPE'!BU27,RÁDIO!BR197,JORNAL!CK37,DIGITAL!K8,'CUSTO GERAÇÃO SPE'!I93)=I68 -> TRUE

Sheet TV ABERTA - SP1
B5: CLIENT: SABESP
B6: CAMPAING: ESCASSEZ HIDRICA - CRÍTICO
BW7: PLANNED
B8: MARKET | C8: CHANNEL | D8: PROGRAMM | E8: DAY | F8: START TIME | G8: END TIME | H8: SEC | I8: JANEIRO | AN8: FEVEREIRO | BP8: INS. | BQ8: CUSTO TABELA UNITÁRIO (BRUTO) | BR8: DESC. % | BS8: CUSTO NEGOCIADO UNITÁRIO (BRUTO) | BT8: CUSTO TOTAL NEGOCIADO (BRUTO) | BU8: CUSTO TOTAL DESEMBOLSO SABESP | BW8: AUD. AS ABCDE 25+ | BX8: TRP | BY8: CPP | CA8: RESUMO
I9: T | J9: F | K9: S | L9: S | M9: M | N9: T | O9: W | P9: T | Q9: F | R9: S | S9: S | T9: M | U9: T | V9: W | W9: T | X9: F | Y9: S | Z9: S | AA9: M | AB9: T | AC9: W | AD9: T | AE9: F | AF9: S | AG9: S | AH9: M | AI9: T | AJ9: W | AK9: T | AL9: F | AM9: S | AN9: S | AO9: M | AP9: T | AQ9: W | AR9: T | AS9: F | AT9: S | AU9: S | AV9: M | AW9: T | AX9: W | AY9: T | AZ9: F | BA9: S | BB9: S | BC9: M | BD9: T | BE9: W | BF9: T | BG9: F | BH9: S | BI9: S | BJ9: M | BK9: T | BL9: W | BM9: T | BN9: F | BO9: S
I10: 1 | J10: 2 | K10: 3 | L10: 4 | M10: 5 | N10: 6 | O10: 7 | P10: 8 | Q10: 9 | R10: 10 | S10: 11 | T10: 12 | U10: 13 | V10: 14 | W10: 15 | X10: 16 | Y10: 17 | Z10: =Y10+1 -> 18 | AA10: =Z10+1 -> 19 | AB10: =AA10+1 -> 20 | AC10: =AB10+1 -> 21 | AD10: =AC10+1 -> 22 | AE10: =AD10+1 -> 23 | AF10: =AE10+1 -> 24 | AG10: =AF10+1 -> 25 | ... AM10: =AL10+1 -> 31 | AN10: 1 | AO10: 2 | AP10: 3 | AQ10: 4 | AR10: 5 | AS10: 6 | AT10: 7 | AU10: 8 | AV10: 9 | AW10: 10 | AX10: 11 | AY10: 12 | AZ10: 13 | BA10: 14 | BB10: 15 | BC10: 16 | BD10: 17 | BE10: =BD10+1 -> 18 | BF10: =BE10+1 -> 19 | BG10: =BF10+1 -> 20 | BH10: =BG10+1 -> 21 | BI10: =BH10+1 -> 22 | BJ10: =BI10+1 -> 23 | BK10: =BJ10+1 -> 24 | BL10: =BK10+1 -> 25 | ... BO10: =BN10+1 -> 28 | CA10: CHANNEL | CB10: JANEIRO | CD10: FEVEREIRO
CB12: INS | CC12: INVESTIMENTO $ | CD12: INS | CE12: INVESTIMENTO $
B13: SÃO PAULO CAPITAL | C13: TV GLOBO | D13: NOVELA II | E13: SEG-SEX | F13: 0.81944444 | G13: 0.85416667 | H13: 30 | AJ13: 1 | BP13: =SUM(I13:BO13) -> 1 | BQ13: 131844 | BR13: 1 | BS13: =BQ13*(1-BR13) -> 0 | BT13: =BS13*BP13 -> 0 | BU13: =BT13*0.8 -> 0 | BW13: 12.33 | BX13: =BW13*BP13 -> 12.33 | BY13: =IFERROR(BU13/BX13,0) -> 0 | CA13: TV GLOBO | CB13: =COUNTA(I13:AM13) -> 1 | CC13: =CB13*BS13*0.8 -> 0 | CD13: =COUNTA(AN13:BO13) -> 0 | CE13: =CD13*BS13*0.8 -> 0 | CF13: =SUM(CC13,CE13)=BU13 -> TRUE
D14: NOVELA III | E14: SEG-SEX | F14: 0.88888889 | G14: 0.93402778 | H14: 30 | AH14: 1 | AK14: 1 | BP14: =SUM(I14:BO14) -> 2 | BQ14: 182594 | BR14: 0 | BS14: =BQ14*(1-BR14) -> 182594 | BT14: =BS14*BP14 -> 365188 | BU14: =BT14*0.8 -> 292150.4 | BW14: 13.35 | BX14: =BW14*BP14 -> 26.7 | BY14: =IFERROR(BU14/BX14,0) -> 10941.963 | CA14: TV GLOBO | CB14: =COUNTA(I14:AM14) -> 2 | CC14: =CB14*BS14*0.8 -> 292150.4 | CD14: =COUNTA(AN14:BO14) -> 0 | CE14: =CD14*BS14*0.8 -> 0 | CF14: =SUM(CC14,CE14)=BU14 -> TRUE
D16: JORNAL HOJE | E16: SEG-SEX | F16: 0.55902778 | G16: 0.61458333 | H16: 30 | AO16: 1 | AR16: 1 | AW16: 1 | BP16: =SUM(I16:BO16) -> 3 | BQ16: 41050 | BR16: 0.30844153 | BS16: =BQ16*(1-BR16) -> 28388.475 | BT16: =BS16*BP16 -> 85165.426 | BU16: =BT16*0.8 -> 68132.341 | BW16: 5.92 | BX16: =BW16*BP16 -> 17.76 | BY16: =IFERROR(BU16/BX16,0) -> 3836.2804 | CA16: TV GLOBO | CB16: =COUNTA(I16:AM16) -> 0 | CC16: =CB16*BS16*0.8 -> 0 | CD16: =COUNTA(AN16:BO16) -> 3 | CE16: =CD16*BS16*0.8 -> 68132.341 | CF16: =SUM(CC16,CE16)=BU16 -> TRUE
D17: BOM DIA BRASIL | E17: SEG-SEX | F17: 0.33333333 | G17: 0.39583333 | H17: 30 | AQ17: 1 | AV17: 1 | AY17: 1 | AZ17: 1 | BP17: =SUM(I17:BO17) -> 4 | BQ17: 25643 | BR17: 0.30844153 | BS17: =BQ17*(1-BR17) -> 17733.634 | BT17: =BS17*BP17 -> 70934.536 | BU17: =BT17*0.8 -> 56747.628 | BW17: 4.94 | BX17: =BW17*BP17 -> 19.76 | BY17: =IFERROR(BU17/BX17,0) -> 2871.8435 | CA17: TV GLOBO | CB17: =COUNTA(I17:AM17) -> 0 | CC17: =CB17*BS17*0.8 -> 0 | CD17: =COUNTA(AN17:BO17) -> 4 | CE17: =CD17*BS17*0.8 -> 56747.628 | CF17: =SUM(CC17,CE17)=BU17 -> TRUE
D18: BOM DIA PRACA | E18: SEG-SEX | F18: 0.25 | G18: 0.35416667 | H18: 30 | AP18: 1 | AR18: 1 | AS18: 1 | AW18: 1 | AX18: 1 | BP18: =SUM(I18:BO18) -> 5 | BQ18: 18183 | BR18: 0.30844153 | BS18: =BQ18*(1-BR18) -> 12574.608 | BT18: =BS18*BP18 -> 62873.039 | BU18: =BT18*0.8 -> 50298.431 | BW18: 4.41 | BX18: =BW18*BP18 -> 22.05 | BY18: =IFERROR(BU18/BX18,0) -> 2281.108 | CA18: TV GLOBO | CB18: =COUNTA(I18:AM18) -> 0 | CC18: =CB18*BS18*0.8 -> 0 | CD18: =COUNTA(AN18:BO18) -> 5 | CE18: =CD18*BS18*0.8 -> 50298.431 | CF18: =SUM(CC18,CE18)=BU18 -> TRUE
D20: JORNAL NACIONAL | E20: SEG-SEX | F20: 0.85416667 | G20: 0.88888889 | H20: 30 | AV20: 1 | BP20: =SUM(I20:BO20) -> 1 | BQ20: 180006 | BR20: 0 | BS20: =BQ20*(1-BR20) -> 180006 | BT20: =BS20*BP20 -> 180006 | BU20: =BT20*0.8 -> 144004.8 | BW20: 13.07 | BX20: =BW20*BP20 -> 13.07 | BY20: =IFERROR(BU20/BX20,0) -> 11017.965 | CA20: TV GLOBO | CB20: =COUNTA(I20:AM20) -> 0 | CC20: =CB20*BS20*0.8 -> 0 | CD20: =COUNTA(AN20:BO20) -> 1 | CE20: =CD20*BS20*0.8 -> 144004.8 | CF20: =SUM(CC20,CE20)=BU20 -> TRUE
D21: FANTASTICO | E21: DOM | F21: 0.85416667 | G21: 0.96527778 | H21: 30 | AU21: 1 | BP21: =SUM(I21:BO21) -> 1 | BQ21: 144982 | BR21: 0 | BS21: =BQ21*(1-BR21) -> 144982 | BT21: =BS21*BP21 -> 144982 | BU21: =BT21*0.8 -> 115985.6 | BW21: 8.8 | BX21: =BW21*BP21 -> 8.8 | BY21: =IFERROR(BU21/BX21,0) -> 13180.182 | CA21: TV GLOBO | CB21: =COUNTA(I21:AM21) -> 0 | CC21: =CB21*BS21*0.8 -> 0 | CD21: =COUNTA(AN21:BO21) -> 1 | CE21: =CD21*BS21*0.8 -> 115985.6 | CF21: =SUM(CC21,CE21)=BU21 -> TRUE
D22: JORNAL DA GLOBO | E22: SEG-SEX | F22: 0.041666667 | G22: 0.076388889 | H22: 30 | AO22: 1 | AQ22: 1 | AW22: 1 | AY22: 1 | BP22: =SUM(I22:BO22) -> 4 | BQ22: 28729 | BR22: 1 | BS22: =BQ22*(1-BR22) -> 0 | BT22: =BS22*BP22 -> 0 | BU22: =BT22*0.8 -> 0 | BW22: 3.7 | BX22: =BW22*BP22 -> 14.8 | BY22: =IFERROR(BU22/BX22,0) -> 0 | CA22: TV GLOBO | CB22: =COUNTA(I22:AM22) -> 0 | CC22: =CB22*BS22*0.8 -> 0 | CD22: =COUNTA(AN22:BO22) -> 4 | CE22: =CD22*BS22*0.8 -> 0 | CF22: =SUM(CC22,CE22)=BU22 -> TRUE
D24: NOVELA I | E24: SEG-SEX | F24: 0.76736111 | G24: 0.79861111 | H24: 30 | AH24: 1 | AK24: 1 | BP24: =SUM(I24:BO24) -> 2 | BQ24: 98392 | BR24: 0 | BS24: =BQ24*(1-BR24) -> 98392 | BT24: =BS24*BP24 -> 196784 | BU24: =BT24*0.8 -> 157427.2 | BW24: 8.51 | BX24: =BW24*BP24 -> 17.02 | BY24: =IFERROR(BU24/BX24,0) -> 9249.5417 | CA24: TV GLOBO | CB24: =COUNTA(I24:AM24) -> 2 | CC24: =CB24*BS24*0.8 -> 157427.2 | CD24: =COUNTA(AN24:BO24) -> 0 | CE24: =CD24*BS24*0.8 -> 0 | CF24: =SUM(CC24,CE24)=BU24 -> TRUE
D25: NOVELA II | E25: SEG-SEX | F25: 0.81944444 | G25: 0.85416667 | H25: 30 | AI25: 1 | AL25: 1 | BP25: =SUM(I25:BO25) -> 2 | BQ25: 131844 | BR25: 0 | BS25: =BQ25*(1-BR25) -> 131844 | BT25: =BS25*BP25 -> 263688 | BU25: =BT25*0.8 -> 210950.4 | BW25: 12.33 | BX25: =BW25*BP25 -> 24.66 | BY25: =IFERROR(BU25/BX25,0) -> 8554.3552 | CA25: TV GLOBO | CB25: =COUNTA(I25:AM25) -> 2 | CC25: =CB25*BS25*0.8 -> 210950.4 | CD25: =COUNTA(AN25:BO25) -> 0 | CE25: =CD25*BS25*0.8 -> 0 | CF25: =SUM(CC25,CE25)=BU25 -> TRUE
D26: NOVELA I | E26: SÁB | F26: 0.77777778 | G26: 0.80902778 | H26: 30 | AJ26: 1 | BP26: =SUM(I26:BO26) -> 1 | BQ26: 98392 | BR26: 1 | BS26: =BQ26*(1-BR26) -> 0 | BT26: =BS26*BP26 -> 0 | BU26: =BT26*0.8 -> 0 | BW26: 11.08 | BX26: =BW26*BP26 -> 11.08 | BY26: =IFERROR(BU26/BX26,0) -> 0 | CA26: TV GLOBO | CB26: =COUNTA(I26:AM26) -> 1 | CC26: =CB26*BS26*0.8 -> 0 | CD26: =COUNTA(AN26:BO26) -> 0 | CE26: =CD26*BS26*0.8 -> 0 | CF26: =SUM(CC26,CE26)=BU26 -> TRUE
D28: JORNAL NACIONAL | E28: SEG-SEX | F28: 0.88888889 | G28: 0.93402778 | H28: 60 | AE28: 1 | BP28: =SUM(I28:BO28) -> 1 | BQ28: =180006*2 -> 360012 | BR28: 0 | BS28: =BQ28*(1-BR28) -> 360012 | BT28: =BS28*BP28 -> 360012 | BU28: =BT28*0.8 -> 288009.6 | BW28: 13.07 | BX28: =BW28*BP28 -> 13.07 | BY28: =IFERROR(BU28/BX28,0) -> 22035.93 | CA28: TV GLOBO | CB28: =COUNTA(I28:AM28) -> 1 | CC28: =CB28*BS28*0.8 -> 288009.6 | CD28: =COUNTA(AN28:BO28) -> 0 | CE28: =CD28*BS28*0.8 -> 0 | CF28: =SUM(CC28,CE28)=BU28 -> TRUE
D29: FANTASTICO | E29: DOM | F29: 0.85416667 | G29: 0.96527778 | H29: 60 | AG29: 1 | BP29: =SUM(I29:BO29) -> 1 | BQ29: =144982*2 -> 289964 | BR29: 0 | BS29: =BQ29*(1-BR29) -> 289964 | BT29: =BS29*BP29 -> 289964 | BU29: =BT29*0.8 -> 231971.2 | BW29: 8.8 | BX29: =BW29*BP29 -> 8.8 | BY29: =IFERROR(BU29/BX29,0) -> 26360.364 | CA29: TV GLOBO | CB29: =COUNTA(I29:AM29) -> 1 | CC29: =CB29*BS29*0.8 -> 231971.2 | CD29: =COUNTA(AN29:BO29) -> 0 | CE29: =CD29*BS29*0.8 -> 0 | CF29: =SUM(CC29,CE29)=BU29 -> TRUE
D30: PRACA TV 2 ED SAB | E30: SÁB | F30: 0.80902778 | G30: 0.82291667 | H30: 60 | AF30: 1 | BP30: =SUM(I30:BO30) -> 1 | BQ30: =112324*2 -> 224648 | BR30: 1 | BS30: =BQ30*(1-BR30) -> 0 | BT30: =BS30*BP30 -> 0 | BU30: =BT30*0.8 -> 0 | BW30: 12.39 | BX30: =BW30*BP30 -> 12.39 | BY30: =IFERROR(BU30/BX30,0) -> 0 | CA30: TV GLOBO | CB30: =COUNTA(I30:AM30) -> 1 | CC30: =CB30*BS30*0.8 -> 0 | CD30: =COUNTA(AN30:BO30) -> 0 | CE30: =CD30*BS30*0.8 -> 0 | CF30: =SUM(CC30,CE30)=BU30 -> TRUE
D32: JORNAL NACIONAL | E32: SEG-SEX | F32: 0.85416667 | G32: 0.88888889 | H32: 60 | AD32: 1 | BP32: =SUM(I32:BO32) -> 1 | BQ32: =(180006*2) -> 360012 | BR32: 0.1 | BS32: =BQ32*(1-BR32) -> 324010.8 | BT32: =BS32*BP32 -> 324010.8 | BU32: =BT32*0.8 -> 259208.64 | BW32: 13.07 | BX32: =BW32*BP32 -> 13.07 | BY32: =IFERROR(BU32/BX32,0) -> 19832.337 | CA32: TV GLOBO | CB32: =COUNTA(I32:AM32) -> 1 | CC32: =CB32*BS32*0.8 -> 259208.64 | CD32: =COUNTA(AN32:BO32) -> 0 | CE32: =CD32*BS32*0.8 -> 0 | CF32: =SUM(CC32,CE32)=BU32 -> TRUE
CA33: TT | CB33: =SUM(CB13:CB32) -> 12 | CC33: =SUM(CC13:CC32) -> 1439717.4 | CD33: =SUM(CD13:CD32) -> 18 | CE33: =SUM(CE13:CE32) -> 435168.8
C34: BANDEIRANTES | D34: BORA BRASIL | E34: SEG-SEX | F34: 0.375 | G34: 11:00 | H34: 30 | AK34: 1 | AR34: 1 | AY34: 1 | BP34: =SUM(I34:BO34) -> 3 | BQ34: 10649 | BR34: 0.85 | BS34: =BQ34*(1-BR34) -> 1597.35 | BT34: =BS34*BP34 -> 4792.05 | BU34: =BT34*0.8 -> 3833.64 | BW34: 0.24 | BX34: =BW34*BP34 -> 0.72 | BY34: =IFERROR(BU34/BX34,0) -> 5324.5 | CA34: BANDEIRANTES | CB34: =COUNTA(I34:AM34) -> 1 | CC34: =CB34*BS34*0.8 -> 1277.88 | CD34: =COUNTA(AN34:BO34) -> 2 | CE34: =CD34*BS34*0.8 -> 2555.76 | CF34: =SUM(CC34,CE34)=BU34 -> TRUE
D35: BORA BRASIL | E35: SEG-SEX | F35: 0.375 | G35: 11:00 | H35: 60 | AE35: 1 | BP35: =SUM(I35:BO35) -> 1 | BQ35: 21298 | BR35: 0.85 | BS35: =BQ35*(1-BR35) -> 3194.7 | BT35: =BS35*BP35 -> 3194.7 | BU35: =BT35*0.8 -> 2555.76 | BW35: 0.24 | BX35: =BW35*BP35 -> 0.24 | BY35: =IFERROR(BU35/BX35,0) -> 10649 | CA35: BANDEIRANTES | CB35: =COUNTA(I35:AM35) -> 1 | CC35: =CB35*BS35*0.8 -> 2555.76 | CD35: =COUNTA(AN35:BO35) -> 0 | CE35: =CD35*BS35*0.8 -> 0 | CF35: =SUM(CC35,CE35)=BU35 -> TRUE
D36: BRASIL URGENTE | E36: SEG-SÁB | F36: 0.66666667 | G36: 17:30 | H36: 30 | AL36: 1 | AS36: 1 | AZ36: 1 | BP36: =SUM(I36:BO36) -> 3 | BQ36: 37711 | BR36: 0.85 | BS36: =BQ36*(1-BR36) -> 5656.65 | BT36: =BS36*BP36 -> 16969.95 | BU36: =BT36*0.8 -> 13575.96 | BW36: 1.43 | BX36: =BW36*BP36 -> 4.29 | BY36: =IFERROR(BU36/BX36,0) -> 3164.5594 | CA36: BANDEIRANTES | CB36: =COUNTA(I36:AM36) -> 1 | CC36: =CB36*BS36*0.8 -> 4525.32 | CD36: =COUNTA(AN36:BO36) -> 2 | CE36: =CD36*BS36*0.8 -> 9050.64 | CF36: =SUM(CC36,CE36)=BU36 -> TRUE
D37: BRASIL URGENTE | E37: SEG-SÁB | F37: 0.66666667 | G37: 17:30 | H37: 60 | AE37: 1 | BP37: =SUM(I37:BO37) -> 1 | BQ37: 75422 | BR37: 0.85 | BS37: =BQ37*(1-BR37) -> 11313.3 | BT37: =BS37*BP37 -> 11313.3 | BU37: =BT37*0.8 -> 9050.64 | BW37: 1.43 | BX37: =BW37*BP37 -> 1.43 | BY37: =IFERROR(BU37/BX37,0) -> 6329.1189 | CA37: BANDEIRANTES | CB37: =COUNTA(I37:AM37) -> 1 | CC37: =CB37*BS37*0.8 -> 9050.64 | CD37: =COUNTA(AN37:BO37) -> 0 | CE37: =CD37*BS37*0.8 -> 0 | CF37: =SUM(CC37,CE37)=BU37 -> TRUE
D38: CANAL LIVRE | E38: DOM | F38: 0.95833333 | G38: 00:00 | H38: 30 | AU38: 1 | BP38: =SUM(I38:BO38) -> 1 | BQ38: 19480 | BR38: 0.85 | BS38: =BQ38*(1-BR38) -> 2922 | BT38: =BS38*BP38 -> 2922 | BU38: =BT38*0.8 -> 2337.6 | BW38: 0.21 | BX38: =BW38*BP38 -> 0.21 | BY38: =IFERROR(BU38/BX38,0) -> 11131.429 | CA38: BANDEIRANTES | CB38: =COUNTA(I38:AM38) -> 0 | CC38: =CB38*BS38*0.8 -> 0 | CD38: =COUNTA(AN38:BO38) -> 1 | CE38: =CD38*BS38*0.8 -> 2337.6 | CF38: =SUM(CC38,CE38)=BU38 -> TRUE
D39: CANAL LIVRE | E39: DOM | F39: 0.95833333 | G39: 00:00 | H39: 60 | AG39: 1 | BP39: =SUM(I39:BO39) -> 1 | BQ39: 38960 | BR39: 0.85 | BS39: =BQ39*(1-BR39) -> 5844 | BT39: =BS39*BP39 -> 5844 | BU39: =BT39*0.8 -> 4675.2 | BW39: 0.21 | BX39: =BW39*BP39 -> 0.21 | BY39: =IFERROR(BU39/BX39,0) -> 22262.857 | CA39: BANDEIRANTES | CB39: =COUNTA(I39:AM39) -> 1 | CC39: =CB39*BS39*0.8 -> 4675.2 | CD39: =COUNTA(AN39:BO39) -> 0 | CE39: =CD39*BS39*0.8 -> 0 | CF39: =SUM(CC39,CE39)=BU39 -> TRUE
D40: JORNAL DA NOITE | E40: SEG-SEX | F40: 0.010416667 | G40: 01:15 | H40: 30 | AJ40: 1 | AQ40: 1 | AX40: 1 | BP40: =SUM(I40:BO40) -> 3 | BQ40: 20453 | BR40: 0.85 | BS40: =BQ40*(1-BR40) -> 3067.95 | BT40: =BS40*BP40 -> 9203.85 | BU40: =BT40*0.8 -> 7363.08 | BW40: 0.34 | BX40: =BW40*BP40 -> 1.02 | BY40: =IFERROR(BU40/BX40,0) -> 7218.7059 | CA40: BANDEIRANTES | CB40: =COUNTA(I40:AM40) -> 1 | CC40: =CB40*BS40*0.8 -> 2454.36 | CD40: =COUNTA(AN40:BO40) -> 2 | CE40: =CD40*BS40*0.8 -> 4908.72 | CF40: =SUM(CC40,CE40)=BU40 -> TRUE
D41: JORNAL DA NOITE | E41: SEG-SEX | F41: 0.010416667 | G41: 01:15 | H41: 60 | AE41: 1 | BP41: =SUM(I41:BO41) -> 1 | BQ41: 40906 | BR41: 0.85 | BS41: =BQ41*(1-BR41) -> 6135.9 | BT41: =BS41*BP41 -> 6135.9 | BU41: =BT41*0.8 -> 4908.72 | BW41: 0.34 | BX41: =BW41*BP41 -> 0.34 | BY41: =IFERROR(BU41/BX41,0) -> 14437.412 | CA41: BANDEIRANTES | CB41: =COUNTA(I41:AM41) -> 1 | CC41: =CB41*BS41*0.8 -> 4908.72 | CD41: =COUNTA(AN41:BO41) -> 0 | CE41: =CD41*BS41*0.8 -> 0 | CF41: =SUM(CC41,CE41)=BU41 -> TRUE
D42: NOVELA I | E42: SEG-SEX | F42: 0.29166667 | G42: 08:00 | H42: 30 | BP42: =SUM(I42:BO42) -> 0 | BQ42: 10649 | BR42: 0.85 | BS42: =BQ42*(1-BR42) -> 1597.35 | BT42: =BS42*BP42 -> 0 | BU42: =BT42*0.8 -> 0 | BW42: 0.1 | BX42: =BW42*BP42 -> 0 | BY42: =IFERROR(BU42/BX42,0) -> 0 | CA42: BANDEIRANTES | CB42: =COUNTA(I42:AM42) -> 0 | CC42: =CB42*BS42*0.8 -> 0 | CD42: =COUNTA(AN42:BO42) -> 0 | CE42: =CD42*BS42*0.8 -> 0 | CF42: =SUM(CC42,CE42)=BU42 -> TRUE
D43: NOVELA II | E43: SEG-SEX | F43: 0.85416667 | G43: 21:25 | H43: 30 | AH43: 1 | AO43: 1 | AV43: 1 | BP43: =SUM(I43:BO43) -> 3 | BQ43: 66739 | BR43: 0.85 | BS43: =BQ43*(1-BR43) -> 10010.85 | BT43: =BS43*BP43 -> 30032.55 | BU43: =BT43*0.8 -> 24026.04 | BW43: 0.71 | BX43: =BW43*BP43 -> 2.13 | BY43: =IFERROR(BU43/BX43,0) -> 11279.831 | CA43: BANDEIRANTES | CB43: =COUNTA(I43:AM43) -> 1 | CC43: =CB43*BS43*0.8 -> 8008.68 | CD43: =COUNTA(AN43:BO43) -> 2 | CE43: =CD43*BS43*0.8 -> 16017.36 | CF43: =SUM(CC43,CE43)=BU43 -> TRUE
D44: NOVELA II | E44: SEG-SEX | F44: 0.85416667 | G44: 21:25 | H44: 60 | AE44: 1 | BP44: =SUM(I44:BO44) -> 1 | BQ44: 133478 | BR44: 0.85 | BS44: =BQ44*(1-BR44) -> 20021.7 | BT44: =BS44*BP44 -> 20021.7 | BU44: =BT44*0.8 -> 16017.36 | BW44: 0.71 | BX44: =BW44*BP44 -> 0.71 | BY44: =IFERROR(BU44/BX44,0) -> 22559.662 | CA44: BANDEIRANTES | CB44: =COUNTA(I44:AM44) -> 1 | CC44: =CB44*BS44*0.8 -> 16017.36 | CD44: =COUNTA(AN44:BO44) -> 0 | CE44: =CD44*BS44*0.8 -> 0 | CF44: =SUM(CC44,CE44)=BU44 -> TRUE
CA45: TT | CB45: =SUM(CB34:CB44) -> 9 | CC45: =SUM(CC34:CC44) -> 53473.92 | CD45: =SUM(CD34:CD44) -> 9 | CE45: =SUM(CE34:CE44) -> 34870.08
C46: RECORD | D46: CIDADE ALERTA ED SAB | E46: SÁB | F46: 0.70833333 | G46: 0.82291667 | H46: 30 | AM46: 1 | AT46: 1 | BP46: =SUM(I46:BO46) -> 2 | BQ46: 51691 | BR46: 0.8 | BS46: =BQ46*(1-BR46) -> 10338.2 | BT46: =BS46*BP46 -> 20676.4 | BU46: =BT46*0.8 -> 16541.12 | BW46: 2.19 | BX46: =BW46*BP46 -> 4.38 | BY46: =IFERROR(BU46/BX46,0) -> 3776.5114 | CA46: RECORD | CB46: =COUNTA(I46:AM46) -> 1 | CC46: =CB46*BS46*0.8 -> 8270.56 | CD46: =COUNTA(AN46:BO46) -> 1 | CE46: =CD46*BS46*0.8 -> 8270.56 | CF46: =SUM(CC46,CE46)=BU46 -> TRUE
D47: CIDADE ALERTA 2 SAB | E47: SÁB | F47: 0.875 | G47: 22:30 | H47: 60 | AF47: 1 | BP47: =SUM(I47:BO47) -> 1 | BQ47: 103382 | BR47: 0.8 | BS47: =BQ47*(1-BR47) -> 20676.4 | BT47: =BS47*BP47 -> 20676.4 | BU47: =BT47*0.8 -> 16541.12 | BW47: 2.19 | BX47: =BW47*BP47 -> 2.19 | BY47: =IFERROR(BU47/BX47,0) -> 7553.0228 | CA47: RECORD | CB47: =COUNTA(I47:AM47) -> 1 | CC47: =CB47*BS47*0.8 -> 16541.12 | CD47: =COUNTA(AN47:BO47) -> 0 | CE47: =CD47*BS47*0.8 -> 0 | CF47: =SUM(CC47,CE47)=BU47 -> TRUE
D48: DOMINGO ESPETACULAR | E48: DOM | F48: 0.75 | G48: 20:00 | H48: 30 | AN48: 1 | AU48: 1 | BP48: =SUM(I48:BO48) -> 2 | BQ48: 326000 | BR48: 0.8 | BS48: =BQ48*(1-BR48) -> 65200 | BT48: =BS48*BP48 -> 130400 | BU48: =BT48*0.8 -> 104320 | BW48: 3.05 | BX48: =BW48*BP48 -> 6.1 | BY48: =IFERROR(BU48/BX48,0) -> 17101.639 | CA48: RECORD | CB48: =COUNTA(I48:AM48) -> 0 | CC48: =CB48*BS48*0.8 -> 0 | CD48: =COUNTA(AN48:BO48) -> 2 | CE48: =CD48*BS48*0.8 -> 104320 | CF48: =SUM(CC48,CE48)=BU48 -> TRUE
D49: DOMINGO ESPETACULAR | E49: DOM | F49: 0.75 | G49: 20:00 | H49: 60 | AG49: 1 | BP49: =SUM(I49:BO49) -> 1 | BQ49: 652000 | BR49: 0.8 | BS49: =BQ49*(1-BR49) -> 130400 | BT49: =BS49*BP49 -> 130400 | BU49: =BT49*0.8 -> 104320 | BW49: 3.05 | BX49: =BW49*BP49 -> 3.05 | BY49: =IFERROR(BU49/BX49,0) -> 34203.279 | CA49: RECORD | CB49: =COUNTA(I49:AM49) -> 1 | CC49: =CB49*BS49*0.8 -> 104320 | CD49: =COUNTA(AN49:BO49) -> 0 | CE49: =CD49*BS49*0.8 -> 0 | CF49: =SUM(CC49,CE49)=BU49 -> TRUE
D50: FALA BRASIL | E50: SEG-SEX | F50: 0.35416667 | G50: 09:35 | H50: 30 | AJ50: 1 | AQ50: 1 | AX50: 1 | BP50: =SUM(I50:BO50) -> 3 | BQ50: 69921 | BR50: 0.8 | BS50: =BQ50*(1-BR50) -> 13984.2 | BT50: =BS50*BP50 -> 41952.6 | BU50: =BT50*0.8 -> 33562.08 | BW50: 1.95 | BX50: =BW50*BP50 -> 5.85 | BY50: =IFERROR(BU50/BX50,0) -> 5737.1077 | CA50: RECORD | CB50: =COUNTA(I50:AM50) -> 1 | CC50: =CB50*BS50*0.8 -> 11187.36 | CD50: =COUNTA(AN50:BO50) -> 2 | CE50: =CD50*BS50*0.8 -> 22374.72 | CF50: =SUM(CC50,CE50)=BU50 -> TRUE
D51: FALA BRASIL | E51: SEG-SEX | F51: 0.35416667 | G51: 09:35 | H51: 60 | AE51: 1 | BP51: =SUM(I51:BO51) -> 1 | BQ51: 139842 | BR51: 0.8 | BS51: =BQ51*(1-BR51) -> 27968.4 | BT51: =BS51*BP51 -> 27968.4 | BU51: =BT51*0.8 -> 22374.72 | BW51: 1.95 | BX51: =BW51*BP51 -> 1.95 | BY51: =IFERROR(BU51/BX51,0) -> 11474.215 | CA51: RECORD | CB51: =COUNTA(I51:AM51) -> 1 | CC51: =CB51*BS51*0.8 -> 22374.72 | CD51: =COUNTA(AN51:BO51) -> 0 | CE51: =CD51*BS51*0.8 -> 0 | CF51: =SUM(CC51,CE51)=BU51 -> TRUE
D52: HOJE EM DIA | E52: SEG-SEX | F52: 0.39930556 | G52: 11:30 | H52: 30 | AI52: 1 | AP52: 1 | AW52: 1 | BP52: =SUM(I52:BO52) -> 3 | BQ52: 50003 | BR52: 0.8 | BS52: =BQ52*(1-BR52) -> 10000.6 | BT52: =BS52*BP52 -> 30001.8 | BU52: =BT52*0.8 -> 24001.44 | BW52: 2.01 | BX52: =BW52*BP52 -> 6.03 | BY52: =IFERROR(BU52/BX52,0) -> 3980.3383 | CA52: RECORD | CB52: =COUNTA(I52:AM52) -> 1 | CC52: =CB52*BS52*0.8 -> 8000.48 | CD52: =COUNTA(AN52:BO52) -> 2 | CE52: =CD52*BS52*0.8 -> 16000.96 | CF52: =SUM(CC52,CE52)=BU52 -> TRUE
D53: NOVELA 22H | E53: SEG-SEX | F53: 0.91666667 | G53: 22:30 | H53: 30 | AK53: 1 | AR53: 1 | AY53: 1 | BP53: =SUM(I53:BO53) -> 3 | BQ53: 177561 | BR53: 0.8 | BS53: =BQ53*(1-BR53) -> 35512.2 | BT53: =BS53*BP53 -> 106536.6 | BU53: =BT53*0.8 -> 85229.28 | BW53: 2.27 | BX53: =BW53*BP53 -> 6.81 | BY53: =IFERROR(BU53/BX53,0) -> 12515.313 | CA53: RECORD | CB53: =COUNTA(I53:AM53) -> 1 | CC53: =CB53*BS53*0.8 -> 28409.76 | CD53: =COUNTA(AN53:BO53) -> 2 | CE53: =CD53*BS53*0.8 -> 56819.52 | CF53: =SUM(CC53,CE53)=BU53 -> TRUE
D54: NOVELA 22H | E54: SEG-SEX | F54: 0.91666667 | G54: 22:30 | H54: 60 | AE54: 1 | BP54: =SUM(I54:BO54) -> 1 | BQ54: 355122 | BR54: 0.8 | BS54: =BQ54*(1-BR54) -> 71024.4 | BT54: =BS54*BP54 -> 71024.4 | BU54: =BT54*0.8 -> 56819.52 | BW54: 2.27 | BX54: =BW54*BP54 -> 2.27 | BY54: =IFERROR(BU54/BX54,0) -> 25030.626 | CA54: RECORD | CB54: =COUNTA(I54:AM54) -> 1 | CC54: =CB54*BS54*0.8 -> 56819.52 | CD54: =COUNTA(AN54:BO54) -> 0 | CE54: =CD54*BS54*0.8 -> 0 | CF54: =SUM(CC54,CE54)=BU54 -> TRUE
D55: NOVELA 3 | E55: SEG-SEX | F55: 0.875 | G55: 22:00 | H55: 30 | AL55: 1 | AS55: 1 | AZ55: 1 | BP55: =SUM(I55:BO55) -> 3 | BQ55: 231000 | BR55: 0.8 | BS55: =BQ55*(1-BR55) -> 46200 | BT55: =BS55*BP55 -> 138600 | BU55: =BT55*0.8 -> 110880 | BW55: 2.56 | BX55: =BW55*BP55 -> 7.68 | BY55: =IFERROR(BU55/BX55,0) -> 14437.5 | CA55: RECORD | CB55: =COUNTA(I55:AM55) -> 1 | CC55: =CB55*BS55*0.8 -> 36960 | CD55: =COUNTA(AN55:BO55) -> 2 | CE55: =CD55*BS55*0.8 -> 73920 | CF55: =SUM(CC55,CE55)=BU55 -> TRUE
D56: NOVELA 3 | E56: SEG-SEX | F56: 0.875 | G56: 22:00 | H56: 60 | AE56: 1 | BP56: =SUM(I56:BO56) -> 1 | BQ56: 462000 | BR56: 0.8 | BS56: =BQ56*(1-BR56) -> 92400 | BT56: =BS56*BP56 -> 92400 | BU56: =BT56*0.8 -> 73920 | BW56: 2.56 | BX56: =BW56*BP56 -> 2.56 | BY56: =IFERROR(BU56/BX56,0) -> 28875 | CA56: RECORD | CB56: =COUNTA(I56:AM56) -> 1 | CC56: =CB56*BS56*0.8 -> 73920 | CD56: =COUNTA(AN56:BO56) -> 0 | CE56: =CD56*BS56*0.8 -> 0 | CF56: =SUM(CC56,CE56)=BU56 -> TRUE
D57: NOVELA DA TARDE 1 | E57: SEG-SEX | F57: 0.64583333 | G57: 16:30 | H57: 30 | AH57: 1 | AO57: 1 | AV57: 1 | BP57: =SUM(I57:BO57) -> 3 | BQ57: 64486 | BR57: 0.8 | BS57: =BQ57*(1-BR57) -> 12897.2 | BT57: =BS57*BP57 -> 38691.6 | BU57: =BT57*0.8 -> 30953.28 | BW57: 2.39 | BX57: =BW57*BP57 -> 7.17 | BY57: =IFERROR(BU57/BX57,0) -> 4317.0544 | CA57: RECORD | CB57: =COUNTA(I57:AM57) -> 1 | CC57: =CB57*BS57*0.8 -> 10317.76 | CD57: =COUNTA(AN57:BO57) -> 2 | CE57: =CD57*BS57*0.8 -> 20635.52 | CF57: =SUM(CC57,CE57)=BU57 -> TRUE
CA58: TT | CB58: =SUM(CB46:CB57) -> 11 | CC58: =SUM(CC46:CC57) -> 377121.28 | CD58: =SUM(CD46:CD57) -> 13 | CE58: =SUM(CE46:CE57) -> 302341.28
C59: SBT | D59: ALO VOCE | E59: SEG-SEX | F59: 0.45833333 | G59: 13:45 | H59: 30 | AH59: 1 | BP59: =SUM(I59:BO59) -> 1 | BQ59: 59000 | BR59: 0.75 | BS59: =BQ59*(1-BR59) -> 14750 | BT59: =BS59*BP59 -> 14750 | BU59: =BT59*0.8 -> 11800 | BW59: 1.45 | BX59: =BW59*BP59 -> 1.45 | BY59: =IFERROR(BU59/BX59,0) -> 8137.931 | CA59: SBT | CB59: =COUNTA(I59:AM59) -> 1 | CC59: =CB59*BS59*0.8 -> 11800 | CD59: =COUNTA(AN59:BO59) -> 0 | CE59: =CD59*BS59*0.8 -> 0 | CF59: =SUM(CC59,CE59)=BU59 -> TRUE
D60: DOMINGO LEGAL 1 | E60: DOM | F60: 0.46875 | G60: 15:15 | H60: 30 | BP60: =SUM(I60:BO60) -> 0 | BQ60: 152300 | BR60: 0.75 | BS60: =BQ60*(1-BR60) -> 38075 | BT60: =BS60*BP60 -> 0 | BU60: =BT60*0.8 -> 0 | BW60: 2.99 | BX60: =BW60*BP60 -> 0 | BY60: =IFERROR(BU60/BX60,0) -> 0 | CA60: SBT | CB60: =COUNTA(I60:AM60) -> 0 | CC60: =CB60*BS60*0.8 -> 0 | CD60: =COUNTA(AN60:BO60) -> 0 | CE60: =CD60*BS60*0.8 -> 0 | CF60: =SUM(CC60,CE60)=BU60 -> TRUE
D61: DOMINGO LEGAL 1 | E61: DOM | F61: 0.46875 | G61: 15:15 | H61: 60 | AG61: 1 | BP61: =SUM(I61:BO61) -> 1 | BQ61: 304600 | BR61: 0.75 | BS61: =BQ61*(1-BR61) -> 76150 | BT61: =BS61*BP61 -> 76150 | BU61: =BT61*0.8 -> 60920 | BW61: 2.99 | BX61: =BW61*BP61 -> 2.99 | BY61: =IFERROR(BU61/BX61,0) -> 20374.582 | CA61: SBT | CB61: =COUNTA(I61:AM61) -> 1 | CC61: =CB61*BS61*0.8 -> 60920 | CD61: =COUNTA(AN61:BO61) -> 0 | CE61: =CD61*BS61*0.8 -> 0 | CF61: =SUM(CC61,CE61)=BU61 -> TRUE
D62: NOVELA NOITE | E62: SEG-SEX | F62: 0.875 | G62: 22:15 | H62: 30 | AJ62: 1 | BP62: =SUM(I62:BO62) -> 1 | BQ62: 192000 | BR62: 0.75 | BS62: =BQ62*(1-BR62) -> 48000 | BT62: =BS62*BP62 -> 48000 | BU62: =BT62*0.8 -> 38400 | BW62: 2.14 | BX62: =BW62*BP62 -> 2.14 | BY62: =IFERROR(BU62/BX62,0) -> 17943.925 | CA62: SBT | CB62: =COUNTA(I62:AM62) -> 1 | CC62: =CB62*BS62*0.8 -> 38400 | CD62: =COUNTA(AN62:BO62) -> 0 | CE62: =CD62*BS62*0.8 -> 0 | CF62: =SUM(CC62,CE62)=BU62 -> TRUE
D63: NOVELA NOITE | E63: SEG-SEX | F63: 0.875 | G63: 22:15 | H63: 60 | BP63: =SUM(I63:BO63) -> 0 | BQ63: 384000 | BR63: 0.75 | BS63: =BQ63*(1-BR63) -> 96000 | BT63: =BS63*BP63 -> 0 | BU63: =BT63*0.8 -> 0 | BW63: 2.14 | BX63: =BW63*BP63 -> 0 | BY63: =IFERROR(BU63/BX63,0) -> 0 | CA63: SBT | CB63: =COUNTA(I63:AM63) -> 0 | CC63: =CB63*BS63*0.8 -> 0 | CD63: =COUNTA(AN63:BO63) -> 0 | CE63: =CD63*BS63*0.8 -> 0 | CF63: =SUM(CC63,CE63)=BU63 -> TRUE
D64: NOVELA NOITE 18H | E64: SEG-SEX | F64: 0.73958333 | G64: 18:30 | H64: 30 | AK64: 1 | BP64: =SUM(I64:BO64) -> 1 | BQ64: 98800 | BR64: 0.75 | BS64: =BQ64*(1-BR64) -> 24700 | BT64: =BS64*BP64 -> 24700 | BU64: =BT64*0.8 -> 19760 | BW64: 1.08 | BX64: =BW64*BP64 -> 1.08 | BY64: =IFERROR(BU64/BX64,0) -> 18296.296 | CA64: SBT | CB64: =COUNTA(I64:AM64) -> 1 | CC64: =CB64*BS64*0.8 -> 19760 | CD64: =COUNTA(AN64:BO64) -> 0 | CE64: =CD64*BS64*0.8 -> 0 | CF64: =SUM(CC64,CE64)=BU64 -> TRUE
D65: NOVELA TARDE 14H | E65: SEG-SEX | F65: 0.60416667 | G65: 15:30 | H65: 30 | AJ65: 1 | BP65: =SUM(I65:BO65) -> 1 | BQ65: 94300 | BR65: 0.75 | BS65: =BQ65*(1-BR65) -> 23575 | BT65: =BS65*BP65 -> 23575 | BU65: =BT65*0.8 -> 18860 | BW65: 1.58 | BX65: =BW65*BP65 -> 1.58 | BY65: =IFERROR(BU65/BX65,0) -> 11936.709 | CA65: SBT | CB65: =COUNTA(I65:AM65) -> 1 | CC65: =CB65*BS65*0.8 -> 18860 | CD65: =COUNTA(AN65:BO65) -> 0 | CE65: =CD65*BS65*0.8 -> 0 | CF65: =SUM(CC65,CE65)=BU65 -> TRUE
D66: PRIMEIRO IMPACTO | E66: SEG-SEX | F66: 0.35416667 | G66: 11:00 | H66: 30 | AI66: 1 | BP66: =SUM(I66:BO66) -> 1 | BQ66: 48800 | BR66: 0.75 | BS66: =BQ66*(1-BR66) -> 12200 | BT66: =BS66*BP66 -> 12200 | BU66: =BT66*0.8 -> 9760 | BW66: 1.38 | BX66: =BW66*BP66 -> 1.38 | BY66: =IFERROR(BU66/BX66,0) -> 7072.4638 | CA66: SBT | CB66: =COUNTA(I66:AM66) -> 1 | CC66: =CB66*BS66*0.8 -> 9760 | CD66: =COUNTA(AN66:BO66) -> 0 | CE66: =CD66*BS66*0.8 -> 0 | CF66: =SUM(CC66,CE66)=BU66 -> TRUE
D67: SBT MANHA | E67: SEG-SEX | F67: 0.3125 | G67: 08:30 | H67: 30 | AL67: 1 | BP67: =SUM(I67:BO67) -> 1 | BQ67: 48800 | BR67: 0.75 | BS67: =BQ67*(1-BR67) -> 12200 | BT67: =BS67*BP67 -> 12200 | BU67: =BT67*0.8 -> 9760 | BW67: 1.25 | BX67: =BW67*BP67 -> 1.25 | BY67: =IFERROR(BU67/BX67,0) -> 7808 | CA67: SBT | CB67: =COUNTA(I67:AM67) -> 1 | CC67: =CB67*BS67*0.8 -> 9760 | CD67: =COUNTA(AN67:BO67) -> 0 | CE67: =CD67*BS67*0.8 -> 0 | CF67: =SUM(CC67,CE67)=BU67 -> TRUE
D68: SBT MANHA | E68: SEG-SEX | F68: 0.3125 | G68: 08:30 | H68: 60 | AE68: 1 | BP68: =SUM(I68:BO68) -> 1 | BQ68: 97600 | BR68: 0.75 | BS68: =BQ68*(1-BR68) -> 24400 | BT68: =BS68*BP68 -> 24400 | BU68: =BT68*0.8 -> 19520 | BW68: 1.25 | BX68: =BW68*BP68 -> 1.25 | BY68: =IFERROR(BU68/BX68,0) -> 15616 | CA68: SBT | CB68: =COUNTA(I68:AM68) -> 1 | CC68: =CB68*BS68*0.8 -> 19520 | CD68: =COUNTA(AN68:BO68) -> 0 | CE68: =CD68*BS68*0.8 -> 0 | CF68: =SUM(CC68,CE68)=BU68 -> TRUE
D69: SBT NOTICIAS 1A ED | E69: SEG-SEX | F69: 0.45833333 | G69: 15:00 | H69: 30 | AM69: 1 | BP69: =SUM(I69:BO69) -> 1 | BQ69: 48800 | BR69: 0.75 | BS69: =BQ69*(1-BR69) -> 12200 | BT69: =BS69*BP69 -> 12200 | BU69: =BT69*0.8 -> 9760 | BW69: 1.17 | BX69: =BW69*BP69 -> 1.17 | BY69: =IFERROR(BU69/BX69,0) -> 8341.8803 | CA69: SBT | CB69: =COUNTA(I69:AM69) -> 1 | CC69: =CB69*BS69*0.8 -> 9760 | CD69: =COUNTA(AN69:BO69) -> 0 | CE69: =CD69*BS69*0.8 -> 0 | CF69: =SUM(CC69,CE69)=BU69 -> TRUE
D70: SBT NOTICIAS 1A ED | E70: SEG-SEX | F70: 0.45833333 | G70: 15:00 | H70: 60 | AF70: 1 | BP70: =SUM(I70:BO70) -> 1 | BQ70: 97600 | BR70: 0.75 | BS70: =BQ70*(1-BR70) -> 24400 | BT70: =BS70*BP70 -> 24400 | BU70: =BT70*0.8 -> 19520 | BW70: 1.17 | BX70: =BW70*BP70 -> 1.17 | BY70: =IFERROR(BU70/BX70,0) -> 16683.761 | CA70: SBT | CB70: =COUNTA(I70:AM70) -> 1 | CC70: =CB70*BS70*0.8 -> 19520 | CD70: =COUNTA(AN70:BO70) -> 0 | CE70: =CD70*BS70*0.8 -> 0 | CF70: =SUM(CC70,CE70)=BU70 -> TRUE
D71: ALO VOCE | E71: SEG-SEX | F71: 0.45833333 | G71: 13:45 | H71: 30 | AO71: 1 | AV71: 1 | BP71: =SUM(I71:BO71) -> 2 | BQ71: 59000 | BR71: 0.8333 | BS71: =BQ71*(1-BR71) -> 9835.3 | BT71: =BS71*BP71 -> 19670.6 | BU71: =BT71*0.8 -> 15736.48 | BW71: 1.45 | BX71: =BW71*BP71 -> 2.9 | BY71: =IFERROR(BU71/BX71,0) -> 5426.3724 | CA71: SBT | CB71: =COUNTA(I71:AM71) -> 0 | CC71: =CB71*BS71*0.8 -> 0 | CD71: =COUNTA(AN71:BO71) -> 2 | CE71: =CD71*BS71*0.8 -> 15736.48 | CF71: =SUM(CC71,CE71)=BU71 -> TRUE
D72: DOMINGO LEGAL 1 | E72: DOM | F72: 0.46875 | G72: 15:15 | H72: 30 | AN72: 1 | AU72: 1 | BP72: =SUM(I72:BO72) -> 2 | BQ72: 152300 | BR72: 0.8333 | BS72: =BQ72*(1-BR72) -> 25388.41 | BT72: =BS72*BP72 -> 50776.82 | BU72: =BT72*0.8 -> 40621.456 | BW72: 2.99 | BX72: =BW72*BP72 -> 5.98 | BY72: =IFERROR(BU72/BX72,0) -> 6792.8856 | CA72: SBT | CB72: =COUNTA(I72:AM72) -> 0 | CC72: =CB72*BS72*0.8 -> 0 | CD72: =COUNTA(AN72:BO72) -> 2 | CE72: =CD72*BS72*0.8 -> 40621.456 | CF72: =SUM(CC72,CE72)=BU72 -> TRUE
D73: DOMINGO LEGAL 1 | E73: DOM | F73: 0.46875 | G73: 15:15 | H73: 60 | BP73: =SUM(I73:BO73) -> 0 | BQ73: 304600 | BR73: 0.8333 | BS73: =BQ73*(1-BR73) -> 50776.82 | BT73: =BS73*BP73 -> 0 | BU73: =BT73*0.8 -> 0 | BW73: 2.99 | BX73: =BW73*BP73 -> 0 | BY73: =IFERROR(BU73/BX73,0) -> 0 | CA73: SBT | CB73: =COUNTA(I73:AM73) -> 0 | CC73: =CB73*BS73*0.8 -> 0 | CD73: =COUNTA(AN73:BO73) -> 0 | CE73: =CD73*BS73*0.8 -> 0 | CF73: =SUM(CC73,CE73)=BU73 -> TRUE
D74: NOVELA NOITE | E74: SEG-SEX | F74: 0.875 | G74: 22:15 | H74: 30 | AO74: 1 | AV74: 1 | BP74: =SUM(I74:BO74) -> 2 | BQ74: 192000 | BR74: 0.8333 | BS74: =BQ74*(1-BR74) -> 32006.4 | BT74: =BS74*BP74 -> 64012.8 | BU74: =BT74*0.8 -> 51210.24 | BW74: 2.14 | BX74: =BW74*BP74 -> 4.28 | BY74: =IFERROR(BU74/BX74,0) -> 11965.009 | CA74: SBT | CB74: =COUNTA(I74:AM74) -> 0 | CC74: =CB74*BS74*0.8 -> 0 | CD74: =COUNTA(AN74:BO74) -> 2 | CE74: =CD74*BS74*0.8 -> 51210.24 | CF74: =SUM(CC74,CE74)=BU74 -> TRUE
D75: NOVELA NOITE | E75: SEG-SEX | F75: 0.875 | G75: 22:15 | H75: 60 | BP75: =SUM(I75:BO75) -> 0 | BQ75: 384000 | BR75: 0.8333 | BS75: =BQ75*(1-BR75) -> 64012.8 | BT75: =BS75*BP75 -> 0 | BU75: =BT75*0.8 -> 0 | BW75: 2.14 | BX75: =BW75*BP75 -> 0 | BY75: =IFERROR(BU75/BX75,0) -> 0 | CA75: SBT | CB75: =COUNTA(I75:AM75) -> 0 | CC75: =CB75*BS75*0.8 -> 0 | CD75: =COUNTA(AN75:BO75) -> 0 | CE75: =CD75*BS75*0.8 -> 0 | CF75: =SUM(CC75,CE75)=BU75 -> TRUE
D76: NOVELA NOITE 18H | E76: SEG-SEX | F76: 0.73958333 | G76: 18:30 | H76: 30 | AR76: 1 | AY76: 1 | BP76: =SUM(I76:BO76) -> 2 | BQ76: 98800 | BR76: 0.8333 | BS76: =BQ76*(1-BR76) -> 16469.96 | BT76: =BS76*BP76 -> 32939.92 | BU76: =BT76*0.8 -> 26351.936 | BW76: 1.08 | BX76: =BW76*BP76 -> 2.16 | BY76: =IFERROR(BU76/BX76,0) -> 12199.97 | CA76: SBT | CB76: =COUNTA(I76:AM76) -> 0 | CC76: =CB76*BS76*0.8 -> 0 | CD76: =COUNTA(AN76:BO76) -> 2 | CE76: =CD76*BS76*0.8 -> 26351.936 | CF76: =SUM(CC76,CE76)=BU76 -> TRUE
D77: NOVELA TARDE 14H | E77: SEG-SEX | F77: 0.60416667 | G77: 15:30 | H77: 30 | AQ77: 1 | AX77: 1 | BP77: =SUM(I77:BO77) -> 2 | BQ77: 94300 | BR77: 0.8333 | BS77: =BQ77*(1-BR77) -> 15719.81 | BT77: =BS77*BP77 -> 31439.62 | BU77: =BT77*0.8 -> 25151.696 | BW77: 1.58 | BX77: =BW77*BP77 -> 3.16 | BY77: =IFERROR(BU77/BX77,0) -> 7959.3975 | CA77: SBT | CB77: =COUNTA(I77:AM77) -> 0 | CC77: =CB77*BS77*0.8 -> 0 | CD77: =COUNTA(AN77:BO77) -> 2 | CE77: =CD77*BS77*0.8 -> 25151.696 | CF77: =SUM(CC77,CE77)=BU77 -> TRUE
D78: PRIMEIRO IMPACTO | E78: SEG-SEX | F78: 0.35416667 | G78: 11:00 | H78: 30 | AP78: 1 | AW78: 1 | BP78: =SUM(I78:BO78) -> 2 | BQ78: 48800 | BR78: 0.8333 | BS78: =BQ78*(1-BR78) -> 8134.96 | BT78: =BS78*BP78 -> 16269.92 | BU78: =BT78*0.8 -> 13015.936 | BW78: 1.38 | BX78: =BW78*BP78 -> 2.76 | BY78: =IFERROR(BU78/BX78,0) -> 4715.9188 | CA78: SBT | CB78: =COUNTA(I78:AM78) -> 0 | CC78: =CB78*BS78*0.8 -> 0 | CD78: =COUNTA(AN78:BO78) -> 2 | CE78: =CD78*BS78*0.8 -> 13015.936 | CF78: =SUM(CC78,CE78)=BU78 -> TRUE
D79: SBT MANHA | E79: SEG-SEX | F79: 0.3125 | G79: 08:30 | H79: 30 | AS79: 1 | AZ79: 1 | BP79: =SUM(I79:BO79) -> 2 | BQ79: 48800 | BR79: 0.8333 | BS79: =BQ79*(1-BR79) -> 8134.96 | BT79: =BS79*BP79 -> 16269.92 | BU79: =BT79*0.8 -> 13015.936 | BW79: 1.25 | BX79: =BW79*BP79 -> 2.5 | BY79: =IFERROR(BU79/BX79,0) -> 5206.3744 | CA79: SBT | CB79: =COUNTA(I79:AM79) -> 0 | CC79: =CB79*BS79*0.8 -> 0 | CD79: =COUNTA(AN79:BO79) -> 2 | CE79: =CD79*BS79*0.8 -> 13015.936 | CF79: =SUM(CC79,CE79)=BU79 -> TRUE
D80: SBT MANHA | E80: SEG-SEX | F80: 0.3125 | G80: 08:30 | H80: 60 | BP80: =SUM(I80:BO80) -> 0 | BQ80: 97600 | BR80: 0.8333 | BS80: =BQ80*(1-BR80) -> 16269.92 | BT80: =BS80*BP80 -> 0 | BU80: =BT80*0.8 -> 0 | BW80: 1.25 | BX80: =BW80*BP80 -> 0 | BY80: =IFERROR(BU80/BX80,0) -> 0 | CA80: SBT | CB80: =COUNTA(I80:AM80) -> 0 | CC80: =CB80*BS80*0.8 -> 0 | CD80: =COUNTA(AN80:BO80) -> 0 | CE80: =CD80*BS80*0.8 -> 0 | CF80: =SUM(CC80,CE80)=BU80 -> TRUE
D81: SBT NOTICIAS 1A ED | E81: SEG-SEX | F81: 0.45833333 | G81: 15:00 | H81: 30 | AT81: 1 | BP81: =SUM(I81:BO81) -> 1 | BQ81: 48800 | BR81: 0.8333 | BS81: =BQ81*(1-BR81) -> 8134.96 | BT81: =BS81*BP81 -> 8134.96 | BU81: =BT81*0.8 -> 6507.968 | BW81: 1.17 | BX81: =BW81*BP81 -> 1.17 | BY81: =IFERROR(BU81/BX81,0) -> 5562.3658 | CA81: SBT | CB81: =COUNTA(I81:AM81) -> 0 | CC81: =CB81*BS81*0.8 -> 0 | CD81: =COUNTA(AN81:BO81) -> 1 | CE81: =CD81*BS81*0.8 -> 6507.968 | CF81: =SUM(CC81,CE81)=BU81 -> TRUE
D82: SBT NOTICIAS 1A ED | E82: SEG-SEX | F82: 0.45833333 | G82: 15:00 | H82: 60 | BP82: =SUM(I82:BO82) -> 0 | BQ82: 97600 | BR82: 0.8333 | BS82: =BQ82*(1-BR82) -> 16269.92 | BT82: =BS82*BP82 -> 0 | BU82: =BT82*0.8 -> 0 | BW82: 1.17 | BX82: =BW82*BP82 -> 0 | BY82: =IFERROR(BU82/BX82,0) -> 0 | CA82: SBT | CB82: =COUNTA(I82:AM82) -> 0 | CC82: =CB82*BS82*0.8 -> 0 | CD82: =COUNTA(AN82:BO82) -> 0 | CE82: =CD82*BS82*0.8 -> 0 | CF82: =SUM(CC82,CE82)=BU82 -> TRUE
CA83: TT | CB83: =SUM(CB59:CB82) -> 10 | CC83: =SUM(CC59:CC82) -> 218060 | CD83: =SUM(CD59:CD82) -> 15 | CE83: =SUM(CE59:CE82) -> 191611.65
C84: REDE TV | D84: A TARDE E SUA | E84: SEG-SEX | F84: 0.625 | G84: 17:00 | H84: 30 | AL84: 1 | AS84: 1 | AZ84: 1 | BP84: =SUM(I84:BO84) -> 3 | BQ84: 43446 | BR84: 0.85 | BS84: =BQ84*(1-BR84) -> 6516.9 | BT84: =BS84*BP84 -> 19550.7 | BU84: =BT84*0.8 -> 15640.56 | BW84: 0.44 | BX84: =BW84*BP84 -> 1.32 | BY84: =IFERROR(BU84/BX84,0) -> 11848.909 | CA84: REDE TV | CB84: =COUNTA(I84:AM84) -> 1 | CC84: =CB84*BS84*0.8 -> 5213.52 | CD84: =COUNTA(AN84:BO84) -> 2 | CE84: =CD84*BS84*0.8 -> 10427.04 | CF84: =SUM(CC84,CE84)=BU84 -> TRUE
D85: A TARDE E SUA | E85: SEG-SEX | F85: 0.625 | G85: 17:00 | H85: 60 | AE85: 1 | BP85: =SUM(I85:BO85) -> 1 | BQ85: 86892 | BR85: 0.85 | BS85: =BQ85*(1-BR85) -> 13033.8 | BT85: =BS85*BP85 -> 13033.8 | BU85: =BT85*0.8 -> 10427.04 | BW85: 0.44 | BX85: =BW85*BP85 -> 0.44 | BY85: =IFERROR(BU85/BX85,0) -> 23697.818 | CA85: REDE TV | CB85: =COUNTA(I85:AM85) -> 1 | CC85: =CB85*BS85*0.8 -> 10427.04 | CD85: =COUNTA(AN85:BO85) -> 0 | CE85: =CD85*BS85*0.8 -> 0 | CF85: =SUM(CC85,CE85)=BU85 -> TRUE
D86: FICA COM A GENTE | E86: SEG-SEX | F86: 0.44791667 | G86: 12:00 | H86: 30 | AJ86: 1 | AQ86: 1 | AX86: 1 | BP86: =SUM(I86:BO86) -> 3 | BQ86: 52743 | BR86: 0.85 | BS86: =BQ86*(1-BR86) -> 7911.45 | BT86: =BS86*BP86 -> 23734.35 | BU86: =BT86*0.8 -> 18987.48 | BW86: 0.1 | BX86: =BW86*BP86 -> 0.3 | BY86: =IFERROR(BU86/BX86,0) -> 63291.6 | CA86: REDE TV | CB86: =COUNTA(I86:AM86) -> 1 | CC86: =CB86*BS86*0.8 -> 6329.16 | CD86: =COUNTA(AN86:BO86) -> 2 | CE86: =CD86*BS86*0.8 -> 12658.32 | CF86: =SUM(CC86,CE86)=BU86 -> TRUE
D87: LEITURA DINAMICA | E87: SEG-SEX | F87: 0.020833333 | G87: 01:00 | H87: 30 | AI87: 1 | AK87: 1 | AO87: 1 | AR87: 1 | AV87: 1 | AY87: 1 | BP87: =SUM(I87:BO87) -> 6 | BQ87: 37063 | BR87: 0.85 | BS87: =BQ87*(1-BR87) -> 5559.45 | BT87: =BS87*BP87 -> 33356.7 | BU87: =BT87*0.8 -> 26685.36 | BW87: 0.14 | BX87: =BW87*BP87 -> 0.84 | BY87: =IFERROR(BU87/BX87,0) -> 31768.286 | CA87: REDE TV | CB87: =COUNTA(I87:AM87) -> 2 | CC87: =CB87*BS87*0.8 -> 8895.12 | CD87: =COUNTA(AN87:BO87) -> 4 | CE87: =CD87*BS87*0.8 -> 17790.24 | CF87: =SUM(CC87,CE87)=BU87 -> TRUE
D88: LEITURA DINAMICA | E88: SEG-SEX | F88: 0.020833333 | G88: 01:00 | H88: 60 | AE88: 1 | BP88: =SUM(I88:BO88) -> 1 | BQ88: 74126 | BR88: 0.85 | BS88: =BQ88*(1-BR88) -> 11118.9 | BT88: =BS88*BP88 -> 11118.9 | BU88: =BT88*0.8 -> 8895.12 | BW88: 0.14 | BX88: =BW88*BP88 -> 0.14 | BY88: =IFERROR(BU88/BX88,0) -> 63536.571 | CA88: REDE TV | CB88: =COUNTA(I88:AM88) -> 1 | CC88: =CB88*BS88*0.8 -> 8895.12 | CD88: =COUNTA(AN88:BO88) -> 0 | CE88: =CD88*BS88*0.8 -> 0 | CF88: =SUM(CC88,CE88)=BU88 -> TRUE
D89: MANHA COM VOCE | E89: SEG-SEX | F89: 0.41666667 | G89: 10:45 | H89: 30 | BP89: =SUM(I89:BO89) -> 0 | BQ89: 40707 | BR89: 0.85 | BS89: =BQ89*(1-BR89) -> 6106.05 | BT89: =BS89*BP89 -> 0 | BU89: =BT89*0.8 -> 0 | BW89: 0.1 | BX89: =BW89*BP89 -> 0 | BY89: =IFERROR(BU89/BX89,0) -> 0 | CA89: REDE TV | CB89: =COUNTA(I89:AM89) -> 0 | CC89: =CB89*BS89*0.8 -> 0 | CD89: =COUNTA(AN89:BO89) -> 0 | CE89: =CD89*BS89*0.8 -> 0 | CF89: =SUM(CC89,CE89)=BU89 -> TRUE
CA90: TT | CB90: =SUM(CB84:CB89) -> 6 | CC90: =SUM(CC84:CC89) -> 39759.96 | CD90: =SUM(CD84:CD89) -> 8 | CE90: =SUM(CE84:CE89) -> 40875.6
C91: CULTURA | D91: AGROCULTURA MAT | E91: DOM | F91: 0.41666667 | G91: 10:30 | H91: 30 | AN91: 1 | AU91: 1 | BP91: =SUM(I91:BO91) -> 2 | BQ91: 11300 | BR91: 0.88 | BS91: =BQ91*(1-BR91) -> 1356 | BT91: =BS91*BP91 -> 2712 | BU91: =BT91*0.8 -> 2169.6 | BW91: 0.1 | BX91: =BW91*BP91 -> 0.2 | BY91: =IFERROR(BU91/BX91,0) -> 10848 | CA91: CULTURA | CB91: =COUNTA(I91:AM91) -> 0 | CC91: =CB91*BS91*0.8 -> 0 | CD91: =COUNTA(AN91:BO91) -> 2 | CE91: =CD91*BS91*0.8 -> 2169.6 | CF91: =SUM(CC91,CE91)=BU91 -> TRUE
D92: AGROCULTURA MAT | E92: DOM | F92: 0.41666667 | G92: 10:30 | H92: 60 | AG92: 1 | BP92: =SUM(I92:BO92) -> 1 | BQ92: 22600 | BR92: 0.88 | BS92: =BQ92*(1-BR92) -> 2712 | BT92: =BS92*BP92 -> 2712 | BU92: =BT92*0.8 -> 2169.6 | BW92: 0.1 | BX92: =BW92*BP92 -> 0.1 | BY92: =IFERROR(BU92/BX92,0) -> 21696 | CA92: CULTURA | CB92: =COUNTA(I92:AM92) -> 1 | CC92: =CB92*BS92*0.8 -> 2169.6 | CD92: =COUNTA(AN92:BO92) -> 0 | CE92: =CD92*BS92*0.8 -> 0 | CF92: =SUM(CC92,CE92)=BU92 -> TRUE
D93: ARENA DOS SABERES | E93: QUI | F93: 0.83333333 | G93: 21:00 | H93: 30 | AK93: 1 | AR93: 1 | AY93: 1 | BP93: =SUM(I93:BO93) -> 3 | BQ93: 15600 | BR93: 0.88 | BS93: =BQ93*(1-BR93) -> 1872 | BT93: =BS93*BP93 -> 5616 | BU93: =BT93*0.8 -> 4492.8 | BW93: 0.18 | BX93: =BW93*BP93 -> 0.54 | BY93: =IFERROR(BU93/BX93,0) -> 8320 | CA93: CULTURA | CB93: =COUNTA(I93:AM93) -> 1 | CC93: =CB93*BS93*0.8 -> 1497.6 | CD93: =COUNTA(AN93:BO93) -> 2 | CE93: =CD93*BS93*0.8 -> 2995.2 | CF93: =SUM(CC93,CE93)=BU93 -> TRUE
D94: ARENA DOS SABERES | E94: QUI | F94: 0.83333333 | G94: 21:00 | H94: 60 | BP94: =SUM(I94:BO94) -> 0 | BQ94: 31200 | BR94: 0.88 | BS94: =BQ94*(1-BR94) -> 3744 | BT94: =BS94*BP94 -> 0 | BU94: =BT94*0.8 -> 0 | BW94: 0.18 | BX94: =BW94*BP94 -> 0 | BY94: =IFERROR(BU94/BX94,0) -> 0 | CA94: CULTURA | CB94: =COUNTA(I94:AM94) -> 0 | CC94: =CB94*BS94*0.8 -> 0 | CD94: =COUNTA(AN94:BO94) -> 0 | CE94: =CD94*BS94*0.8 -> 0 | CF94: =SUM(CC94,CE94)=BU94 -> TRUE
D95: ENTRELINHAS | E95: SEX | F95: 0.83333333 | G95: 20:30 | H95: 30 | AL95: 1 | AS95: 1 | AZ95: 1 | BP95: =SUM(I95:BO95) -> 3 | BQ95: 15600 | BR95: 0.88 | BS95: =BQ95*(1-BR95) -> 1872 | BT95: =BS95*BP95 -> 5616 | BU95: =BT95*0.8 -> 4492.8 | BW95: 0.11 | BX95: =BW95*BP95 -> 0.33 | BY95: =IFERROR(BU95/BX95,0) -> 13614.545 | CA95: CULTURA | CB95: =COUNTA(I95:AM95) -> 1 | CC95: =CB95*BS95*0.8 -> 1497.6 | CD95: =COUNTA(AN95:BO95) -> 2 | CE95: =CD95*BS95*0.8 -> 2995.2 | CF95: =SUM(CC95,CE95)=BU95 -> TRUE
D96: ENTRELINHAS | E96: SEX | F96: 0.83333333 | G96: 20:30 | H96: 60 | AE96: 1 | BP96: =SUM(I96:BO96) -> 1 | BQ96: 31200 | BR96: 0.88 | BS96: =BQ96*(1-BR96) -> 3744 | BT96: =BS96*BP96 -> 3744 | BU96: =BT96*0.8 -> 2995.2 | BW96: 0.11 | BX96: =BW96*BP96 -> 0.11 | BY96: =IFERROR(BU96/BX96,0) -> 27229.091 | CA96: CULTURA | CB96: =COUNTA(I96:AM96) -> 1 | CC96: =CB96*BS96*0.8 -> 2995.2 | CD96: =COUNTA(AN96:BO96) -> 0 | CE96: =CD96*BS96*0.8 -> 0 | CF96: =SUM(CC96,CE96)=BU96 -> TRUE
D97: METROPOLIS NOT | E97: SEG | F97: 0.95833333 | G97: 23:30 | H97: 30 | AJ97: 1 | AQ97: 1 | AX97: 1 | BP97: =SUM(I97:BO97) -> 3 | BQ97: 7200 | BR97: 0.88 | BS97: =BQ97*(1-BR97) -> 864 | BT97: =BS97*BP97 -> 2592 | BU97: =BT97*0.8 -> 2073.6 | BW97: 0.18 | BX97: =BW97*BP97 -> 0.54 | BY97: =IFERROR(BU97/BX97,0) -> 3840 | CA97: CULTURA | CB97: =COUNTA(I97:AM97) -> 1 | CC97: =CB97*BS97*0.8 -> 691.2 | CD97: =COUNTA(AN97:BO97) -> 2 | CE97: =CD97*BS97*0.8 -> 1382.4 | CF97: =SUM(CC97,CE97)=BU97 -> TRUE
D98: OPINIAO | E98: SEX | F98: 0.85416667 | G98: 21:00 | H98: 30 | AL98: 1 | AS98: 1 | AZ98: 1 | BP98: =SUM(I98:BO98) -> 3 | BQ98: 16800 | BR98: 0.88 | BS98: =BQ98*(1-BR98) -> 2016 | BT98: =BS98*BP98 -> 6048 | BU98: =BT98*0.8 -> 4838.4 | BW98: 0.1 | BX98: =BW98*BP98 -> 0.3 | BY98: =IFERROR(BU98/BX98,0) -> 16128 | CA98: CULTURA | CB98: =COUNTA(I98:AM98) -> 1 | CC98: =CB98*BS98*0.8 -> 1612.8 | CD98: =COUNTA(AN98:BO98) -> 2 | CE98: =CD98*BS98*0.8 -> 3225.6 | CF98: =SUM(CC98,CE98)=BU98 -> TRUE
D99: OPINIAO | E99: SEX | F99: 0.85416667 | G99: 21:00 | H99: 60 | AE99: 1 | BP99: =SUM(I99:BO99) -> 1 | BQ99: 33600 | BR99: 0.88 | BS99: =BQ99*(1-BR99) -> 4032 | BT99: =BS99*BP99 -> 4032 | BU99: =BT99*0.8 -> 3225.6 | BW99: 0.1 | BX99: =BW99*BP99 -> 0.1 | BY99: =IFERROR(BU99/BX99,0) -> 32256 | CA99: CULTURA | CB99: =COUNTA(I99:AM99) -> 1 | CC99: =CB99*BS99*0.8 -> 3225.6 | CD99: =COUNTA(AN99:BO99) -> 0 | CE99: =CD99*BS99*0.8 -> 0 | CF99: =SUM(CC99,CE99)=BU99 -> TRUE
CA100: TT | CB100: =SUM(CB91:CB99) -> 7 | CC100: =SUM(CC91:CC99) -> 13689.6 | CD100: =SUM(CD91:CD99) -> 10 | CE100: =SUM(CE91:CE99) -> 12768
C101: GAZETA | D101: GAZETA ESPORTIVA | E101: SEG-SEX | F101: 0.75 | G101: 19:00 | H101: 30 | AL101: 1 | AS101: 1 | AZ101: 1 | BP101: =SUM(I101:BO101) -> 3 | BQ101: 24948 | BR101: 0.85 | BS101: =BQ101*(1-BR101) -> 3742.2 | BT101: =BS101*BP101 -> 11226.6 | BU101: =BT101*0.8 -> 8981.28 | BW101: 0.38 | BX101: =BW101*BP101 -> 1.14 | BY101: =IFERROR(BU101/BX101,0) -> 7878.3158 | CA101: GAZETA | CB101: =COUNTA(I101:AM101) -> 1 | CC101: =CB101*BS101*0.8 -> 2993.76 | CD101: =COUNTA(AN101:BO101) -> 2 | CE101: =CD101*BS101*0.8 -> 5987.52 | CF101: =SUM(CC101,CE101)=BU101 -> TRUE
D102: GAZETA ESPORTIVA | E102: SEG-SEX | F102: 0.75 | G102: 19:00 | H102: 60 | AE102: 1 | BP102: =SUM(I102:BO102) -> 1 | BQ102: =BQ101*2 -> 49896 | BR102: 0.85 | BS102: =BQ102*(1-BR102) -> 7484.4 | BT102: =BS102*BP102 -> 7484.4 | BU102: =BT102*0.8 -> 5987.52 | BW102: 0.38 | BX102: =BW102*BP102 -> 0.38 | BY102: =IFERROR(BU102/BX102,0) -> 15756.632 | CA102: GAZETA | CB102: =COUNTA(I102:AM102) -> 1 | CC102: =CB102*BS102*0.8 -> 5987.52 | CD102: =COUNTA(AN102:BO102) -> 0 | CE102: =CD102*BS102*0.8 -> 0 | CF102: =SUM(CC102,CE102)=BU102 -> TRUE
D103: MULHERES | E103: SEG-SEX | F103: 0.60416667 | G103: 18:00 | H103: 30 | AK103: 1 | AR103: 1 | BP103: =SUM(I103:BO103) -> 2 | BQ103: 14364 | BR103: 0.85 | BS103: =BQ103*(1-BR103) -> 2154.6 | BT103: =BS103*BP103 -> 4309.2 | BU103: =BT103*0.8 -> 3447.36 | BW103: 0.18 | BX103: =BW103*BP103 -> 0.36 | BY103: =IFERROR(BU103/BX103,0) -> 9576 | CA103: GAZETA | CB103: =COUNTA(I103:AM103) -> 1 | CC103: =CB103*BS103*0.8 -> 1723.68 | CD103: =COUNTA(AN103:BO103) -> 1 | CE103: =CD103*BS103*0.8 -> 1723.68 | CF103: =SUM(CC103,CE103)=BU103 -> TRUE
D104: VOCE BONITA | E104: SEG-SEX | F104: 0.54166667 | G104: 14:30 | H104: 30 | AH104: 1 | AQ104: 1 | AV104: 1 | BP104: =SUM(I104:BO104) -> 3 | BQ104: 6048 | BR104: 0.85 | BS104: =BQ104*(1-BR104) -> 907.2 | BT104: =BS104*BP104 -> 2721.6 | BU104: =BT104*0.8 -> 2177.28 | BW104: 0.1 | BX104: =BW104*BP104 -> 0.3 | BY104: =IFERROR(BU104/BX104,0) -> 7257.6 | CA104: GAZETA | CB104: =COUNTA(I104:AM104) -> 1 | CC104: =CB104*BS104*0.8 -> 725.76 | CD104: =COUNTA(AN104:BO104) -> 2 | CE104: =CD104*BS104*0.8 -> 1451.52 | CF104: =SUM(CC104,CE104)=BU104 -> TRUE
D105: VOCE BONITA | E105: SEG-SEX | F105: 0.54166667 | G105: 14:30 | H105: 60 | AE105: 1 | BP105: =SUM(I105:BO105) -> 1 | BQ105: =BQ104*2 -> 12096 | BR105: 0.85 | BS105: =BQ105*(1-BR105) -> 1814.4 | BT105: =BS105*BP105 -> 1814.4 | BU105: =BT105*0.8 -> 1451.52 | BW105: 0.1 | BX105: =BW105*BP105 -> 0.1 | BY105: =IFERROR(BU105/BX105,0) -> 14515.2 | CA105: GAZETA | CB105: =COUNTA(I105:AM105) -> 1 | CC105: =CB105*BS105*0.8 -> 1451.52 | CD105: =COUNTA(AN105:BO105) -> 0 | CE105: =CD105*BS105*0.8 -> 0 | CF105: =SUM(CC105,CE105)=BU105 -> TRUE
CA106: TT | CB106: =SUM(CB101:CB105) -> 5 | CC106: =SUM(CC101:CC105) -> 12882.24 | CD106: =SUM(CD101:CD105) -> 5 | CE106: =SUM(CE101:CE105) -> 9162.72
B108: TT OPEN TV | I108: =COUNTA(I12:I23) -> 0 | J108: =COUNTA(J12:J23) -> 0 | K108: =COUNTA(K12:K23) -> 0 | L108: =COUNTA(L12:L23) -> 0 | M108: =COUNTA(M12:M23) -> 0 | N108: =SUM(N12:N23) -> 0 | O108: =SUM(O12:O23) -> 0 | P108: =SUM(P12:P23) -> 0 | Q108: =SUM(Q12:Q106) -> 0 | R108: =SUM(R12:R106) -> 0 | S108: =SUM(S12:S106) -> 0 | T108: =SUM(T12:T106) -> 0 | U108: =SUM(U12:U106) -> 0 | V108: =SUM(V12:V106) -> 0 | W108: =SUM(W12:W106) -> 0 | X108: =SUM(X12:X106) -> 0 | ... AE108: =SUM(AE12:AE106) -> 15 | AF108: =SUM(AF13:AF107) -> 3 | AG108: =SUM(AG13:AG107) -> 5 | AH108: =SUM(AH12:AH23) -> 1 | AI108: =SUM(AI12:AI23) -> 0 | AJ108: =SUM(AJ12:AJ23) -> 1 | AK108: =SUM(AK12:AK23) -> 1 | AL108: =SUM(AL12:AL23) -> 0 | AM108: =SUM(AM12:AM23) -> 0 | AN108: =COUNTA(AN12:AN23) -> 0 | AO108: =COUNTA(AO12:AO23) -> 2 | AP108: =COUNTA(AP12:AP23) -> 1 | AQ108: =COUNTA(AQ12:AQ23) -> 2 | AR108: =COUNTA(AR12:AR23) -> 2 | AS108: =SUM(AS12:AS23) -> 1 | AT108: =SUM(AT12:AT23) -> 0 | AU108: =SUM(AU12:AU23) -> 1 | AV108: =SUM(AV12:AV106) -> 8 | AW108: =SUM(AW12:AW106) -> 5 | AX108: =SUM(AX12:AX106) -> 6 | AY108: =SUM(AY12:AY106) -> 7 | AZ108: =SUM(AZ12:AZ106) -> 8 | BA108: =SUM(BA12:BA106) -> 0 | BB108: =SUM(BB12:BB106) -> 0 | BC108: =SUM(BC12:BC106) -> 0 | ... BJ108: =SUM(BJ12:BJ106) -> 0 | BK108: =SUM(BK13:BK107) -> 0 | BL108: =SUM(BL13:BL107) -> 0 | BM108: =SUM(BM12:BM23) -> 0 | BN108: =SUM(BN12:BN23) -> 0 | BO108: =SUM(BO12:BO23) -> 0 | BP108: =SUM(BP13:BP106) -> 138 | BT108: =SUM(BT13:BT106) -> 3976878.2 | BU108: =SUM(BU13:BU106) -> 3181502.6 | BX108: =SUM(BX12:BX106) -> 350.61 | BY108: =BU108/BX108 -> 9074.1923 | CA108: TT GERAL | CB108: =CB33+CB45+CB58+CB106+CB100+CB90+CB83 -> 60 | CC108: =CC33+CC45+CC58+CC106+CC100+CC90+CC83 -> 2154704.4 | CD108: =CD33+CD45+CD58+CD106+CD100+CD90+CD83 -> 78 | CE108: =CE33+CE45+CE58+CE106+CE100+CE90+CE83 -> 1026798.1
BT109: UTILIZAÇÃO DE PACOTE | BU109: =SUM(BU59:BU89) -> 490307.21
B110: DETALHE | BT110: TOTAL FATURÁVEL | BU110: =BU108-BU109 -> 2691195.4 | BW110: TARGET AS ABCDE 25+ (14MM) | BY110: SP1: | CD110: TT | CE110: =CC108+CE108 -> 3181502.6
B111: EMISSORA | C111: INSERÇÕES | D111: INVESTIMENTO | E111: TRP | F111: % AUDIÊNCIA | G111: % INVESTIMENTO | BW111: COBERTURA | BX111: 0.52 | BY111: 14277800 | CE111: =CE110=BU108 -> TRUE
...

Sheet TV ABERTA - SPE
B5: CLIENT: SABESP
B6: CAMPAING: ESCASSEZ HIDRICA - CRÍTICO
BW7: PLANNED
B8: MARKET | C8: CHANNEL | D8: PROGRAMM | E8: DAY | F8: START TIME | G8: END TIME | H8: SEC | I8: JANEIRO | BP8: INS. | BQ8: CUSTO TABELA UNITÁRIO (BRUTO) | BR8: DESC. % | BS8: CUSTO NEGOCIADO UNITÁRIO (BRUTO) | BT8: CUSTO TOTAL NEGOCIADO (BRUTO) | BU8: CUSTO TOTAL DESEMBOLSO SABESP | BW8: AUD. AS ABCDE 25+ | BX8: TRP | BY8: CPP | CA8: RESUMO
I9: T | J9: F | K9: S | L9: S | M9: M | N9: T | O9: W | P9: T | Q9: F | R9: S | S9: S | T9: M | U9: T | V9: W | W9: T | X9: F | Y9: S | Z9: S | AA9: M | AB9: T | AC9: W | AD9: T | AE9: F | AF9: S | AG9: S | AH9: M | AI9: T | AJ9: W | AK9: T | AL9: F | AM9: S | AN9: S | AO9: M | AP9: T | AQ9: W | AR9: T | AS9: F | AT9: S | AU9: S | AV9: M | AW9: T | AX9: W | AY9: T | AZ9: F | BA9: S | BB9: S | BC9: M | BD9: T | BE9: W | BF9: T | BG9: F | BH9: S | BI9: S | BJ9: M | BK9: T | BL9: W | BM9: T | BN9: F | BO9: S
I10: 1 | J10: 2 | K10: 3 | L10: 4 | M10: 5 | N10: 6 | O10: 7 | P10: 8 | Q10: 9 | R10: 10 | S10: 11 | T10: 12 | U10: 13 | V10: 14 | W10: 15 | X10: 16 | Y10: 17 | Z10: =Y10+1 -> 18 | AA10: =Z10+1 -> 19 | AB10: =AA10+1 -> 20 | AC10: =AB10+1 -> 21 | AD10: =AC10+1 -> 22 | AE10: =AD10+1 -> 23 | AF10: =AE10+1 -> 24 | AG10: =AF10+1 -> 25 | ... AM10: =AL10+1 -> 31 | AN10: 1 | AO10: 2 | AP10: 3 | AQ10: 4 | AR10: 5 | AS10: 6 | AT10: 7 | AU10: 8 | AV10: 9 | AW10: 10 | AX10: 11 | AY10: 12 | AZ10: 13 | BA10: 14 | BB10: 15 | BC10: 16 | BD10: 17 | BE10: =BD10+1 -> 18 | BF10: =BE10+1 -> 19 | BG10: =BF10+1 -> 20 | BH10: =BG10+1 -> 21 | BI10: =BH10+1 -> 22 | BJ10: =BI10+1 -> 23 | BK10: =BJ10+1 -> 24 | BL10: =BK10+1 -> 25 | ... BO10: =BN10+1 -> 28 | CA10: CHANNEL | CB10: JANEIRO | CD10: FEVEREIRO
CB12: INS | CC12: INVESTIMENTO $ | CD12: INS | CE12: INVESTIMENTO $
B13: SÃO PAULO ESTADO | C13: TV GLOBO | D13: NOVELA II | E13: SEG-SEX | F13: 0.81944444 | G13: 0.85416667 | H13: 30 | AJ13: 1 | BP13: =SUM(I13:BO13) -> 1 | BQ13: 217403 | BR13: 1 | BS13: =BQ13*(1-BR13) -> 0 | BT13: =BS13*BP13 -> 0 | BU13: =BT13*0.8 -> 0 | BW13: 12.33 | BX13: =BW13*BP13 -> 12.33 | BY13: =IFERROR(BU13/BX13,0) -> 0 | CA13: TV GLOBO | CB13: =COUNTA(I13:AM13) -> 1 | CC13: =CB13*BS13*0.8 -> 0 | CD13: =COUNTA(AN13:BO13) -> 0 | CE13: =CD13*BS13*0.8 -> 0 | CF13: =SUM(CC13,CE13)=BU13 -> TRUE
D14: NOVELA III | E14: SEG-SEX | F14: 0.88888889 | G14: 0.93402778 | H14: 30 | AH14: 1 | AK14: 1 | BP14: =SUM(I14:BO14) -> 2 | BQ14: 318624 | BR14: 0 | BS14: =BQ14*(1-BR14) -> 318624 | BT14: =BS14*BP14 -> 637248 | BU14: =BT14*0.8 -> 509798.4 | BW14: 13.35 | BX14: =BW14*BP14 -> 26.7 | BY14: =IFERROR(BU14/BX14,0) -> 19093.573 | CA14: TV GLOBO | CB14: =COUNTA(I14:AM14) -> 2 | CC14: =CB14*BS14*0.8 -> 509798.4 | CD14: =COUNTA(AN14:BO14) -> 0 | CE14: =CD14*BS14*0.8 -> 0 | CF14: =SUM(CC14,CE14)=BU14 -> TRUE
D16: NOVELA II | E16: SEG-SEX | F16: 0.81944444 | G16: 0.85416667 | H16: 30 | AO16: 1 | AR16: 1 | AW16: 1 | BP16: =SUM(I16:BO16) -> 3 | BQ16: 217403 | BR16: 0 | BS16: =BQ16*(1-BR16) -> 217403 | BT16: =BS16*BP16 -> 652209 | BU16: =BT16*0.8 -> 521767.2 | BW16: 12.33 | BX16: =BW16*BP16 -> 36.99 | BY16: =IFERROR(BU16/BX16,0) -> 14105.629 | CA16: TV GLOBO | CB16: =COUNTA(I16:AM16) -> 0 | CC16: =CB16*BS16*0.8 -> 0 | CD16: =COUNTA(AN16:BO16) -> 3 | CE16: =CD16*BS16*0.8 -> 521767.2 | CF16: =SUM(CC16,CE16)=BU16 -> TRUE
D17: NOVELA I | E17: SEG-SEX | F17: 0.76736111 | G17: 0.79861111 | H17: 30 | AS17: 1 | BP17: =SUM(I17:BO17) -> 1 | BQ17: 163381 | BR17: 1 | BS17: =BQ17*(1-BR17) -> 0 | BT17: =BS17*BP17 -> 0 | BU17: =BT17*0.8 -> 0 | BW17: 8.51 | BX17: =BW17*BP17 -> 8.51 | BY17: =IFERROR(BU17/BX17,0) -> 0 | CA17: TV GLOBO | CB17: =COUNTA(I17:AM17) -> 0 | CC17: =CB17*BS17*0.8 -> 0 | CD17: =COUNTA(AN17:BO17) -> 1 | CE17: =CD17*BS17*0.8 -> 0 | CF17: =SUM(CC17,CE17)=BU17 -> TRUE
D19: JORNAL NACIONAL | E19: SEG-SEX | F19: 0.85416667 | G19: 0.88888889 | H19: 30 | AV19: 1 | BP19: =SUM(I19:BO19) -> 1 | BQ19: 316309 | BR19: 0 | BS19: =BQ19*(1-BR19) -> 316309 | BT19: =BS19*BP19 -> 316309 | BU19: =BT19*0.8 -> 253047.2 | BW19: 13.07 | BX19: =BW19*BP19 -> 13.07 | BY19: =IFERROR(BU19/BX19,0) -> 19360.918 | CA19: TV GLOBO | CB19: =COUNTA(I19:AM19) -> 0 | CC19: =CB19*BS19*0.8 -> 0 | CD19: =COUNTA(AN19:BO19) -> 1 | CE19: =CD19*BS19*0.8 -> 253047.2 | CF19: =SUM(CC19,CE19)=BU19 -> TRUE
D20: FANTASTICO | E20: DOM | F20: 0.85416667 | G20: 0.96527778 | H20: 30 | AU20: 1 | BP20: =SUM(I20:BO20) -> 1 | BQ20: 252044 | BR20: 0 | BS20: =BQ20*(1-BR20) -> 252044 | BT20: =BS20*BP20 -> 252044 | BU20: =BT20*0.8 -> 201635.2 | BW20: 8.8 | BX20: =BW20*BP20 -> 8.8 | BY20: =IFERROR(BU20/BX20,0) -> 22913.091 | CA20: TV GLOBO | CB20: =COUNTA(I20:AM20) -> 0 | CC20: =CB20*BS20*0.8 -> 0 | CD20: =COUNTA(AN20:BO20) -> 1 | CE20: =CD20*BS20*0.8 -> 201635.2 | CF20: =SUM(CC20,CE20)=BU20 -> TRUE
D21: JORNAL DA GLOBO | E21: SEG-SEX | F21: 0.041666667 | G21: 0.076388889 | H21: 30 | AO21: 1 | AQ21: 1 | AW21: 1 | AY21: 1 | BP21: =SUM(I21:BO21) -> 4 | BQ21: 43682 | BR21: 1 | BS21: =BQ21*(1-BR21) -> 0 | BT21: =BS21*BP21 -> 0 | BU21: =BT21*0.8 -> 0 | BW21: 3.7 | BX21: =BW21*BP21 -> 14.8 | BY21: =IFERROR(BU21/BX21,0) -> 0 | CA21: TV GLOBO | CB21: =COUNTA(I21:AM21) -> 0 | CC21: =CB21*BS21*0.8 -> 0 | CD21: =COUNTA(AN21:BO21) -> 4 | CE21: =CD21*BS21*0.8 -> 0 | CF21: =SUM(CC21,CE21)=BU21 -> TRUE
D23: NOVELA I | E23: SEG-SEX | F23: 0.76736111 | G23: 0.79861111 | H23: 30 | AH23: 1 | AK23: 1 | BP23: =SUM(I23:BO23) -> 2 | BQ23: 163381 | BR23: 0 | BS23: =BQ23*(1-BR23) -> 163381 | BT23: =BS23*BP23 -> 326762 | BU23: =BT23*0.8 -> 261409.6 | BW23: 8.51 | BX23: =BW23*BP23 -> 17.02 | BY23: =IFERROR(BU23/BX23,0) -> 15358.966 | CA23: TV GLOBO | CB23: =COUNTA(I23:AM23) -> 2 | CC23: =CB23*BS23*0.8 -> 261409.6 | CD23: =COUNTA(AN23:BO23) -> 0 | CE23: =CD23*BS23*0.8 -> 0 | CF23: =SUM(CC23,CE23)=BU23 -> TRUE
D24: NOVELA II | E24: SEG-SEX | F24: 0.81944444 | G24: 0.85416667 | H24: 30 | AI24: 1 | AL24: 1 | BP24: =SUM(I24:BO24) -> 2 | BQ24: 217403 | BR24: 0 | BS24: =BQ24*(1-BR24) -> 217403 | BT24: =BS24*BP24 -> 434806 | BU24: =BT24*0.8 -> 347844.8 | BW24: 12.33 | BX24: =BW24*BP24 -> 24.66 | BY24: =IFERROR(BU24/BX24,0) -> 14105.629 | CA24: TV GLOBO | CB24: =COUNTA(I24:AM24) -> 2 | CC24: =CB24*BS24*0.8 -> 347844.8 | CD24: =COUNTA(AN24:BO24) -> 0 | CE24: =CD24*BS24*0.8 -> 0 | CF24: =SUM(CC24,CE24)=BU24 -> TRUE
D25: NOVELA I SAB | E25: SÁB | F25: 0.77777778 | G25: 0.80902778 | H25: 30 | AM25: 1 | AT25: 1 | BP25: =SUM(I25:BO25) -> 2 | BQ25: 172884 | BR25: 1 | BS25: =BQ25*(1-BR25) -> 0 | BT25: =BS25*BP25 -> 0 | BU25: =BT25*0.8 -> 0 | BW25: 11.08 | BX25: =BW25*BP25 -> 22.16 | BY25: =IFERROR(BU25/BX25,0) -> 0 | CA25: TV GLOBO | CB25: =COUNTA(I25:AM25) -> 1 | CC25: =CB25*BS25*0.8 -> 0 | CD25: =COUNTA(AN25:BO25) -> 1 | CE25: =CD25*BS25*0.8 -> 0 | CF25: =SUM(CC25,CE25)=BU25 -> TRUE
D27: NOVELA III | E27: SEG-SEX | F27: 0.88888889 | G27: 0.93402778 | H27: 60 | AD27: 1 | BP27: =SUM(I27:BO27) -> 1 | BQ27: =318624*2 -> 637248 | BR27: 0 | BS27: =BQ27*(1-BR27) -> 637248 | BT27: =BS27*BP27 -> 637248 | BU27: =BT27*0.8 -> 509798.4 | BW27: 13.35 | BX27: =BW27*BP27 -> 13.35 | BY27: =IFERROR(BU27/BX27,0) -> 38187.146 | CA27: TV GLOBO | CB27: =COUNTA(I27:AM27) -> 1 | CC27: =CB27*BS27*0.8 -> 509798.4 | CD27: =COUNTA(AN27:BO27) -> 0 | CE27: =CD27*BS27*0.8 -> 0 | CF27: =SUM(CC27,CE27)=BU27 -> TRUE
D28: NOVELA III SAB | E28: SÁB | F28: 0.88888889 | G28: 0.93402778 | H28: 60 | AF28: 1 | BP28: =SUM(I28:BO28) -> 1 | BQ28: =257775*2 -> 515550 | BR28: 0 | BS28: =BQ28*(1-BR28) -> 515550 | BT28: =BS28*BP28 -> 515550 | BU28: =BT28*0.8 -> 412440 | BW28: 11.18 | BX28: =BW28*BP28 -> 11.18 | BY28: =IFERROR(BU28/BX28,0) -> 36890.877 | CA28: TV GLOBO | CB28: =COUNTA(I28:AM28) -> 1 | CC28: =CB28*BS28*0.8 -> 412440 | CD28: =COUNTA(AN28:BO28) -> 0 | CE28: =CD28*BS28*0.8 -> 0 | CF28: =SUM(CC28,CE28)=BU28 -> TRUE
D29: NOVELA II | E29: SEG-SEX | F29: 0.81944444 | G29: 0.85416667 | H29: 60 | AE29: 1 | BP29: =SUM(I29:BO29) -> 1 | BQ29: =217403*2 -> 434806 | BR29: 1 | BS29: =BQ29*(1-BR29) -> 0 | BT29: =BS29*BP29 -> 0 | BU29: =BT29*0.8 -> 0 | BW29: 12.33 | BX29: =BW29*BP29 -> 12.33 | BY29: =IFERROR(BU29/BX29,0) -> 0 | CA29: TV GLOBO | CB29: =COUNTA(I29:AM29) -> 1 | CC29: =CB29*BS29*0.8 -> 0 | CD29: =COUNTA(AN29:BO29) -> 0 | CE29: =CD29*BS29*0.8 -> 0 | CF29: =SUM(CC29,CE29)=BU29 -> TRUE
D31: JORNAL NACIONAL - PRIMEIRISSIMA | E31: SEG-SEX | F31: 0.85416667 | G31: 0.88888889 | H31: 60 | AC31: 1 | BP31: =SUM(I31:BO31) -> 1 | BQ31: =(316309*2)*1.2 -> 759141.6 | BR31: 0.1 | BS31: =BQ31*(1-BR31) -> 683227.44 | BT31: =BS31*BP31 -> 683227.44 | BU31: =BT31*0.8 -> 546581.95 | BW31: 13.07 | BX31: =BW31*BP31 -> 13.07 | BY31: =IFERROR(BU31/BX31,0) -> 41819.583 | CA31: TV GLOBO | CB31: =COUNTA(I31:AM31) -> 1 | CC31: =CB31*BS31*0.8 -> 546581.95 | CD31: =COUNTA(AN31:BO31) -> 0 | CE31: =CD31*BS31*0.8 -> 0 | CF31: =SUM(CC31,CE31)=BU31 -> TRUE
CA32: TT | CB32: =SUM(CB13:CB31) -> 12 | CC32: =SUM(CC13:CC31) -> 2587873.2 | CD32: =SUM(CD13:CD31) -> 11 | CE32: =SUM(CE13:CE31) -> 976449.6
C33: BANDEIRANTES | D33: BORA BRASIL | E33: SEG-SEX | F33: 0.375 | G33: 11:00 | H33: 30 | AK33: 1 | AR33: 1 | AY33: 1 | BP33: =SUM(I33:BO33) -> 3 | BQ33: 18884 | BR33: 0.85 | BS33: =BQ33*(1-BR33) -> 2832.6 | BT33: =BS33*BP33 -> 8497.8 | BU33: =BT33*0.8 -> 6798.24 | BW33: 0.24 | BX33: =BW33*BP33 -> 0.72 | BY33: =IFERROR(BU33/BX33,0) -> 9442 | CA33: BANDEIRANTES | CB33: =COUNTA(I33:AM33) -> 1 | CC33: =CB33*BS33*0.8 -> 2266.08 | CD33: =COUNTA(AN33:BO33) -> 2 | CE33: =CD33*BS33*0.8 -> 4532.16 | CF33: =SUM(CC33,CE33)=BU33 -> TRUE
D34: BORA BRASIL | E34: SEG-SEX | F34: 0.375 | G34: 11:00 | H34: 60 | AD34: 1 | BP34: =SUM(I34:BO34) -> 1 | BQ34: 37768 | BR34: 0.85 | BS34: =BQ34*(1-BR34) -> 5665.2 | BT34: =BS34*BP34 -> 5665.2 | BU34: =BT34*0.8 -> 4532.16 | BW34: 0.24 | BX34: =BW34*BP34 -> 0.24 | BY34: =IFERROR(BU34/BX34,0) -> 18884 | CA34: BANDEIRANTES | CB34: =COUNTA(I34:AM34) -> 1 | CC34: =CB34*BS34*0.8 -> 4532.16 | CD34: =COUNTA(AN34:BO34) -> 0 | CE34: =CD34*BS34*0.8 -> 0 | CF34: =SUM(CC34,CE34)=BU34 -> TRUE
D35: BRASIL URGENTE | E35: SEG-SÁB | F35: 0.66666667 | G35: 17:30 | H35: 30 | AL35: 1 | AS35: 1 | AZ35: 1 | BP35: =SUM(I35:BO35) -> 3 | BQ35: 66878 | BR35: 0.85 | BS35: =BQ35*(1-BR35) -> 10031.7 | BT35: =BS35*BP35 -> 30095.1 | BU35: =BT35*0.8 -> 24076.08 | BW35: 1.43 | BX35: =BW35*BP35 -> 4.29 | BY35: =IFERROR(BU35/BX35,0) -> 5612.1399 | CA35: BANDEIRANTES | CB35: =COUNTA(I35:AM35) -> 1 | CC35: =CB35*BS35*0.8 -> 8025.36 | CD35: =COUNTA(AN35:BO35) -> 2 | CE35: =CD35*BS35*0.8 -> 16050.72 | CF35: =SUM(CC35,CE35)=BU35 -> TRUE
D36: BRASIL URGENTE | E36: SEG-SÁB | F36: 0.66666667 | G36: 17:30 | H36: 60 | AE36: 1 | BP36: =SUM(I36:BO36) -> 1 | BQ36: 133756 | BR36: 0.85 | BS36: =BQ36*(1-BR36) -> 20063.4 | BT36: =BS36*BP36 -> 20063.4 | BU36: =BT36*0.8 -> 16050.72 | BW36: 1.43 | BX36: =BW36*BP36 -> 1.43 | BY36: =IFERROR(BU36/BX36,0) -> 11224.28 | CA36: BANDEIRANTES | CB36: =COUNTA(I36:AM36) -> 1 | CC36: =CB36*BS36*0.8 -> 16050.72 | CD36: =COUNTA(AN36:BO36) -> 0 | CE36: =CD36*BS36*0.8 -> 0 | CF36: =SUM(CC36,CE36)=BU36 -> TRUE
D37: CANAL LIVRE | E37: DOM | F37: 0.95833333 | G37: 00:00 | H37: 30 | AU37: 1 | BP37: =SUM(I37:BO37) -> 1 | BQ37: 34546 | BR37: 0.85 | BS37: =BQ37*(1-BR37) -> 5181.9 | BT37: =BS37*BP37 -> 5181.9 | BU37: =BT37*0.8 -> 4145.52 | BW37: 0.21 | BX37: =BW37*BP37 -> 0.21 | BY37: =IFERROR(BU37/BX37,0) -> 19740.571 | CA37: BANDEIRANTES | CB37: =COUNTA(I37:AM37) -> 0 | CC37: =CB37*BS37*0.8 -> 0 | CD37: =COUNTA(AN37:BO37) -> 1 | CE37: =CD37*BS37*0.8 -> 4145.52 | CF37: =SUM(CC37,CE37)=BU37 -> TRUE
D38: CANAL LIVRE | E38: DOM | F38: 0.95833333 | G38: 00:00 | H38: 60 | AG38: 1 | BP38: =SUM(I38:BO38) -> 1 | BQ38: 69092 | BR38: 0.85 | BS38: =BQ38*(1-BR38) -> 10363.8 | BT38: =BS38*BP38 -> 10363.8 | BU38: =BT38*0.8 -> 8291.04 | BW38: 0.21 | BX38: =BW38*BP38 -> 0.21 | BY38: =IFERROR(BU38/BX38,0) -> 39481.143 | CA38: BANDEIRANTES | CB38: =COUNTA(I38:AM38) -> 1 | CC38: =CB38*BS38*0.8 -> 8291.04 | CD38: =COUNTA(AN38:BO38) -> 0 | CE38: =CD38*BS38*0.8 -> 0 | CF38: =SUM(CC38,CE38)=BU38 -> TRUE
D39: JORNAL DA NOITE | E39: SEG-SEX | F39: 0.010416667 | G39: 01:15 | H39: 30 | AJ39: 1 | AQ39: 1 | AX39: 1 | BP39: =SUM(I39:BO39) -> 3 | BQ39: 36271 | BR39: 0.85 | BS39: =BQ39*(1-BR39) -> 5440.65 | BT39: =BS39*BP39 -> 16321.95 | BU39: =BT39*0.8 -> 13057.56 | BW39: 0.34 | BX39: =BW39*BP39 -> 1.02 | BY39: =IFERROR(BU39/BX39,0) -> 12801.529 | CA39: BANDEIRANTES | CB39: =COUNTA(I39:AM39) -> 1 | CC39: =CB39*BS39*0.8 -> 4352.52 | CD39: =COUNTA(AN39:BO39) -> 2 | CE39: =CD39*BS39*0.8 -> 8705.04 | CF39: =SUM(CC39,CE39)=BU39 -> TRUE
D40: JORNAL DA NOITE | E40: SEG-SEX | F40: 0.010416667 | G40: 01:15 | H40: 60 | AD40: 1 | BP40: =SUM(I40:BO40) -> 1 | BQ40: 72542 | BR40: 0.85 | BS40: =BQ40*(1-BR40) -> 10881.3 | BT40: =BS40*BP40 -> 10881.3 | BU40: =BT40*0.8 -> 8705.04 | BW40: 0.34 | BX40: =BW40*BP40 -> 0.34 | BY40: =IFERROR(BU40/BX40,0) -> 25603.059 | CA40: BANDEIRANTES | CB40: =COUNTA(I40:AM40) -> 1 | CC40: =CB40*BS40*0.8 -> 8705.04 | CD40: =COUNTA(AN40:BO40) -> 0 | CE40: =CD40*BS40*0.8 -> 0 | CF40: =SUM(CC40,CE40)=BU40 -> TRUE
D41: NOVELA I | E41: SEG-SEX | F41: 0.29166667 | G41: 08:00 | H41: 30 | BP41: =SUM(I41:BO41) -> 0 | BQ41: 16564 | BR41: 0.85 | BS41: =BQ41*(1-BR41) -> 2484.6 | BT41: =BS41*BP41 -> 0 | BU41: =BT41*0.8 -> 0 | BW41: 0.1 | BX41: =BW41*BP41 -> 0 | BY41: =IFERROR(BU41/BX41,0) -> 0 | CA41: BANDEIRANTES | CB41: =COUNTA(I41:AM41) -> 0 | CC41: =CB41*BS41*0.8 -> 0 | CD41: =COUNTA(AN41:BO41) -> 0 | CE41: =CD41*BS41*0.8 -> 0 | CF41: =SUM(CC41,CE41)=BU41 -> TRUE
D42: NOVELA II | E42: SEG-SEX | F42: 0.85416667 | G42: 21:25 | H42: 30 | AH42: 1 | AO42: 1 | AV42: 1 | BP42: =SUM(I42:BO42) -> 3 | BQ42: 118356 | BR42: 0.85 | BS42: =BQ42*(1-BR42) -> 17753.4 | BT42: =BS42*BP42 -> 53260.2 | BU42: =BT42*0.8 -> 42608.16 | BW42: 0.71 | BX42: =BW42*BP42 -> 2.13 | BY42: =IFERROR(BU42/BX42,0) -> 20003.831 | CA42: BANDEIRANTES | CB42: =COUNTA(I42:AM42) -> 1 | CC42: =CB42*BS42*0.8 -> 14202.72 | CD42: =COUNTA(AN42:BO42) -> 2 | CE42: =CD42*BS42*0.8 -> 28405.44 | CF42: =SUM(CC42,CE42)=BU42 -> TRUE
D43: NOVELA II | E43: SEG-SEX | F43: 0.85416667 | G43: 21:25 | H43: 60 | AE43: 1 | BP43: =SUM(I43:BO43) -> 1 | BQ43: 236712 | BR43: 0.85 | BS43: =BQ43*(1-BR43) -> 35506.8 | BT43: =BS43*BP43 -> 35506.8 | BU43: =BT43*0.8 -> 28405.44 | BW43: 0.71 | BX43: =BW43*BP43 -> 0.71 | BY43: =IFERROR(BU43/BX43,0) -> 40007.662 | CA43: BANDEIRANTES | CB43: =COUNTA(I43:AM43) -> 1 | CC43: =CB43*BS43*0.8 -> 28405.44 | CD43: =COUNTA(AN43:BO43) -> 0 | CE43: =CD43*BS43*0.8 -> 0 | CF43: =SUM(CC43,CE43)=BU43 -> TRUE
CA44: TT | CB44: =SUM(CB33:CB43) -> 9 | CC44: =SUM(CC33:CC43) -> 94831.08 | CD44: =SUM(CD33:CD43) -> 9 | CE44: =SUM(CE33:CE43) -> 61838.88
C45: RECORD | D45: CIDADE ALERTA 2 SAB | E45: SÁB | F45: 0.875 | G45: 22:30 | H45: 30 | AM45: 1 | AT45: 1 | BA45: 1 | BP45: =SUM(I45:BO45) -> 3 | BQ45: 68258 | BR45: 0.8 | BS45: =BQ45*(1-BR45) -> 13651.6 | BT45: =BS45*BP45 -> 40954.8 | BU45: =BT45*0.8 -> 32763.84 | BW45: 2.19 | BX45: =BW45*BP45 -> 6.57 | BY45: =IFERROR(BU45/BX45,0) -> 4986.8858 | CA45: RECORD | CB45: =COUNTA(I45:AM45) -> 1 | CC45: =CB45*BS45*0.8 -> 10921.28 | CD45: =COUNTA(AN45:BO45) -> 2 | CE45: =CD45*BS45*0.8 -> 21842.56 | CF45: =SUM(CC45,CE45)=BU45 -> TRUE
D46: CIDADE ALERTA 2 SAB | E46: SÁB | F46: 0.875 | G46: 22:30 | H46: 60 | AF46: 1 | BP46: =SUM(I46:BO46) -> 1 | BQ46: 136516 | BR46: 0.8 | BS46: =BQ46*(1-BR46) -> 27303.2 | BT46: =BS46*BP46 -> 27303.2 | BU46: =BT46*0.8 -> 21842.56 | BW46: 2.19 | BX46: =BW46*BP46 -> 2.19 | BY46: =IFERROR(BU46/BX46,0) -> 9973.7717 | CA46: RECORD | CB46: =COUNTA(I46:AM46) -> 1 | CC46: =CB46*BS46*0.8 -> 21842.56 | CD46: =COUNTA(AN46:BO46) -> 0 | CE46: =CD46*BS46*0.8 -> 0 | CF46: =SUM(CC46,CE46)=BU46 -> TRUE
D47: DOMINGO ESPETACULAR | E47: DOM | F47: 0.75 | G47: 20:00 | H47: 30 | AN47: 1 | AU47: 1 | BB47: 1 | BP47: =SUM(I47:BO47) -> 3 | BQ47: 393224 | BR47: 0.8 | BS47: =BQ47*(1-BR47) -> 78644.8 | BT47: =BS47*BP47 -> 235934.4 | BU47: =BT47*0.8 -> 188747.52 | BW47: 3.05 | BX47: =BW47*BP47 -> 9.15 | BY47: =IFERROR(BU47/BX47,0) -> 20628.144 | CA47: RECORD | CB47: =COUNTA(I47:AM47) -> 0 | CC47: =CB47*BS47*0.8 -> 0 | CD47: =COUNTA(AN47:BO47) -> 3 | CE47: =CD47*BS47*0.8 -> 188747.52 | CF47: =SUM(CC47,CE47)=BU47 -> TRUE
D48: DOMINGO ESPETACULAR | E48: DOM | F48: 0.75 | G48: 20:00 | H48: 60 | AG48: 1 | BP48: =SUM(I48:BO48) -> 1 | BQ48: 786448 | BR48: 0.8 | BS48: =BQ48*(1-BR48) -> 157289.6 | BT48: =BS48*BP48 -> 157289.6 | BU48: =BT48*0.8 -> 125831.68 | BW48: 3.05 | BX48: =BW48*BP48 -> 3.05 | BY48: =IFERROR(BU48/BX48,0) -> 41256.289 | CA48: RECORD | CB48: =COUNTA(I48:AM48) -> 1 | CC48: =CB48*BS48*0.8 -> 125831.68 | CD48: =COUNTA(AN48:BO48) -> 0 | CE48: =CD48*BS48*0.8 -> 0 | CF48: =SUM(CC48,CE48)=BU48 -> TRUE
D49: FALA BRASIL | E49: SEG-SEX | F49: 0.35416667 | G49: 09:35 | H49: 30 | AJ49: 1 | AQ49: 1 | AX49: 1 | BP49: =SUM(I49:BO49) -> 3 | BQ49: 88342 | BR49: 0.8 | BS49: =BQ49*(1-BR49) -> 17668.4 | BT49: =BS49*BP49 -> 53005.2 | BU49: =BT49*0.8 -> 42404.16 | BW49: 1.95 | BX49: =BW49*BP49 -> 5.85 | BY49: =IFERROR(BU49/BX49,0) -> 7248.5744 | CA49: RECORD | CB49: =COUNTA(I49:AM49) -> 1 | CC49: =CB49*BS49*0.8 -> 14134.72 | CD49: =COUNTA(AN49:BO49) -> 2 | CE49: =CD49*BS49*0.8 -> 28269.44 | CF49: =SUM(CC49,CE49)=BU49 -> TRUE
D50: FALA BRASIL | E50: SEG-SEX | F50: 0.35416667 | G50: 09:35 | H50: 60 | AE50: 1 | BP50: =SUM(I50:BO50) -> 1 | BQ50: 176684 | BR50: 0.8 | BS50: =BQ50*(1-BR50) -> 35336.8 | BT50: =BS50*BP50 -> 35336.8 | BU50: =BT50*0.8 -> 28269.44 | BW50: 1.95 | BX50: =BW50*BP50 -> 1.95 | BY50: =IFERROR(BU50/BX50,0) -> 14497.149 | CA50: RECORD | CB50: =COUNTA(I50:AM50) -> 1 | CC50: =CB50*BS50*0.8 -> 28269.44 | CD50: =COUNTA(AN50:BO50) -> 0 | CE50: =CD50*BS50*0.8 -> 0 | CF50: =SUM(CC50,CE50)=BU50 -> TRUE
D51: HOJE EM DIA | E51: SEG-SEX | F51: 0.39930556 | G51: 11:30 | H51: 30 | AI51: 1 | AP51: 1 | AW51: 1 | BP51: =SUM(I51:BO51) -> 3 | BQ51: 68116 | BR51: 0.8 | BS51: =BQ51*(1-BR51) -> 13623.2 | BT51: =BS51*BP51 -> 40869.6 | BU51: =BT51*0.8 -> 32695.68 | BW51: 2.01 | BX51: =BW51*BP51 -> 6.03 | BY51: =IFERROR(BU51/BX51,0) -> 5422.1692 | CA51: RECORD | CB51: =COUNTA(I51:AM51) -> 1 | CC51: =CB51*BS51*0.8 -> 10898.56 | CD51: =COUNTA(AN51:BO51) -> 2 | CE51: =CD51*BS51*0.8 -> 21797.12 | CF51: =SUM(CC51,CE51)=BU51 -> TRUE
D52: NOVELA 22H | E52: SEG-SEX | F52: 0.91666667 | G52: 22:30 | H52: 30 | AK52: 1 | AR52: 1 | AY52: 1 | BP52: =SUM(I52:BO52) -> 3 | BQ52: 235310 | BR52: 0.8 | BS52: =BQ52*(1-BR52) -> 47062 | BT52: =BS52*BP52 -> 141186 | BU52: =BT52*0.8 -> 112948.8 | BW52: 2.27 | BX52: =BW52*BP52 -> 6.81 | BY52: =IFERROR(BU52/BX52,0) -> 16585.727 | CA52: RECORD | CB52: =COUNTA(I52:AM52) -> 1 | CC52: =CB52*BS52*0.8 -> 37649.6 | CD52: =COUNTA(AN52:BO52) -> 2 | CE52: =CD52*BS52*0.8 -> 75299.2 | CF52: =SUM(CC52,CE52)=BU52 -> TRUE
D53: NOVELA 22H | E53: SEG-SEX | F53: 0.91666667 | G53: 22:30 | H53: 60 | AD53: 1 | BP53: =SUM(I53:BO53) -> 1 | BQ53: 470620 | BR53: 0.8 | BS53: =BQ53*(1-BR53) -> 94124 | BT53: =BS53*BP53 -> 94124 | BU53: =BT53*0.8 -> 75299.2 | BW53: 2.27 | BX53: =BW53*BP53 -> 2.27 | BY53: =IFERROR(BU53/BX53,0) -> 33171.454 | CA53: RECORD | CB53: =COUNTA(I53:AM53) -> 1 | CC53: =CB53*BS53*0.8 -> 75299.2 | CD53: =COUNTA(AN53:BO53) -> 0 | CE53: =CD53*BS53*0.8 -> 0 | CF53: =SUM(CC53,CE53)=BU53 -> TRUE
D54: NOVELA 3 | E54: SEG-SEX | F54: 0.875 | G54: 22:00 | H54: 30 | AL54: 1 | AS54: 1 | AZ54: 1 | BP54: =SUM(I54:BO54) -> 3 | BQ54: 297974 | BR54: 0.8 | BS54: =BQ54*(1-BR54) -> 59594.8 | BT54: =BS54*BP54 -> 178784.4 | BU54: =BT54*0.8 -> 143027.52 | BW54: 2.56 | BX54: =BW54*BP54 -> 7.68 | BY54: =IFERROR(BU54/BX54,0) -> 18623.375 | CA54: RECORD | CB54: =COUNTA(I54:AM54) -> 1 | CC54: =CB54*BS54*0.8 -> 47675.84 | CD54: =COUNTA(AN54:BO54) -> 2 | CE54: =CD54*BS54*0.8 -> 95351.68 | CF54: =SUM(CC54,CE54)=BU54 -> TRUE
D55: NOVELA 3 | E55: SEG-SEX | F55: 0.875 | G55: 22:00 | H55: 60 | AE55: 1 | BP55: =SUM(I55:BO55) -> 1 | BQ55: 595948 | BR55: 0.8 | BS55: =BQ55*(1-BR55) -> 119189.6 | BT55: =BS55*BP55 -> 119189.6 | BU55: =BT55*0.8 -> 95351.68 | BW55: 2.56 | BX55: =BW55*BP55 -> 2.56 | BY55: =IFERROR(BU55/BX55,0) -> 37246.75 | CA55: RECORD | CB55: =COUNTA(I55:AM55) -> 1 | CC55: =CB55*BS55*0.8 -> 95351.68 | CD55: =COUNTA(AN55:BO55) -> 0 | CE55: =CD55*BS55*0.8 -> 0 | CF55: =SUM(CC55,CE55)=BU55 -> TRUE
D56: NOVELA DA TARDE 1 | E56: SEG-SEX | F56: 0.64583333 | G56: 16:30 | H56: 30 | AH56: 1 | AO56: 1 | AV56: 1 | BP56: =SUM(I56:BO56) -> 3 | BQ56: 87447 | BR56: 0.8 | BS56: =BQ56*(1-BR56) -> 17489.4 | BT56: =BS56*BP56 -> 52468.2 | BU56: =BT56*0.8 -> 41974.56 | BW56: 2.39 | BX56: =BW56*BP56 -> 7.17 | BY56: =IFERROR(BU56/BX56,0) -> 5854.1925 | CA56: RECORD | CB56: =COUNTA(I56:AM56) -> 1 | CC56: =CB56*BS56*0.8 -> 13991.52 | CD56: =COUNTA(AN56:BO56) -> 2 | CE56: =CD56*BS56*0.8 -> 27983.04 | CF56: =SUM(CC56,CE56)=BU56 -> TRUE
CA57: TT | CB57: =SUM(CB45:CB56) -> 11 | CC57: =SUM(CC45:CC56) -> 481866.08 | CD57: =SUM(CD45:CD56) -> 15 | CE57: =SUM(CE45:CE56) -> 459290.56
C58: SBT | D58: ALO VOCE | E58: SEG-SEX | F58: 0.45833333 | G58: 13:45 | H58: 30 | AH58: 1 | AO58: 1 | AV58: 1 | BP58: =SUM(I58:BO58) -> 3 | BQ58: 89256 | BR58: 0.75 | BS58: =BQ58*(1-BR58) -> 22314 | BT58: =BS58*BP58 -> 66942 | BU58: =BT58*0.8 -> 53553.6 | BW58: 1.45 | BX58: =BW58*BP58 -> 4.35 | BY58: =IFERROR(BU58/BX58,0) -> 12311.172 | CA58: SBT | CB58: =COUNTA(I58:AM58) -> 1 | CC58: =CB58*BS58*0.8 -> 17851.2 | CD58: =COUNTA(AN58:BO58) -> 2 | CE58: =CD58*BS58*0.8 -> 35702.4 | CF58: =SUM(CC58,CE58)=BU58 -> TRUE
D59: DOMINGO LEGAL 1 | E59: DOM | F59: 0.46875 | G59: 15:15 | H59: 30 | AN59: 1 | AU59: 1 | BB59: 1 | BP59: =SUM(I59:BO59) -> 3 | BQ59: 206148 | BR59: 0.75 | BS59: =BQ59*(1-BR59) -> 51537 | BT59: =BS59*BP59 -> 154611 | BU59: =BT59*0.8 -> 123688.8 | BW59: 2.99 | BX59: =BW59*BP59 -> 8.97 | BY59: =IFERROR(BU59/BX59,0) -> 13789.164 | CA59: SBT | CB59: =COUNTA(I59:AM59) -> 0 | CC59: =CB59*BS59*0.8 -> 0 | CD59: =COUNTA(AN59:BO59) -> 3 | CE59: =CD59*BS59*0.8 -> 123688.8 | CF59: =SUM(CC59,CE59)=BU59 -> TRUE
D60: DOMINGO LEGAL 1 | E60: DOM | F60: 0.46875 | G60: 15:15 | H60: 60 | AG60: 1 | BP60: =SUM(I60:BO60) -> 1 | BQ60: 412296 | BR60: 0.75 | BS60: =BQ60*(1-BR60) -> 103074 | BT60: =BS60*BP60 -> 103074 | BU60: =BT60*0.8 -> 82459.2 | BW60: 2.99 | BX60: =BW60*BP60 -> 2.99 | BY60: =IFERROR(BU60/BX60,0) -> 27578.328 | CA60: SBT | CB60: =COUNTA(I60:AM60) -> 1 | CC60: =CB60*BS60*0.8 -> 82459.2 | CD60: =COUNTA(AN60:BO60) -> 0 | CE60: =CD60*BS60*0.8 -> 0 | CF60: =SUM(CC60,CE60)=BU60 -> TRUE
D61: NOVELA NOITE | E61: SEG-SEX | F61: 0.875 | G61: 22:15 | H61: 30 | AH61: 1 | AO61: 1 | AV61: 1 | BP61: =SUM(I61:BO61) -> 3 | BQ61: 249316 | BR61: 0.75 | BS61: =BQ61*(1-BR61) -> 62329 | BT61: =BS61*BP61 -> 186987 | BU61: =BT61*0.8 -> 149589.6 | BW61: 2.14 | BX61: =BW61*BP61 -> 6.42 | BY61: =IFERROR(BU61/BX61,0) -> 23300.561 | CA61: SBT | CB61: =COUNTA(I61:AM61) -> 1 | CC61: =CB61*BS61*0.8 -> 49863.2 | CD61: =COUNTA(AN61:BO61) -> 2 | CE61: =CD61*BS61*0.8 -> 99726.4 | CF61: =SUM(CC61,CE61)=BU61 -> TRUE
D62: NOVELA NOITE | E62: SEG-SEX | F62: 0.875 | G62: 22:15 | H62: 60 | AD62: 1 | BP62: =SUM(I62:BO62) -> 1 | BQ62: 498632 | BR62: 0.75 | BS62: =BQ62*(1-BR62) -> 124658 | BT62: =BS62*BP62 -> 124658 | BU62: =BT62*0.8 -> 99726.4 | BW62: 2.14 | BX62: =BW62*BP62 -> 2.14 | BY62: =IFERROR(BU62/BX62,0) -> 46601.121 | CA62: SBT | CB62: =COUNTA(I62:AM62) -> 1 | CC62: =CB62*BS62*0.8 -> 99726.4 | CD62: =COUNTA(AN62:BO62) -> 0 | CE62: =CD62*BS62*0.8 -> 0 | CF62: =SUM(CC62,CE62)=BU62 -> TRUE
D63: NOVELA NOITE 18H | E63: SEG-SEX | F63: 0.73958333 | G63: 18:30 | H63: 30 | AK63: 1 | AR63: 1 | AY63: 1 | BP63: =SUM(I63:BO63) -> 3 | BQ63: 149464 | BR63: 0.75 | BS63: =BQ63*(1-BR63) -> 37366 | BT63: =BS63*BP63 -> 112098 | BU63: =BT63*0.8 -> 89678.4 | BW63: 1.08 | BX63: =BW63*BP63 -> 3.24 | BY63: =IFERROR(BU63/BX63,0) -> 27678.519 | CA63: SBT | CB63: =COUNTA(I63:AM63) -> 1 | CC63: =CB63*BS63*0.8 -> 29892.8 | CD63: =COUNTA(AN63:BO63) -> 2 | CE63: =CD63*BS63*0.8 -> 59785.6 | CF63: =SUM(CC63,CE63)=BU63 -> TRUE
D64: NOVELA TARDE 14H | E64: SEG-SEX | F64: 0.60416667 | G64: 15:30 | H64: 30 | AJ64: 1 | AQ64: 1 | AX64: 1 | BP64: =SUM(I64:BO64) -> 3 | BQ64: 128521 | BR64: 0.75 | BS64: =BQ64*(1-BR64) -> 32130.25 | BT64: =BS64*BP64 -> 96390.75 | BU64: =BT64*0.8 -> 77112.6 | BW64: 1.58 | BX64: =BW64*BP64 -> 4.74 | BY64: =IFERROR(BU64/BX64,0) -> 16268.481 | CA64: SBT | CB64: =COUNTA(I64:AM64) -> 1 | CC64: =CB64*BS64*0.8 -> 25704.2 | CD64: =COUNTA(AN64:BO64) -> 2 | CE64: =CD64*BS64*0.8 -> 51408.4 | CF64: =SUM(CC64,CE64)=BU64 -> TRUE
D65: PRIMEIRO IMPACTO | E65: SEG-SEX | F65: 0.35416667 | G65: 11:00 | H65: 30 | AI65: 1 | AP65: 1 | AW65: 1 | BP65: =SUM(I65:BO65) -> 3 | BQ65: 73583 | BR65: 0.75 | BS65: =BQ65*(1-BR65) -> 18395.75 | BT65: =BS65*BP65 -> 55187.25 | BU65: =BT65*0.8 -> 44149.8 | BW65: 1.38 | BX65: =BW65*BP65 -> 4.14 | BY65: =IFERROR(BU65/BX65,0) -> 10664.203 | CA65: SBT | CB65: =COUNTA(I65:AM65) -> 1 | CC65: =CB65*BS65*0.8 -> 14716.6 | CD65: =COUNTA(AN65:BO65) -> 2 | CE65: =CD65*BS65*0.8 -> 29433.2 | CF65: =SUM(CC65,CE65)=BU65 -> TRUE
D66: SBT MANHA | E66: SEG-SEX | F66: 0.3125 | G66: 08:30 | H66: 30 | AL66: 1 | AS66: 1 | AZ66: 1 | BP66: =SUM(I66:BO66) -> 3 | BQ66: 73583 | BR66: 0.75 | BS66: =BQ66*(1-BR66) -> 18395.75 | BT66: =BS66*BP66 -> 55187.25 | BU66: =BT66*0.8 -> 44149.8 | BW66: 1.25 | BX66: =BW66*BP66 -> 3.75 | BY66: =IFERROR(BU66/BX66,0) -> 11773.28 | CA66: SBT | CB66: =COUNTA(I66:AM66) -> 1 | CC66: =CB66*BS66*0.8 -> 14716.6 | CD66: =COUNTA(AN66:BO66) -> 2 | CE66: =CD66*BS66*0.8 -> 29433.2 | CF66: =SUM(CC66,CE66)=BU66 -> TRUE
D67: SBT MANHA | E67: SEG-SEX | F67: 0.3125 | G67: 08:30 | H67: 60 | AE67: 1 | BP67: =SUM(I67:BO67) -> 1 | BQ67: 147166 | BR67: 0.75 | BS67: =BQ67*(1-BR67) -> 36791.5 | BT67: =BS67*BP67 -> 36791.5 | BU67: =BT67*0.8 -> 29433.2 | BW67: 1.25 | BX67: =BW67*BP67 -> 1.25 | BY67: =IFERROR(BU67/BX67,0) -> 23546.56 | CA67: SBT | CB67: =COUNTA(I67:AM67) -> 1 | CC67: =CB67*BS67*0.8 -> 29433.2 | CD67: =COUNTA(AN67:BO67) -> 0 | CE67: =CD67*BS67*0.8 -> 0 | CF67: =SUM(CC67,CE67)=BU67 -> TRUE
D68: SBT NOTICIAS 1A ED | E68: SEG-SEX | F68: 0.45833333 | G68: 15:00 | H68: 30 | AM68: 1 | AT68: 1 | BA68: 1 | BP68: =SUM(I68:BO68) -> 3 | BQ68: 73583 | BR68: 0.75 | BS68: =BQ68*(1-BR68) -> 18395.75 | BT68: =BS68*BP68 -> 55187.25 | BU68: =BT68*0.8 -> 44149.8 | BW68: 1.17 | BX68: =BW68*BP68 -> 3.51 | BY68: =IFERROR(BU68/BX68,0) -> 12578.291 | CA68: SBT | CB68: =COUNTA(I68:AM68) -> 1 | CC68: =CB68*BS68*0.8 -> 14716.6 | CD68: =COUNTA(AN68:BO68) -> 2 | CE68: =CD68*BS68*0.8 -> 29433.2 | CF68: =SUM(CC68,CE68)=BU68 -> TRUE
D69: SBT NOTICIAS 1A ED | E69: SEG-SEX | F69: 0.45833333 | G69: 15:00 | H69: 60 | AF69: 1 | BP69: =SUM(I69:BO69) -> 1 | BQ69: 147166 | BR69: 0.75 | BS69: =BQ69*(1-BR69) -> 36791.5 | BT69: =BS69*BP69 -> 36791.5 | BU69: =BT69*0.8 -> 29433.2 | BW69: 1.17 | BX69: =BW69*BP69 -> 1.17 | BY69: =IFERROR(BU69/BX69,0) -> 25156.581 | CA69: SBT | CB69: =COUNTA(I69:AM69) -> 1 | CC69: =CB69*BS69*0.8 -> 29433.2 | CD69: =COUNTA(AN69:BO69) -> 0 | CE69: =CD69*BS69*0.8 -> 0 | CF69: =SUM(CC69,CE69)=BU69 -> TRUE
CA70: TT | CB70: =SUM(CB58:CB69) -> 11 | CC70: =SUM(CC58:CC69) -> 408513.2 | CD70: =SUM(CD58:CD69) -> 17 | CE70: =SUM(CE58:CE69) -> 458611.2
B72: TT OPEN TV | I72: =COUNTA(I12:I22) -> 0 | J72: =COUNTA(J12:J22) -> 0 | K72: =COUNTA(K12:K22) -> 0 | L72: =COUNTA(L12:L22) -> 0 | M72: =COUNTA(M12:M22) -> 0 | N72: =SUM(N12:N22) -> 0 | O72: =SUM(O12:O22) -> 0 | P72: =SUM(P12:P22) -> 0 | Q72: =SUM(Q12:Q70) -> 0 | R72: =SUM(R12:R70) -> 0 | S72: =SUM(S12:S70) -> 0 | T72: =SUM(T12:T70) -> 0 | U72: =SUM(U12:U70) -> 0 | V72: =SUM(V12:V70) -> 0 | W72: =SUM(W12:W70) -> 0 | X72: =SUM(X12:X70) -> 0 | ... BJ72: =SUM(BJ12:BJ70) -> 0 | BK72: =SUM(BK13:BK71) -> 0 | BL72: =SUM(BL13:BL71) -> 0 | BM72: =SUM(BM12:BM22) -> 0 | BN72: =SUM(BN12:BN22) -> 0 | BO72: =SUM(BO12:BO22) -> 0 | BP72: =SUM(BP13:BP70) -> 95 | BT72: =SUM(BT13:BT70) -> 6911592.2 | BU72: =SUM(BU13:BU70) -> 5529273.8 | BX72: =SUM(BX12:BX70) -> 354.22 | BY72: =BU72/BX72 -> 15609.716 | CA72: TT GERAL | CB72: =CB32+CB44+CB57+CB70 -> 43 | CC72: =CC32+CC44+CC57+CC70 -> 3573083.5 | CD72: =CD32+CD44+CD57+CD70 -> 52 | CE72: =CE32+CE44+CE57+CE70 -> 1956190.2
BT73: UTILIZAÇÃO DE PACOTE | BU73: =SUM(BU58:BU69) -> 867124.4
BT74: TOTAL FATURÁVEL | BU74: =BU72-BU73 -> 4662149.4 | BW74: TARGET AS ABCDE 25+ (32MM) | BY74: SPE: | CD74: TT | CE74: =CC72+CE72 -> 5529273.8
BW75: COBERTURA | BX75: 0.52 | BY75: 32157000 | CE75: =CE74=BU72 -> TRUE
BW76: ALCANCE | BX76: =BY75*BX75 -> 16721640
BW77: FREQUÊNCIA | BX77: 4.1
BW78: IMPACTOS | BX78: =BY75*BX72% -> 1.1390653e+08
BW79: CPM | BX79: =BU72/BX78*1000 -> 48.542204

Sheet TV ABERTA - COLCHÃO REP - SP1
B5: CLIENT: SABESP
B6: CAMPAING: ESCASSEZ HIDRICA - CRÍTICO
BW7: PLANNED
B8: MARKET | C8: CHANNEL | D8: PROGRAMM | E8: DAY | F8: START TIME | G8: END TIME | H8: SEC | I8: JANEIRO | BP8: INS. | BQ8: CUSTO TABELA UNITÁRIO (BRUTO) | BR8: DESC. % | BS8: CUSTO NEGOCIADO UNITÁRIO (BRUTO) | BT8: CUSTO TOTAL NEGOCIADO (BRUTO) | BU8: CUSTO TOTAL DESEMBOLSO SABESP | BW8: AUD. AS ABCDE 25+ | BX8: TRP | BY8: CPP | CA8: RESUMO
I9: T | J9: F | K9: S | L9: S | M9: M | N9: T | O9: W | P9: T | Q9: F | R9: S | S9: S | T9: M | U9: T | V9: W | W9: T | X9: F | Y9: S | Z9: S | AA9: M | AB9: T | AC9: W | AD9: T | AE9: F | AF9: S | AG9: S | AH9: M | AI9: T | AJ9: W | AK9: T | AL9: F | AM9: S | AN9: S | AO9: M | AP9: T | AQ9: W | AR9: T | AS9: F | AT9: S | AU9: S | AV9: M | AW9: T | AX9: W | AY9: T | AZ9: F | BA9: S | BB9: S | BC9: M | BD9: T | BE9: W | BF9: T | BG9: F | BH9: S | BI9: S | BJ9: M | BK9: T | BL9: W | BM9: T | BN9: F | BO9: S
I10: 1 | J10: 2 | K10: 3 | L10: 4 | M10: 5 | N10: 6 | O10: 7 | P10: 8 | Q10: 9 | R10: 10 | S10: 11 | T10: 12 | U10: 13 | V10: 14 | W10: 15 | X10: 16 | Y10: 17 | Z10: =Y10+1 -> 18 | AA10: =Z10+1 -> 19 | AB10: =AA10+1 -> 20 | AC10: =AB10+1 -> 21 | AD10: =AC10+1 -> 22 | AE10: =AD10+1 -> 23 | AF10: =AE10+1 -> 24 | AG10: =AF10+1 -> 25 | ... AM10: =AL10+1 -> 31 | AN10: 1 | AO10: 2 | AP10: 3 | AQ10: 4 | AR10: 5 | AS10: 6 | AT10: 7 | AU10: 8 | AV10: 9 | AW10: 10 | AX10: 11 | AY10: 12 | AZ10: 13 | BA10: 14 | BB10: 15 | BC10: 16 | BD10: 17 | BE10: =BD10+1 -> 18 | BF10: =BE10+1 -> 19 | BG10: =BF10+1 -> 20 | BH10: =BG10+1 -> 21 | BI10: =BH10+1 -> 22 | BJ10: =BI10+1 -> 23 | BK10: =BJ10+1 -> 24 | BL10: =BK10+1 -> 25 | ... BO10: =BN10+1 -> 28 | CA10: CHANNEL | CB10: JANEIRO | CD10: FEVEREIRO
CB12: INS | CC12: INVESTIMENTO $ | CD12: INS | CE12: INVESTIMENTO $
B13: SÃO PAULO CAPITAL | C13: TV GLOBO | D13: PRACA TV 1 EDICAO | E13: SEG-SEX | F13: 0.48958333 | G13: 13:00 | H13: 30 | AH13: 1 | AJ13: 1 | AL13: 1 | AP13: 1 | AR13: 1 | AV13: 1 | AX13: 1 | AZ13: 1 | BP13: =SUM(I13:BO13) -> 8 | BQ13: 27572 | BR13: 0.1 | BS13: =BQ13*(1-BR13) -> 24814.8 | BT13: =BS13*BP13 -> 198518.4 | BU13: =BT13*0.8 -> 158814.72 | BW13: 5.24 | BX13: =BW13*BP13 -> 41.92 | BY13: =IFERROR(BU13/BX13,0) -> 3788.5191 | CA13: TV GLOBO | CB13: =COUNTA(I13:AM13) -> 3 | CC13: =CB13*BS13*0.8 -> 59555.52 | CD13: =COUNTA(AN13:BO13) -> 5 | CE13: =CD13*BS13*0.8 -> 99259.2 | CF13: =SUM(CC13,CE13)=BU13 -> TRUE
E14: SEG-SEX | F14: 0.48958333 | G14: 13:00 | H14: 60 | AE14: 1 | BP14: =SUM(I14:BO14) -> 1 | BQ14: 55144 | BR14: 0.1 | BS14: =BQ14*(1-BR14) -> 49629.6 | BT14: =BS14*BP14 -> 49629.6 | BU14: =BT14*0.8 -> 39703.68 | BW14: 5.24 | BX14: =BW14*BP14 -> 5.24 | BY14: =IFERROR(BU14/BX14,0) -> 7577.0382 | CA14: TV GLOBO | CB14: =COUNTA(I14:AM14) -> 1 | CC14: =CB14*BS14*0.8 -> 39703.68 | CD14: =COUNTA(AN14:BO14) -> 0 | CE14: =CD14*BS14*0.8 -> 0 | CF14: =SUM(CC14,CE14)=BU14 -> TRUE
D15: PRACA TV 2 EDICAO | E15: SEG-SEX | F15: 0.79861111 | G15: 19:40 | H15: 30 | AK15: 1 | AO15: 1 | AS15: 1 | AY15: 1 | BP15: =SUM(I15:BO15) -> 4 | BQ15: 112324 | BR15: 0.1 | BS15: =BQ15*(1-BR15) -> 101091.6 | BT15: =BS15*BP15 -> 404366.4 | BU15: =BT15*0.8 -> 323493.12 | BW15: 12.39 | BX15: =BW15*BP15 -> 49.56 | BY15: =IFERROR(BU15/BX15,0) -> 6527.3027 | CA15: TV GLOBO | CB15: =COUNTA(I15:AM15) -> 1 | CC15: =CB15*BS15*0.8 -> 80873.28 | CD15: =COUNTA(AN15:BO15) -> 3 | CE15: =CD15*BS15*0.8 -> 242619.84 | CF15: =SUM(CC15,CE15)=BU15 -> TRUE
E16: SEG-SEX | F16: 0.79861111 | G16: 19:40 | H16: 60 | AD16: 1 | BP16: =SUM(I16:BO16) -> 1 | BQ16: 224648 | BR16: 0.1 | BS16: =BQ16*(1-BR16) -> 202183.2 | BT16: =BS16*BP16 -> 202183.2 | BU16: =BT16*0.8 -> 161746.56 | BW16: 12.39 | BX16: =BW16*BP16 -> 12.39 | BY16: =IFERROR(BU16/BX16,0) -> 13054.605 | CA16: TV GLOBO | CB16: =COUNTA(I16:AM16) -> 1 | CC16: =CB16*BS16*0.8 -> 161746.56 | CD16: =COUNTA(AN16:BO16) -> 0 | CE16: =CD16*BS16*0.8 -> 0 | CF16: =SUM(CC16,CE16)=BU16 -> TRUE
CA17: TT | CB17: =SUM(CB13:CB16) -> 6 | CC17: =SUM(CC13:CC16) -> 341879.04 | CD17: =SUM(CD13:CD16) -> 8 | CE17: =SUM(CE13:CE16) -> 341879.04
C18: BANDEIRANTES | D18: JORNAL DA BAND | E18: SEG-SEX | F18: 0.80555556 | G18: 20:30 | H18: 30 | AI18: 1 | AK18: 1 | AP18: 1 | AR18: 1 | AW18: 1 | AY18: 1 | BP18: =SUM(I18:BO18) -> 6 | BQ18: 107608 | BR18: 0.85 | BS18: =BQ18*(1-BR18) -> 16141.2 | BT18: =BS18*BP18 -> 96847.2 | BU18: =BT18*0.8 -> 77477.76 | BW18: 1.59 | BX18: =BW18*BP18 -> 9.54 | BY18: =IFERROR(BU18/BX18,0) -> 8121.3585 | CA18: BANDEIRANTES | CB18: =COUNTA(I18:AM18) -> 2 | CC18: =CB18*BS18*0.8 -> 25825.92 | CD18: =COUNTA(AN18:BO18) -> 4 | CE18: =CD18*BS18*0.8 -> 51651.84 | CF18: =SUM(CC18,CE18)=BU18 -> TRUE
E19: SEG-SEX | F19: 0.80555556 | G19: 20:30 | H19: 60 | AD19: 1 | BP19: =SUM(I19:BO19) -> 1 | BQ19: 215216 | BR19: 0.85 | BS19: =BQ19*(1-BR19) -> 32282.4 | BT19: =BS19*BP19 -> 32282.4 | BU19: =BT19*0.8 -> 25825.92 | BW19: 1.59 | BX19: =BW19*BP19 -> 1.59 | BY19: =IFERROR(BU19/BX19,0) -> 16242.717 | CA19: BANDEIRANTES | CB19: =COUNTA(I19:AM19) -> 1 | CC19: =CB19*BS19*0.8 -> 25825.92 | CD19: =COUNTA(AN19:BO19) -> 0 | CE19: =CD19*BS19*0.8 -> 0 | CF19: =SUM(CC19,CE19)=BU19 -> TRUE
CA20: TT | CB20: =SUM(CB18:CB19) -> 3 | CC20: =SUM(CC18:CC19) -> 51651.84 | CD20: =SUM(CD18:CD19) -> 4 | CE20: =SUM(CE18:CE19) -> 51651.84
C21: RECORD | D21: JORNAL DA RECORD | E21: SEG-SEX | F21: 0.82986111 | G21: 21:00 | H21: 30 | AJ21: 1 | AL21: 1 | AQ21: 1 | AS21: 1 | AX21: 1 | AZ21: 1 | BP21: =SUM(I21:BO21) -> 6 | BQ21: 335107 | BR21: 0.8 | BS21: =BQ21*(1-BR21) -> 67021.4 | BT21: =BS21*BP21 -> 402128.4 | BU21: =BT21*0.8 -> 321702.72 | BW21: 3.53 | BX21: =BW21*BP21 -> 21.18 | BY21: =IFERROR(BU21/BX21,0) -> 15188.986 | CA21: RECORD | CB21: =COUNTA(I21:AM21) -> 2 | CC21: =CB21*BS21*0.8 -> 107234.24 | CD21: =COUNTA(AN21:BO21) -> 4 | CE21: =CD21*BS21*0.8 -> 214468.48 | CF21: =SUM(CC21,CE21)=BU21 -> TRUE
E22: SEG-SEX | F22: 0.82986111 | G22: 21:00 | H22: 60 | AE22: 1 | BP22: =SUM(I22:BO22) -> 1 | BQ22: 670214 | BR22: 0.8 | BS22: =BQ22*(1-BR22) -> 134042.8 | BT22: =BS22*BP22 -> 134042.8 | BU22: =BT22*0.8 -> 107234.24 | BW22: 3.53 | BX22: =BW22*BP22 -> 3.53 | BY22: =IFERROR(BU22/BX22,0) -> 30377.972 | CA22: RECORD | CB22: =COUNTA(I22:AM22) -> 1 | CC22: =CB22*BS22*0.8 -> 107234.24 | CD22: =COUNTA(AN22:BO22) -> 0 | CE22: =CD22*BS22*0.8 -> 0 | CF22: =SUM(CC22,CE22)=BU22 -> TRUE
CA23: TT | CB23: =SUM(CB21:CB22) -> 3 | CC23: =SUM(CC21:CC22) -> 214468.48 | CD23: =SUM(CD21:CD22) -> 4 | CE23: =SUM(CE21:CE22) -> 214468.48
C24: SBT | D24: SBT BRASIL | E24: SEG-SEX | F24: 0.82291667 | G24: 21:00 | H24: 30 | AI24: 1 | AK24: 1 | AP24: 1 | AR24: 1 | AW24: 1 | AY24: 1 | BP24: =SUM(I24:BO24) -> 6 | BQ24: 155300 | BR24: 0.75 | BS24: =BQ24*(1-BR24) -> 38825 | BT24: =BS24*BP24 -> 232950 | BU24: =BT24*0.8 -> 186360 | BW24: 1.91 | BX24: =BW24*BP24 -> 11.46 | BY24: =IFERROR(BU24/BX24,0) -> 16261.78 | CA24: SBT | CB24: =COUNTA(I24:AM24) -> 2 | CC24: =CB24*BS24*0.8 -> 62120 | CD24: =COUNTA(AN24:BO24) -> 4 | CE24: =CD24*BS24*0.8 -> 124240 | CF24: =SUM(CC24,CE24)=BU24 -> TRUE
CA25: TT | CB25: =SUM(CB24) -> 2 | CC25: =SUM(CC24) -> 62120 | CD25: =SUM(CD24) -> 4 | CE25: =SUM(CE24) -> 124240
C26: REDE TV | D26: REDETV! NEWS | E26: SEG-SEX | F26: 0.82986111 | G26: 20:30 | H26: 30 | AI26: 1 | AL26: 1 | AP26: 1 | AS26: 1 | AW26: 1 | AZ26: 1 | BP26: =SUM(I26:BO26) -> 6 | BQ26: 83652 | BR26: 0.85 | BS26: =BQ26*(1-BR26) -> 12547.8 | BT26: =BS26*BP26 -> 75286.8 | BU26: =BT26*0.8 -> 60229.44 | BW26: 0.14 | BX26: =BW26*BP26 -> 0.84 | BY26: =IFERROR(BU26/BX26,0) -> 71701.714 | CA26: REDE TV | CB26: =COUNTA(I26:AM26) -> 2 | CC26: =CB26*BS26*0.8 -> 20076.48 | CD26: =COUNTA(AN26:BO26) -> 4 | CE26: =CD26*BS26*0.8 -> 40152.96 | CF26: =SUM(CC26,CE26)=BU26 -> TRUE
E27: SEG-SEX | F27: 0.82986111 | G27: 20:30 | H27: 60 | AE27: 1 | BP27: =SUM(I27:BO27) -> 1 | BQ27: 167304 | BR27: 0.85 | BS27: =BQ27*(1-BR27) -> 25095.6 | BT27: =BS27*BP27 -> 25095.6 | BU27: =BT27*0.8 -> 20076.48 | BW27: 0.14 | BX27: =BW27*BP27 -> 0.14 | BY27: =IFERROR(BU27/BX27,0) -> 143403.43 | CA27: REDE TV | CB27: =COUNTA(I27:AM27) -> 1 | CC27: =CB27*BS27*0.8 -> 20076.48 | CD27: =COUNTA(AN27:BO27) -> 0 | CE27: =CD27*BS27*0.8 -> 0 | CF27: =SUM(CC27,CE27)=BU27 -> TRUE
CA28: TT | CB28: =SUM(CB26:CB27) -> 3 | CC28: =SUM(CC26:CC27) -> 40152.96 | CD28: =SUM(CD26:CD27) -> 4 | CE28: =SUM(CE26:CE27) -> 40152.96
B30: TT OPEN TV | I30: =COUNTA(I12:I16) -> 0 | J30: =COUNTA(J12:J16) -> 0 | K30: =COUNTA(K12:K16) -> 0 | L30: =COUNTA(L12:L16) -> 0 | M30: =COUNTA(M12:M16) -> 0 | N30: =SUM(N12:N16) -> 0 | O30: =SUM(O12:O16) -> 0 | P30: =SUM(P12:P16) -> 0 | Q30: =SUM(Q12:Q28) -> 0 | R30: =SUM(R12:R28) -> 0 | S30: =SUM(S12:S28) -> 0 | T30: =SUM(T12:T28) -> 0 | U30: =SUM(U12:U28) -> 0 | V30: =SUM(V12:V28) -> 0 | W30: =SUM(W12:W28) -> 0 | X30: =SUM(X12:X28) -> 0 | ... BJ30: =SUM(BJ12:BJ28) -> 0 | BK30: =SUM(BK13:BK29) -> 0 | BL30: =SUM(BL13:BL29) -> 0 | BM30: =SUM(BM12:BM16) -> 0 | BN30: =SUM(BN12:BN16) -> 0 | BO30: =SUM(BO12:BO16) -> 0 | BP30: =SUM(BP13:BP28) -> 41 | BT30: =SUM(BT13:BT28) -> 1853330.8 | BU30: =SUM(BU13:BU28) -> 1482664.6 | BX30: =SUM(BX13:BX27) -> 157.39 | BY30: =BU30/BX30 -> 9420.323 | CA30: TT GERAL | CB30: =CB17+CB20+CB23+CB28+CB25 -> 17 | CC30: =CC17+CC20+CC23+CC28+CC25 -> 710272.32 | CD30: =CD17+CD20+CD23+CD28+CD25 -> 24 | CE30: =CE17+CE20+CE23+CE28+CE25 -> 772392.32
BT31: UTILIZAÇÃO DE PACOTE | BU31: =SUM(BU24:BU27) -> 266665.92
BT32: TOTAL FATURÁVEL | BU32: =BU30-BU31 -> 1215998.7 | CD32: TT | CE32: =CC30+CE30 -> 1482664.6
CE33: =CE32=BU30 -> TRUE

Sheet TV ABERTA - COLCHÃO REP - SPE
B5: CLIENT: SABESP
B6: CAMPAING: ESCASSEZ HIDRICA - CRÍTICO
BW7: PLANNED
B8: MARKET | C8: CHANNEL | D8: PROGRAMM | E8: DAY | F8: START TIME | G8: END TIME | H8: SEC | I8: JANEIRO | BP8: INS. | BQ8: CUSTO TABELA UNITÁRIO (BRUTO) | BR8: DESC. % | BS8: CUSTO NEGOCIADO UNITÁRIO (BRUTO) | BT8: CUSTO TOTAL NEGOCIADO (BRUTO) | BU8: CUSTO TOTAL DESEMBOLSO SABESP | BW8: AUD. AS ABCDE 25+ | BX8: TRP | BY8: CPP | CA8: RESUMO
I9: T | J9: F | K9: S | L9: S | M9: M | N9: T | O9: W | P9: T | Q9: F | R9: S | S9: S | T9: M | U9: T | V9: W | W9: T | X9: F | Y9: S | Z9: S | AA9: M | AB9: T | AC9: W | AD9: T | AE9: F | AF9: S | AG9: S | AH9: M | AI9: T | AJ9: W | AK9: T | AL9: F | AM9: S | AN9: S | AO9: M | AP9: T | AQ9: W | AR9: T | AS9: F | AT9: S | AU9: S | AV9: M | AW9: T | AX9: W | AY9: T | AZ9: F | BA9: S | BB9: S | BC9: M | BD9: T | BE9: W | BF9: T | BG9: F | BH9: S | BI9: S | BJ9: M | BK9: T | BL9: W | BM9: T | BN9: F | BO9: S
I10: 1 | J10: 2 | K10: 3 | L10: 4 | M10: 5 | N10: 6 | O10: 7 | P10: 8 | Q10: 9 | R10: 10 | S10: 11 | T10: 12 | U10: 13 | V10: 14 | W10: 15 | X10: 16 | Y10: 17 | Z10: =Y10+1 -> 18 | AA10: =Z10+1 -> 19 | AB10: =AA10+1 -> 20 | AC10: =AB10+1 -> 21 | AD10: =AC10+1 -> 22 | AE10: =AD10+1 -> 23 | AF10: =AE10+1 -> 24 | AG10: =AF10+1 -> 25 | ... AM10: =AL10+1 -> 31 | AN10: 1 | AO10: 2 | AP10: 3 | AQ10: 4 | AR10: 5 | AS10: 6 | AT10: 7 | AU10: 8 | AV10: 9 | AW10: 10 | AX10: 11 | AY10: 12 | AZ10: 13 | BA10: 14 | BB10: 15 | BC10: 16 | BD10: 17 | BE10: =BD10+1 -> 18 | BF10: =BE10+1 -> 19 | BG10: =BF10+1 -> 20 | BH10: =BG10+1 -> 21 | BI10: =BH10+1 -> 22 | BJ10: =BI10+1 -> 23 | BK10: =BJ10+1 -> 24 | BL10: =BK10+1 -> 25 | ... BO10: =BN10+1 -> 28 | CA10: CHANNEL | CB10: JANEIRO | CD10: FEVEREIRO
CB12: INS | CC12: INVESTIMENTO $ | CD12: INS | CE12: INVESTIMENTO $
B13: SÃO PAULO ESTADO | C13: TV GLOBO | D13: PRACA TV 1 EDICAO | E13: SEG-SEX | F13: 0.48958333 | G13: 13:00 | H13: 30 | AH13: 1 | AJ13: 1 | AL13: 1 | AP13: 1 | AR13: 1 | AV13: 1 | AX13: 1 | AZ13: 1 | BP13: =SUM(I13:BO13) -> 8 | BQ13: 64054 | BR13: 0.1 | BS13: =BQ13*(1-BR13) -> 57648.6 | BT13: =BS13*BP13 -> 461188.8 | BU13: =BT13*0.8 -> 368951.04 | BW13: 5.24 | BX13: =BW13*BP13 -> 41.92 | BY13: =IFERROR(BU13/BX13,0) -> 8801.313 | CA13: TV GLOBO | CB13: =COUNTA(I13:AM13) -> 3 | CC13: =CB13*BS13*0.8 -> 138356.64 | CD13: =COUNTA(AN13:BO13) -> 5 | CE13: =CD13*BS13*0.8 -> 230594.4 | CF13: =SUM(CC13,CE13)=BU13 -> TRUE
E14: SEG-SEX | F14: 0.48958333 | G14: 13:00 | H14: 60 | AE14: 1 | BP14: =SUM(I14:BO14) -> 1 | BQ14: 128108 | BR14: 0.1 | BS14: =BQ14*(1-BR14) -> 115297.2 | BT14: =BS14*BP14 -> 115297.2 | BU14: =BT14*0.8 -> 92237.76 | BW14: 5.24 | BX14: =BW14*BP14 -> 5.24 | BY14: =IFERROR(BU14/BX14,0) -> 17602.626 | CA14: TV GLOBO | CB14: =COUNTA(I14:AM14) -> 1 | CC14: =CB14*BS14*0.8 -> 92237.76 | CD14: =COUNTA(AN14:BO14) -> 0 | CE14: =CD14*BS14*0.8 -> 0 | CF14: =SUM(CC14,CE14)=BU14 -> TRUE
D15: PRACA TV 2 EDICAO | E15: SEG-SEX | F15: 0.79861111 | G15: 19:40 | H15: 30 | AK15: 1 | AO15: 1 | AS15: 1 | AY15: 1 | BP15: =SUM(I15:BO15) -> 4 | BQ15: 200802 | BR15: 0.1 | BS15: =BQ15*(1-BR15) -> 180721.8 | BT15: =BS15*BP15 -> 722887.2 | BU15: =BT15*0.8 -> 578309.76 | BW15: 12.39 | BX15: =BW15*BP15 -> 49.56 | BY15: =IFERROR(BU15/BX15,0) -> 11668.881 | CA15: TV GLOBO | CB15: =COUNTA(I15:AM15) -> 1 | CC15: =CB15*BS15*0.8 -> 144577.44 | CD15: =COUNTA(AN15:BO15) -> 3 | CE15: =CD15*BS15*0.8 -> 433732.32 | CF15: =SUM(CC15,CE15)=BU15 -> TRUE
E16: SEG-SEX | F16: 0.79861111 | G16: 19:40 | H16: 60 | AD16: 1 | BP16: =SUM(I16:BO16) -> 1 | BQ16: 401604 | BR16: 0.1 | BS16: =BQ16*(1-BR16) -> 361443.6 | BT16: =BS16*BP16 -> 361443.6 | BU16: =BT16*0.8 -> 289154.88 | BW16: 12.39 | BX16: =BW16*BP16 -> 12.39 | BY16: =IFERROR(BU16/BX16,0) -> 23337.763 | CA16: TV GLOBO | CB16: =COUNTA(I16:AM16) -> 1 | CC16: =CB16*BS16*0.8 -> 289154.88 | CD16: =COUNTA(AN16:BO16) -> 0 | CE16: =CD16*BS16*0.8 -> 0 | CF16: =SUM(CC16,CE16)=BU16 -> TRUE
CA17: TT | CB17: =SUM(CB13:CB16) -> 6 | CC17: =SUM(CC13:CC16) -> 664326.72 | CD17: =SUM(CD13:CD16) -> 8 | CE17: =SUM(CE13:CE16) -> 664326.72
C18: BANDEIRANTES | D18: JORNAL DA BAND | E18: SEG-SEX | F18: 0.80555556 | G18: 20:30 | H18: 30 | AI18: 1 | AK18: 1 | AP18: 1 | AR18: 1 | AW18: 1 | AY18: 1 | BP18: =SUM(I18:BO18) -> 6 | BQ18: 190834 | BR18: 0.85 | BS18: =BQ18*(1-BR18) -> 28625.1 | BT18: =BS18*BP18 -> 171750.6 | BU18: =BT18*0.8 -> 137400.48 | BW18: 1.59 | BX18: =BW18*BP18 -> 9.54 | BY18: =IFERROR(BU18/BX18,0) -> 14402.566 | CA18: BANDEIRANTES | CB18: =COUNTA(I18:AM18) -> 2 | CC18: =CB18*BS18*0.8 -> 45800.16 | CD18: =COUNTA(AN18:BO18) -> 4 | CE18: =CD18*BS18*0.8 -> 91600.32 | CF18: =SUM(CC18,CE18)=BU18 -> TRUE
E19: SEG-SEX | F19: 0.80555556 | G19: 20:30 | H19: 60 | AD19: 1 | BP19: =SUM(I19:BO19) -> 1 | BQ19: 381668 | BR19: 0.85 | BS19: =BQ19*(1-BR19) -> 57250.2 | BT19: =BS19*BP19 -> 57250.2 | BU19: =BT19*0.8 -> 45800.16 | BW19: 1.59 | BX19: =BW19*BP19 -> 1.59 | BY19: =IFERROR(BU19/BX19,0) -> 28805.132 | CA19: BANDEIRANTES | CB19: =COUNTA(I19:AM19) -> 1 | CC19: =CB19*BS19*0.8 -> 45800.16 | CD19: =COUNTA(AN19:BO19) -> 0 | CE19: =CD19*BS19*0.8 -> 0 | CF19: =SUM(CC19,CE19)=BU19 -> TRUE
CA20: TT | CB20: =SUM(CB18:CB19) -> 3 | CC20: =SUM(CC18:CC19) -> 91600.32 | CD20: =SUM(CD18:CD19) -> 4 | CE20: =SUM(CE18:CE19) -> 91600.32
C21: RECORD | D21: JORNAL DA RECORD | E21: SEG-SEX | F21: 0.82986111 | G21: 21:00 | H21: 30 | AJ21: 1 | AL21: 1 | AQ21: 1 | AS21: 1 | AX21: 1 | AZ21: 1 | BP21: =SUM(I21:BO21) -> 6 | BQ21: 405550 | BR21: 0.8 | BS21: =BQ21*(1-BR21) -> 81110 | BT21: =BS21*BP21 -> 486660 | BU21: =BT21*0.8 -> 389328 | BW21: 3.53 | BX21: =BW21*BP21 -> 21.18 | BY21: =IFERROR(BU21/BX21,0) -> 18381.87 | CA21: RECORD | CB21: =COUNTA(I21:AM21) -> 2 | CC21: =CB21*BS21*0.8 -> 129776 | CD21: =COUNTA(AN21:BO21) -> 4 | CE21: =CD21*BS21*0.8 -> 259552 | CF21: =SUM(CC21,CE21)=BU21 -> TRUE
E22: SEG-SEX | F22: 0.82986111 | G22: 21:00 | H22: 60 | AE22: 1 | BP22: =SUM(I22:BO22) -> 1 | BQ22: 811100 | BR22: 0.8 | BS22: =BQ22*(1-BR22) -> 162220 | BT22: =BS22*BP22 -> 162220 | BU22: =BT22*0.8 -> 129776 | BW22: 3.53 | BX22: =BW22*BP22 -> 3.53 | BY22: =IFERROR(BU22/BX22,0) -> 36763.739 | CA22: RECORD | CB22: =COUNTA(I22:AM22) -> 1 | CC22: =CB22*BS22*0.8 -> 129776 | CD22: =COUNTA(AN22:BO22) -> 0 | CE22: =CD22*BS22*0.8 -> 0 | CF22: =SUM(CC22,CE22)=BU22 -> TRUE
CA23: TT | CB23: =SUM(CB21:CB22) -> 3 | CC23: =SUM(CC21:CC22) -> 259552 | CD23: =SUM(CD21:CD22) -> 4 | CE23: =SUM(CE21:CE22) -> 259552
C24: SBT | D24: SBT BRASIL | E24: SEG-SEX | F24: 0.82291667 | G24: 21:00 | H24: 30 | AI24: 1 | AK24: 1 | AP24: 1 | AR24: 1 | AW24: 1 | AY24: 1 | BP24: =SUM(I24:BO24) -> 6 | BQ24: 201971 | BR24: 0.75 | BS24: =BQ24*(1-BR24) -> 50492.75 | BT24: =BS24*BP24 -> 302956.5 | BU24: =BT24*0.8 -> 242365.2 | BW24: 1.91 | BX24: =BW24*BP24 -> 11.46 | BY24: =IFERROR(BU24/BX24,0) -> 21148.796 | CA24: SBT | CB24: =COUNTA(I24:AM24) -> 2 | CC24: =CB24*BS24*0.8 -> 80788.4 | CD24: =COUNTA(AN24:BO24) -> 4 | CE24: =CD24*BS24*0.8 -> 161576.8 | CF24: =SUM(CC24,CE24)=BU24 -> TRUE
CA25: TT | CB25: =SUM(CB24) -> 2 | CC25: =SUM(CC24) -> 80788.4 | CD25: =SUM(CD24) -> 4 | CE25: =SUM(CE24) -> 161576.8
B27: TT OPEN TV | I27: =COUNTA(I12:I16) -> 0 | J27: =COUNTA(J12:J16) -> 0 | K27: =COUNTA(K12:K16) -> 0 | L27: =COUNTA(L12:L16) -> 0 | M27: =COUNTA(M12:M16) -> 0 | N27: =SUM(N12:N16) -> 0 | O27: =SUM(O12:O16) -> 0 | P27: =SUM(P12:P16) -> 0 | Q27: =SUM(Q12:Q25) -> 0 | R27: =SUM(R12:R25) -> 0 | S27: =SUM(S12:S25) -> 0 | T27: =SUM(T12:T25) -> 0 | U27: =SUM(U12:U25) -> 0 | V27: =SUM(V12:V25) -> 0 | W27: =SUM(W12:W25) -> 0 | X27: =SUM(X12:X25) -> 0 | ... BJ27: =SUM(BJ12:BJ25) -> 0 | BK27: =SUM(BK13:BK26) -> 0 | BL27: =SUM(BL13:BL26) -> 0 | BM27: =SUM(BM12:BM16) -> 0 | BN27: =SUM(BN12:BN16) -> 0 | BO27: =SUM(BO12:BO16) -> 0 | BP27: =SUM(BP13:BP25) -> 34 | BT27: =SUM(BT13:BT25) -> 2841654.1 | BU27: =SUM(BU13:BU25) -> 2273323.3 | BX27: =SUM(BX13:BX25) -> 156.41 | BY27: =BU27/BX27 -> 14534.386 | CA27: TT GERAL | CB27: =CB17+CB20+CB23+CB25 -> 14 | CC27: =CC17+CC20+CC23+CC25 -> 1096267.4 | CD27: =CD17+CD20+CD23+CD25 -> 20 | CE27: =CE17+CE20+CE23+CE25 -> 1177055.8
BT28: UTILIZAÇÃO DE PACOTE | BU28: =SUM(BU24:BU24) -> 242365.2
BT29: TOTAL FATURÁVEL | BU29: =BU27-BU28 -> 2030958.1 | CD29: TT | CE29: =CC27+CE27 -> 2273323.3
CE30: =CE29=BU27 -> TRUE

Sheet TV PAGA - COLCHÃO REP - SP1
B5: CLIENT: SABESP
B6: CAMPAING: ESCASSEZ HIDRICA - CRÍTICO
BW7: PLANNED
B8: MARKET | C8: CHANNEL | D8: PROGRAMM | E8: DAY | F8: START TIME | G8: END TIME | H8: SEC | I8: JANEIRO | BP8: INS. | BQ8: CUSTO TABELA UNITÁRIO (BRUTO) | BR8: DESC. % | BS8: CUSTO NEGOCIADO UNITÁRIO (BRUTO) | BT8: CUSTO TOTAL NEGOCIADO (BRUTO) | BU8: CUSTO TOTAL DESEMBOLSO SABESP | BW8: AUD. AS ABCDE 25+ | BX8: TRP | BY8: CPP | CA8: RESUMO
I9: T | J9: F | K9: S | L9: S | M9: M | N9: T | O9: W | P9: T | Q9: F | R9: S | S9: S | T9: M | U9: T | V9: W | W9: T | X9: F | Y9: S | Z9: S | AA9: M | AB9: T | AC9: W | AD9: T | AE9: F | AF9: S | AG9: S | AH9: M | AI9: T | AJ9: W | AK9: T | AL9: F | AM9: S | AN9: S | AO9: M | AP9: T | AQ9: W | AR9: T | AS9: F | AT9: S | AU9: S | AV9: M | AW9: T | AX9: W | AY9: T | AZ9: F | BA9: S | BB9: S | BC9: M | BD9: T | BE9: W | BF9: T | BG9: F | BH9: S | BI9: S | BJ9: M | BK9: T | BL9: W | BM9: T | BN9: F | BO9: S
I10: 1 | J10: 2 | K10: 3 | L10: 4 | M10: 5 | N10: 6 | O10: 7 | P10: 8 | Q10: 9 | R10: 10 | S10: 11 | T10: 12 | U10: 13 | V10: 14 | W10: 15 | X10: 16 | Y10: 17 | Z10: =Y10+1 -> 18 | AA10: =Z10+1 -> 19 | AB10: =AA10+1 -> 20 | AC10: =AB10+1 -> 21 | AD10: =AC10+1 -> 22 | AE10: =AD10+1 -> 23 | AF10: =AE10+1 -> 24 | AG10: =AF10+1 -> 25 | ... AM10: =AL10+1 -> 31 | AN10: 1 | AO10: 2 | AP10: 3 | AQ10: 4 | AR10: 5 | AS10: 6 | AT10: 7 | AU10: 8 | AV10: 9 | AW10: 10 | AX10: 11 | AY10: 12 | AZ10: 13 | BA10: 14 | BB10: 15 | BC10: 16 | BD10: 17 | BE10: =BD10+1 -> 18 | BF10: =BE10+1 -> 19 | BG10: =BF10+1 -> 20 | BH10: =BG10+1 -> 21 | BI10: =BH10+1 -> 22 | BJ10: =BI10+1 -> 23 | BK10: =BJ10+1 -> 24 | BL10: =BK10+1 -> 25 | ... BO10: =BN10+1 -> 28 | CA10: CHANNEL | CB10: JANEIRO | CD10: FEVEREIRO
CB12: INS | CC12: INVESTIMENTO $ | CD12: INS | CE12: INVESTIMENTO $
B13: SÃO PAULO CAPITAL | C13: GLOBONEWS | D13: GLOBO NEWS EM PAUTA | E13: SEG-SEX | F13: 0.83333333 | G13: 22:00 | H13: 30 | AI13: 1 | AK13: 1 | AO13: 1 | AR13: 1 | AV13: 1 | AX13: 1 | BP13: =SUM(I13:BO13) -> 6 | BQ13: 4180 | BR13: 0.4 | BS13: =BQ13*(1-BR13) -> 2508 | BT13: =BS13*BP13 -> 15048 | BU13: =BT13*0.8 -> 12038.4 | BW13: 0.05 | BX13: =BW13*BP13 -> 0.3 | BY13: =IFERROR(BU13/BX13,0) -> 40128 | CA13: GLOBONEWS | CB13: =COUNTA(I13:AM13) -> 2 | CC13: =CB13*BS13*0.8 -> 4012.8 | CD13: =COUNTA(AN13:BO13) -> 4 | CE13: =CD13*BS13*0.8 -> 8025.6 | CF13: =SUM(CC13,CE13)=BU13 -> TRUE
E14: SEG-SEX | F14: 0.83333333 | G14: 22:00 | H14: 60 | AE14: 1 | BP14: =SUM(I14:BO14) -> 1 | BQ14: 8360 | BR14: 0.4 | BS14: =BQ14*(1-BR14) -> 5016 | BT14: =BS14*BP14 -> 5016 | BU14: =BT14*0.8 -> 4012.8 | BW14: 0.05 | BX14: =BW14*BP14 -> 0.05 | BY14: =IFERROR(BU14/BX14,0) -> 80256 | CA14: GLOBONEWS | CB14: =COUNTA(I14:AM14) -> 1 | CC14: =CB14*BS14*0.8 -> 4012.8 | CD14: =COUNTA(AN14:BO14) -> 0 | CE14: =CD14*BS14*0.8 -> 0 | CF14: =SUM(CC14,CE14)=BU14 -> TRUE
D15: JORNAL DAS DEZ P | E15: SEG-SEX | F15: 0.91666667 | G15: 00:00 | H15: 30 | AH15: 1 | AJ15: 1 | AP15: 1 | AS15: 1 | AW15: 1 | AY15: 1 | BP15: =SUM(I15:BO15) -> 6 | BQ15: 5760 | BR15: 0.4 | BS15: =BQ15*(1-BR15) -> 3456 | BT15: =BS15*BP15 -> 20736 | BU15: =BT15*0.8 -> 16588.8 | BW15: 0.05 | BX15: =BW15*BP15 -> 0.3 | BY15: =IFERROR(BU15/BX15,0) -> 55296 | CA15: GLOBONEWS | CB15: =COUNTA(I15:AM15) -> 2 | CC15: =CB15*BS15*0.8 -> 5529.6 | CD15: =COUNTA(AN15:BO15) -> 4 | CE15: =CD15*BS15*0.8 -> 11059.2 | CF15: =SUM(CC15,CE15)=BU15 -> TRUE
E16: SEG-SEX | F16: 0.91666667 | G16: 00:00 | H16: 60 | AD16: 1 | BP16: =SUM(I16:BO16) -> 1 | BQ16: 11520 | BR16: 0.4 | BS16: =BQ16*(1-BR16) -> 6912 | BT16: =BS16*BP16 -> 6912 | BU16: =BT16*0.8 -> 5529.6 | BW16: 0.05 | BX16: =BW16*BP16 -> 0.05 | BY16: =IFERROR(BU16/BX16,0) -> 110592 | CA16: GLOBONEWS | CB16: =COUNTA(I16:AM16) -> 1 | CC16: =CB16*BS16*0.8 -> 5529.6 | CD16: =COUNTA(AN16:BO16) -> 0 | CE16: =CD16*BS16*0.8 -> 0 | CF16: =SUM(CC16,CE16)=BU16 -> TRUE
CA17: TT | CB17: =SUM(CB13:CB16) -> 6 | CC17: =SUM(CC13:CC16) -> 19084.8 | CD17: =SUM(CD13:CD16) -> 8 | CE17: =SUM(CE13:CE16) -> 19084.8
C18: CNN BRASIL | D18: CNN PRIME TIME P | E18: SEG-SEX | F18: 0.83333333 | G18: 22:00 | H18: 30 | AI18: 1 | AK18: 1 | AP18: 1 | AR18: 1 | AV18: 1 | AX18: 1 | BP18: =SUM(I18:BO18) -> 6 | BQ18: 11130 | BR18: 0.5 | BS18: =BQ18*(1-BR18) -> 5565 | BT18: =BS18*BP18 -> 33390 | BU18: =BT18*0.8 -> 26712 | BW18: 0.11 | BX18: =BW18*BP18 -> 0.66 | BY18: =IFERROR(BU18/BX18,0) -> 40472.727 | CA18: CNN BRASIL | CB18: =COUNTA(I18:AM18) -> 2 | CC18: =CB18*BS18*0.8 -> 8904 | CD18: =COUNTA(AN18:BO18) -> 4 | CE18: =CD18*BS18*0.8 -> 17808 | CF18: =SUM(CC18,CE18)=BU18 -> TRUE
E19: SEG-SEX | F19: 0.83333333 | G19: 22:00 | H19: 60 | AD19: 1 | BP19: =SUM(I19:BO19) -> 1 | BQ19: 22260 | BR19: 0.5 | BS19: =BQ19*(1-BR19) -> 11130 | BT19: =BS19*BP19 -> 11130 | BU19: =BT19*0.8 -> 8904 | BW19: 0.11 | BX19: =BW19*BP19 -> 0.11 | BY19: =IFERROR(BU19/BX19,0) -> 80945.455 | CA19: CNN BRASIL | CB19: =COUNTA(I19:AM19) -> 1 | CC19: =CB19*BS19*0.8 -> 8904 | CD19: =COUNTA(AN19:BO19) -> 0 | CE19: =CD19*BS19*0.8 -> 0 | CF19: =SUM(CC19,CE19)=BU19 -> TRUE
CA20: TT | CB20: =SUM(CB18:CB19) -> 3 | CC20: =SUM(CC18:CC19) -> 17808 | CD20: =SUM(CD18:CD19) -> 4 | CE20: =SUM(CE18:CE19) -> 17808
B21: SÃO PAULO ESTADO | C21: RECORD NEWS | D21: JORNAL RECORD NEWS | E21: SEG-SEX | F21: 0.875 | G21: 22:00 | H21: 30 | AI21: 1 | AL21: 1 | AR21: 1 | AS21: 1 | AW21: 1 | AZ21: 1 | BP21: =SUM(I21:BO21) -> 6 | BQ21: 22000 | BR21: 0.75 | BS21: =BQ21*(1-BR21) -> 5500 | BT21: =BS21*BP21 -> 33000 | BU21: =BT21*0.8 -> 26400 | BW21: 0.13 | BX21: =BW21*BP21 -> 0.78 | BY21: =IFERROR(BU21/BX21,0) -> 33846.154 | CA21: RECORD NEWS | CB21: =COUNTA(I21:AM21) -> 2 | CC21: =CB21*BS21*0.8 -> 8800 | CD21: =COUNTA(AN21:BO21) -> 4 | CE21: =CD21*BS21*0.8 -> 17600 | CF21: =SUM(CC21,CE21)=BU21 -> TRUE
E22: SEG-SEX | F22: 0.875 | G22: 22:00 | H22: 60 | AE22: 1 | BP22: =SUM(I22:BO22) -> 1 | BQ22: 44000 | BR22: 0.75 | BS22: =BQ22*(1-BR22) -> 11000 | BT22: =BS22*BP22 -> 11000 | BU22: =BT22*0.8 -> 8800 | BW22: 0.13 | BX22: =BW22*BP22 -> 0.13 | BY22: =IFERROR(BU22/BX22,0) -> 67692.308 | CA22: RECORD NEWS | CB22: =COUNTA(I22:AM22) -> 1 | CC22: =CB22*BS22*0.8 -> 8800 | CD22: =COUNTA(AN22:BO22) -> 0 | CE22: =CD22*BS22*0.8 -> 0 | CF22: =SUM(CC22,CE22)=BU22 -> TRUE
CA23: TT | CB23: =SUM(CB21:CB22) -> 3 | CC23: =SUM(CC21:CC22) -> 17600 | CD23: =SUM(CD21:CD22) -> 4 | CE23: =SUM(CE21:CE22) -> 17600
B24: SÃO PAULO CAPITAL | C24: BAND NEWS | D24: JOR BANDNEWS 2ED NOT | E24: SEG-SEX | F24: 0.8125 | G24: 0.85416667 | H24: 30 | AH24: 1 | AK24: 1 | AP24: 1 | AR24: 1 | AW24: 1 | AY24: 1 | BP24: =SUM(I24:BO24) -> 6 | BQ24: 9631 | BR24: 0.7 | BS24: =BQ24*(1-BR24) -> 2889.3 | BT24: =BS24*BP24 -> 17335.8 | BU24: =BT24*0.8 -> 13868.64 | BW24: 0.015 | BX24: =BW24*BP24 -> 0.09 | BY24: =IFERROR(BU24/BX24,0) -> 154096 | CA24: BAND NEWS | CB24: =COUNTA(I24:AM24) -> 2 | CC24: =CB24*BS24*0.8 -> 4622.88 | CD24: =COUNTA(AN24:BO24) -> 4 | CE24: =CD24*BS24*0.8 -> 9245.76 | CF24: =SUM(CC24,CE24)=BU24 -> TRUE
E25: SEG-SEX | F25: 0.8125 | G25: 0.85416667 | H25: 60 | AD25: 1 | BP25: =SUM(I25:BO25) -> 1 | BQ25: 19262 | BR25: 0.7 | BS25: =BQ25*(1-BR25) -> 5778.6 | BT25: =BS25*BP25 -> 5778.6 | BU25: =BT25*0.8 -> 4622.88 | BW25: 0.015 | BX25: =BW25*BP25 -> 0.015 | BY25: =IFERROR(BU25/BX25,0) -> 308192 | CA25: BAND NEWS | CB25: =COUNTA(I25:AM25) -> 1 | CC25: =CB25*BS25*0.8 -> 4622.88 | CD25: =COUNTA(AN25:BO25) -> 0 | CE25: =CD25*BS25*0.8 -> 0 | CF25: =SUM(CC25,CE25)=BU25 -> TRUE
CA26: TT | CB26: =SUM(CB24:CB25) -> 3 | CC26: =SUM(CC24:CC25) -> 9245.76 | CD26: =SUM(CD24:CD25) -> 4 | CE26: =SUM(CE24:CE25) -> 9245.76
B28: TT PAY TV | I28: =COUNTA(I12:I16) -> 0 | J28: =COUNTA(J12:J16) -> 0 | K28: =COUNTA(K12:K16) -> 0 | L28: =COUNTA(L12:L16) -> 0 | M28: =COUNTA(M12:M16) -> 0 | N28: =SUM(N12:N16) -> 0 | O28: =SUM(O12:O16) -> 0 | P28: =SUM(P12:P16) -> 0 | Q28: =SUM(Q12:Q26) -> 0 | R28: =SUM(R12:R26) -> 0 | S28: =SUM(S12:S26) -> 0 | T28: =SUM(T12:T26) -> 0 | U28: =SUM(U12:U26) -> 0 | V28: =SUM(V12:V26) -> 0 | W28: =SUM(W12:W26) -> 0 | X28: =SUM(X12:X26) -> 0 | ... BJ28: =SUM(BJ12:BJ26) -> 0 | BK28: =SUM(BK13:BK27) -> 0 | BL28: =SUM(BL13:BL27) -> 0 | BM28: =SUM(BM12:BM16) -> 0 | BN28: =SUM(BN12:BN16) -> 0 | BO28: =SUM(BO12:BO16) -> 0 | BP28: =SUM(BP13:BP26) -> 35 | BT28: =SUM(BT13:BT26) -> 159346.4 | BU28: =SUM(BU13:BU26) -> 127477.12 | BX28: =SUM(BX13:BX26) -> 2.485 | BY28: =BU28/BX28 -> 51298.64 | CA28: TT GERAL | CB28: =CB20+CB23+CB26 -> 9 | CC28: =CC17+CC20+CC23+CC26 -> 63738.56 | CD28: =CD20+CD23+CD26 -> 12 | CE28: =CE17+CE20+CE23+CE26 -> 63738.56
CD30: TT | CE30: =CC28+CE28 -> 127477.12
CE31: =CE30=BU28 -> TRUE

Sheet TV PAGA - COLCHÃO REP - SPE
B5: CLIENT: SABESP
B6: CAMPAING: ESCASSEZ HIDRICA - CRÍTICO
BW7: PLANNED
B8: MARKET | C8: CHANNEL | D8: PROGRAMM | E8: DAY | F8: START TIME | G8: END TIME | H8: SEC | I8: JANEIRO | BP8: INS. | BQ8: CUSTO TABELA UNITÁRIO (BRUTO) | BR8: DESC. % | BS8: CUSTO NEGOCIADO UNITÁRIO (BRUTO) | BT8: CUSTO TOTAL NEGOCIADO (BRUTO) | BU8: CUSTO TOTAL DESEMBOLSO SABESP | BW8: AUD. AS ABCDE 25+ | BX8: TRP | BY8: CPP | CA8: RESUMO
I9: T | J9: F | K9: S | L9: S | M9: M | N9: T | O9: W | P9: T | Q9: F | R9: S | S9: S | T9: M | U9: T | V9: W | W9: T | X9: F | Y9: S | Z9: S | AA9: M | AB9: T | AC9: W | AD9: T | AE9: F | AF9: S | AG9: S | AH9: M | AI9: T | AJ9: W | AK9: T | AL9: F | AM9: S | AN9: S | AO9: M | AP9: T | AQ9: W | AR9: T | AS9: F | AT9: S | AU9: S | AV9: M | AW9: T | AX9: W | AY9: T | AZ9: F | BA9: S | BB9: S | BC9: M | BD9: T | BE9: W | BF9: T | BG9: F | BH9: S | BI9: S | BJ9: M | BK9: T | BL9: W | BM9: T | BN9: F | BO9: S
I10: 1 | J10: 2 | K10: 3 | L10: 4 | M10: 5 | N10: 6 | O10: 7 | P10: 8 | Q10: 9 | R10: 10 | S10: 11 | T10: 12 | U10: 13 | V10: 14 | W10: 15 | X10: 16 | Y10: 17 | Z10: =Y10+1 -> 18 | AA10: =Z10+1 -> 19 | AB10: =AA10+1 -> 20 | AC10: =AB10+1 -> 21 | AD10: =AC10+1 -> 22 | AE10: =AD10+1 -> 23 | AF10: =AE10+1 -> 24 | AG10: =AF10+1 -> 25 | ... AM10: =AL10+1 -> 31 | AN10: 1 | AO10: 2 | AP10: 3 | AQ10: 4 | AR10: 5 | AS10: 6 | AT10: 7 | AU10: 8 | AV10: 9 | AW10: 10 | AX10: 11 | AY10: 12 | AZ10: 13 | BA10: 14 | BB10: 15 | BC10: 16 | BD10: 17 | BE10: =BD10+1 -> 18 | BF10: =BE10+1 -> 19 | BG10: =BF10+1 -> 20 | BH10: =BG10+1 -> 21 | BI10: =BH10+1 -> 22 | BJ10: =BI10+1 -> 23 | BK10: =BJ10+1 -> 24 | BL10: =BK10+1 -> 25 | ... BO10: =BN10+1 -> 28 | CA10: CHANNEL | CB10: JANEIRO | CD10: FEVEREIRO
CB12: INS | CC12: INVESTIMENTO $ | CD12: INS | CE12: INVESTIMENTO $
B13: SÃO PAULO ESTADO | C13: GLOBONEWS | D13: GLOBO NEWS EM PAUTA | E13: SEG-SEX | F13: 0.83333333 | G13: 22:00 | H13: 30 | AI13: 1 | AK13: 1 | AO13: 1 | AR13: 1 | AV13: 1 | AX13: 1 | BP13: =SUM(I13:BO13) -> 6 | BQ13: 4180 | BR13: 0.4 | BS13: =BQ13*(1-BR13) -> 2508 | BT13: =BS13*BP13 -> 15048 | BU13: =BT13*0.8 -> 12038.4 | BW13: 0.05 | BX13: =BW13*BP13 -> 0.3 | BY13: =IFERROR(BU13/BX13,0) -> 40128 | CA13: GLOBONEWS | CB13: =COUNTA(I13:AM13) -> 2 | CC13: =CB13*BS13*0.8 -> 4012.8 | CD13: =COUNTA(AN13:BO13) -> 4 | CE13: =CD13*BS13*0.8 -> 8025.6 | CF13: =SUM(CC13,CE13)=BU13 -> TRUE
C14: SP1 | E14: SEG-SEX | F14: 0.83333333 | G14: 22:00 | H14: 60 | AE14: 1 | BP14: =SUM(I14:BO14) -> 1 | BQ14: 8360 | BR14: 0.4 | BS14: =BQ14*(1-BR14) -> 5016 | BT14: =BS14*BP14 -> 5016 | BU14: =BT14*0.8 -> 4012.8 | BW14: 0.05 | BX14: =BW14*BP14 -> 0.05 | BY14: =IFERROR(BU14/BX14,0) -> 80256 | CA14: GLOBONEWS | CB14: =COUNTA(I14:AM14) -> 1 | CC14: =CB14*BS14*0.8 -> 4012.8 | CD14: =COUNTA(AN14:BO14) -> 0 | CE14: =CD14*BS14*0.8 -> 0 | CF14: =SUM(CC14,CE14)=BU14 -> TRUE
D15: JORNAL DAS DEZ P | E15: SEG-SEX | F15: 0.91666667 | G15: 00:00 | H15: 30 | AH15: 1 | AJ15: 1 | AP15: 1 | AS15: 1 | AW15: 1 | AY15: 1 | BP15: =SUM(I15:BO15) -> 6 | BQ15: 5760 | BR15: 0.4 | BS15: =BQ15*(1-BR15) -> 3456 | BT15: =BS15*BP15 -> 20736 | BU15: =BT15*0.8 -> 16588.8 | BW15: 0.05 | BX15: =BW15*BP15 -> 0.3 | BY15: =IFERROR(BU15/BX15,0) -> 55296 | CA15: GLOBONEWS | CB15: =COUNTA(I15:AM15) -> 2 | CC15: =CB15*BS15*0.8 -> 5529.6 | CD15: =COUNTA(AN15:BO15) -> 4 | CE15: =CD15*BS15*0.8 -> 11059.2 | CF15: =SUM(CC15,CE15)=BU15 -> TRUE
E16: SEG-SEX | F16: 0.91666667 | G16: 00:00 | H16: 60 | AD16: 1 | BP16: =SUM(I16:BO16) -> 1 | BQ16: 11520 | BR16: 0.4 | BS16: =BQ16*(1-BR16) -> 6912 | BT16: =BS16*BP16 -> 6912 | BU16: =BT16*0.8 -> 5529.6 | BW16: 0.05 | BX16: =BW16*BP16 -> 0.05 | BY16: =IFERROR(BU16/BX16,0) -> 110592 | CA16: GLOBONEWS | CB16: =COUNTA(I16:AM16) -> 1 | CC16: =CB16*BS16*0.8 -> 5529.6 | CD16: =COUNTA(AN16:BO16) -> 0 | CE16: =CD16*BS16*0.8 -> 0 | CF16: =SUM(CC16,CE16)=BU16 -> TRUE
C18: GLOBONEWS | D18: GLOBO NEWS EM PAUTA | E18: SEG-SEX | F18: 0.83333333 | G18: 22:00 | H18: 30 | AI18: 1 | AK18: 1 | AO18: 1 | AR18: 1 | AV18: 1 | AX18: 1 | BP18: =SUM(I18:BO18) -> 6 | BQ18: 640 | BR18: 0.4 | BS18: =BQ18*(1-BR18) -> 384 | BT18: =BS18*BP18 -> 2304 | BU18: =BT18*0.8 -> 1843.2 | BW18: 0.05 | BX18: =BW18*BP18 -> 0.3 | BY18: =IFERROR(BU18/BX18,0) -> 6144 | CA18: GLOBONEWS | CB18: =COUNTA(I18:AM18) -> 2 | CC18: =CB18*BS18*0.8 -> 614.4 | CD18: =COUNTA(AN18:BO18) -> 4 | CE18: =CD18*BS18*0.8 -> 1228.8 | CF18: =SUM(CC18,CE18)=BU18 -> TRUE
C19: SANTOS | E19: SEG-SEX | F19: 0.83333333 | G19: 22:00 | H19: 60 | AE19: 1 | BP19: =SUM(I19:BO19) -> 1 | BQ19: 1280 | BR19: 0.4 | BS19: =BQ19*(1-BR19) -> 768 | BT19: =BS19*BP19 -> 768 | BU19: =BT19*0.8 -> 614.4 | BW19: 0.05 | BX19: =BW19*BP19 -> 0.05 | BY19: =IFERROR(BU19/BX19,0) -> 12288 | CA19: GLOBONEWS | CB19: =COUNTA(I19:AM19) -> 1 | CC19: =CB19*BS19*0.8 -> 614.4 | CD19: =COUNTA(AN19:BO19) -> 0 | CE19: =CD19*BS19*0.8 -> 0 | CF19: =SUM(CC19,CE19)=BU19 -> TRUE
D20: JORNAL DAS DEZ P | E20: SEG-SEX | F20: 0.91666667 | G20: 00:00 | H20: 30 | AH20: 1 | AJ20: 1 | AP20: 1 | AS20: 1 | AW20: 1 | AY20: 1 | BP20: =SUM(I20:BO20) -> 6 | BQ20: 860 | BR20: 0.4 | BS20: =BQ20*(1-BR20) -> 516 | BT20: =BS20*BP20 -> 3096 | BU20: =BT20*0.8 -> 2476.8 | BW20: 0.05 | BX20: =BW20*BP20 -> 0.3 | BY20: =IFERROR(BU20/BX20,0) -> 8256 | CA20: GLOBONEWS | CB20: =COUNTA(I20:AM20) -> 2 | CC20: =CB20*BS20*0.8 -> 825.6 | CD20: =COUNTA(AN20:BO20) -> 4 | CE20: =CD20*BS20*0.8 -> 1651.2 | CF20: =SUM(CC20,CE20)=BU20 -> TRUE
E21: SEG-SEX | F21: 0.91666667 | G21: 00:00 | H21: 60 | AD21: 1 | BP21: =SUM(I21:BO21) -> 1 | BQ21: 1720 | BR21: 0.4 | BS21: =BQ21*(1-BR21) -> 1032 | BT21: =BS21*BP21 -> 1032 | BU21: =BT21*0.8 -> 825.6 | BW21: 0.05 | BX21: =BW21*BP21 -> 0.05 | BY21: =IFERROR(BU21/BX21,0) -> 16512 | CA21: GLOBONEWS | CB21: =COUNTA(I21:AM21) -> 1 | CC21: =CB21*BS21*0.8 -> 825.6 | CD21: =COUNTA(AN21:BO21) -> 0 | CE21: =CD21*BS21*0.8 -> 0 | CF21: =SUM(CC21,CE21)=BU21 -> TRUE
C23: GLOBONEWS | D23: GLOBO NEWS EM PAUTA | E23: SEG-SEX | F23: 0.83333333 | G23: 22:00 | H23: 30 | AI23: 1 | AK23: 1 | AO23: 1 | AR23: 1 | AV23: 1 | AX23: 1 | BP23: =SUM(I23:BO23) -> 6 | BQ23: 1140 | BR23: 0.4 | BS23: =BQ23*(1-BR23) -> 684 | BT23: =BS23*BP23 -> 4104 | BU23: =BT23*0.8 -> 3283.2 | BW23: 0.05 | BX23: =BW23*BP23 -> 0.3 | BY23: =IFERROR(BU23/BX23,0) -> 10944 | CA23: GLOBONEWS | CB23: =COUNTA(I23:AM23) -> 2 | CC23: =CB23*BS23*0.8 -> 1094.4 | CD23: =COUNTA(AN23:BO23) -> 4 | CE23: =CD23*BS23*0.8 -> 2188.8 | CF23: =SUM(CC23,CE23)=BU23 -> TRUE
C24: CAMPINAS | E24: SEG-SEX | F24: 0.83333333 | G24: 22:00 | H24: 60 | AE24: 1 | BP24: =SUM(I24:BO24) -> 1 | BQ24: 2280 | BR24: 0.4 | BS24: =BQ24*(1-BR24) -> 1368 | BT24: =BS24*BP24 -> 1368 | BU24: =BT24*0.8 -> 1094.4 | BW24: 0.05 | BX24: =BW24*BP24 -> 0.05 | BY24: =IFERROR(BU24/BX24,0) -> 21888 | CA24: GLOBONEWS | CB24: =COUNTA(I24:AM24) -> 1 | CC24: =CB24*BS24*0.8 -> 1094.4 | CD24: =COUNTA(AN24:BO24) -> 0 | CE24: =CD24*BS24*0.8 -> 0 | CF24: =SUM(CC24,CE24)=BU24 -> TRUE
D25: JORNAL DAS DEZ P | E25: SEG-SEX | F25: 0.91666667 | G25: 00:00 | H25: 30 | AH25: 1 | AJ25: 1 | AP25: 1 | AS25: 1 | AW25: 1 | AY25: 1 | BP25: =SUM(I25:BO25) -> 6 | BQ25: 1550 | BR25: 0.4 | BS25: =BQ25*(1-BR25) -> 930 | BT25: =BS25*BP25 -> 5580 | BU25: =BT25*0.8 -> 4464 | BW25: 0.05 | BX25: =BW25*BP25 -> 0.3 | BY25: =IFERROR(BU25/BX25,0) -> 14880 | CA25: GLOBONEWS | CB25: =COUNTA(I25:AM25) -> 2 | CC25: =CB25*BS25*0.8 -> 1488 | CD25: =COUNTA(AN25:BO25) -> 4 | CE25: =CD25*BS25*0.8 -> 2976 | CF25: =SUM(CC25,CE25)=BU25 -> TRUE
E26: SEG-SEX | F26: 0.91666667 | G26: 00:00 | H26: 60 | AD26: 1 | BP26: =SUM(I26:BO26) -> 1 | BQ26: 3100 | BR26: 0.4 | BS26: =BQ26*(1-BR26) -> 1860 | BT26: =BS26*BP26 -> 1860 | BU26: =BT26*0.8 -> 1488 | BW26: 0.05 | BX26: =BW26*BP26 -> 0.05 | BY26: =IFERROR(BU26/BX26,0) -> 29760 | CA26: GLOBONEWS | CB26: =COUNTA(I26:AM26) -> 1 | CC26: =CB26*BS26*0.8 -> 1488 | CD26: =COUNTA(AN26:BO26) -> 0 | CE26: =CD26*BS26*0.8 -> 0 | CF26: =SUM(CC26,CE26)=BU26 -> TRUE
C28: GLOBONEWS | D28: GLOBO NEWS EM PAUTA | E28: SEG-SEX | F28: 0.83333333 | G28: 22:00 | H28: 30 | AI28: 1 | AK28: 1 | AO28: 1 | AR28: 1 | AV28: 1 | AX28: 1 | BP28: =SUM(I28:BO28) -> 6 | BQ28: 440 | BR28: 0.4 | BS28: =BQ28*(1-BR28) -> 264 | BT28: =BS28*BP28 -> 1584 | BU28: =BT28*0.8 -> 1267.2 | BW28: 0.05 | BX28: =BW28*BP28 -> 0.3 | BY28: =IFERROR(BU28/BX28,0) -> 4224 | CA28: GLOBONEWS | CB28: =COUNTA(I28:AM28) -> 2 | CC28: =CB28*BS28*0.8 -> 422.4 | CD28: =COUNTA(AN28:BO28) -> 4 | CE28: =CD28*BS28*0.8 -> 844.8 | CF28: =SUM(CC28,CE28)=BU28 -> TRUE
C29: RIBEIRÃO PRETO | E29: SEG-SEX | F29: 0.83333333 | G29: 22:00 | H29: 60 | AE29: 1 | BP29: =SUM(I29:BO29) -> 1 | BQ29: 880 | BR29: 0.4 | BS29: =BQ29*(1-BR29) -> 528 | BT29: =BS29*BP29 -> 528 | BU29: =BT29*0.8 -> 422.4 | BW29: 0.05 | BX29: =BW29*BP29 -> 0.05 | BY29: =IFERROR(BU29/BX29,0) -> 8448 | CA29: GLOBONEWS | CB29: =COUNTA(I29:AM29) -> 1 | CC29: =CB29*BS29*0.8 -> 422.4 | CD29: =COUNTA(AN29:BO29) -> 0 | CE29: =CD29*BS29*0.8 -> 0 | CF29: =SUM(CC29,CE29)=BU29 -> TRUE
D30: JORNAL DAS DEZ P | E30: SEG-SEX | F30: 0.91666667 | G30: 00:00 | H30: 30 | AH30: 1 | AJ30: 1 | AP30: 1 | AS30: 1 | AW30: 1 | AY30: 1 | BP30: =SUM(I30:BO30) -> 6 | BQ30: 600 | BR30: 0.4 | BS30: =BQ30*(1-BR30) -> 360 | BT30: =BS30*BP30 -> 2160 | BU30: =BT30*0.8 -> 1728 | BW30: 0.05 | BX30: =BW30*BP30 -> 0.3 | BY30: =IFERROR(BU30/BX30,0) -> 5760 | CA30: GLOBONEWS | CB30: =COUNTA(I30:AM30) -> 2 | CC30: =CB30*BS30*0.8 -> 576 | CD30: =COUNTA(AN30:BO30) -> 4 | CE30: =CD30*BS30*0.8 -> 1152 | CF30: =SUM(CC30,CE30)=BU30 -> TRUE
E31: SEG-SEX | F31: 0.91666667 | G31: 00:00 | H31: 60 | AD31: 1 | BP31: =SUM(I31:BO31) -> 1 | BQ31: 1200 | BR31: 0.4 | BS31: =BQ31*(1-BR31) -> 720 | BT31: =BS31*BP31 -> 720 | BU31: =BT31*0.8 -> 576 | BW31: 0.05 | BX31: =BW31*BP31 -> 0.05 | BY31: =IFERROR(BU31/BX31,0) -> 11520 | CA31: GLOBONEWS | CB31: =COUNTA(I31:AM31) -> 1 | CC31: =CB31*BS31*0.8 -> 576 | CD31: =COUNTA(AN31:BO31) -> 0 | CE31: =CD31*BS31*0.8 -> 0 | CF31: =SUM(CC31,CE31)=BU31 -> TRUE
C33: GLOBONEWS | D33: GLOBO NEWS EM PAUTA | E33: SEG-SEX | F33: 0.83333333 | G33: 22:00 | H33: 30 | AI33: 1 | AK33: 1 | AO33: 1 | AR33: 1 | AV33: 1 | AX33: 1 | BP33: =SUM(I33:BO33) -> 6 | BQ33: 440 | BR33: 0.4 | BS33: =BQ33*(1-BR33) -> 264 | BT33: =BS33*BP33 -> 1584 | BU33: =BT33*0.8 -> 1267.2 | BW33: 0.05 | BX33: =BW33*BP33 -> 0.3 | BY33: =IFERROR(BU33/BX33,0) -> 4224 | CA33: GLOBONEWS | CB33: =COUNTA(I33:AM33) -> 2 | CC33: =CB33*BS33*0.8 -> 422.4 | CD33: =COUNTA(AN33:BO33) -> 4 | CE33: =CD33*BS33*0.8 -> 844.8 | CF33: =SUM(CC33,CE33)=BU33 -> TRUE
C34: SÃO JOSÉ DOS CAMPOS | E34: SEG-SEX | F34: 0.83333333 | G34: 22:00 | H34: 60 | AE34: 1 | BP34: =SUM(I34:BO34) -> 1 | BQ34: 880 | BR34: 0.4 | BS34: =BQ34*(1-BR34) -> 528 | BT34: =BS34*BP34 -> 528 | BU34: =BT34*0.8 -> 422.4 | BW34: 0.05 | BX34: =BW34*BP34 -> 0.05 | BY34: =IFERROR(BU34/BX34,0) -> 8448 | CA34: GLOBONEWS | CB34: =COUNTA(I34:AM34) -> 1 | CC34: =CB34*BS34*0.8 -> 422.4 | CD34: =COUNTA(AN34:BO34) -> 0 | CE34: =CD34*BS34*0.8 -> 0 | CF34: =SUM(CC34,CE34)=BU34 -> TRUE
D35: JORNAL DAS DEZ P | E35: SEG-SEX | F35: 0.91666667 | G35: 00:00 | H35: 30 | AH35: 1 | AJ35: 1 | AP35: 1 | AS35: 1 | AW35: 1 | AY35: 1 | BP35: =SUM(I35:BO35) -> 6 | BQ35: 600 | BR35: 0.4 | BS35: =BQ35*(1-BR35) -> 360 | BT35: =BS35*BP35 -> 2160 | BU35: =BT35*0.8 -> 1728 | BW35: 0.05 | BX35: =BW35*BP35 -> 0.3 | BY35: =IFERROR(BU35/BX35,0) -> 5760 | CA35: GLOBONEWS | CB35: =COUNTA(I35:AM35) -> 2 | CC35: =CB35*BS35*0.8 -> 576 | CD35: =COUNTA(AN35:BO35) -> 4 | CE35: =CD35*BS35*0.8 -> 1152 | CF35: =SUM(CC35,CE35)=BU35 -> TRUE
D36: JORNAL DAS DEZ P | E36: SEG-SEX | F36: 0.91666667 | G36: 00:00 | H36: 60 | AD36: 1 | BP36: =SUM(I36:BO36) -> 1 | BQ36: 1200 | BR36: 0.4 | BS36: =BQ36*(1-BR36) -> 720 | BT36: =BS36*BP36 -> 720 | BU36: =BT36*0.8 -> 576 | BW36: 0.05 | BX36: =BW36*BP36 -> 0.05 | BY36: =IFERROR(BU36/BX36,0) -> 11520 | CA36: GLOBONEWS | CB36: =COUNTA(I36:AM36) -> 1 | CC36: =CB36*BS36*0.8 -> 576 | CD36: =COUNTA(AN36:BO36) -> 0 | CE36: =CD36*BS36*0.8 -> 0 | CF36: =SUM(CC36,CE36)=BU36 -> TRUE
CA37: TT | CB37: =SUM(CB13:CB36) -> 30 | CC37: =SUM(CC13:CC36) -> 31123.2 | CD37: =SUM(CD13:CD36) -> 40 | CE37: =SUM(CE13:CE36) -> 31123.2
C38: CNN BRASIL | D38: CNN PRIME TIME P | E38: SEG-SEX | F38: 0.83333333 | G38: 22:00 | H38: 30 | AI38: 1 | AK38: 1 | AP38: 1 | AR38: 1 | AV38: 1 | AX38: 1 | BP38: =SUM(I38:BO38) -> 6 | BQ38: 11130 | BR38: 0.5 | BS38: =BQ38*(1-BR38) -> 5565 | BT38: =BS38*BP38 -> 33390 | BU38: =BT38*0.8 -> 26712 | BW38: 0.11 | BX38: =BW38*BP38 -> 0.66 | BY38: =IFERROR(BU38/BX38,0) -> 40472.727 | CA38: CNN BRASIL | CB38: =COUNTA(I38:AM38) -> 2 | CC38: =CB38*BS38*0.8 -> 8904 | CD38: =COUNTA(AN38:BO38) -> 4 | CE38: =CD38*BS38*0.8 -> 17808 | CF38: =SUM(CC38,CE38)=BU38 -> TRUE
E39: SEG-SEX | F39: 0.83333333 | G39: 22:00 | H39: 60 | AD39: 1 | BP39: =SUM(I39:BO39) -> 1 | BQ39: 22260 | BR39: 0.5 | BS39: =BQ39*(1-BR39) -> 11130 | BT39: =BS39*BP39 -> 11130 | BU39: =BT39*0.8 -> 8904 | BW39: 0.11 | BX39: =BW39*BP39 -> 0.11 | BY39: =IFERROR(BU39/BX39,0) -> 80945.455 | CA39: CNN BRASIL | CB39: =COUNTA(I39:AM39) -> 1 | CC39: =CB39*BS39*0.8 -> 8904 | CD39: =COUNTA(AN39:BO39) -> 0 | CE39: =CD39*BS39*0.8 -> 0 | CF39: =SUM(CC39,CE39)=BU39 -> TRUE
CA40: TT | CB40: =SUM(CB38:CB39) -> 3 | CC40: =SUM(CC38:CC39) -> 17808 | CD40: =SUM(CD38:CD39) -> 4 | CE40: =SUM(CE38:CE39) -> 17808
C41: RECORD NEWS | D41: JORNAL RECORD NEWS | E41: SEG-SEX | F41: 0.875 | G41: 22:00 | H41: 30 | AI41: 1 | AL41: 1 | AR41: 1 | AS41: 1 | AW41: 1 | AZ41: 1 | BP41: =SUM(I41:BO41) -> 6 | BQ41: 22000 | BR41: 0.75 | BS41: =BQ41*(1-BR41) -> 5500 | BT41: =BS41*BP41 -> 33000 | BU41: =BT41*0.8 -> 26400 | BW41: 0.13 | BX41: =BW41*BP41 -> 0.78 | BY41: =IFERROR(BU41/BX41,0) -> 33846.154 | CA41: RECORD NEWS | CB41: =COUNTA(I41:AM41) -> 2 | CC41: =CB41*BS41*0.8 -> 8800 | CD41: =COUNTA(AN41:BO41) -> 4 | CE41: =CD41*BS41*0.8 -> 17600 | CF41: =SUM(CC41,CE41)=BU41 -> TRUE
E42: SEG-SEX | F42: 0.875 | G42: 22:00 | H42: 60 | AE42: 1 | BP42: =SUM(I42:BO42) -> 1 | BQ42: 44000 | BR42: 0.75 | BS42: =BQ42*(1-BR42) -> 11000 | BT42: =BS42*BP42 -> 11000 | BU42: =BT42*0.8 -> 8800 | BW42: 0.13 | BX42: =BW42*BP42 -> 0.13 | BY42: =IFERROR(BU42/BX42,0) -> 67692.308 | CA42: RECORD NEWS | CB42: =COUNTA(I42:AM42) -> 1 | CC42: =CB42*BS42*0.8 -> 8800 | CD42: =COUNTA(AN42:BO42) -> 0 | CE42: =CD42*BS42*0.8 -> 0 | CF42: =SUM(CC42,CE42)=BU42 -> TRUE
CA43: TT | CB43: =SUM(CB41:CB42) -> 3 | CC43: =SUM(CC41:CC42) -> 17600 | CD43: =SUM(CD41:CD42) -> 4 | CE43: =SUM(CE41:CE42) -> 17600
B44: SÃO PAULO CAPITAL | C44: BAND NEWS | D44: JOR BANDNEWS 2ED NOT | E44: SEG-SEX | F44: 0.8125 | G44: 0.85416667 | H44: 30 | AH44: 1 | AK44: 1 | AP44: 1 | AR44: 1 | AW44: 1 | AY44: 1 | BP44: =SUM(I44:BO44) -> 6 | BQ44: 9631 | BR44: 0.7 | BS44: =BQ44*(1-BR44) -> 2889.3 | BT44: =BS44*BP44 -> 17335.8 | BU44: =BT44*0.8 -> 13868.64 | BW44: 0.015 | BX44: =BW44*BP44 -> 0.09 | BY44: =IFERROR(BU44/BX44,0) -> 154096 | CA44: BAND NEWS | CB44: =COUNTA(I44:AM44) -> 2 | CC44: =CB44*BS44*0.8 -> 4622.88 | CD44: =COUNTA(AN44:BO44) -> 4 | CE44: =CD44*BS44*0.8 -> 9245.76 | CF44: =SUM(CC44,CE44)=BU44 -> TRUE
E45: SEG-SEX | F45: 0.8125 | G45: 0.85416667 | H45: 60 | AD45: 1 | BP45: =SUM(I45:BO45) -> 1 | BQ45: 19262 | BR45: 0.7 | BS45: =BQ45*(1-BR45) -> 5778.6 | BT45: =BS45*BP45 -> 5778.6 | BU45: =BT45*0.8 -> 4622.88 | BW45: 0.015 | BX45: =BW45*BP45 -> 0.015 | BY45: =IFERROR(BU45/BX45,0) -> 308192 | CA45: BAND NEWS | CB45: =COUNTA(I45:AM45) -> 1 | CC45: =CB45*BS45*0.8 -> 4622.88 | CD45: =COUNTA(AN45:BO45) -> 0 | CE45: =CD45*BS45*0.8 -> 0 | CF45: =SUM(CC45,CE45)=BU45 -> TRUE
CA46: TT | CB46: =SUM(CB44:CB45) -> 3 | CC46: =SUM(CC44:CC45) -> 9245.76 | CD46: =SUM(CD44:CD45) -> 4 | CE46: =SUM(CE44:CE45) -> 9245.76
B48: TT PAY TV | I48: =COUNTA(I12:I16) -> 0 | J48: =COUNTA(J12:J16) -> 0 | K48: =COUNTA(K12:K16) -> 0 | L48: =COUNTA(L12:L16) -> 0 | M48: =COUNTA(M12:M16) -> 0 | N48: =SUM(N12:N16) -> 0 | O48: =SUM(O12:O16) -> 0 | P48: =SUM(P12:P16) -> 0 | Q48: =SUM(Q12:Q46) -> 0 | R48: =SUM(R12:R46) -> 0 | S48: =SUM(S12:S46) -> 0 | T48: =SUM(T12:T46) -> 0 | U48: =SUM(U12:U46) -> 0 | V48: =SUM(V12:V46) -> 0 | W48: =SUM(W12:W46) -> 0 | X48: =SUM(X12:X46) -> 0 | ... BJ48: =SUM(BJ12:BJ46) -> 0 | BK48: =SUM(BK13:BK47) -> 0 | BL48: =SUM(BL13:BL47) -> 0 | BM48: =SUM(BM12:BM16) -> 0 | BN48: =SUM(BN12:BN16) -> 0 | BO48: =SUM(BO12:BO16) -> 0 | BP48: =SUM(BP13:BP46) -> 91 | BT48: =SUM(BT13:BT46) -> 189442.4 | BU48: =SUM(BU13:BU46) -> 151553.92 | BX48: =SUM(BX13:BX45) -> 5.285 | BY48: =BU48/BX48 -> 28676.238 | CA48: TT GERAL | CB48: =CB17+CB40+CB43+CB46 -> 9 | CC48: =CC37+CC40+CC43+CC46 -> 75776.96 | CD48: =CD17+CD40+CD43+CD46 -> 12 | CE48: =CE37+CE40+CE43+CE46 -> 75776.96
CD50: TT | CE50: =CC48+CE48 -> 151553.92
CE51: =CE50=BU48 -> TRUE

Sheet RÁDIO versão completa
B5: CLIENT: SABESP
B6: CAMPAING: VERÃO 25/26
B8: MARKET | C8: CHANNEL | D8: PROPERTY | E8: FORMAT: LOCUÇÃO DE CABINE | F8: OUTUBRO | AK8: NOVEMBRO | BD8: DEZEMBRO | BH8: JANEIRO | BO8: INS. | BP8: CUSTO TABELA UNITÁRIO (BRUTO) | BQ8: DESC. % | BR8: CUSTO NEGOCIADO UNITÁRIO (BRUTO) | BS8: CUSTO TOTAL NEGOCIADO (BRUTO) | BT8: CUSTO TOTAL DESEMBOLSO CLIENTE | BV8: SHARE DE INVESTIMENTO % | BW8: SHARE DE AUDIÊNCIA % | BY8: IA% | BZ8: IA# | CA8: TRP | CB8: POPULAÇÃO TT. | CC8: UNIV. RÁDIO AS ABCDE 18+ | CD8: IMPACTOS ESTIMADOS | CE8: CPM | CG8: RÁDIO | CH8: VALOR UNITÁRIO LIQUIDO | CI8: DEZEMBRO | CK8: JANEIRO
F9: W | G9: T | H9: F | I9: S | J9: S | K9: M | L9: T | M9: W | N9: T | O9: F | P9: S | Q9: S | R9: M | S9: T | T9: W | U9: T | V9: F | W9: S | X9: S | Y9: M | Z9: T | AA9: W | AB9: T | AC9: F | AD9: S | AE9: S | AF9: M | AG9: T | AH9: W | AI9: T | AJ9: F | AK9: S | AL9: S | AM9: M | AN9: T | AO9: W | AP9: T | AQ9: F | AR9: S | AS9: S | AT9: M | AU9: T | AV9: W | AW9: T | AX9: F | AY9: S | AZ9: S | BA9: M | BB9: T | BC9: W | BD9: S | BE9: M | BF9: T | BG9: W | BH9: T | BI9: F | BJ9: S | BK9: S | BL9: F | BM9: S | BN9: S
F10: 1 | G10: 2 | H10: 3 | I10: 4 | J10: 5 | K10: 6 | L10: 7 | M10: 8 | N10: 9 | O10: 10 | P10: 11 | Q10: 12 | R10: 13 | S10: 14 | T10: 15 | U10: 16 | V10: 17 | W10: 18 | X10: 19 | Y10: 20 | Z10: 21 | AA10: 22 | AB10: 23 | AC10: 24 | AD10: 25 | AE10: 26 | AF10: 27 | AG10: 28 | AH10: 29 | AI10: 30 | AJ10: 31 | AK10: 1 | AL10: 2 | AM10: 3 | AN10: 4 | AO10: 5 | AP10: 6 | AQ10: 7 | AR10: 8 | AS10: 9 | AT10: 10 | AU10: 11 | AV10: 12 | AW10: 13 | AX10: 14 | AY10: 15 | AZ10: 16 | BA10: 17 | BB10: 18 | BC10: 19 | BD10: 28 | BE10: =BD10+1 -> 29 | BF10: =BE10+1 -> 30 | BG10: =BF10+1 -> 31 | BH10: 1 | BI10: =BH10+1 -> 2 | BJ10: =BI10+1 -> 3 | BK10: =BJ10+1 -> 4 | BL10: =BK10+1 -> 5 | BM10: =BL10+1 -> 6 | BN10: =BM10+1 -> 7 | CI10: INS. | CJ10: INV. LIQUIDO | CK10: INS. | CL10: INV. LIQUIDO
B13: RÁDIO JORNALISMO | C13: JOVEM PAN
B14: SÃO PAULO - CAPITAL | C14: ROTATIVO | D14: SEG À SEX 06H00-19H00 | E14: 30'' | BE14: 3 | BF14: 3 | BG14: 3 | BH14: 3 | BI14: 3 | BJ14: 3 | BK14: 3 | BL14: 3 | BO14: =SUM(F14:BN14) -> 24 | BP14: =13891.5 -> 13891.5 | BQ14: 0.6599 | BR14: =BP14*(1-BQ14) -> 4724.4991 | BS14: =BR14*BO14 -> 113387.98 | BT14: =BS14*0.8 -> 90710.384 | BV14: {=SUM(BT14:BT15/$BT$29)} -> 0.31554698 | BW14: 0.31796335 | BY14: 0.97 | BZ14: 97631 | CA14: =BY14*BO14 -> 23.28 | CB14: 11451245 | CC14: 16255139 | CD14: =CC14*CA14/100 -> 3784196.4 | CE14: =SUM(BT14:BT15)/SUM(CD14:CD15)*1000 -> 19.997899 | CG14: JOVEM PAN | CH14: =BR14*0.8 -> 3779.5993 | CI14: =SUM(AK14:BG14) -> 9 | CJ14: =CH14*CI14 -> 34016.394 | CK14: =SUM(BH14:BN14) -> 15 | CL14: =CK14*CH14 -> 56693.99 | CM14: =(CJ14+CL14)=BT14 -> TRUE
C15: FAIXA MUSICAL | D15: SEG À SEX 14H00-24H00 | E15: 30'' | BE15: 1 | BF15: 1 | BG15: 1 | BH15: 1 | BI15: 1 | BJ15: 1 | BK15: 1 | BL15: 1 | BO15: =SUM(F15:BN15) -> 8 | BP15: =4681.95 -> 4681.95 | BQ15: 0.6599 | BR15: =BP15*(1-BQ15) -> 1592.3312 | BS15: =BR15*BO15 -> 12738.65 | BT15: =BS15*0.8 -> 10190.92 | BY15: 0.97 | BZ15: 97631 | CA15: =BY15*BO15 -> 7.76 | CB15: 11451245 | CC15: 16255139 | CD15: =CC15*CA15/100 -> 1261398.8 | CH15: =BR15*0.8 -> 1273.865 | CI15: =SUM(AK15:BG15) -> 3 | CJ15: =CH15*CI15 -> 3821.5949 | CK15: =SUM(BH15:BN15) -> 5 | CL15: =CK15*CH15 -> 6369.3248 | CM15: =(CJ15+CL15)=BT15 -> TRUE
C18: BAND NEWS FM | D18: SEG À SEX 06H00-19H00 | E18: 30'' | BE18: 5 | BF18: 5 | BG18: 5 | BH18: 4 | BI18: 4 | BJ18: 4 | BK18: 4 | BL18: 4 | BO18: =SUM(F18:BN18) -> 35 | BP18: =7604 -> 7604 | BQ18: 0.65 | BR18: =BP18*(1-BQ18) -> 2661.4 | BS18: =BR18*BO18 -> 93149 | BT18: =BS18*0.8 -> 74519.2 | BV18: =SUM(BT18:BT19)/$BT$29 -> 0.23304266 | BW18: 0.26616162 | BY18: 0.92 | BZ18: 81725 | CA18: =BY18*BO18 -> 32.2 | CB18: 11451245 | CC18: 16255139 | CD18: =CC18*CA18/100 -> 5234154.8 | CE18: =BT18/CD18*1000 -> 14.237103 | CG18: BAND NEWS FM | CH18: =BR18*0.8 -> 2129.12 | CI18: =SUM(AK18:BG18) -> 15 | CJ18: =CH18*CI18 -> 31936.8 | CK18: =SUM(BH18:BN18) -> 20 | CL18: =CK18*CH18 -> 42582.4 | CM18: =(CJ18+CL18)=BT18 -> TRUE
C19: ROTATIVO | E19: 30'' | BO19: =SUM(F19:BN19) -> 0 | BP19: =7604 -> 7604 | BQ19: 1 | BR19: =BP19*(1-BQ19) -> 0 | BS19: =BR19*BO19 -> 0 | BT19: =BS19*0.8 -> 0 | BY19: 0.92 | BZ19: 81725 | CA19: =BY19*BO19 -> 0 | CB19: 11451245 | CC19: 17116728 | CD19: =CC19*CA19/100 -> 0 | CE19: =BT19/CD19*1000 -> #DIV/0! | CH19: =BR19*0.8 -> 0 | CI19: =SUM(AK19:BN19) -> 0 | CJ19: =CH19*CI19 -> 0 | CK19: =SUM(AM19:BP19) -> 7604 | CL19: =CJ19*CK19 -> 0 | CM19: =SUM(#REF!,CJ19,#REF!)=BT19 -> #REF!
C22: BANDEIRANTES FM | D22: SEG À SEX 06H00-09H00 | E22: 30'' | BE22: 4 | BF22: 4 | BG22: 4 | BH22: 3 | BI22: 3 | BJ22: 3 | BK22: 3 | BL22: 3 | BO22: =SUM(F22:BN22) -> 27 | BP22: =8190 -> 8190 | BQ22: 0.65 | BR22: =BP22*(1-BQ22) -> 2866.5 | BS22: =BR22*BO22 -> 77395.5 | BT22: =BS22*0.8 -> 61916.4 | BV22: {=SUM(BT22:BT23/$BT$29)} -> 0.19363013 | BW22: 0.1968604 | BY22: 0.89 | BZ22: 60446 | CA22: =BY22*BO22 -> 24.03 | CB22: 11451245 | CC22: 16255139 | CD22: =CC22*(CA22+CA24)/100 -> 3906109.9 | CE22: =BT22/CD22*1000 -> 15.851167 | CG22: BANDEIRANTES FM | CH22: =BR22*0.8 -> 2293.2 | CI22: =SUM(AK22:BG22) -> 12 | CJ22: =CH22*CI22 -> 27518.4 | CK22: =SUM(BH22:BN22) -> 15 | CL22: =CK22*CH22 -> 34398 | CM22: =(CJ22+CL22)=BT22 -> TRUE
C23: ROTATIVO | E23: 30'' | BO23: =SUM(F23:BN23) -> 0 | BP23: =8190 -> 8190 | BQ23: 1 | BR23: =BP23*(1-BQ23) -> 0 | BS23: =BR23*BO23 -> 0 | BT23: =BS23*0.8 -> 0 | BY23: 0.89 | BZ23: 60446 | CA23: =BY23*BO23 -> 0 | CB23: 11451245 | CC23: 17116728 | CD23: =CC23*(CA23+CA25)/100 -> 0 | CE23: =BT23/CD23*1000 -> #DIV/0! | CH23: =BR23*0.8 -> 0 | CI23: =SUM(AK23:BN23) -> 0 | CJ23: =CH23*CI23 -> 0 | CK23: =SUM(AM23:BP23) -> 8190 | CL23: =CJ23*CK23 -> 0
C26: CBN | D26: SEG À SEX 06H00-19H00 | E26: 30'' | BE26: 2 | BF26: 2 | BG26: 2 | BH26: 2 | BI26: 2 | BJ26: 2 | BK26: 2 | BL26: 2 | BO26: =SUM(F26:BN26) -> 16 | BP26: =10733 -> 10733 | BQ26: 0.4 | BR26: =BP26*(1-BQ26) -> 6439.8 | BS26: =BR26*BO26 -> 103036.8 | BT26: =BS26*0.8 -> 82429.44 | BV26: =SUM(BT26:BT27)/$BT$29 -> 0.25778023 | BW26: 0.25901462 | BY26: 0.87 | BZ26: 67249 | CA26: =BY26*BO26 -> 13.92 | CB26: 11451245 | CC26: 16255139 | CD26: =CC26*CA26/100 -> 2262715.3 | CE26: =BT26/CD26*1000 -> 36.429434 | CG26: CBN | CH26: =BR26*0.8 -> 5151.84 | CI26: =SUM(AK26:BG26) -> 6 | CJ26: =CH26*CI26 -> 30911.04 | CK26: =SUM(BH26:BN26) -> 10 | CL26: =CK26*CH26 -> 51518.4 | CM26: =(CJ26+CL26)=BT26 -> TRUE
C27: ROTATIVO | E27: 30'' | BO27: =SUM(F27:BN27) -> 0 | BP27: =10733 -> 10733 | BQ27: 1 | BR27: =BP27*(1-BQ27) -> 0 | BS27: =BR27*BO27 -> 0 | BT27: =BS27*0.8 -> 0 | BY27: 0.87 | BZ27: 67249 | CA27: =BY27*BO27 -> 0 | CB27: 11451245 | CC27: 21515727 | CD27: =CC27*CA27/100 -> 0 | CE27: =BT27/CD27*1000 -> #DIV/0! | CH27: =BR27*0.8 -> 0 | CI27: =SUM(AK27:BN27) -> 0 | CJ27: =CH27*CI27 -> 0 | CK27: =SUM(AM27:BP27) -> 10733 | CL27: =CJ27*CK27 -> 0
B29: TOTAL RADIO SP CAPITAL - JORNALISMO | F29: =SUM(F12:F28) -> 0 | G29: =SUM(G12:G28) -> 0 | H29: =SUM(H12:H28) -> 0 | I29: =SUM(I12:I28) -> 0 | J29: =SUM(J12:J28) -> 0 | K29: =SUM(K12:K28) -> 0 | L29: =SUM(L12:L28) -> 0 | M29: =SUM(M12:M28) -> 0 | ... Z29: =SUM(Z12:Z28) -> 0 | AA29: =SUM(AA12:AA27) -> 0 | AB29: =SUM(AB12:AB28) -> 0 | AC29: =SUM(AC12:AC28) -> 0 | AD29: =SUM(AD12:AD28) -> 0 | AE29: =SUM(AE12:AE28) -> 0 | AF29: =SUM(AF12:AF28) -> 0 | AG29: =SUM(AG12:AG28) -> 0 | AH29: =SUM(AH12:AH28) -> 0 | AI29: =SUM(AI12:AI28) -> 0 | ... BO29: =SUM(BO12:BO28) -> 110 | BS29: =SUM(BS12:BS28) -> 399707.93 | BT29: =SUM(BT12:BT28) -> 319766.34 | CB29: =CB26 -> 11451245 | CD29: =SUM(CD12:CD28) -> 16448575 | CE29: =BT29/CD29*1000 -> 19.440367 | CI29: =SUM(CI12:CI28) -> 45 | CJ29: =SUM(CJ12:CJ28) -> 128204.23 | CK29: =SUM(CK12:CK28) -> 26592 | CL29: =SUM(CL12:CL28) -> 191562.11 | CM29: =(CJ29+CL29)=BT29 -> TRUE
B31: MARKET | C31: CHANNEL | D31: PROPERTY | E31: FORMAT: SPOT | F31: OUTUBRO | BD31: DEZEMBRO | BH31: JANEIRO | BO31: INS. | BP31: CUSTO TABELA UNITÁRIO (BRUTO) | BQ31: DESC. % | BR31: CUSTO NEGOCIADO UNITÁRIO (BRUTO) | BS31: CUSTO TOTAL NEGOCIADO (BRUTO) | BT31: CUSTO TOTAL DESEMBOLSO CLIENTE | BV31: SHARE DE INVESTIMENTO % | BW31: SHARE DE AUDIÊNCIA % | BY31: IA% | BZ31: IA# | CA31: TRP | CB31: POPULAÇÃO TT. | CC31: UNIV. RÁDIO AS ABCDE 18+ | CD31: IMPACTOS ESTIMADOS | CE31: CPM | CG31: RÁDIO | CH31: VALOR UNITÁRIO LIQUIDO | CI31: DEZEMBRO | CK31: JANEIRO
F32: W | G32: T | H32: F | I32: S | J32: S | K32: M | L32: T | M32: W | N32: T | O32: F | P32: S | Q32: S | R32: M | S32: T | T32: W | U32: T | V32: F | W32: S | X32: S | Y32: M | Z32: T | AA32: W | AB32: T | AC32: F | AD32: S | AE32: S | AF32: M | AG32: T | AH32: W | AI32: T | AJ32: F | AK32: S | AL32: S | AM32: M | AN32: T | AO32: W | AP32: T | AQ32: F | AR32: S | AS32: S | AT32: M | AU32: T | AV32: W | AW32: T | AX32: F | AY32: S | AZ32: S | BA32: M | BB32: T | BC32: W | BD32: S | BE32: M | BF32: T | BG32: W | BH32: T | BI32: F | BJ32: S | BK32: S | BL32: F | BM32: S | BN32: S
F33: 1 | G33: 2 | H33: 3 | I33: 4 | J33: 5 | K33: 6 | L33: 7 | M33: 8 | N33: 9 | O33: 10 | P33: 11 | Q33: 12 | R33: 13 | S33: 14 | T33: 15 | U33: 16 | V33: 17 | W33: 18 | X33: 19 | Y33: 20 | Z33: 21 | AA33: 22 | AB33: 23 | AC33: 24 | AD33: 25 | AE33: 26 | AF33: 27 | AG33: 28 | AH33: 29 | AI33: 30 | AJ33: 31 | AK33: 1 | AL33: 2 | AM33: 3 | AN33: 4 | AO33: 5 | AP33: 6 | AQ33: 7 | AR33: 8 | AS33: 9 | AT33: 10 | AU33: 11 | AV33: 12 | AW33: 13 | AX33: 14 | AY33: 15 | AZ33: 16 | BA33: 17 | BB33: 18 | BC33: 19 | BD33: 28 | BE33: =BD33+1 -> 29 | BF33: =BE33+1 -> 30 | BG33: =BF33+1 -> 31 | BH33: 1 | BI33: =BH33+1 -> 2 | BJ33: =BI33+1 -> 3 | BK33: =BJ33+1 -> 4 | BL33: =BK33+1 -> 5 | BM33: =BL33+1 -> 6 | BN33: =BM33+1 -> 7 | CI33: INS. | CJ33: INV. LIQUIDO | CK33: INS. | CL33: INV. LIQUIDO
B35: RÁDIO MUSICAL | C35: NATIVA FM | D35: SEG À DOM 06H00-19H00 | E35: 30'' | BE35: 3 | BF35: 3 | BG35: 3 | BH35: 3 | BI35: 3 | BJ35: 3 | BK35: 3 | BL35: 3 | BO35: =SUM(F35:BN35) -> 24 | BP35: =3624 -> 3624 | BQ35: 0.63 | BR35: =BP35*(1-BQ35) -> 1340.88 | BS35: =BR35*BO35 -> 32181.12 | BT35: =BS35*0.8 -> 25744.896 | BV35: =BT35/$BT$81 -> 0.062819327 | BW35: 0.055898255 | BY35: =BZ35/CC35*100 -> 0.49702669 | BZ35: 80792.38 | CA35: =BY35*BO35 -> 11.928641 | CB35: 11451245 | CC35: 16255139 | CD35: =CC35*CA35/100 -> 1939017.1 | CE35: =BT35/CD35*1000 -> 13.277292 | CG35: NATIVA | CH35: =BR35*0.8 -> 1072.704 | CI35: =SUM(AK35:BG35) -> 9 | CJ35: =CH35*CI35 -> 9654.336 | CK35: =SUM(BH35:BN35) -> 15 | CL35: =CK35*CH35 -> 16090.56 | CM35: =(CJ35+CL35)=BT35 -> TRUE
B36: SÃO PAULO - CAPITAL | E36: 30'' | BO36: =SUM(F36:BN36) -> 0 | BP36: =3624 -> 3624 | BQ36: 1 | BR36: =BP36*(1-BQ36) -> 0 | BS36: =BR36*BO36 -> 0 | BT36: =BS36*0.8 -> 0 | BY36: =BZ36/CC36*100 -> 0.47200832 | BZ36: 80792.38 | CA36: =BY36*BO36 -> 0 | CB36: 11451245 | CC36: 17116728 | CD36: =CC36*CA36/100 -> 0 | CE36: =BT36/CD36*1000 -> #DIV/0! | CH36: =BR36*0.8 -> 0 | CI36: =SUM(AK36:BN36) -> 0 | CJ36: =CH36*CI36 -> 0 | CK36: =SUM(AM36:BP36) -> 3624 | CL36: =CJ36*CK36 -> 0 | CM36: =SUM(#REF!,CJ36,#REF!)=BT36 -> #REF!
B37: SÃO PAULO - CAPITAL
C39: BAND FM | D39: SEG À DOM 06H00-19H00 | E39: 30'' | BE39: 4 | BF39: 4 | BG39: 4 | BH39: 4 | BI39: 4 | BJ39: 4 | BK39: 4 | BL39: 4 | BO39: =SUM(F39:BN39) -> 32 | BP39: =4270 -> 4270 | BQ39: 0.65 | BR39: =BP39*(1-BQ39) -> 1494.5 | BS39: =BR39*BO39 -> 47824 | BT39: =BS39*0.8 -> 38259.2 | BV39: =BT39/$BT$81 -> 0.093355094 | BW39: 0.08560711 | BY39: =BZ39/CC39*100 -> 0.76557863 | BZ39: 124445.87 | CA39: =BY39*BO39 -> 24.498516 | CB39: 11451245 | CC39: 16255139 | CD39: =CC39*CA39/100 -> 3982267.8 | CE39: =BT39/CD39*1000 -> 9.6073899 | CG39: BAND FM | CH39: =BR39*0.8 -> 1195.6 | CI39: =SUM(AK39:BG39) -> 12 | CJ39: =CH39*CI39 -> 14347.2 | CK39: =SUM(BH39:BN39) -> 20 | CL39: =CK39*CH39 -> 23912 | CM39: =(CJ39+CL39)=BT39 -> TRUE
E40: 30'' | BO40: =SUM(F40:BN40) -> 0 | BP40: =4270 -> 4270 | BQ40: 1 | BR40: =BP40*(1-BQ40) -> 0 | BS40: =BR40*BO40 -> 0 | BT40: =BS40*0.8 -> 0 | BY40: =BZ40/CC40*100 -> 0.7270424 | BZ40: 124445.87 | CA40: =BY40*BO40 -> 0 | CB40: 11451245 | CC40: 17116728 | CD40: =CC40*CA40/100 -> 0 | CE40: =BT40/CD40*1000 -> #DIV/0! | CH40: =BR40*0.8 -> 0 | CI40: =SUM(AK40:BN40) -> 0 | CJ40: =CH40*CI40 -> 0 | CK40: =SUM(AM40:BP40) -> 4270 | CL40: =CJ40*CK40 -> 0 | CM40: =SUM(#REF!,CJ40,#REF!)=BT40 -> #REF!
C43: 89 ROCK FM | D43: SEG À DOM 06H00-19H00 | E43: 30'' | BE43: 4 | BF43: 4 | BG43: 4 | BH43: 4 | BI43: 4 | BJ43: 4 | BK43: 4 | BL43: 4 | BO43: =SUM(F43:BN43) -> 32 | BP43: =4448 -> 4448 | BQ43: 0.7 | BR43: =BP43*(1-BQ43) -> 1334.4 | BS43: =BR43*BO43 -> 42700.8 | BT43: =BS43*0.8 -> 34160.64 | BV43: =BT43/$BT$81 -> 0.083354324 | BW43: 0.076893333 | BY43: =BZ43/CC43*100 -> 0.56035731 | BZ43: 91086.86 | CA43: =BY43*BO43 -> 17.931434 | CB43: 11451245 | CC43: 16255139 | CD43: =CC43*CA43/100 -> 2914779.5 | CE43: =BT43/CD43*1000 -> 11.719802 | CG43: 89 ROCK FM | CH43: =BR43*0.8 -> 1067.52 | CI43: =SUM(AK43:BG43) -> 12 | CJ43: =CH43*CI43 -> 12810.24 | CK43: =SUM(BH43:BN43) -> 20 | CL43: =CK43*CH43 -> 21350.4 | CM43: =(CJ43+CL43)=BT43 -> TRUE
C46: ALPHA FM | D46: SEG À DOM 06H00-19H00 | E46: 30'' | BE46: 4 | BF46: 4 | BG46: 4 | BH46: 3 | BI46: 3 | BJ46: 3 | BK46: 3 | BL46: 3 | BO46: =SUM(F46:BN46) -> 27 | BP46: =4800 -> 4800 | BQ46: 0.58 | BR46: =BP46*(1-BQ46) -> 2016 | BS46: =BR46*BO46 -> 54432 | BT46: =BS46*0.8 -> 43545.6 | BV46: =BT46/$BT$81 -> 0.10625428 | BW46: 0.09770284 | BY46: =BZ46/CC46*100 -> 0.88456217 | BZ46: 143786.81 | CA46: =BY46*BO46 -> 23.883179 | CB46: 11451245 | CC46: 16255139 | CD46: =CC46*CA46/100 -> 3882243.9 | CE46: =BT46/CD46*1000 -> 11.216606 | CG46: ALPHA FM | CH46: =BR46*0.8 -> 1612.8 | CI46: =SUM(AK46:BG46) -> 12 | CJ46: =CH46*CI46 -> 19353.6 | CK46: =SUM(BH46:BN46) -> 15 | CL46: =CK46*CH46 -> 24192 | CM46: =(CJ46+CL46)=BT46 -> TRUE
C49: DISNEY FM | D49: SEG À DOM 06H00-19H00 | E49: 30'' | BE49: 3 | BF49: 3 | BG49: 3 | BH49: 3 | BI49: 3 | BL49: 3 | BO49: =SUM(F49:BN49) -> 18 | BP49: =3700 -> 3700 | BQ49: 0.61 | BR49: =BP49*(1-BQ49) -> 1443 | BS49: =BR49*BO49 -> 25974 | BT49: =BS49*0.8 -> 20779.2 | BV49: =BT49/$BT$81 -> 0.050702685 | BW49: 0.051110058 | BY49: =BZ49/CC49*100 -> 0.28165794 | BZ49: 45783.89 | CA49: =BY49*BO49 -> 5.069843 | CB49: 11451245 | CC49: 16255139 | CD49: =CC49*(CA49+CA51)/100 -> 824110.02 | CE49: =BT49/CD49*1000 -> 25.214109 | CG49: DISNEY FM | CH49: =BR49*0.8 -> 1154.4 | CI49: =SUM(AK49:BG49) -> 9 | CJ49: =CH49*CI49 -> 10389.6 | CK49: =SUM(BH49:BN49) -> 9 | CL49: =CK49*CH49 -> 10389.6 | CM49: =(CJ49+CL49)=BT49 -> TRUE
C52: ENERGIA 97 FM | D52: SEG À DOM 06H00-19H00 | E52: 30'' | BE52: 4 | BF52: 4 | BG52: 4 | BH52: 4 | BI52: 4 | BJ52: 4 | BK52: 4 | BL52: 4 | BO52: =SUM(F52:BN52) -> 32 | BP52: 990.99 | BQ52: 0.5 | BR52: =BP52*(1-BQ52) -> 495.495 | BS52: =BR52*BO52 -> 15855.84 | BT52: =BS52*0.8 -> 12684.672 | BV52: =BT52/$BT$81 -> 0.030951477 | BW52: 0.031110058 | BY52: =BZ52/CC52*100 -> 0.29396027 | BZ52: 47783.65 | CA52: =BY52*BO52 -> 9.4067285 | CB52: 11451245 | CC52: 16255139 | CD52: =CC52*CA52/100 -> 1529076.8 | CE52: =BT52/CD52*1000 -> 8.2956409 | CG52: ENERGIA 97 FM | CH52: =BR52*0.8 -> 396.396 | CI52: =SUM(AK52:BG52) -> 12 | CJ52: =CH52*CI52 -> 4756.752 | CK52: =SUM(BH52:BN52) -> 20 | CL52: =CK52*CH52 -> 7927.92 | CM52: =(CJ52+CL52)=BT52 -> TRUE
C55: KISS FM | D55: SEG À DOM 06H00-19H00 | E55: 30'' | BE55: 3 | BF55: 3 | BG55: 3 | BH55: 3 | BI55: 3 | BJ55: 3 | BK55: 3 | BL55: 3 | BO55: =SUM(F55:BN55) -> 24 | BP55: =3900 -> 3900 | BQ55: 0.7011 | BR55: =BP55*(1-BQ55) -> 1165.71 | BS55: =BP55*BO55*(1-BQ55) -> 27977.04 | BT55: =BS55*0.8 -> 22381.632 | BV55: =BT55/$BT$81 -> 0.05461273 | BW55: 0.047536391 | BY55: =BZ55/CC55*100 -> 0.43037534 | BZ55: 69958.11 | CA55: =BY55*BO55 -> 10.329008 | CB55: 11451245 | CC55: 16255139 | CD55: =CC55*(CA55+CA57)/100 -> 1678994.6 | CE55: =BT55/CD55*1000 -> 13.330377 | CG55: KISS FM | CH55: =BR55*0.8 -> 932.568 | CI55: =SUM(AK55:BG55) -> 9 | CJ55: =CH55*CI55 -> 8393.112 | CK55: =SUM(BH55:BN55) -> 15 | CL55: =CK55*CH55 -> 13988.52 | CM55: =(CJ55+CL55)=BT55 -> TRUE
C58: GAZETA FM | D58: SEG À DOM 06H00-19H00 | E58: 30'' | BE58: 4 | BF58: 4 | BG58: 4 | BH58: 4 | BI58: 4 | BJ58: 4 | BK58: 4 | BL58: 4 | BO58: =SUM(F58:BN58) -> 32 | BP58: =2968 -> 2968 | BQ58: 0.62 | BR58: =BP58*(1-BQ58) -> 1127.84 | BS58: =BR58*BO58 -> 36090.88 | BT58: =BS58*0.8 -> 28872.704 | BV58: =BT58/$BT$81 -> 0.070451395 | BW58: 0.068857471 | BY58: =BZ58/CC58*100 -> 0.44233587 | BZ58: 71902.31 | CA58: =BY58*BO58 -> 14.154748 | CB58: 11451245 | CC58: 16255139 | CD58: =CC58*CA58/100 -> 2300873.9 | CE58: =BT58/CD58*1000 -> 12.548582 | CG58: GAZETA FM | CH58: =BR58*0.8 -> 902.272 | CI58: =SUM(AK58:BG58) -> 12 | CJ58: =CH58*CI58 -> 10827.264 | CK58: =SUM(BH58:BN58) -> 20 | CL58: =CK58*CH58 -> 18045.44 | CM58: =(CJ58+CL58)=BT58 -> TRUE
C61: 105 FM | D61: SEG À DOM 05H00-18H00 | E61: 30'' | BE61: 4 | BF61: 4 | BG61: 4 | BH61: 4 | BI61: 4 | BJ61: 4 | BK61: 4 | BL61: 4 | BO61: =SUM(F61:BN61) -> 32 | BP61: =1610 -> 1610 | BQ61: 0.55 | BR61: =BP61*(1-BQ61) -> 724.5 | BS61: =BR61*BO61 -> 23184 | BT61: =BS61*0.8 -> 18547.2 | BV61: =BT61/$BT$81 -> 0.045256451 | BW61: 0.048388488 | BY61: =BZ61/CC61*100 -> 0.43808989 | BZ61: 71212.12 | CA61: =BY61*BO61 -> 14.018876 | CB61: 11451245 | CC61: 16255139 | CD61: =CC61*CA61/100 -> 2278787.8 | CE61: =BT61/CD61*1000 -> 8.139064 | CG61: 105 FM | CH61: =BR61*0.8 -> 579.6 | CI61: =SUM(AK61:BG61) -> 12 | CJ61: =CH61*CI61 -> 6955.2 | CK61: =SUM(BH61:BN61) -> 20 | CL61: =CK61*CH61 -> 11592 | CM61: =(CJ61+CL61)=BT61 -> TRUE | EO61: =SUM(F61:EN61) -> 30119696
C64: RÁDIO MIX | D64: SEG À DOM 06H00-19H00 | E64: 30'' | BE64: 3 | BF64: 3 | BG64: 3 | BH64: 3 | BI64: 3 | BJ64: 3 | BK64: 3 | BL64: 3 | BO64: =SUM(F64:BN64) -> 24 | BP64: =5205 -> 5205 | BQ64: 0.75 | BR64: =BP64*(1-BQ64) -> 1301.25 | BS64: =BR64*BO64 -> 31230 | BT64: =BS64*0.8 -> 24984 | BV64: =BT64/$BT$81 -> 0.060962688 | BW64: 0.057246938 | BY64: =BZ64/CC64*100 -> 0.42775475 | BZ64: 69532.13 | CA64: =BY64*BO64 -> 10.266114 | CB64: 11451245 | CC64: 16255139 | CD64: =CC64*CA64/100 -> 1668771.1 | CE64: =BT64/CD64*1000 -> 14.971496 | CG64: RÁDIO MIX | CH64: =BR64*0.8 -> 1041 | CI64: =SUM(AK64:BG64) -> 9 | CJ64: =CH64*CI64 -> 9369 | CK64: =SUM(BH64:BN64) -> 15 | CL64: =CK64*CH64 -> 15615 | CM64: =(CJ64+CL64)=BT64 -> TRUE
C67: TRANSAMÉRICA FM | D67: SEG À SEX 06H00-19H00 | E67: 30'' | BE67: 4 | BF67: 4 | BG67: 4 | BH67: 4 | BI67: 4 | BJ67: 4 | BK67: 4 | BL67: 4 | BO67: =SUM(F67:BN67) -> 32 | BP67: =3877 -> 3877 | BQ67: 0.8 | BR67: =BP67*(1-BQ67) -> 775.4 | BS67: =BR67*BO67 -> 24812.8 | BT67: =BS67*0.8 -> 19850.24 | BV67: =BT67/$BT$81 -> 0.048435959 | BW67: 0.045629449 | BY67: =BZ67/CC67*100 -> 0.22298511 | BZ67: 36246.54 | CA67: =BY67*BO67 -> 7.1355236 | CB67: 11451245 | CC67: 16255139 | CD67: =CC67*(CA67+CA69)/100 -> 1159889.3 | CE67: =BT67/CD67*1000 -> 17.113909 | CG67: TRANSAMÉRICA FM | CH67: =BR67*0.8 -> 620.32 | CI67: =SUM(AK67:BG67) -> 12 | CJ67: =CH67*CI67 -> 7443.84 | CK67: =SUM(BH67:BN67) -> 20 | CL67: =CK67*CH67 -> 12406.4 | CM67: =(CJ67+CL67)=BT67 -> TRUE
C70: MASSA FM | D70: SEG À DOM 06H00-19H00 | E70: 30'' | BE70: 4 | BF70: 4 | BG70: 4 | BH70: 4 | BI70: 4 | BJ70: 4 | BK70: 4 | BL70: 4 | BO70: =SUM(F70:BN70) -> 32 | BP70: =2166 -> 2166 | BQ70: 0.73 | BR70: =BP70*(1-BQ70) -> 584.82 | BS70: =BR70*BO70 -> 18714.24 | BT70: =BS70*0.8 -> 14971.392 | BV70: =BT70/$BT$81 -> 0.036531232 | BW70: 0.036231217 | BY70: =BZ70/CC70*100 -> 0.30991565 | BZ70: 50377.22 | CA70: =BY70*BO70 -> 9.9173009 | CB70: 11451245 | CC70: 16255139 | CD70: =CC70*CA70/100 -> 1612071 | CE70: =BT70/CD70*1000 -> 9.2870547 | CG70: MASSA FM | CH70: =BR70*0.8 -> 467.856 | CI70: =SUM(AK70:BG70) -> 12 | CJ70: =CH70*CI70 -> 5614.272 | CK70: =SUM(BH70:BN70) -> 20 | CL70: =CK70*CH70 -> 9357.12 | CM70: =(CJ70+CL70)=BT70 -> TRUE
C73: ANTENA 1 | D73: SEG À SEX 06H00-19H00 | E73: 30'' | BE73: 4 | BF73: 4 | BG73: 4 | BH73: 4 | BI73: 4 | BJ73: 4 | BK73: 4 | BL73: 4 | BO73: =SUM(F73:BN73) -> 32 | BP73: =6617 -> 6617 | BQ73: 0.75 | BR73: =BP73*(1-BQ73) -> 1654.25 | BS73: =BR73*BO73 -> 52936 | BT73: =BS73*0.8 -> 42348.8 | BV73: =BT73/$BT$81 -> 0.103334 | BW73: 0.099775299 | BY73: =BZ73/CC73*100 -> 0.72225344 | BZ73: 117403.3 | CA73: =BY73*BO73 -> 23.11211 | CB73: 11451245 | CC73: 16255139 | CD73: =CC73*CA73/100 -> 3756905.6 | CE73: =BT73/CD73*1000 -> 11.272256 | CG73: ANTENA 1 | CH73: =BR73*0.8 -> 1323.4 | CI73: =SUM(AK73:BG73) -> 12 | CJ73: =CH73*CI73 -> 15880.8 | CK73: =SUM(BH73:BN73) -> 20 | CL73: =CK73*CH73 -> 26468 | CM73: =(CJ73+CL73)=BT73 -> TRUE
C76: NOVABRASIL | D76: SEG À DOM 09H00-20H00 | E76: 30'' | BE76: 4 | BF76: 4 | BG76: 4 | BH76: 4 | BI76: 4 | BJ76: 4 | BK76: 4 | BL76: 4 | BO76: =SUM(F76:BN76) -> 32 | BP76: =5275.6 -> 5275.6 | BQ76: 0.8 | BR76: =BP76*(1-BQ76) -> 1055.12 | BS76: =BR76*BO76 -> 33763.84 | BT76: =BS76*0.8 -> 27011.072 | BV76: =BT76/$BT$81 -> 0.065908884 | BW76: 0.065906448 | BY76: =BZ76/CC76*100 -> 0.37035051 | BZ76: 60200.99 | CA76: =BY76*BO76 -> 11.851216 | CB76: 11451245 | CC76: 16255139 | CD76: =CC76*(CA76+CA78)/100 -> 1926431.7 | CE76: =BT76/CD76*1000 -> 14.021298 | CG76: NOVABRASIL | CH76: =BR76*0.8 -> 844.096 | CI76: =SUM(AK76:BG76) -> 12 | CJ76: =CH76*CI76 -> 10129.152 | CK76: =SUM(BH76:BN76) -> 20 | CL76: =CK76*CH76 -> 16881.92 | CM76: =(CJ76+CL76)=BT76 -> TRUE
C79: TRANSCONTINENTAL | D79: SEG À DOM 06H00-19H00 | E79: 30'' | BE79: 3 | BF79: 3 | BG79: 3 | BH79: 3 | BI79: 3 | BJ79: 3 | BK79: 3 | BL79: 3 | BO79: =SUM(F79:BN79) -> 24 | BP79: =3717 -> 3717 | BQ79: 0.5 | BR79: =BP79*(1-BQ79) -> 1858.5 | BS79: =BR79*BO79 -> 44604 | BT79: =BS79*0.8 -> 35683.2 | BV79: =BT79/$BT$81 -> 0.087069476 | BW79: 0.086909353 | BY79: =BZ79/CC79*100 -> 0.60577034 | BZ79: 98468.81 | CA79: =BY79*BO79 -> 14.538488 | CB79: 11451245 | CC79: 16255139 | CD79: =CC79*(CA79+CA81)/100 -> 2363251.4 | CE79: =BT79/CD79*1000 -> 15.099197 | CG79: TRANSCONTINENTAL | CH79: =BR79*0.8 -> 1486.8 | CI79: =SUM(AK79:BG79) -> 9 | CJ79: =CH79*CI79 -> 13381.2 | CK79: =SUM(BH79:BN79) -> 15 | CL79: =CK79*CH79 -> 22302 | CM79: =(CJ79+CL79)=BT79 -> TRUE
B81: TOTAL RADIO SP CAPITAL | F81: =SUM(F34:F80) -> 0 | G81: =SUM(G34:G80) -> 0 | H81: =SUM(H34:H80) -> 0 | I81: =SUM(I34:I80) -> 0 | J81: =SUM(J34:J80) -> 0 | K81: =SUM(K34:K80) -> 0 | L81: =SUM(L34:L80) -> 0 | M81: =SUM(M34:M80) -> 0 | ... BO81: =SUM(BO34:BO80) -> 429 | BS81: =SUM(BS34:BS80) -> 512280.56 | BT81: =SUM(BT34:BT80) -> 409824.45 | CB81: =CB79 -> 11451245 | CD81: =SUM(CD34:CD80) -> 33817472 | CE81: =BT81/CD81*1000 -> 12.118719 | CI81: =SUM(CI34:CI80) -> 165 | CJ81: =SUM(CJ34:CJ80) -> 159305.57 | CK81: =SUM(CK34:CK80) -> 8158 | CL81: =SUM(CL34:CL80) -> 250518.88 | CM81: =(CJ81+CL81)=BT81 -> TRUE
B83: CARAGUATATUBA | SÃO SABASTIÃO | UBATUBA - LITORAL NORTE | C83: CARAGUA FM | D83: 07h00 as 19h00 | E83: 30" | BO83: =SUM(F83:AI83) -> 0 | BP83: 165 | BQ83: 0.58 | BR83: =BP83*(1-BQ83) -> 69.3 | BS83: =BR83*BO83 -> 0 | BT83: =BR83*0.8 -> 55.44 | BV83: =BS83*0.8 -> 0 | BY83: =BZ83/CC83*100 -> 3.8168405 | BZ83: 2351 | CA83: =BY83*BO83 -> 0 | CB83: 125194 | CC83: 61595.448 | CD83: 188080 | CE83: =BV83/CD83*1000 -> 0 | CG83: CARAGUA FM | CI83: =SUM(#REF!) -> #REF! | CJ83: =#REF!*CI83 -> #REF! | CK83: =SUM(#REF!) -> #REF! | CL83: =#REF!*CK83 -> #REF!
C84: (via Caraguatatuba)
C86: BEIRA MAR FM | D86: 07h00 as 19h00 | E86: 30" | BO86: =SUM(F86:AI86) -> 0 | BP86: 310 | BQ86: 0.3 | BR86: =BP86*(1-BQ86) -> 217 | BS86: =BR86*BO86 -> 0 | BT86: =BR86*0.8 -> 173.6 | BV86: =BS86*0.8 -> 0 | BY86: =BZ86/CC86*100 -> 3.0700541 | BZ86: 1402 | CA86: =BY86*BO86 -> 0 | CB86: 92819 | CC86: 45666.948 | CD86: 112160 | CE86: =BV86/CD86*1000 -> 0 | CG86: =C86 -> BEIRA MAR FM | CI86: =SUM(#REF!) -> #REF! | CJ86: =#REF!*CI86 -> #REF! | CK86: =SUM(#REF!) -> #REF! | CL86: =#REF!*CK86 -> #REF!
C87: (via Ubatuba)
C89: MORADA FM | D89: 07h00 as 19h00 | E89: 30" | BO89: =SUM(F89:AI89) -> 0 | BP89: 800 | BQ89: 0.8 | BR89: =BP89*(1-BQ89) -> 160 | BS89: =BR89*BO89 -> 0 | BT89: =BR89*0.8 -> 128 | BV89: =BS89*0.8 -> 0 | BY89: =BZ89/CC89*100 -> #DIV/0! | CA89: =BY89*BO89 -> #DIV/0! | CE89: =BV89/CD89*1000 -> #DIV/0! | CG89: =C89 -> MORADA FM | CI89: =SUM(#REF!) -> #REF! | CJ89: =#REF!*CI89 -> #REF! | CK89: =SUM(#REF!) -> #REF! | CL89: =#REF!*CK89 -> #REF!
C90: (via São Sebastião)
C92: ANTENA 1 | D92: 07h00 as 19h00 | E92: 30" | BO92: =SUM(F92:AI92) -> 0 | BP92: 178 | BQ92: 0.78 | BR92: =BP92*(1-BQ92) -> 39.16 | BS92: =BR92*BO92 -> 0 | BT92: =BR92*0.8 -> 31.328 | BV92: =BS92*0.8 -> 0 | BY92: =BZ92/CC92*100 -> #DIV/0! | CA92: =BY92*BO92 -> #DIV/0! | CE92: =BV92/CD92*1000 -> #DIV/0! | CG92: =C92 -> ANTENA 1 | CI92: =SUM(#REF!) -> #REF! | CJ92: =#REF!*CI92 -> #REF! | CK92: =SUM(#REF!) -> #REF! | CL92: =#REF!*CK92 -> #REF!
C93: (via Ilha Bela - São Sebastião)
C95: RÁDIO PRAIA FM | D95: 07h00 as 19h00 | E95: 30" | BO95: =SUM(#REF!) -> #REF! | BQ95: 0.4 | BR95: =BP95*(1-BQ95) -> 0 | BS95: =BR95*BO95 -> #REF! | BT95: =BR95*0.8 -> 0 | BV95: =BS95*0.8 -> #REF! | CA95: =BY95*BO95 -> #REF! | CE95: =BV95/CD95*1000 -> #REF! | CG95: =C95 -> RÁDIO PRAIA FM | CI95: =SUM(#REF!) -> #REF! | CJ95: =#REF!*CI95 -> #REF! | CK95: =SUM(#REF!) -> #REF! | CL95: =#REF!*CK95 -> #REF!
C98: RÁDIO ANTENA 8 | D98: 07h00 as 19h00 | E98: 30" | BO98: =SUM(F98:AI98) -> 0 | BP98: 120 | BQ98: 0.3 | BR98: =BP98*(1-BQ98) -> 84 | BS98: =BR98*BO98 -> 0 | BT98: =BR98*0.8 -> 67.2 | BV98: =BS98*0.8 -> 0 | CA98: =BY98*BO98 -> 0 | CE98: =BV98/CD98*1000 -> #DIV/0! | CG98: =C98 -> RÁDIO ANTENA 8 | CI98: =SUM(#REF!) -> #REF! | CJ98: =#REF!*CI98 -> #REF! | CK98: =SUM(#REF!) -> #REF! | CL98: =#REF!*CK98 -> #REF!
C99: (via Caraguatatuba)
C101: ROCK NEWS LITORAL | D101: 07h00 as 19h00 | E101: 30" | BO101: =SUM(#REF!) -> #REF! | BQ101: 0.4 | BR101: =BP101*(1-BQ101) -> 0 | BS101: =BR101*BO101 -> #REF! | BT101: =BR101*0.8 -> 0 | BV101: =BS101*0.8 -> #REF! | CA101: =BY101*BO101 -> #REF! | CE101: =BV101/CD101*1000 -> #REF! | CG101: =C101 -> ROCK NEWS LITORAL | CI101: =SUM(#REF!) -> #REF! | CJ101: =#REF!*CI101 -> #REF! | CK101: =SUM(#REF!) -> #REF! | CL101: =#REF!*CK101 -> #REF!
C102: (via São Sebastião)
C104: ONDA 101.1 | D104: 07h00 as 19h00 | E104: 30" | BO104: =SUM(#REF!) -> #REF! | BQ104: 0.4 | BR104: =BP104*(1-BQ104) -> 0 | BS104: =BR104*BO104 -> #REF! | BT104: =BR104*0.8 -> 0 | BV104: =BS104*0.8 -> #REF! | CA104: =BY104*BO104 -> #REF! | CE104: =BV104/CD104*1000 -> #REF! | CG104: =C104 -> ONDA 101.1 | CI104: =SUM(#REF!) -> #REF! | CJ104: =#REF!*CI104 -> #REF! | CK104: =SUM(#REF!) -> #REF! | CL104: =#REF!*CK104 -> #REF!
C105: (via São Sebastião)
C107: COSTA AZUL | D107: 07h00 as 19h00 | E107: 30" | BO107: =SUM(#REF!) -> #REF! | BQ107: 0.4 | BR107: =BP107*(1-BQ107) -> 0 | BS107: =BR107*BO107 -> #REF! | BT107: =BR107*0.8 -> 0 | BV107: =BS107*0.8 -> #REF! | CA107: =BY107*BO107 -> #REF! | CE107: =BV107/CD107*1000 -> #REF! | CG107: =C107 -> COSTA AZUL | CI107: =SUM(#REF!) -> #REF! | CJ107: =#REF!*CI107 -> #REF! | CK107: =SUM(#REF!) -> #REF! | CL107: =#REF!*CK107 -> #REF!
B110: TOTAL RÁDIO LITORAL NORTE | F110: =SUM(F82:F109) -> 0 | G110: =SUM(G82:G109) -> 0 | H110: =SUM(H82:H109) -> 0 | I110: =SUM(I82:I109) -> 0 | J110: =SUM(J82:J109) -> 0 | K110: =SUM(K82:K109) -> 0 | L110: =SUM(L82:L109) -> 0 | M110: =SUM(M82:M109) -> 0 | N110: =SUM(N82:N84) -> 0 | O110: =SUM(O82:O84) -> 0 | P110: =SUM(P82:P84) -> 0 | Q110: =SUM(Q82:Q84) -> 0 | R110: =SUM(R82:R84) -> 0 | S110: =SUM(S82:S84) -> 0 | T110: =SUM(T82:T84) -> 0 | U110: =SUM(U82:U84) -> 0 | ... AJ110: =SUM(AJ82:AJ84) -> 0 | AK110: =SUM(AK82:AK109) -> 0 | AL110: =SUM(AL82:AL109) -> 0 | AM110: =SUM(AM82:AM109) -> 0 | AN110: =SUM(AN82:AN109) -> 0 | AO110: =SUM(AO82:AO109) -> 0 | AP110: =SUM(AP82:AP109) -> 0 | AQ110: =SUM(AQ82:AQ109) -> 0 | AR110: =SUM(AR82:AR109) -> 0 | AS110: =SUM(AS82:AS84) -> 0 | AT110: =SUM(AT82:AT84) -> 0 | AU110: =SUM(AU82:AU84) -> 0 | AV110: =SUM(AV82:AV84) -> 0 | AW110: =SUM(AW82:AW84) -> 0 | AX110: =SUM(AX82:AX84) -> 0 | AY110: =SUM(AY82:AY84) -> 0 | AZ110: =SUM(AZ82:AZ84) -> 0 | ... BN110: =SUM(BN82:BN84) -> 0 | BO110: =SUM(BO82:BO109) -> #REF! | BS110: =SUM(BS82:BS109) -> #REF! | BT110: =SUM(BT82:BT109) -> 455.568 | BV110: =SUM(BV82:BV109) -> #REF! | CD110: =SUM(CD82:CD109) -> 300240 | CE110: =BV110/CD110*1000 -> #REF!
B112: SANTOS - BAIXADA SANTISTA | C112: TRI FM | D112: 06h00 as 19h00 | E112: 30" | BO112: =SUM(F112:S112) -> 0 | BP112: 0 | BQ112: 0 | BR112: 0 | BS112: =BR112*BO112 -> 0 | BT112: =BR112*0.8 -> 0 | BV112: =BS112*0.8 -> 0 | BY112: =BZ112/CC112*100 -> 12.336811 | BZ112: 26342 | CA112: =BY112*BO112 -> 0 | CB112: 433991 | CC112: 213523.57 | CD112: =CC112*CA112% -> 0 | CE112: =BV112/CD112*1000 -> #DIV/0! | CG112: TRI FM | CI112: =SUM(#REF!) -> #REF! | CJ112: =#REF!*CI112 -> #REF! | CK112: =SUM(#REF!) -> #REF! | CL112: =#REF!*CK112 -> #REF!
C115: GUARUJA FM | D115: 07h00 as 19h00 | E115: 30" | BO115: =SUM(F115:S115) -> 0 | BP115: 500 | BQ115: 0.5 | BR115: =BP115*(1-BQ115) -> 250 | BS115: =BR115*BO115 -> 0 | BT115: =BR115*0.8 -> 200 | BV115: =BS115*0.8 -> 0 | BY115: =BZ115/CC115*100 -> 9.7492749 | BZ115: 20817 | CA115: =BY115*BO115 -> 0 | CB115: 433991 | CC115: 213523.57 | CD115: =CC115*CA115% -> 0 | CE115: =BV115/CD115*1000 -> #DIV/0! | CG115: GUARUJA FM | CI115: =SUM(#REF!) -> #REF! | CJ115: =#REF!*CI115 -> #REF! | CK115: =SUM(#REF!) -> #REF! | CL115: =#REF!*CK115 -> #REF!
C118: SAUDADE FM | D118: 07h00 as 19h00 | E118: 30" | BO118: =SUM(F118:S118) -> 0 | BP118: 580 | BQ118: 0.5 | BR118: =BP118*(1-BQ118) -> 290 | BS118: =BR118*BO118 -> 0 | BT118: =BR118*0.8 -> 232 | BV118: =BS118*0.8 -> 0 | BY118: =BZ118/CC118*100 -> 12.888507 | BZ118: 27520 | CA118: =BY118*BO118 -> 0 | CB118: 433991 | CC118: 213523.57 | CD118: =CC118*CA118% -> 0 | CE118: =BV118/CD118*1000 -> #DIV/0! | CG118: SAUDADE FM | CI118: =SUM(#REF!) -> #REF! | CJ118: =#REF!*CI118 -> #REF! | CK118: =SUM(#REF!) -> #REF! | CL118: =#REF!*CK118 -> #REF!
C121: SANTA CECILIA FM | D121: 07h00 as 19h00 | E121: 30" | BO121: =SUM(F121:S121) -> 0 | BP121: 568.83 | BQ121: 0.75 | BR121: =BP121*(1-BQ121) -> 142.2075 | BS121: =BR121*BO121 -> 0 | BT121: =BR121*0.8 -> 113.766 | BV121: =BS121*0.8 -> 0 | BY121: =BZ121/CC121*100 -> 4.86129 | BZ121: 10380 | CA121: =BY121*BO121 -> 0 | CB121: 433991 | CC121: 213523.57 | CD121: =CC121*CA121% -> 0 | CE121: =BV121/CD121*1000 -> #DIV/0! | CG121: =C121 -> SANTA CECILIA FM | CI121: =SUM(#REF!) -> #REF! | CJ121: =#REF!*CI121 -> #REF! | CK121: =SUM(#REF!) -> #REF! | CL121: =#REF!*CK121 -> #REF!
C124: JOVEM PAN FM | D124: 07h00 as 19h00 | E124: 30" | BO124: =SUM(F124:S124) -> 0 | BP124: 330 | BQ124: 0.5 | BR124: =BP124*(1-BQ124) -> 165 | BS124: =BR124*BO124 -> 0 | BT124: =BR124*0.8 -> 132 | BV124: =BS124*0.8 -> 0 | BY124: =BZ124/CC124*100 -> 3.4399012 | BZ124: 7345 | CA124: =BY124*BO124 -> 0 | CB124: 433991 | CC124: 213523.57 | CD124: =CC124*CA124% -> 0 | CE124: =BV124/CD124*1000 -> #DIV/0! | CG124: =C124 -> JOVEM PAN FM | CI124: =SUM(#REF!) -> #REF! | CJ124: =#REF!*CI124 -> #REF! | CK124: =SUM(#REF!) -> #REF! | CL124: =#REF!*CK124 -> #REF!
C127: MIX FM | D127: 07h00 as 19h00 | E127: 30" | BO127: =SUM(F127:S127) -> 0 | BP127: 505 | BQ127: 0.6 | BR127: =BP127*(1-BQ127) -> 202 | BS127: =BR127*BO127 -> 0 | BT127: =BR127*0.8 -> 161.6 | BV127: =BS127*0.8 -> 0 | BY127: =BZ127/CC127*100 -> 2.1426206 | BZ127: 4575 | CA127: =BY127*BO127 -> 0 | CB127: 433991 | CC127: 213523.57 | CD127: =CC127*CA127% -> 0 | CE127: =BV127/CD127*1000 -> #DIV/0! | CG127: =C127 -> MIX FM | CI127: =SUM(#REF!) -> #REF! | CJ127: =#REF!*CI127 -> #REF! | CK127: =SUM(#REF!) -> #REF! | CL127: =#REF!*CK127 -> #REF!
C130: BOA NOVA FM | D130: 07h00 as 19h00 | E130: 30" | BO130: =SUM(F130:S130) -> 0 | BP130: =87.5*1.3 -> 113.75 | BQ130: 0.5 | BR130: =BP130*(1-BQ130) -> 56.875 | BS130: =BR130*BO130 -> 0 | BT130: =BR130*0.8 -> 45.5 | BV130: =BS130*0.8 -> 0 | BY130: =BZ130/CC130*100 -> 0.1114631 | BZ130: 238 | CA130: =BY130*BO130 -> 0 | CB130: 433991 | CC130: 213523.57 | CD130: =CC130*CA130% -> 0 | CE130: =BV130/CD130*1000 -> #DIV/0! | CG130: =C130 -> BOA NOVA FM | CI130: =SUM(#REF!) -> #REF! | CJ130: =#REF!*CI130 -> #REF! | CK130: =SUM(#REF!) -> #REF! | CL130: =#REF!*CK130 -> #REF!
C133: KISS FM | D133: 07h00 as 19h00 | E133: 30" | BO133: =SUM(F133:S133) -> 0 | BP133: 1058 | BQ133: 0.7 | BR133: =BP133*(1-BQ133) -> 317.4 | BS133: =BR133*BO133 -> 0 | BT133: =BR133*0.8 -> 253.92 | BV133: =BS133*0.8 -> 0 | BY133: =BZ133/CC133*100 -> 0.58635212 | BZ133: 1252 | CA133: =BY133*BO133 -> 0 | CB133: 433991 | CC133: 213523.57 | CD133: =CC133*(CA133+CA134)% -> 0 | CE133: =BV133/CD133*1000 -> #DIV/0! | CG133: =C133 -> KISS FM | CI133: =SUM(#REF!) -> #REF! | CJ133: =#REF!*CI133 -> #REF! | CK133: =SUM(#REF!) -> #REF! | CL133: =#REF!*CK133 -> #REF!
BO134: =SUM(F134:S134) -> 0 | BP134: 847.8 | BQ134: 1 | BR134: =BP134*(1-BQ134) -> 0 | BS134: =BR134*BO134 -> 0 | BT134: =BR134*0.8 -> 0 | BV134: =BS134*0.8 -> 0 | CA134: =BY133*BO134 -> 0
B136: TOTAL RÁDIO SANTOS - BAIXADA SANTISTA | F136: =SUM(F111:F135) -> 0 | G136: =SUM(G111:G135) -> 0 | H136: =SUM(H111:H135) -> 0 | I136: =SUM(I111:I135) -> 0 | J136: =SUM(J111:J135) -> 0 | K136: =SUM(K111:K135) -> 0 | L136: =SUM(L111:L135) -> 0 | M136: =SUM(M111:M135) -> 0 | ... BO136: =SUM(BO111:BO135) -> 0 | BS136: =SUM(BS111:BS135) -> 0 | BT136: =SUM(BT111:BT135) -> 1138.786 | BV136: =SUM(BV111:BV135) -> 0 | CD136: =SUM(CD111:CD135) -> 0 | CE136: =BV136/CD136*1000 -> #DIV/0!
C138: METROPOLITANA FM | D138: 07h00 as 19h00 | E138: 30" | BO138: =SUM(#REF!) -> #REF! | BQ138: 0.4 | BR138: =BP138*(1-BQ138) -> 0 | BS138: =BR138*BO138 -> #REF! | BT138: =BR138*0.8 -> 0 | BV138: =BS138*0.8 -> #REF! | BY138: =BZ138/CC138*100 -> 2.4049146 | BZ138: 3796 | CA138: 192.39317 | CB138: 320820 | CC138: 157843.44 | CE138: =BV138/CD138*1000 -> #REF! | CG138: METROPOLITANA FM | CI138: =SUM(#REF!) -> #REF! | CJ138: =#REF!*CI138 -> #REF! | CK138: =SUM(#REF!) -> #REF! | CL138: =#REF!*CK138 -> #REF!
B140: TAUBATE E SÃO JOSE DOS CAMPOS | C140: BAND VALE | D140: 07h00 as 19h00 | E140: 30" | BO140: =SUM(F140:AI140) -> 0 | BP140: 197.36842 | BQ140: 0 | BR140: =BP140*(1-BQ140) -> 197.36842 | BS140: 15000 | BT140: =BR140*0.8 -> 157.89474 | BV140: =BS140*0.8 -> 12000 | BY140: =BZ140/CC140*100 -> 3.4401176 | BZ140: 5430 | CA140: =BY140*BO140 -> 0 | CB140: 320820 | CC140: 157843.44 | CD140: =CC140*CA140% -> 0 | CE140: =BV140/CD140*1000 -> #DIV/0! | CG140: BAND VALE | CI140: =SUM(#REF!) -> #REF! | CJ140: =BX140/2 -> 0 | CK140: =SUM(#REF!) -> #REF! | CL140: =BZ140/2 -> 2715
C141: (via S.J.Campos)
C143: STEREO VALE | D143: 07h00 as 19h00 | E143: 30" | BO143: =SUM(F143:AI143) -> 0 | BP143: 131.57895 | BQ143: 0 | BR143: =BP143*(1-BQ143) -> 131.57895 | BS143: 10000 | BT143: =BR143*0.8 -> 105.26316 | BV143: =BS143*0.8 -> 8000 | BY143: =BZ143/CC143*100 -> 2.5183182 | BZ143: 3975 | CA143: =BY143*BO143 -> 0 | CB143: 320820 | CC143: 157843.44 | CD143: =CC143*CA143% -> 0 | CE143: =BV143/CD143*1000 -> #DIV/0! | CG143: =C143 -> STEREO VALE | CI143: =SUM(#REF!) -> #REF! | CJ143: =BX143/2 -> 0 | CK143: =SUM(#REF!) -> #REF! | CL143: =BZ143/2 -> 1987.5
C144: (via S.J.Campos)
C146: NATIVA FM | D146: 07h00 as 19h00 | E146: 30" | BO146: =SUM(F146:AI146) -> 0 | BP146: 157.89474 | BQ146: 0 | BR146: =BP146*(1-BQ146) -> 157.89474 | BS146: 12000 | BT146: =BR146*0.8 -> 126.31579 | BV146: =BS146*0.8 -> 9600 | BY146: =BZ146/CC146*100 -> 5.2780147 | BZ146: 8331 | CA146: =BY146*BO146 -> 0 | CB146: 320820 | CC146: 157843.44 | CD146: =CC146*CA146% -> 0 | CE146: =BV146/CD146*1000 -> #DIV/0! | CG146: =C146 -> NATIVA FM | CI146: =SUM(#REF!) -> #REF! | CJ146: =BX146/2 -> 0 | CK146: =SUM(#REF!) -> #REF! | CL146: =BZ146/2 -> 4165.5
C147: (via S.J.Campos)
C149: ÓTIMA FM | D149: 07h00 as 19h00 | E149: 30" | BO149: =SUM(F149:AI149) -> 0 | BP149: 255 | BQ149: =(BP149-BR149)/BP149 -> 0.4 | BR149: 153 | BS149: =BR149*BO149 -> 0 | BT149: =BR149*0.8 -> 122.4 | BV149: =BS149*0.8 -> 0 | BY149: =BZ149/CC149*100 -> 7.6189419 | BZ149: 12026 | CA149: =BY149*BO149 -> 0 | CB149: 320820 | CC149: 157843.44 | CD149: =CC149*CA149% -> 0 | CE149: =BV149/CD149*1000 -> #DIV/0! | CG149: =C149 -> ÓTIMA FM | CI149: =SUM(#REF!) -> #REF! | CJ149: =#REF!*CI149 -> #REF! | CK149: =SUM(#REF!) -> #REF! | CL149: =#REF!*CK149 -> #REF!
C150: (via S.J.Campos)
C152: ANTENA 1 FM | D152: 07h00 as 19h00 | E152: 30" | BO152: =SUM(F152:AI152) -> 0 | BP152: 331 | BQ152: 0.78 | BR152: =BP152*(1-BQ152) -> 72.82 | BS152: =BR152*BO152 -> 0 | BT152: =BR152*0.8 -> 58.256 | BV152: =BS152*0.8 -> 0 | BY152: =BZ152/CC152*100 -> 3.5161423 | BZ152: 5550 | CA152: =BY152*BO152 -> 0 | CB152: 320820 | CC152: 157843.44 | CD152: =CC152*CA152% -> 0 | CE152: =BV152/CD152*1000 -> #DIV/0! | CG152: =C152 -> ANTENA 1 FM | CI152: =SUM(#REF!) -> #REF! | CJ152: =#REF!*CI152 -> #REF! | CK152: =SUM(#REF!) -> #REF! | CL152: =#REF!*CK152 -> #REF!
C153: (via S.J.Campos)
C155: JOVEM PAN FM | D155: 07h00 as 19h00 | E155: 30" | BO155: =SUM(F155:AI155) -> 0 | BP155: 325 | BQ155: 0.5 | BR155: =BP155*(1-BQ155) -> 162.5 | BS155: =BR155*BO155 -> 0 | BT155: =BR155*0.8 -> 130 | BV155: =BS155*0.8 -> 0 | BY155: =BZ155/CC155*100 -> 2.4087159 | BZ155: 3802 | CA155: =BY155*BO155 -> 0 | CB155: 320820 | CC155: 157843.44 | CD155: =CC155*CA155% -> 0 | CE155: =BV155/CD155*1000 -> #DIV/0! | CG155: =C155 -> JOVEM PAN FM | CI155: =SUM(#REF!) -> #REF! | CJ155: =#REF!*CI155 -> #REF! | CK155: =SUM(#REF!) -> #REF! | CL155: =#REF!*CK155 -> #REF!
C156: (via Taubaté)
C158: CANÇÃO NOVA FM | D158: 07h00 as 19h00 | E158: 30" | BO158: =SUM(F158:AI158) -> 0 | BP158: 184 | BQ158: 0.4 | BR158: =BP158*(1-BQ158) -> 110.4 | BS158: =BR158*BO158 -> 0 | BT158: =BR158*0.8 -> 88.32 | BV158: =BS158*0.8 -> 0 | BY158: =BZ158/CC158*100 -> 1.7206924 | BZ158: 2716 | CA158: =BY158*BO158 -> 0 | CB158: 320820 | CC158: 157843.44 | CD158: =CC158*CA158% -> 0 | CE158: =BV158/CD158*1000 -> #DIV/0! | CG158: =C158 -> CANÇÃO NOVA FM | CI158: =SUM(#REF!) -> #REF! | CJ158: =#REF!*CI158 -> #REF! | CK158: =SUM(#REF!) -> #REF! | CL158: =#REF!*CK158 -> #REF!
C159: (via S.J.Campos)
C161: MIX FM | D161: 07h00 as 19h00 | E161: 30" | BO161: =SUM(F161:AI161) -> 0 | BP161: 160 | BQ161: 0.4 | BR161: =BP161*(1-BQ161) -> 96 | BS161: =BR161*BO161 -> 0 | BT161: =BR161*0.8 -> 76.8 | BV161: =BS161*0.8 -> 0 | BY161: =BZ161/CC161*100 -> 1.6966179 | BZ161: 2678 | CA161: =BY161*BO161 -> 0 | CB161: 320820 | CC161: 157843.44 | CD161: 324862 | CE161: =BV161/CD161*1000 -> 0 | CG161: =C161 -> MIX FM | CI161: =SUM(#REF!) -> #REF! | CJ161: =#REF!*CI161 -> #REF! | CK161: =SUM(#REF!) -> #REF! | CL161: =#REF!*CK161 -> #REF!
C162: (via S.J.Campos)
B164: TOTAL RÁDIO TAUBATE E SÃO JOSÉ DOS CAMPOS | F164: =SUM(F137:F163) -> 0 | G164: =SUM(G137:G163) -> 0 | H164: =SUM(H137:H163) -> 0 | I164: =SUM(I137:I163) -> 0 | J164: =SUM(J137:J163) -> 0 | K164: =SUM(K137:K163) -> 0 | L164: =SUM(L137:L163) -> 0 | M164: =SUM(M137:M163) -> 0 | ... BO164: =SUM(BO137:BO163) -> #REF! | BS164: =SUM(BS137:BS163) -> #REF! | BT164: =SUM(BT137:BT163) -> 865.24968 | BV164: =SUM(BV137:BV163) -> #REF! | CD164: =SUM(CD137:CD163) -> 324862 | CE164: =BV164/CD164*1000 -> #REF!
B166: BOTUCATU | C166: CLUBE FM | D166: 06h00 as 19h00 | E166: 30" | BO166: =SUM(F166:AI166) -> 0 | BP166: 200 | BQ166: 0.6 | BR166: =BP166*(1-BQ166) -> 80 | BS166: =BR166*BO166 -> 0 | BT166: =BR166*0.8 -> 64 | BV166: =BS166*0.8 -> 0 | CB166: 145155 | CE166: =BV166/CD166*1000 -> #DIV/0! | CG166: =C166 -> CLUBE FM | CI166: =SUM(#REF!) -> #REF! | CJ166: =#REF!*CI166 -> #REF! | CK166: =SUM(#REF!) -> #REF! | CL166: =#REF!*CK166 -> #REF!
B168: TOTAL RÁDIO BOTUCATU | F168: =SUM(F165:F167) -> 0 | G168: =SUM(G165:G167) -> 0 | H168: =SUM(H165:H167) -> 0 | I168: =SUM(I165:I167) -> 0 | J168: =SUM(J165:J167) -> 0 | K168: =SUM(K165:K167) -> 0 | L168: =SUM(L165:L167) -> 0 | M168: =SUM(M165:M167) -> 0 | ... BO168: =SUM(BO165:BO167) -> 0 | BS168: =SUM(BS165:BS167) -> 0 | BT168: =SUM(BT165:BT167) -> 64 | BV168: =SUM(BV165:BV167) -> 0 | CD168: =SUM(CD165:CD167) -> 0 | CE168: =BV168/CD168*1000 -> #DIV/0!
B170: LINS | C170: CLUBE FM | D170: 06h00 as 19h00 | E170: 30" | BO170: =SUM(F170:AI170) -> 0 | BP170: =21*1.25 -> 26.25 | BQ170: 0.3 | BR170: =BP170*(1-BQ170) -> 18.375 | BS170: =BR170*BO170 -> 0 | BT170: =BR170*0.8 -> 14.7 | BV170: =BS170*0.8 -> 0 | CA170: =BY170*BO170 -> 0 | CB170: 74779 | CD170: =CC170*CA170% -> 0 | CE170: =BV170/CD170*1000 -> #DIV/0! | CG170: =C170 -> CLUBE FM | CI170: =SUM(#REF!) -> #REF! | CJ170: =#REF!*CI170 -> #REF! | CK170: =SUM(#REF!) -> #REF! | CL170: =#REF!*CK170 -> #REF!
CI171: =SUM(#REF!) -> #REF! | CK171: =SUM(#REF!) -> #REF!
C172: RÁDIO AMIGA FM | D172: 06h00 as 19h00 | E172: 30" | BO172: =SUM(F172:AI172) -> 0 | BP172: =BR172/0.64 -> 121.5625 | BQ172: 0.36 | BR172: 77.8 | BS172: =BR172*BO172 -> 0 | BT172: =BR172*0.8 -> 62.24 | BV172: =BS172*0.8 -> 0 | CA172: =BY172*BO172 -> 0 | CB172: 74779 | CD172: =CC172*CA172% -> 0 | CE172: =BV172/CD172*1000 -> #DIV/0! | CG172: =C172 -> RÁDIO AMIGA FM | CJ172: =#REF!*CI171 -> #REF! | CL172: =#REF!*CK171 -> #REF!
B174: TOTAL RÁDIO LINS | F174: =SUM(F169:F173) -> 0 | G174: =SUM(G169:G173) -> 0 | H174: =SUM(H169:H173) -> 0 | I174: =SUM(I169:I173) -> 0 | J174: =SUM(J169:J173) -> 0 | K174: =SUM(K169:K173) -> 0 | L174: =SUM(L169:L173) -> 0 | M174: =SUM(M169:M173) -> 0 | ... BO174: =SUM(BO169:BO173) -> 0 | BS174: =SUM(BS169:BS173) -> 0 | BT174: =SUM(BT169:BT173) -> 76.94 | BV174: =SUM(BV169:BV173) -> 0 | CD174: =SUM(CD169:CD173) -> 0 | CE174: =BV174/CD174*1000 -> #DIV/0!
B176: PRESIDENTE PRUDENTE | C176: FRONTEIRA FM | D176: 06h00 as 19h00 | E176: 30" | BO176: =SUM(F176:AI176) -> 0 | BP176: 121 | BQ176: 0.5 | BR176: =BP176*(1-BQ176) -> 60.5 | BS176: =BR176*BO176 -> 0 | BT176: =BR176*0.8 -> 48.4 | BV176: =BS176*0.8 -> 0 | CA176: =BY176*BO176 -> 0 | CB176: 225668 | CD176: =CC176*CA176% -> 0 | CE176: =BV176/CD176*1000 -> #DIV/0! | CG176: =C176 -> FRONTEIRA FM | CI176: =SUM(#REF!) -> #REF! | CJ176: =#REF!*CI176 -> #REF! | CK176: =SUM(#REF!) -> #REF! | CL176: =#REF!*CK176 -> #REF!
C178: RÁDIO 98,1 | D178: 06h00 as 19h00 | E178: 30" | BO178: =SUM(F178:AI178) -> 0 | BP178: 218.5 | BQ178: 0.5 | BR178: =BP178*(1-BQ178) -> 109.25 | BS178: =BR178*BO178 -> 0 | BT178: =BR178*0.8 -> 87.4 | BV178: =BS178*0.8 -> 0 | CA178: =BY178*BO178 -> 0 | CB178: 225668 | CD178: =CC178*CA178% -> 0 | CE178: =BV178/CD178*1000 -> #DIV/0! | CG178: =C178 -> RÁDIO 98,1 | CI178: =SUM(#REF!) -> #REF! | CJ178: =#REF!*CI178 -> #REF! | CK178: =SUM(#REF!) -> #REF! | CL178: =#REF!*CK178 -> #REF!
C180: 101 FM | D180: 06h00 as 19h00 | E180: 30" | BO180: =SUM(F180:AI180) -> 0 | BP180: 427 | BQ180: 0.45 | BR180: =BP180*(1-BQ180) -> 234.85 | BS180: =BR180*BO180 -> 0 | BT180: =BR180*0.8 -> 187.88 | BV180: =BS180*0.8 -> 0 | CA180: =BY180*BO180 -> 0 | CB180: 225668 | CD180: =CC180*CA180% -> 0 | CE180: =BV180/CD180*1000 -> #DIV/0! | CG180: =C180 -> 101 FM | CI180: =SUM(#REF!) -> #REF! | CJ180: =#REF!*CI180 -> #REF! | CK180: =SUM(#REF!) -> #REF! | CL180: =#REF!*CK180 -> #REF!
B182: TOTAL RÁDIO PRESIDENTE PRUDENTE | F182: =SUM(F175:F181) -> 0 | G182: =SUM(G175:G181) -> 0 | H182: =SUM(H175:H181) -> 0 | I182: =SUM(I175:I181) -> 0 | J182: =SUM(J175:J181) -> 0 | K182: =SUM(K175:K181) -> 0 | L182: =SUM(L175:L181) -> 0 | M182: =SUM(M175:M181) -> 0 | ... BO182: =SUM(BO175:BO181) -> 0 | BS182: =SUM(BS175:BS181) -> 0 | BT182: =SUM(BT175:BT181) -> 323.68 | BV182: =SUM(BV175:BV181) -> 0 | CD182: =SUM(CD175:CD181) -> 0 | CE182: =BV182/CD182*1000 -> #DIV/0!
B184: MARKET | C184: CHANNEL | D184: PROPERTY | E184: FORMAT: SPOT | F184: OUTUBRO | BD184: DEZEMBRO | BH184: JANEIRO | BO184: INS. | BP184: CUSTO TABELA UNITÁRIO (BRUTO) | BQ184: DESC. % | BR184: CUSTO NEGOCIADO UNITÁRIO (BRUTO) | BS184: CUSTO TOTAL NEGOCIADO (BRUTO) | BT184: CUSTO TOTAL DESEMBOLSO CLIENTE | BV184: SHARE DE INVESTIMENTO % | BW184: SHARE DE AUDIÊNCIA % | BY184: IA% | BZ184: IA# | CA184: TRP | CB184: POPULAÇÃO TT. | CC184: UNIV. RÁDIO AS ABCDE 18+ | CD184: IMPACTOS ESTIMADOS | CE184: CPM | CG184: RÁDIO | CH184: VALOR UNITÁRIO LIQUIDO | CI184: DEZEMBRO | CK184: JANEIRO
F185: W | G185: T | H185: F | I185: S | J185: S | K185: M | L185: T | M185: W | N185: T | O185: F | P185: S | Q185: S | R185: M | S185: T | T185: W | U185: T | V185: F | W185: S | X185: S | Y185: M | Z185: T | AA185: W | AB185: T | AC185: F | AD185: S | AE185: S | AF185: M | AG185: T | AH185: W | AI185: T | AJ185: F | AK185: S | AL185: S | AM185: M | AN185: T | AO185: W | AP185: T | AQ185: F | AR185: S | AS185: S | AT185: M | AU185: T | AV185: W | AW185: T | AX185: F | AY185: S | AZ185: S | BA185: M | BB185: T | BC185: W | BD185: S | BE185: M | BF185: T | BG185: W | BH185: T | BI185: F | BJ185: S | BK185: S | BL185: F | BM185: S | BN185: S
F186: 1 | G186: 2 | H186: 3 | I186: 4 | J186: 5 | K186: 6 | L186: 7 | M186: 8 | N186: 9 | O186: 10 | P186: 11 | Q186: 12 | R186: 13 | S186: 14 | T186: 15 | U186: 16 | V186: 17 | W186: 18 | X186: 19 | Y186: 20 | Z186: 21 | AA186: 22 | AB186: 23 | AC186: 24 | AD186: 25 | AE186: 26 | AF186: 27 | AG186: 28 | AH186: 29 | AI186: 30 | AJ186: 31 | AK186: 1 | AL186: 2 | AM186: 3 | AN186: 4 | AO186: 5 | AP186: 6 | AQ186: 7 | AR186: 8 | AS186: 9 | AT186: 10 | AU186: 11 | AV186: 12 | AW186: 13 | AX186: 14 | AY186: 15 | AZ186: 16 | BA186: 17 | BB186: 18 | BC186: 19 | BD186: 28 | BE186: =BD186+1 -> 29 | BF186: =BE186+1 -> 30 | BG186: =BF186+1 -> 31 | BH186: 1 | BI186: =BH186+1 -> 2 | BJ186: =BI186+1 -> 3 | BK186: =BJ186+1 -> 4 | BL186: =BK186+1 -> 5 | BM186: =BL186+1 -> 6 | BN186: =BM186+1 -> 7 | CI186: INS. | CJ186: INV. LIQUIDO | CK186: INS. | CL186: INV. LIQUIDO
B188: BOTUCATU | C188: CLUBE FM | D188: 06h00 as 19h00 | E188: 30" | BE188: 4 | BF188: 4 | BG188: 4 | BH188: 4 | BI188: 4 | BJ188: 4 | BK188: 4 | BL188: 4 | BO188: =SUM(AK188:BN188) -> 32 | BP188: 200 | BQ188: 0.6 | BR188: =BP188*(1-BQ188) -> 80 | BS188: =BR188*BO188 -> 2560 | BT188: =BS188*0.8 -> 2048 | BV188: =BT188/BT191 -> 1 | BW188: - | CB188: 145155 | CG188: =C188 -> CLUBE FM | CH188: =BR188*0.8 -> 64 | CI188: =SUM(AK188:BG188) -> 12 | CJ188: =CH188*CI188 -> 768 | CK188: =SUM(BH188:BN188) -> 20 | CL188: =CK188*CH188 -> 1280 | CM188: =(CJ188+CL188)=BT188 -> TRUE
B191: TOTAL BOTUCATU | F191: =SUM(F144:F190) -> 1 | G191: =SUM(G144:G190) -> 2 | H191: =SUM(H144:H190) -> 3 | I191: =SUM(I144:I190) -> 4 | J191: =SUM(J144:J190) -> 5 | K191: =SUM(K144:K190) -> 6 | L191: =SUM(L144:L190) -> 7 | M191: =SUM(M144:M190) -> 8 | ... BC191: =SUM(BC144:BC190) -> 19 | BD191: =SUM(BD187:BD190) -> 0 | BE191: =SUM(BE187:BE190) -> 4 | BF191: =SUM(BF187:BF190) -> 4 | BG191: =SUM(BG187:BG190) -> 4 | BH191: =SUM(BH187:BH190) -> 4 | BI191: =SUM(BI187:BI190) -> 4 | BJ191: =SUM(BJ187:BJ190) -> 4 | BK191: =SUM(BK187:BK190) -> 4 | ... BT191: =SUM(BT187:BT190) -> 2048 | CB191: =SUM(CB187:CB190) -> 145155 | CC191: =SUM(CC187:CC190) -> 0 | CD191: =SUM(CD187:CD190) -> 0 | CE191: =SUM(CE187:CE190) -> 0 | CG191: =SUM(CG187:CG190) -> 0 | CH191: =SUM(CH187:CH190) -> 64 | CI191: =SUM(CI187:CI190) -> 12 | CJ191: =SUM(CJ187:CJ190) -> 768 | CK191: =SUM(CK187:CK190) -> 20 | CL191: =SUM(CL187:CL190) -> 1280 | CM191: =(CJ191+CL191)=BT191 -> TRUE
B193: LINS | C193: CLUBE FM | D193: 06h00 as 19h00 | E193: 30" | BE193: 4 | BF193: 4 | BG193: 4 | BH193: 4 | BI193: 4 | BJ193: 4 | BK193: 4 | BL193: 4 | BO193: =SUM(AK193:BN193) -> 32 | BP193: =21*1.25 -> 26.25 | BQ193: 0.3 | BR193: =BP193*(1-BQ193) -> 18.375 | BS193: =BR193*BO193 -> 588 | BT193: =BS193*0.8 -> 470.4 | BV193: =BT193/BT198 -> 0.19105797 | BW193: - | CB193: 74779 | CG193: =C193 -> CLUBE FM | CH193: =BR193*0.8 -> 14.7 | CI193: =SUM(AK193:BG193) -> 12 | CJ193: =CH193*CI193 -> 176.4 | CK193: =SUM(BH193:BN193) -> 20 | CL193: =CK193*CH193 -> 294 | CM193: =(CJ193+CL193)=BT193 -> TRUE
C196: RÁDIO AMIGA FM | D196: 06h00 as 19h00 | E196: 30" | BE196: 4 | BF196: 4 | BG196: 4 | BH196: 4 | BI196: 4 | BJ196: 4 | BK196: 4 | BL196: 4 | BO196: =SUM(AK196:BN196) -> 32 | BP196: 121.5625 | BQ196: 0.36 | BR196: =BP196*(1-BQ196) -> 77.8 | BS196: =BR196*BO196 -> 2489.6 | BT196: =BS196*0.8 -> 1991.68 | BV196: =BT196/BT198 -> 0.80894203 | BW196: - | CB196: 74779 | CG196: =C196 -> RÁDIO AMIGA FM | CH196: =BR196*0.8 -> 62.24 | CI196: =SUM(AK196:BG196) -> 12 | CJ196: =CH196*CI196 -> 746.88 | CK196: =SUM(BH196:BN196) -> 20 | CL196: =CK196*CH196 -> 1244.8 | CM196: =(CJ196+CL196)=BT196 -> TRUE
B198: TOTAL LINS | F198: =SUM(F153:F197) -> 2 | G198: =SUM(G153:G197) -> 4 | H198: =SUM(H153:H197) -> 6 | I198: =SUM(I153:I197) -> 8 | J198: =SUM(J153:J197) -> 10 | K198: =SUM(K153:K197) -> 12 | L198: =SUM(L153:L197) -> 14 | M198: =SUM(M153:M197) -> 16 | ... BC198: =SUM(BC153:BC197) -> 38 | BD198: =SUM(BD192:BD197) -> 0 | BE198: =SUM(BE192:BE197) -> 8 | BF198: =SUM(BF192:BF197) -> 8 | BG198: =SUM(BG192:BG197) -> 8 | BH198: =SUM(BH192:BH197) -> 8 | BI198: =SUM(BI192:BI197) -> 8 | BJ198: =SUM(BJ192:BJ197) -> 8 | BK198: =SUM(BK192:BK197) -> 8 | ... BT198: =SUM(BT192:BT197) -> 2462.08 | BV198: =SUM(BV192:BV197) -> 1 | CB198: =CB193 -> 74779 | CC198: =SUM(CC192:CC197) -> 0 | CD198: =SUM(CD192:CD197) -> 0 | CE198: =SUM(CE192:CE197) -> 0 | CG198: =SUM(CG192:CG197) -> 0 | CH198: =SUM(CH192:CH197) -> 76.94 | CI198: =SUM(CI192:CI197) -> 24 | CJ198: =SUM(CJ192:CJ197) -> 923.28 | CK198: =SUM(CK192:CK197) -> 40 | CL198: =SUM(CL192:CL197) -> 1538.8 | CM198: =(CJ198+CL198)=BT198 -> TRUE
...

Sheet RÁDIO
B5: CLIENT: SABESP
B6: CAMPAING: ESCASSEZ HIDRICA - CRÍTICO
B8: MARKET | C8: CHANNEL | D8: PROPERTY | E8: FORMAT: LOCUÇÃO DE CABINE | F8: JANEIRO | AK8: FEVEREIRO | BM8: INS. | BN8: CUSTO TABELA UNITÁRIO (BRUTO) | BO8: DESC. % | BP8: CUSTO NEGOCIADO UNITÁRIO (BRUTO) | BQ8: CUSTO TOTAL NEGOCIADO (BRUTO) | BR8: CUSTO TOTAL DESEMBOLSO CLIENTE | BT8: SHARE DE INVESTIMENTO % | BU8: SHARE DE AUDIÊNCIA % | BW8: IA% | BX8: IA# | BY8: TRP | BZ8: POPULAÇÃO TT. | CA8: UNIV. RÁDIO AS ABCDE 18+ | CB8: IMPACTOS ESTIMADOS | CC8: CPM | CE8: RÁDIO | CF8: VALOR UNITÁRIO LIQUIDO | CG8: JANEIRO | CI8: FEVEREIRO
F9: T | G9: F | H9: S | I9: S | J9: M | K9: T | L9: W | M9: T | N9: F | O9: S | P9: S | Q9: M | R9: T | S9: W | T9: T | U9: F | V9: S | W9: S | X9: M | Y9: T | Z9: W | AA9: T | AB9: F | AC9: S | AD9: S | AE9: M | AF9: T | AG9: W | AH9: T | AI9: F | AJ9: S | AK9: S | AL9: M | AM9: T | AN9: W | AO9: T | AP9: F | AQ9: S | AR9: S | AS9: M | AT9: T | AU9: W | AV9: T | AW9: F | AX9: S | AY9: S | AZ9: M | BA9: T | BB9: W | BC9: T | BD9: F | BE9: S | BF9: S | BG9: M | BH9: T | BI9: W | BJ9: T | BK9: F | BL9: S
F10: 1 | G10: =F10+1 -> 2 | H10: =G10+1 -> 3 | I10: =H10+1 -> 4 | J10: =I10+1 -> 5 | K10: =J10+1 -> 6 | L10: =K10+1 -> 7 | M10: =L10+1 -> 8 | N10: =M10+1 -> 9 | ... AJ10: =AI10+1 -> 31 | AK10: 1 | AL10: =AK10+1 -> 2 | AM10: =AL10+1 -> 3 | AN10: =AM10+1 -> 4 | AO10: =AN10+1 -> 5 | AP10: =AO10+1 -> 6 | AQ10: =AP10+1 -> 7 | AR10: =AQ10+1 -> 8 | AS10: =AR10+1 -> 9 | ... BL10: =BK10+1 -> 28 | CG10: INS. | CH10: INV. LIQUIDO | CI10: INS. | CJ10: INV. LIQUIDO
B13: RÁDIO JORNALISMO | C13: JOVEM PAN
B14: SÃO PAULO - CAPITAL | C14: ROTATIVO | D14: SEG À SEX 06H00-19H00 | E14: 30'' | AE14: 2 | AF14: 2 | AG14: 2 | AH14: 2 | AI14: 2 | AL14: 2 | AM14: 2 | AN14: 2 | AO14: 2 | AP14: 2 | AS14: 2 | AT14: 2 | AU14: 1 | AV14: 1 | AW14: 1 | BM14: =SUM(F14:BL14) -> 27 | BN14: 14586 | BO14: 0.64 | BP14: =BN14*(1-BO14) -> 5250.96 | BQ14: =BP14*BM14 -> 141775.92 | BR14: =BQ14*0.8 -> 113420.74 | BT14: {=SUM(BR14:BR15/$BR$29)} -> 0.30908322 | BU14: 0.31796335 | BW14: 0.97 | BX14: 97631 | BY14: =BW14*BM14 -> 26.19 | BZ14: 11451245 | CA14: 16255139 | CB14: =CA14*BY14/100 -> 4257220.9 | CC14: =SUM(BR14:BR15)/SUM(CB14:CB15)*1000 -> 30.079639 | CE14: JOVEM PAN | CF14: =BP14*0.8 -> 4200.768 | CG14: =SUM(F14:AJ14) -> 10 | CH14: =CF14*CG14 -> 42007.68 | CI14: =SUM(AK14:BL14) -> 17 | CJ14: =CI14*CF14 -> 71413.056 | CK14: =(CH14+CJ14)=BR14 -> TRUE
D15: SEG À SEX 06H00-19H00 | E15: 60'' | X15: 1 | Y15: 1 | Z15: 1 | AA15: 1 | BM15: =SUM(F15:BL15) -> 4 | BN15: =BN14*2 -> 29172 | BO15: 0.64 | BP15: =BN15*(1-BO15) -> 10501.92 | BQ15: =BP15*BM15 -> 42007.68 | BR15: =BQ15*0.8 -> 33606.144 | BW15: 0.97 | BX15: 97631 | BY15: =BW15*BM15 -> 3.88 | BZ15: 11451245 | CA15: 16255139 | CB15: =CA15*BY15/100 -> 630699.39 | CC15: =SUM(BR15:BR16)/SUM(CB15:CB16)*1000 -> 53.283933 | CE15: JOVEM PAN | CF15: =BP15*0.8 -> 8401.536 | CG15: =SUM(F15:AJ15) -> 4 | CH15: =CF15*CG15 -> 33606.144 | CI15: =SUM(AK15:BL15) -> 0 | CJ15: =CI15*CF15 -> 0 | CK15: =(CH15+CJ15)=BR15 -> TRUE
C18: BAND NEWS FM | D18: SEG À SEX 06H00-19H00 | E18: 30'' | AE18: 2 | AF18: 2 | AG18: 2 | AH18: 2 | AI18: 2 | AL18: 2 | AM18: 2 | AN18: 2 | AO18: 2 | AP18: 2 | AS18: 2 | AT18: 2 | AU18: 2 | AV18: 2 | AW18: 2 | BM18: =SUM(F18:BL18) -> 30 | BN18: 7984 | BO18: 0.65 | BP18: =BN18*(1-BO18) -> 2794.4 | BQ18: =BP18*BM18 -> 83832 | BR18: =BQ18*0.8 -> 67065.6 | BT18: =SUM(BR18:BR19)/$BR$29 -> 0.23497802 | BU18: 0.26616162 | BW18: 0.92 | BX18: 81725 | BY18: =BW18*BM18 -> 27.6 | BZ18: 11451245 | CA18: 16255139 | CB18: =CA18*BY18/100 -> 4486418.4 | CC18: =BR18/CB18*1000 -> 14.948584 | CE18: BAND NEWS FM | CF18: =BP18*0.8 -> 2235.52 | CG18: =SUM(F18:AJ18) -> 10 | CH18: =CF18*CG18 -> 22355.2 | CI18: =SUM(AK18:BL18) -> 20 | CJ18: =CI18*CF18 -> 44710.4 | CK18: =(CH18+CJ18)=BR18 -> TRUE
D19: SEG À SEX 06H00-19H00 | E19: 60'' | X19: 1 | Y19: 3 | Z19: 2 | AA19: 2 | AB19: 2 | BM19: =SUM(F19:BL19) -> 10 | BN19: =BN18*2 -> 15968 | BO19: 0.65 | BP19: =BN19*(1-BO19) -> 5588.8 | BQ19: =BP19*BM19 -> 55888 | BR19: =BQ19*0.8 -> 44710.4 | BW19: 0.92 | BX19: 81725 | BY19: =BW19*BM19 -> 9.2 | BZ19: 11451245 | CA19: 17116728 | CB19: =CA19*BY19/100 -> 1574739 | CC19: =BR19/CB19*1000 -> 28.392261 | CF19: =BP19*0.8 -> 4471.04 | CG19: =SUM(F19:AJ19) -> 10 | CH19: =CF19*CG19 -> 44710.4 | CI19: =SUM(AK19:BL19) -> 0 | CJ19: =CI19*CF19 -> 0 | CK19: =(CH19+CJ19)=BR19 -> TRUE
C22: BANDEIRANTES FM | D22: SEG À SEX 06H00-19H00 | E22: 30'' | AE22: 2 | AF22: 2 | AG22: 2 | AH22: 2 | AI22: 2 | AL22: 2 | AM22: 2 | AN22: 2 | AO22: 2 | AP22: 2 | AS22: 2 | AT22: 2 | AU22: 2 | AV22: 2 | AW22: 2 | BM22: =SUM(F22:BL22) -> 30 | BN22: 8436 | BO22: 0.65 | BP22: =BN22*(1-BO22) -> 2952.6 | BQ22: =BP22*BM22 -> 88578 | BR22: =BQ22*0.8 -> 70862.4 | BT22: {=SUM(BR22:BR23/$BR$29)} -> 0.19862471 | BU22: 0.1968604 | BW22: 0.89 | BX22: 60446 | BY22: =BW22*BM22 -> 26.7 | BZ22: 11451245 | CA22: 16255139 | CB22: =CA22*(BY22+BY24)/100 -> 4340122.1 | CC22: =BR22/CB22*1000 -> 16.327283 | CE22: BANDEIRANTES FM | CF22: =BP22*0.8 -> 2362.08 | CG22: =SUM(F22:AJ22) -> 10 | CH22: =CF22*CG22 -> 23620.8 | CI22: =SUM(AK22:BL22) -> 20 | CJ22: =CI22*CF22 -> 47241.6 | CK22: =(CH22+CJ22)=BR22 -> TRUE
D23: SEG À SEX 06H00-19H00 | E23: 60'' | X23: 1 | Y23: 1 | Z23: 1 | AA23: 1 | AB23: 1 | BM23: =SUM(F23:BL23) -> 5 | BN23: =BN22*2 -> 16872 | BO23: 0.65 | BP23: =BN23*(1-BO23) -> 5905.2 | BQ23: =BP23*BM23 -> 29526 | BR23: =BQ23*0.8 -> 23620.8 | BW23: 0.89 | BX23: 60446 | BY23: =BW23*BM23 -> 4.45 | BZ23: 11451245 | CA23: 17116728 | CB23: =CA23*(BY23+BY25)/100 -> 761694.4 | CC23: =BR23/CB23*1000 -> 31.010862 | CF23: =BP23*0.8 -> 4724.16 | CG23: =SUM(F23:AJ23) -> 5 | CH23: =CF23*CG23 -> 23620.8 | CI23: =SUM(AK23:BL23) -> 0 | CJ23: =CI23*CF23 -> 0
C26: CBN | D26: SEG À SEX 06H00-19H00 | E26: 30'' | AE26: 1 | AF26: 1 | AG26: 1 | AH26: 1 | AI26: 1 | AL26: 1 | AM26: 1 | AN26: 1 | AO26: 1 | AP26: 1 | AS26: 1 | AT26: 1 | BM26: =SUM(F26:BL26) -> 12 | BN26: 11591 | BO26: 0.4 | BP26: =BN26*(1-BO26) -> 6954.6 | BQ26: =BP26*BM26 -> 83455.2 | BR26: =BQ26*0.8 -> 66764.16 | BT26: =SUM(BR26:BR27)/$BR$29 -> 0.25731405 | BU26: 0.25901462 | BW26: 0.87 | BX26: 67249 | BY26: =BW26*BM26 -> 10.44 | BZ26: 11451245 | CA26: 16255139 | CB26: =CA26*BY26/100 -> 1697036.5 | CC26: =BR26/CB26*1000 -> 39.341617 | CE26: CBN | CF26: =BP26*0.8 -> 5563.68 | CG26: =SUM(F26:AJ26) -> 5 | CH26: =CF26*CG26 -> 27818.4 | CI26: =SUM(AK26:BL26) -> 7 | CJ26: =CI26*CF26 -> 38945.76 | CK26: =(CH26+CJ26)=BR26 -> TRUE
D27: SEG À SEX 06H00-19H00 | E27: 60'' | Y27: 2 | Z27: 1 | AA27: 1 | AB27: 1 | BM27: =SUM(F27:BL27) -> 5 | BN27: =BN26*2 -> 23182 | BO27: 0.4 | BP27: =BN27*(1-BO27) -> 13909.2 | BQ27: =BP27*BM27 -> 69546 | BR27: =BQ27*0.8 -> 55636.8 | BW27: 0.87 | BX27: 67249 | BY27: =BW27*BM27 -> 4.35 | BZ27: 11451245 | CA27: 21515727 | CB27: =CA27*BY27/100 -> 935934.13 | CC27: =BR27/CB27*1000 -> 59.445209 | CF27: =BP27*0.8 -> 11127.36 | CG27: =SUM(F27:AJ27) -> 5 | CH27: =CF27*CG27 -> 55636.8 | CI27: =SUM(AK27:BL27) -> 0 | CJ27: =CI27*CF27 -> 0
B29: TOTAL RADIO SP CAPITAL - JORNALISMO | F29: =SUM(F12:F28) -> 0 | G29: =SUM(G12:G28) -> 0 | H29: =SUM(H12:H28) -> 0 | I29: =SUM(I12:I28) -> 0 | J29: =SUM(J12:J28) -> 0 | K29: =SUM(K12:K28) -> 0 | L29: =SUM(L12:L28) -> 0 | M29: =SUM(M12:M28) -> 0 | ... BM29: =SUM(BM12:BM28) -> 123 | BQ29: =SUM(BQ12:BQ28) -> 594608.8 | BR29: =SUM(BR12:BR28) -> 475687.04 | BZ29: =BZ26 -> 11451245 | CB29: =CB26+CB22+CB18+CB14 -> 14780798 | CC29: =BR29/CB29*1000 -> 32.182771 | CG29: {=CG26:CG27+CG22:CG23+CG18:CG19+CG14:CG15} -> 35 | CH29: =SUM(CH12:CH28) -> 273376.22 | CI29: {=CI26:CI27+CI22:CI23+CI18:CI19+CI14:CI15} -> 64 | CJ29: =SUM(CJ12:CJ28) -> 202310.82 | CK29: =(CH29+CJ29)=BR29 -> TRUE
CG30: 24 | CI30: 0
B31: MARKET | C31: CHANNEL | D31: PROPERTY | E31: FORMAT: SPOT | F31: JANEIRO | AK31: FEVEREIRO | BM31: INS. | BN31: CUSTO TABELA UNITÁRIO (BRUTO) | BO31: DESC. % | BP31: CUSTO NEGOCIADO UNITÁRIO (BRUTO) | BQ31: CUSTO TOTAL NEGOCIADO (BRUTO) | BR31: CUSTO TOTAL DESEMBOLSO CLIENTE | BT31: SHARE DE INVESTIMENTO % | BU31: SHARE DE AUDIÊNCIA % | BW31: IA% | BX31: IA# | BY31: TRP | BZ31: POPULAÇÃO TT. | CA31: UNIV. RÁDIO AS ABCDE 18+ | CB31: IMPACTOS ESTIMADOS | CC31: CPM | CE31: RÁDIO | CF31: VALOR UNITÁRIO LIQUIDO | CG31: DEZEMBRO | CI31: JANEIRO
F32: T | G32: F | H32: S | I32: S | J32: M | K32: T | L32: W | M32: T | N32: F | O32: S | P32: S | Q32: M | R32: T | S32: W | T32: T | U32: F | V32: S | W32: S | X32: M | Y32: T | Z32: W | AA32: T | AB32: F | AC32: S | AD32: S | AE32: M | AF32: T | AG32: W | AH32: T | AI32: F | AJ32: S | AK32: S | AL32: M | AM32: T | AN32: W | AO32: T | AP32: F | AQ32: S | AR32: S | AS32: M | AT32: T | AU32: W | AV32: T | AW32: F | AX32: S | AY32: S | AZ32: M | BA32: T | BB32: W | BC32: T | BD32: F | BE32: S | BF32: S | BG32: M | BH32: T | BI32: W | BJ32: T | BK32: F | BL32: S
F33: 1 | G33: =F33+1 -> 2 | H33: =G33+1 -> 3 | I33: =H33+1 -> 4 | J33: =I33+1 -> 5 | K33: =J33+1 -> 6 | L33: =K33+1 -> 7 | M33: =L33+1 -> 8 | N33: =M33+1 -> 9 | ... AJ33: =AI33+1 -> 31 | AK33: 1 | AL33: =AK33+1 -> 2 | AM33: =AL33+1 -> 3 | AN33: =AM33+1 -> 4 | AO33: =AN33+1 -> 5 | AP33: =AO33+1 -> 6 | AQ33: =AP33+1 -> 7 | AR33: =AQ33+1 -> 8 | AS33: =AR33+1 -> 9 | ... BL33: =BK33+1 -> 28 | CG33: INS. | CH33: INV. LIQUIDO | CI33: INS. | CJ33: INV. LIQUIDO
B35: RÁDIO MUSICAL | C35: NATIVA FM | D35: SEG À DOM 06H00-19H00 | E35: 30'' | AC35: 3 | AD35: 3 | AE35: 3 | AF35: 3 | AG35: 3 | AH35: 3 | AI35: 3 | AJ35: 3 | AK35: 3 | AL35: 3 | AM35: 3 | AN35: 3 | AO35: 3 | AP35: 3 | AQ35: 3 | AR35: 3 | AS35: 3 | AT35: 3 | AU35: 3 | AV35: 3 | AW35: 3 | BM35: =SUM(F35:BL35) -> 63 | BN35: 3733 | BO35: 0.63 | BP35: =BN35*(1-BO35) -> 1381.21 | BQ35: =BP35*BM35 -> 87016.23 | BR35: =BQ35*0.8 -> 69612.984 | BT35: =(BR35+BR36)/$BR$94 -> 0.06988844 | BU35: 0.065898255 | BW35: =BX35/CA35*100 -> 0.49702669 | BX35: 80792.38 | BY35: =BW35*BM35 -> 31.312682 | BZ35: 11451245 | CA35: 16255139 | CB35: =CA35*BY35/100 -> 5089919.9 | CC35: =BR35/CB35*1000 -> 13.676636 | CE35: NATIVA | CF35: =BP35*0.8 -> 1104.968 | CG35: =SUM(F35:AJ35) -> 24 | CH35: =CF35*CG35 -> 26519.232 | CI35: =SUM(AK35:BL35) -> 39 | CJ35: =CI35*CF35 -> 43093.752 | CK35: =(CH35+CJ35)=BR35 -> TRUE
