Workbook
Name _1: #REF!
Name _1: #REF!
Name _1: #REF!
Name _10: #REF!
Name _10: #REF!
Name _10: #REF!
Name _11: #REF!
Name _11: #REF!
Name _11: #REF!
Name _12: #REF!
Name _12: #REF!
Name _12: #REF!
Name _13: #REF!
Name _13: #REF!
Name _13: #REF!
Name _14: #REF!
Name _14: #REF!
Name _14: #REF!
Name _15: #REF!
Name _15: #REF!
Name _15: #REF!
Name _16: #REF!
Name _16: #REF!
Name _16: #REF!
Name _17: #REF!
Name _17: #REF!
Name _17: #REF!
Name _18: #REF!
Name _18: #REF!
Name _18: #REF!
Name _19: #REF!
Name _19: #REF!
Name _19: #REF!
Name _1Excel_BuiltIn__FilterDatabase_10_9_1: NA()
Name _2: #REF!
Name _2: #REF!
Name _2: #REF!
Name _20: #REF!
Name _20: #REF!
Name _20: #REF!
Name _21: #REF!
Name _21: #REF!
Name _21: #REF!
Name _22: #REF!
Name _22: #REF!
Name _22: #REF!
Name _23: #REF!
Name _23: #REF!
Name _23: #REF!
Name _24: #REF!
Name _24: #REF!
Name _24: #REF!
Name _25: #REF!
Name _25: #REF!
Name _25: #REF!
Name _26: #REF!
Name _26: #REF!
Name _26: #REF!
Name _27: #REF!
Name _27: #REF!

Sheet COVER
B6: Tactical Media Plan | I6: CONFIDENCIAL
B8: CLIENT: | C8: SABESP
B9: CAMPAING | C9: ESCASSEZ HIDRICA PCJ
B10: TARGET: | C10: AS ABCDE 25+
B14: VERSION | C14: UPDATE DATE | D14: UPDATES:
B15: 1 | C15: 46062 | D15: Ajuste do período de veiculação para 15 dias; Redução do investimento de rádio; Ajuste do período de veiculação dos materiais de 60'' e 30'' de TV.
B16: 2 | C16: 46062 | D16: Ajuste do share de investimentos de TV.
B17: 3 | C17: 46078 | D17: Ajuste conforme compensações

Sheet RESUMO DE MEIOS
B5: CLIENT: SABESP
B6: CAMPAING: ESCASSEZ HIDRICA PCJ
B8: RESUMO DE MEIOS - SÃO PAULO CAPITAL
B10: PRAÇA | C10: MEIO | D10: VEÍCULO | F10: FEVEREIRO | G10: TOTAL BRUTO | H10: VALOR DESEMBOLSO TT | I10: PART GERAL %
B13: CAMPINAS | C13: TV ABERTA | D13: GLOBO | F13: ='TV ABERTA'!AX30*1.25 -> 294327.9 | G13: =SUM(F13:F13) -> 294327.9 | H13: =G13*0.8 -> 235462.32 | I13: =H13/$H$27 -> 0.30086699
B14: CAMPINAS | C14: TV ABERTA | D14: BANDEIRANTES | F14: ='TV ABERTA'!AX43*1.25 -> 20698.95 | G14: =SUM(F14:F14) -> 20698.95 | H14: =G14*0.8 -> 16559.16 | I14: =H14/$H$27 -> 0.021158819
B15: CAMPINAS | C15: TV ABERTA | D15: RECORD | F15: ='TV ABERTA'!AX58*1.25 -> 67579.6 | G15: =SUM(F15:F15) -> 67579.6 | H15: =G15*0.8 -> 54063.68 | I15: =H15/$H$27 -> 0.069081017
B16: CAMPINAS/SANTOS | C16: TV ABERTA | D16: SBT | F16: ='TV ABERTA'!AX75*1.25 -> 46601 | G16: =SUM(F16:F16) -> 46601 | H16: =G16*0.8 -> 37280.8 | I16: =H16/$H$27 -> 0.047636335
B17: SOROCABA | C17: TV ABERTA | D17: GLOBO | F17: ='TV ABERTA'!AX93*1.25 -> 119680.2 | G17: =SUM(F17:F17) -> 119680.2 | H17: =G17*0.8 -> 95744.16 | I17: =H17/$H$27 -> 0.12233914
B18: SOROCABA | C18: TV ABERTA | D18: SBT | F18: ='TV ABERTA'!AX108*1.25 -> 20792.75 | G18: =SUM(F18:F18) -> 20792.75 | H18: =G18*0.8 -> 16634.2 | I18: =H18/$H$27 -> 0.021254703
B19: RIBEIRÃO PRETO | C19: TV ABERTA | D19: GLOBO | F19: ='TV ABERTA'!AX126*1.25 -> 160146.9 | G19: =SUM(F19:F19) -> 160146.9 | H19: =G19*0.8 -> 128117.52 | I19: =H19/$H$27 -> 0.16370489
B20: RIBEIRÃO PRETO | C20: TV ABERTA | D20: BANDEIRANTES | F20: ='TV ABERTA'!AX139*1.25 -> 11295.3 | G20: =SUM(F20:F20) -> 11295.3 | H20: =G20*0.8 -> 9036.24 | I20: =H20/$H$27 -> 0.011546248
B21: RIBEIRÃO PRETO | C21: TV ABERTA | D21: SBT | F21: ='TV ABERTA'!AX152*1.25 -> 22686.75 | G21: =SUM(F21:F21) -> 22686.75 | H21: =G21*0.8 -> 18149.4 | I21: =H21/$H$27 -> 0.023190782
B22: SÃO JOSÉ DOS CAMPOS | C22: TV ABERTA | D22: GLOBO | F22: ='TV ABERTA'!AX170*1.25 -> 95413.5 | G22: =SUM(F22:F22) -> 95413.5 | H22: =G22*0.8 -> 76330.8 | I22: =H22/$H$27 -> 0.097533303
B23: SÃO JOSÉ DOS CAMPOS | C23: TV ABERTA | D23: SBT | F23: ='TV ABERTA'!AX185*1.25 -> 17058.5 | G23: =SUM(F23:F23) -> 17058.5 | H23: =G23*0.8 -> 13646.8 | I23: =H23/$H$27 -> 0.017437489
B24: SÃO CARLOS | C24: TV ABERTA | D24: GLOBO | F24: ='TV ABERTA'!AX203*1.25 -> 71724.6 | G24: =SUM(F24:F24) -> 71724.6 | H24: =G24*0.8 -> 57379.68 | I24: =H24/$H$27 -> 0.073318107
B25: FRANCA | C25: TV ABERTA | D25: RECORD | F25: ='TV ABERTA'!AX218*1.25 -> 30259.9 | G25: =SUM(F25:F25) -> 30259.9 | H25: =G25*0.8 -> 24207.92 | I25: =H25/$H$27 -> 0.030932185
B27: TT TV ABERTA | F27: =SUM(F13:F25) -> 978265.85 | G27: =SUM(G13:G25) -> 978265.85 | H27: =SUM(H13:H25) -> 782612.68 | I27: =SUM(I13:I25) -> 1 | J27: =H27/H39 -> 0.87063457 | K27: =H27=SUM('TV ABERTA'!AP220) -> FALSE
B29: BAIXA MOGIANA | C29: RADIO | D29: BAND FM | F29: ='RÁDIO '!BJ16*1.25 -> 6204 | G29: =SUM(F29:F29) -> 6204 | H29: =G29*0.8 -> 4963.2 | I29: =H29/$H$35 -> 0.047046119
B30: CAMPINAS | C30: RADIO | D30: BAND FM | F30: ='RÁDIO '!BJ20*1.25 -> 50301 | G30: =SUM(F30:F30) -> 50301 | H30: =G30*0.8 -> 40240.8 | I30: =H30/$H$35 -> 0.38144211
B31: CAMPINAS | C31: RADIO | D31: NATIVA FM | F31: ='RÁDIO '!BJ24*1.25 -> 56448 | G31: =SUM(F31:F31) -> 56448 | H31: =G31*0.8 -> 45158.4 | I31: =H31/$H$35 -> 0.42805599
B32: CAMPINAS | C32: RADIO | D32: EDUCADORA | F32: ='RÁDIO '!BJ28*1.25 -> 16508.6 | G32: =SUM(F32:F32) -> 16508.6 | H32: =G32*0.8 -> 13206.88 | I32: =H32/$H$35 -> 0.12518787
B33: MOOCA | C33: RADIO | D33: BAND FM | F33: ='RÁDIO '!BJ32*1.25 -> 2409 | G33: =SUM(F33:F33) -> 2409 | H33: =G33*0.8 -> 1927.2 | I33: =H33/$H$35 -> 0.018267908
B35: TT RÁDIO | F35: =SUM(F29:F33) -> 131870.6 | G35: =SUM(G29:G33) -> 131870.6 | H35: =SUM(H29:H33) -> 105496.48 | I35: =SUM(I29:I33) -> 1 | J35: =H35/H39 -> 0.11736186 | K35: =H35='RÁDIO '!BJ33 -> TRUE
B37: TT GERAÇÃO | F37: ='CUSTO GERAÇÃO'!I43*1.25 -> 13487.5 | G37: =SUM(F37:F37) -> 13487.5 | H37: =G37*0.8 -> 10790 | I37: 1 | J37: =H37/H39 -> 0.012003571
B39: TOTAL GERAL | F39: =SUM(F27,F35,F37) -> 1123624 | G39: =SUM(G27,G35,G37) -> 1123624 | H39: =SUM(H27,H35,H37) -> 898899.16 | J39: =SUM(J10:J38) -> 1
F40: =F39/G39 -> 1 | H40: =SUM('TV ABERTA'!AX220,'RÁDIO '!BJ33,'CUSTO GERAÇÃO'!I43)=H39 -> TRUE

Sheet RESUMO DE MEIOS - SPE
B5: CLIENT: SABESP
B6: CAMPAING: ESCASSEZ HIDRICA - CRÍTICO
B8: RESUMO DE MEIOS - SÃO PAULO ESTADO
B10: PRAÇA | C10: MEIO | D10: VEÍCULO | F10: JANEIRO | G10: FEVEREIRO | H10: TOTAL BRUTO | I10: VALOR DESEMBOLSO TT | J10: PART GERAL %
N12: UTILIZAÇÃO DE SALDO DE PACOTES | P12: SALDO PACOTE | Q12: TOTAL A SER FATURADO
B13: SÃO PAULO ESTADO | C13: TV ABERTA | D13: GLOBO | F13: ='TV ABERTA - SPE'!CC32*1.25 -> 3234841.4 | G13: ='TV ABERTA - SPE'!CE32*1.25 -> 1220562 | H13: =SUM(F13:G13) -> 4455403.4 | I13: =H13*0.8 -> 3564322.8 | J13: =I13/$I$23 -> 0.45681236 | N13: SBT | O13: =I16+I21 -> 1109489.6 | P13: 567311.6 | Q13: =O13-P13 -> 542178
B14: SÃO PAULO ESTADO | C14: TV ABERTA | D14: BANDEIRANTES | F14: ='TV ABERTA - SPE'!CC44*1.25 -> 118538.85 | G14: ='TV ABERTA - SPE'!CE44*1.25 -> 77298.6 | H14: =SUM(F14:G14) -> 195837.45 | I14: =H14*0.8 -> 156669.96 | J14: =I14/$I$23 -> 0.020079207
B15: SÃO PAULO ESTADO | C15: TV ABERTA | D15: RECORD | F15: ='TV ABERTA - SPE'!CC57*1.25 -> 602332.6 | G15: ='TV ABERTA - SPE'!CE57*1.25 -> 574113.2 | H15: =SUM(F15:G15) -> 1176445.8 | I15: =H15*0.8 -> 941156.64 | J15: =I15/$I$23 -> 0.12062095
B16: SÃO PAULO ESTADO | C16: TV ABERTA | D16: SBT | F16: ='TV ABERTA - SPE'!CC70*1.25 -> 510641.5 | G16: ='TV ABERTA - SPE'!CE70*1.25 -> 573264 | H16: =SUM(F16:G16) -> 1083905.5 | I16: =H16*0.8 -> 867124.4 | J16: =I16/$I$23 -> 0.11113279
B18: SÃO PAULO ESTADO | C18: TV ABERTA | D18: GLOBO | F18: ='TV ABERTA - COLCHÃO REP - SPE'!CC17*1.25 -> 830408.4 | G18: ='TV ABERTA - COLCHÃO REP - SPE'!CE17*1.25 -> 830408.4 | H18: =SUM(F18:G18) -> 1660816.8 | I18: =H18*0.8 -> 1328653.4 | J18: =I18/$I$23 -> 0.17028349
B19: SÃO PAULO ESTADO | C19: TV ABERTA | D19: BANDEIRANTES | F19: ='TV ABERTA - COLCHÃO REP - SPE'!CC20*1.25 -> 114500.4 | G19: ='TV ABERTA - COLCHÃO REP - SPE'!CE20*1.25 -> 114500.4 | H19: =SUM(F19:G19) -> 229000.8 | I19: =H19*0.8 -> 183200.64 | J19: =I19/$I$23 -> 0.023479444
B20: SÃO PAULO ESTADO | C20: TV ABERTA | D20: RECORD | F20: ='TV ABERTA - COLCHÃO REP - SPE'!CC23*1.25 -> 324440 | G20: ='TV ABERTA - COLCHÃO REP - SPE'!CE23*1.25 -> 324440 | H20: =SUM(F20:G20) -> 648880 | I20: =H20*0.8 -> 519104 | J20: =I20/$I$23 -> 0.066529644
B21: SÃO PAULO ESTADO | C21: TV ABERTA | D21: SBT | F21: ='TV ABERTA - COLCHÃO REP - SPE'!CC25*1.25 -> 100985.5 | G21: ='TV ABERTA - COLCHÃO REP - SPE'!CE25*1.25 -> 201971 | H21: =SUM(F21:G21) -> 302956.5 | I21: =H21*0.8 -> 242365.2 | J21: =I21/$I$23 -> 0.031062119
B23: TT TV ABERTA | F23: =SUM(F13:F21) -> 5836688.7 | G23: =SUM(G13:G21) -> 3916557.6 | H23: =SUM(H13:H21) -> 9753246.3 | I23: =SUM(I13:I21) -> 7802597 | J23: =SUM(J13:J21) -> 1 | K23: =I23/I68 -> #REF! | L23: =I23=SUM('TV ABERTA - SPE'!BU72,'TV ABERTA - COLCHÃO REP - SPE'!BU27) -> TRUE
B25: SÃO PAULO ESTADO | C25: TV PAGA | D25: GLOBONEWS | F25: ='TV PAGA - COLCHÃO REP - SPE'!CC37*1.25 -> 38904 | G25: ='TV PAGA - COLCHÃO REP - SPE'!CE37*1.25 -> 38904 | H25: =SUM(F25:G25) -> 77808 | I25: =H25*0.8 -> 62246.4 | J25: =I25/$I$30 -> 0.41072115
B26: SÃO PAULO ESTADO | C26: TV PAGA | D26: CNN BRASIL | F26: ='TV PAGA - COLCHÃO REP - SPE'!CC40*1.25 -> 22260 | G26: ='TV PAGA - COLCHÃO REP - SPE'!CE40*1.25 -> 22260 | H26: =SUM(F26:G26) -> 44520 | I26: =H26*0.8 -> 35616 | J26: =I26/$I$30 -> 0.23500547
B27: SÃO PAULO ESTADO | C27: TV PAGA | D27: RECORD NEWS | F27: ='TV PAGA - COLCHÃO REP - SPE'!CC43*1.25 -> 22000 | G27: ='TV PAGA - COLCHÃO REP - SPE'!CE43*1.25 -> 22000 | H27: =SUM(F27:G27) -> 44000 | I27: =H27*0.8 -> 35200 | J27: =I27/$I$30 -> 0.23226057
B28: SÃO PAULO ESTADO | C28: TV PAGA | D28: BAND NEWS | F28: ='TV PAGA - COLCHÃO REP - SPE'!CC46*1.25 -> 11557.2 | G28: ='TV PAGA - COLCHÃO REP - SPE'!CE46*1.25 -> 11557.2 | H28: =SUM(F28:G28) -> 23114.4 | I28: =H28*0.8 -> 18491.52 | J28: =I28/$I$30 -> 0.12201281
B30: TT TV PAGA | F30: =SUM(F25:F29) -> 94721.2 | G30: =SUM(G25:G29) -> 94721.2 | H30: =SUM(H25:H29) -> 189442.4 | I30: =SUM(I25:I29) -> 151553.92 | J30: =SUM(J25:J29) -> 1 | K30: =I30/I68 -> #REF! | L30: =I30='TV PAGA - COLCHÃO REP - SPE'!BU48 -> TRUE
B32: SÃO PAULO | C32: JORNAL | D32: =#REF! -> #REF! | F32: =SUM(#REF!)*1.25 -> #REF! | G32: {=SUM(#REF!*1.25)} -> #REF! | H32: =SUM(F32:G32) -> #REF! | I32: =H32*0.8 -> #REF! | J32: =I32/$I$38 -> #REF!
B33: SÃO PAULO | C33: JORNAL | D33: =#REF! -> #REF! | F33: =SUM(#REF!)*1.25 -> #REF! | G33: =SUM(#REF!)*1.25 -> #REF! | H33: =SUM(F33:G33) -> #REF! | I33: =H33*0.8 -> #REF! | J33: =I33/$I$38 -> #REF!
B34: SÃO PAULO | C34: JORNAL | D34: =#REF! -> #REF! | F34: =SUM(#REF!)*1.25 -> #REF! | G34: =SUM(#REF!)*1.25 -> #REF! | H34: =SUM(F34:G34) -> #REF! | I34: =H34*0.8 -> #REF! | J34: =I34/$I$38 -> #REF!
B35: SÃO PAULO | C35: JORNAL | D35: =#REF! -> #REF! | F35: =SUM(#REF!)*1.25 -> #REF! | G35: =SUM(#REF!)*1.25 -> #REF! | H35: =SUM(F35:G35) -> #REF! | I35: =H35*0.8 -> #REF! | J35: =I35/$I$38 -> #REF!
B36: =#REF! -> #REF! | C36: JORNAL | D36: =#REF! -> #REF! | F36: =SUM(#REF!)*1.25 -> #REF! | G36: =SUM(#REF!)*1.25 -> #REF! | H36: =SUM(F36:G36) -> #REF! | I36: =H36*0.8 -> #REF! | J36: =I36/$I$38 -> #REF!
B38: TT JORNAL | F38: =SUM(F32:F36) -> #REF! | G38: =SUM(G32:G36) -> #REF! | H38: =SUM(H32:H36) -> #REF! | I38: =SUM(I32:I36) -> #REF! | J38: =SUM(J32:J36) -> #REF! | K38: =I38/I68 -> #REF! | L38: =I38=#REF! -> #REF!
B40: SÃO PAULO | C40: RADIO | D40: JOVEM PAN FM | F40: =SUM(#REF!)*1.25 -> #REF! | G40: =SUM(#REF!)*1.25 -> #REF! | H40: =SUM(F40:G40) -> #REF! | I40: =H40*0.8 -> #REF! | J40: =I40/$I$60 -> #REF!
B41: SÃO PAULO | C41: RADIO | D41: BAND NEWS FM | F41: =SUM(#REF!)*1.25 -> #REF! | G41: =SUM(#REF!)*1.25 -> #REF! | H41: =SUM(F41:G41) -> #REF! | I41: =H41*0.8 -> #REF! | J41: =I41/$I$60 -> #REF!
B42: SÃO PAULO | C42: RADIO | D42: BANDEIRANTES | F42: =SUM(#REF!)*1.25 -> #REF! | G42: =SUM(#REF!)*1.25 -> #REF! | H42: =SUM(F42:G42) -> #REF! | I42: =H42*0.8 -> #REF! | J42: =I42/$I$60 -> #REF!
B43: SÃO PAULO | C43: RADIO | D43: CBN | F43: =SUM(#REF!)*1.25 -> #REF! | G43: =SUM(#REF!)*1.25 -> #REF! | H43: =SUM(F43:G43) -> #REF! | I43: =H43*0.8 -> #REF! | J43: =I43/$I$60 -> #REF!
B44: SÃO PAULO | C44: RADIO | D44: NATIVA FM | F44: =SUM(#REF!)*1.25 -> #REF! | G44: =SUM(#REF!)*1.25 -> #REF! | H44: =SUM(F44:G44) -> #REF! | I44: =H44*0.8 -> #REF! | J44: =I44/$I$60 -> #REF!
B45: SÃO PAULO | C45: RADIO | D45: BAND FM | F45: =SUM(#REF!)*1.25 -> #REF! | G45: =SUM(#REF!)*1.25 -> #REF! | H45: =SUM(F45:G45) -> #REF! | I45: =H45*0.8 -> #REF! | J45: =I45/$I$60 -> #REF!
B46: SÃO PAULO | C46: RADIO | D46: 89 ROCK FM | F46: =SUM(#REF!)*1.25 -> #REF! | G46: =SUM(#REF!)*1.25 -> #REF! | H46: =SUM(F46:G46) -> #REF! | I46: =H46*0.8 -> #REF! | J46: =I46/$I$60 -> #REF!
B47: SÃO PAULO | C47: RADIO | D47: ALPHA FM | F47: =SUM(#REF!)*1.25 -> #REF! | G47: =SUM(#REF!)*1.25 -> #REF! | H47: =SUM(F47:G47) -> #REF! | I47: =H47*0.8 -> #REF! | J47: =I47/$I$60 -> #REF!
B48: SÃO PAULO | C48: RADIO | D48: DISNEY FM | F48: =SUM(#REF!)*1.25 -> #REF! | G48: =SUM(#REF!)*1.25 -> #REF! | H48: =SUM(F48:G48) -> #REF! | I48: =H48*0.8 -> #REF! | J48: =I48/$I$60 -> #REF!
B49: SÃO PAULO | C49: RADIO | D49: ENERGIA 97 FM | F49: =SUM(#REF!)*1.25 -> #REF! | G49: =SUM(#REF!)*1.25 -> #REF! | H49: =SUM(F49:G49) -> #REF! | I49: =H49*0.8 -> #REF! | J49: =I49/$I$60 -> #REF!
B50: SÃO PAULO | C50: RADIO | D50: KISS FM | F50: =SUM(#REF!)*1.25 -> #REF! | G50: =SUM(#REF!)*1.25 -> #REF! | H50: =SUM(F50:G50) -> #REF! | I50: =H50*0.8 -> #REF! | J50: =I50/$I$60 -> #REF!
B51: SÃO PAULO | C51: RADIO | D51: GAZETA FM | F51: =SUM(#REF!)*1.25 -> #REF! | G51: =SUM(#REF!)*1.25 -> #REF! | H51: =SUM(F51:G51) -> #REF! | I51: =H51*0.8 -> #REF! | J51: =I51/$I$60 -> #REF!
B52: SÃO PAULO | C52: RADIO | D52: 105 FM | F52: =SUM(#REF!)*1.25 -> #REF! | G52: =SUM(#REF!)*1.25 -> #REF! | H52: =SUM(F52:G52) -> #REF! | I52: =H52*0.8 -> #REF! | J52: =I52/$I$60 -> #REF!
B53: SÃO PAULO | C53: RADIO | D53: RÁDIO MIX | F53: =SUM(#REF!+#REF!)*1.25 -> #REF! | G53: =SUM(#REF!+#REF!)*1.25 -> #REF! | H53: =SUM(F53:G53) -> #REF! | I53: =H53*0.8 -> #REF! | J53: =I53/$I$60 -> #REF!
B54: SÃO PAULO | C54: RADIO | D54: TRANSAMÉRICA FM | F54: =SUM(#REF!)*1.25 -> #REF! | G54: =SUM(#REF!)*1.25 -> #REF! | H54: =SUM(F54:G54) -> #REF! | I54: =H54*0.8 -> #REF! | J54: =I54/$I$60 -> #REF!
B55: SÃO PAULO | C55: RADIO | D55: MASSA FM | F55: =SUM(#REF!)*1.25 -> #REF! | G55: =SUM(#REF!)*1.25 -> #REF! | H55: =SUM(F55:G55) -> #REF! | I55: =H55*0.8 -> #REF! | J55: =I55/$I$60 -> #REF!
B56: SÃO PAULO | C56: RADIO | D56: ANTENA 1 FM | F56: =SUM(#REF!)*1.25 -> #REF! | G56: =SUM(#REF!)*1.25 -> #REF! | H56: =SUM(F56:G56) -> #REF! | I56: =H56*0.8 -> #REF! | J56: =I56/$I$60 -> #REF!
B57: SÃO PAULO | C57: RADIO | D57: NOVABRASIL | F57: =SUM(#REF!)*1.25 -> #REF! | G57: =SUM(#REF!)*1.25 -> #REF! | H57: =SUM(F57:G57) -> #REF! | I57: =H57*0.8 -> #REF! | J57: =I57/$I$60 -> #REF!
B58: SÃO PAULO | C58: RADIO | D58: TRANSCONTINENTAL | F58: =SUM(#REF!)*1.25 -> #REF! | G58: =SUM(#REF!)*1.25 -> #REF! | H58: =SUM(F58:G58) -> #REF! | I58: =H58*0.8 -> #REF! | J58: =I58/$I$60 -> #REF!
B60: TT RÁDIO | F60: =SUM(F40:F58) -> #REF! | G60: =SUM(G40:G58) -> #REF! | H60: =SUM(H40:H58) -> #REF! | I60: =SUM(I40:I58) -> #REF! | J60: =SUM(J40:J58) -> #REF! | K60: =I60/I68 -> #REF! | L60: =I60=#REF! -> #REF!
B62: ABCD | C62: DIGITAL | F62: =SUM(#REF!)*1.25 -> #REF! | G62: {=SUM(#REF!*1.25)} -> #REF! | H62: =SUM(F62:G62) -> #REF! | I62: =H62*0.8 -> #REF! | J62: 1
B64: TT DIGITAL | F64: =F62 -> #REF! | G64: =G62 -> #REF! | H64: =H62 -> #REF! | I64: =I62 -> #REF! | J64: =J62 -> 1 | K64: =I64/I68 -> #REF!
B66: TT GERAÇÃO | F66: ='CUSTO GERAÇÃO SPE'!I93*1.25 -> 36975 | G66: 0 | H66: =SUM(F66:G66) -> 36975 | I66: =H66*0.8 -> 29580 | J66: 1 | K66: =I66/I68 -> #REF!
B68: TOTAL GERAL CAMPANHA ESCASSEZ HIDRICA - CRÍTICO | SPE | F68: =SUM(F23,F30,F38,F60,F64,F66) -> #REF! | G68: =SUM(G23,G30,G38,G60,G64,G66) -> #REF! | H68: =SUM(H23,H30,H38,H60,H64,H66) -> #REF! | I68: =SUM(I23,I30,I38,I60,I64,I66) -> #REF! | K68: =SUM(K10:K67) -> #REF!
F69: =F68/H68 -> #REF! | G69: =G68/H68 -> #REF! | I69: =SUM('TV ABERTA - SPE'!BU72,'TV PAGA - COLCHÃO REP - SPE'!BU48,'TV ABERTA - COLCHÃO REP - SPE'!BU27,#REF!,#REF!,#REF!,'CUSTO GERAÇÃO SPE'!I93)=I68 -> #REF!

Sheet TV ABERTA
B5: CLIENT: SABESP
B6: CAMPAING: ESCASSEZ HIDRICA PCJ
AR7: PLANNED
B8: MARKET | C8: CHANNEL | D8: PROGRAMM | E8: DAY | F8: START TIME | G8: END TIME | H8: SEC | I8: FEVEREIRO | AK8: INS. | AL8: CUSTO TABELA UNITÁRIO (BRUTO) | AM8: DESC. % | AN8: CUSTO NEGOCIADO UNITÁRIO (BRUTO) | AO8: CUSTO TOTAL NEGOCIADO (BRUTO) | AP8: CUSTO TOTAL DESEMBOLSO SABESP | AR8: AUD. AS ABCDE 25+ | AS8: TRP | AT8: CPP | AV8: RESUMO
I9: S | J9: M | K9: T | L9: W | M9: T | N9: F | O9: S | P9: S | Q9: M | R9: T | S9: W | T9: T | U9: F | V9: S | W9: S | X9: M | Y9: T | Z9: W | AA9: T | AB9: F | AC9: S | AD9: S | AE9: M | AF9: T | AG9: W | AH9: T | AI9: F | AJ9: S
I10: 1 | J10: 2 | K10: 3 | L10: 4 | M10: 5 | N10: 6 | O10: 7 | P10: 8 | Q10: 9 | R10: 10 | S10: 11 | T10: 12 | U10: 13 | V10: 14 | W10: 15 | X10: 16 | Y10: 17 | Z10: =Y10+1 -> 18 | AA10: =Z10+1 -> 19 | AB10: =AA10+1 -> 20 | AC10: =AB10+1 -> 21 | AD10: =AC10+1 -> 22 | AE10: =AD10+1 -> 23 | AF10: =AE10+1 -> 24 | AG10: =AF10+1 -> 25 | ... AJ10: =AI10+1 -> 28 | AV10: CHANNEL | AW10: FEVEREIRO
AW12: INS | AX12: INVESTIMENTO $
B13: CAMPINAS | C13: GLOBO | D13: CALDEIRAO | E13: SÁB | F13: 0.67708333 | G13: 18:40 | H13: 60 | AK13: =SUM(I13:AJ13) -> 0 | AL13: 16272 | AM13: 0.1 | AN13: =AL13*(1-AM13) -> 14644.8 | AO13: =AN13*AK13 -> 0 | AP13: =AO13*0.8 -> 0 | AR13: 5.59 | AS13: =AR13*AK13 -> 0 | AT13: =IFERROR(AP13/AS13,0) -> 0 | AV13: TV GLOBO | AW13: =SUM(I13:AJ13) -> 0 | AX13: =AW13*AN13*0.8 -> 0 | AY13: =SUM(AX13)=AP13 -> TRUE
B14: CAMPINAS | C14: GLOBO | D14: CALDEIRAO | E14: SÁB | F14: 0.67708333 | G14: 18:40 | H14: 30 | V14: 1 | AK14: =SUM(I14:AJ14) -> 1 | AL14: 8136 | AM14: 0.1 | AN14: =AL14*(1-AM14) -> 7322.4 | AO14: =AN14*AK14 -> 7322.4 | AP14: =AO14*0.8 -> 5857.92 | AR14: 5.59 | AS14: =AR14*AK14 -> 5.59 | AT14: =IFERROR(AP14/AS14,0) -> 1047.9284 | AV14: TV GLOBO | AW14: =SUM(I14:AJ14) -> 1 | AX14: =AW14*AN14*0.8 -> 5857.92 | AY14: =SUM(AX14)=AP14 -> TRUE
D15: DOMINGAO COM HUCK | E15: DOM | F15: 0.625 | G15: 17:40 | H15: 60 | AK15: =SUM(I15:AJ15) -> 0 | AL15: 25890 | AM15: 0.1 | AN15: =AL15*(1-AM15) -> 23301 | AO15: =AN15*AK15 -> 0 | AP15: =AO15*0.8 -> 0 | AR15: 8.57 | AS15: =AR15*AK15 -> 0 | AT15: =IFERROR(AP15/AS15,0) -> 0 | AV15: TV GLOBO | AW15: =SUM(I15:AJ15) -> 0 | AX15: =AW15*AN15*0.8 -> 0 | AY15: =SUM(AX15)=AP15 -> TRUE
D16: DOMINGAO COM HUCK | E16: DOM | F16: 0.625 | G16: 17:40 | H16: 30 | W16: 1 | AD16: 1 | AK16: =SUM(I16:AJ16) -> 2 | AL16: 12945 | AM16: 0.1 | AN16: =AL16*(1-AM16) -> 11650.5 | AO16: =AN16*AK16 -> 23301 | AP16: =AO16*0.8 -> 18640.8 | AR16: 8.57 | AS16: =AR16*AK16 -> 17.14 | AT16: =IFERROR(AP16/AS16,0) -> 1087.5613 | AV16: TV GLOBO | AW16: =SUM(I16:AJ16) -> 2 | AX16: =AW16*AN16*0.8 -> 18640.8 | AY16: =SUM(AX16)=AP16 -> TRUE
D17: ENCONTRO | E17: SEG-SEX | F17: 0.39583333 | G17: 10:35 | H17: 30 | Z17: 1 | AF17: 1 | AK17: =SUM(I17:AJ17) -> 2 | AL17: 3137 | AM17: 0.1 | AN17: =AL17*(1-AM17) -> 2823.3 | AO17: =AN17*AK17 -> 5646.6 | AP17: =AO17*0.8 -> 4517.28 | AR17: 3.89 | AS17: =AR17*AK17 -> 7.78 | AT17: =IFERROR(AP17/AS17,0) -> 580.62725 | AV17: TV GLOBO | AW17: =SUM(I17:AJ17) -> 2 | AX17: =AW17*AN17*0.8 -> 4517.28 | AY17: =SUM(AX17)=AP17 -> TRUE
D18: JORNAL HOJE | E18: SEG-SÁB | F18: 0.55902778 | G18: 14:45 | H18: 30 | X18: 1 | AE18: 1 | AK18: =SUM(I18:AJ18) -> 2 | AL18: 7947 | AM18: 0.1 | AN18: =AL18*(1-AM18) -> 7152.3 | AO18: =AN18*AK18 -> 14304.6 | AP18: =AO18*0.8 -> 11443.68 | AR18: 5.92 | AS18: =AR18*AK18 -> 11.84 | AT18: =IFERROR(AP18/AS18,0) -> 966.52703 | AV18: TV GLOBO | AW18: =SUM(I18:AJ18) -> 2 | AX18: =AW18*AN18*0.8 -> 11443.68 | AY18: =SUM(AX18)=AP18 -> TRUE
D19: JORNAL NACIONAL | E19: SEG-SEX | F19: 0.85416667 | G19: 21:20 | H19: 60 | S19: 1 | AK19: =SUM(I19:AJ19) -> 1 | AL19: 72530 | AM19: 0.1 | AN19: =AL19*(1-AM19) -> 65277 | AO19: =AN19*AK19 -> 65277 | AP19: =AO19*0.8 -> 52221.6 | AR19: 13.07 | AS19: =AR19*AK19 -> 13.07 | AT19: =IFERROR(AP19/AS19,0) -> 3995.5318 | AV19: TV GLOBO | AW19: =SUM(I19:AJ19) -> 1 | AX19: =AW19*AN19*0.8 -> 52221.6 | AY19: =SUM(AX19)=AP19 -> TRUE
D20: JORNAL NACIONAL | E20: SEG-SEX | F20: 0.85416667 | G20: 21:20 | H20: 30 | AK20: =SUM(I20:AJ20) -> 0 | AL20: 36265 | AM20: 0.1 | AN20: =AL20*(1-AM20) -> 32638.5 | AO20: =AN20*AK20 -> 0 | AP20: =AO20*0.8 -> 0 | AR20: 13.07 | AS20: =AR20*AK20 -> 0 | AT20: =IFERROR(AP20/AS20,0) -> 0 | AV20: TV GLOBO | AW20: =SUM(I20:AJ20) -> 0 | AX20: =AW20*AN20*0.8 -> 0 | AY20: =SUM(AX20)=AP20 -> TRUE
D21: MAIS VOCE | E21: SEG-SEX | F21: 0.44097222 | G21: 11:45 | H21: 60 | AK21: =SUM(I21:AJ21) -> 0 | AL21: 8322 | AM21: 0.1 | AN21: =AL21*(1-AM21) -> 7489.8 | AO21: =AN21*AK21 -> 0 | AP21: =AO21*0.8 -> 0 | AR21: 3.79 | AS21: =AR21*AK21 -> 0 | AT21: =IFERROR(AP21/AS21,0) -> 0 | AV21: TV GLOBO | AW21: =SUM(I21:AJ21) -> 0 | AX21: =AW21*AN21*0.8 -> 0 | AY21: =SUM(AX21)=AP21 -> TRUE
D22: MAIS VOCE | E22: SEG-SEX | F22: 0.44097222 | G22: 11:45 | H22: 30 | U22: 1 | Y22: 1 | AG22: 1 | AK22: =SUM(I22:AJ22) -> 3 | AL22: 4161 | AM22: 0.1 | AN22: =AL22*(1-AM22) -> 3744.9 | AO22: =AN22*AK22 -> 11234.7 | AP22: =AO22*0.8 -> 8987.76 | AR22: 3.79 | AS22: =AR22*AK22 -> 11.37 | AT22: =IFERROR(AP22/AS22,0) -> 790.48021 | AV22: TV GLOBO | AW22: =SUM(I22:AJ22) -> 3 | AX22: =AW22*AN22*0.8 -> 8987.76 | AY22: =SUM(AX22)=AP22 -> TRUE
D23: NOVELA DA TARDE ED E | E23: SEG-SÁB | F23: 0.61458333 | G23: 15:25 | H23: 30 | Y23: 1 | AK23: =SUM(I23:AJ23) -> 1 | AL23: 5441 | AM23: 0.1 | AN23: =AL23*(1-AM23) -> 4896.9 | AO23: =AN23*AK23 -> 4896.9 | AP23: =AO23*0.8 -> 3917.52 | AR23: 6.47 | AS23: =AR23*AK23 -> 6.47 | AT23: =IFERROR(AP23/AS23,0) -> 605.48995 | AV23: TV GLOBO | AW23: =SUM(I23:AJ23) -> 1 | AX23: =AW23*AN23*0.8 -> 3917.52 | AY23: =SUM(AX23)=AP23 -> TRUE
D24: NOVELA I | E24: SEG-SEX | F24: 0.76736111 | G24: 19:10 | H24: 30 | AA24: 1 | AK24: =SUM(I24:AJ24) -> 1 | AL24: 17217 | AM24: 0.1 | AN24: =AL24*(1-AM24) -> 15495.3 | AO24: =AN24*AK24 -> 15495.3 | AP24: =AO24*0.8 -> 12396.24 | AR24: 8.5 | AS24: =AR24*AK24 -> 8.5 | AT24: =IFERROR(AP24/AS24,0) -> 1458.3812 | AV24: TV GLOBO | AW24: =SUM(I24:AJ24) -> 1 | AX24: =AW24*AN24*0.8 -> 12396.24 | AY24: =SUM(AX24)=AP24 -> TRUE
D25: NOVELA II | E25: SEG-SEX | F25: 0.81944444 | G25: 20:30 | H25: 60 | AK25: =SUM(I25:AJ25) -> 0 | AL25: 46286 | AM25: 0.1 | AN25: =AL25*(1-AM25) -> 41657.4 | AO25: =AN25*AK25 -> 0 | AP25: =AO25*0.8 -> 0 | AR25: 12.33 | AS25: =AR25*AK25 -> 0 | AT25: =IFERROR(AP25/AS25,0) -> 0 | AV25: TV GLOBO | AW25: =SUM(I25:AJ25) -> 0 | AX25: =AW25*AN25*0.8 -> 0 | AY25: =SUM(AX25)=AP25 -> TRUE
D26: NOVELA II | E26: SEG-SEX | F26: 0.81944444 | G26: 20:30 | H26: 30 | U26: 1 | Z26: 1 | AK26: =SUM(I26:AJ26) -> 2 | AL26: 23143 | AM26: 0.1 | AN26: =AL26*(1-AM26) -> 20828.7 | AO26: =AN26*AK26 -> 41657.4 | AP26: =AO26*0.8 -> 33325.92 | AR26: 12.33 | AS26: =AR26*AK26 -> 24.66 | AT26: =IFERROR(AP26/AS26,0) -> 1351.4161 | AV26: TV GLOBO | AW26: =SUM(I26:AJ26) -> 2 | AX26: =AW26*AN26*0.8 -> 33325.92 | AY26: =SUM(AX26)=AP26 -> TRUE
D27: NOVELA III | E27: SEG-SEX | F27: 0.88888889 | G27: 22:25 | H27: 60 | T27: 1 | AK27: =SUM(I27:AJ27) -> 1 | AL27: 67712 | AM27: 0.1 | AN27: =AL27*(1-AM27) -> 60940.8 | AO27: =AN27*AK27 -> 60940.8 | AP27: =AO27*0.8 -> 48752.64 | AR27: 13.4 | AS27: =AR27*AK27 -> 13.4 | AT27: =IFERROR(AP27/AS27,0) -> 3638.2567 | AV27: TV GLOBO | AW27: =SUM(I27:AJ27) -> 1 | AX27: =AW27*AN27*0.8 -> 48752.64 | AY27: =SUM(AX27)=AP27 -> TRUE
D28: NOVELA III | E28: SEG-SEX | F28: 0.88888889 | G28: 22:25 | H28: 30 | AF28: 1 | AK28: =SUM(I28:AJ28) -> 1 | AL28: 33856 | AM28: 0.1 | AN28: =AL28*(1-AM28) -> 30470.4 | AO28: =AN28*AK28 -> 30470.4 | AP28: =AO28*0.8 -> 24376.32 | AR28: 13.4 | AS28: =AR28*AK28 -> 13.4 | AT28: =IFERROR(AP28/AS28,0) -> 1819.1284 | AV28: TV GLOBO | AW28: =SUM(I28:AJ28) -> 1 | AX28: =AW28*AN28*0.8 -> 24376.32 | AY28: =SUM(AX28)=AP28 -> TRUE
D29: VALE A PENA VER DE N | E29: SEG-SEX | F29: 0.71180556 | G29: 18:25 | H29: 30 | X29: 1 | AG29: 1 | AK29: =SUM(I29:AJ29) -> 2 | AL29: 7656 | AM29: 0.1 | AN29: =AL29*(1-AM29) -> 6890.4 | AO29: =AN29*AK29 -> 13780.8 | AP29: =AO29*0.8 -> 11024.64 | AR29: 9.21 | AS29: =AR29*AK29 -> 18.42 | AT29: =IFERROR(AP29/AS29,0) -> 598.51466 | AV29: TV GLOBO | AW29: =SUM(I29:AJ29) -> 2 | AX29: =AW29*AN29*0.8 -> 11024.64 | AY29: =SUM(AX29)=AP29 -> TRUE
AV30: TT | AW30: =SUM(AW13:AW29) -> 19 | AX30: =SUM(AX13:AX29) -> 235462.32 | AY30: =SUM(AP13:AP29)=AX30 -> TRUE
C31: BANDEIRANTES | D31: BORA BRASIL | E31: SEG-SEX | F31: 0.375 | G31: 11:00 | H31: 30 | X31: 1 | AE31: 1 | AK31: =SUM(I31:AJ31) -> 2 | AL31: 2662 | AM31: 0.85 | AN31: =AL31*(1-AM31) -> 399.3 | AO31: =AN31*AK31 -> 798.6 | AP31: =AO31*0.8 -> 638.88 | AR31: 0.24 | AS31: =AR31*AK31 -> 0.48 | AT31: =IFERROR(AP31/AS31,0) -> 1331 | AV31: BANDEIRANTES | AW31: =SUM(I31:AJ31) -> 2 | AX31: =AW31*AN31*0.8 -> 638.88 | AY31: =SUM(AX31)=AP31 -> TRUE
D32: BRASIL URGENTE | E32: SEG-SÁB | F32: 0.66666667 | G32: 17:30 | H32: 60 | T32: 1 | AK32: =SUM(I32:AJ32) -> 1 | AL32: 18856 | AM32: 0.85 | AN32: =AL32*(1-AM32) -> 2828.4 | AO32: =AN32*AK32 -> 2828.4 | AP32: =AO32*0.8 -> 2262.72 | AR32: 1.43 | AS32: =AR32*AK32 -> 1.43 | AT32: =IFERROR(AP32/AS32,0) -> 1582.3217 | AV32: BANDEIRANTES | AW32: =SUM(I32:AJ32) -> 1 | AX32: =AW32*AN32*0.8 -> 2262.72 | AY32: =SUM(AX32)=AP32 -> TRUE
D33: BRASIL URGENTE | E33: SEG-SÁB | F33: 0.66666667 | G33: 17:30 | H33: 30 | Z33: 1 | AK33: =SUM(I33:AJ33) -> 1 | AL33: 9428 | AM33: 0.85 | AN33: =AL33*(1-AM33) -> 1414.2 | AO33: =AN33*AK33 -> 1414.2 | AP33: =AO33*0.8 -> 1131.36 | AR33: 1.43 | AS33: =AR33*AK33 -> 1.43 | AT33: =IFERROR(AP33/AS33,0) -> 791.16084 | AV33: BANDEIRANTES | AW33: =SUM(I33:AJ33) -> 1 | AX33: =AW33*AN33*0.8 -> 1131.36 | AY33: =SUM(AX33)=AP33 -> TRUE
D34: CANAL LIVRE | E34: DOM | F34: 0.95833333 | G34: 00:00 | H34: 60 | AK34: =SUM(I34:AJ34) -> 0 | AL34: 9740 | AM34: 0.85 | AN34: =AL34*(1-AM34) -> 1461 | AO34: =AN34*AK34 -> 0 | AP34: =AO34*0.8 -> 0 | AR34: 0.21 | AS34: =AR34*AK34 -> 0 | AT34: =IFERROR(AP34/AS34,0) -> 0 | AV34: BANDEIRANTES | AW34: =SUM(I34:AJ34) -> 0 | AX34: =AW34*AN34*0.8 -> 0 | AY34: =SUM(AX34)=AP34 -> TRUE
D35: CANAL LIVRE | E35: DOM | F35: 0.95833333 | G35: 00:00 | H35: 30 | AD35: 1 | AK35: =SUM(I35:AJ35) -> 1 | AL35: 4870 | AM35: 0.85 | AN35: =AL35*(1-AM35) -> 730.5 | AO35: =AN35*AK35 -> 730.5 | AP35: =AO35*0.8 -> 584.4 | AR35: 0.21 | AS35: =AR35*AK35 -> 0.21 | AT35: =IFERROR(AP35/AS35,0) -> 2782.8571 | AV35: BANDEIRANTES | AW35: =SUM(I35:AJ35) -> 1 | AX35: =AW35*AN35*0.8 -> 584.4 | AY35: =SUM(AX35)=AP35 -> TRUE
D36: JORNAL DA NOITE | E36: SEG-SEX | F36: 0.010416667 | G36: 01:15 | H36: 60 | T36: 1 | AK36: =SUM(I36:AJ36) -> 1 | AL36: 10226 | AM36: 0.85 | AN36: =AL36*(1-AM36) -> 1533.9 | AO36: =AN36*AK36 -> 1533.9 | AP36: =AO36*0.8 -> 1227.12 | AR36: 0.34 | AS36: =AR36*AK36 -> 0.34 | AT36: =IFERROR(AP36/AS36,0) -> 3609.1765 | AV36: BANDEIRANTES | AW36: =SUM(I36:AJ36) -> 1 | AX36: =AW36*AN36*0.8 -> 1227.12 | AY36: =SUM(AX36)=AP36 -> TRUE
D37: JORNAL DA NOITE | E37: SEG-SEX | F37: 0.010416667 | G37: 01:15 | H37: 30 | Y37: 1 | AF37: 1 | AK37: =SUM(I37:AJ37) -> 2 | AL37: 5113 | AM37: 0.85 | AN37: =AL37*(1-AM37) -> 766.95 | AO37: =AN37*AK37 -> 1533.9 | AP37: =AO37*0.8 -> 1227.12 | AR37: 0.34 | AS37: =AR37*AK37 -> 0.68 | AT37: =IFERROR(AP37/AS37,0) -> 1804.5882 | AV37: BANDEIRANTES | AW37: =SUM(I37:AJ37) -> 2 | AX37: =AW37*AN37*0.8 -> 1227.12 | AY37: =SUM(AX37)=AP37 -> TRUE
D38: NOVELA I | E38: SEG-SEX | F38: 0.29166667 | G38: 08:00 | H38: 30 | AA38: 1 | AG38: 1 | AK38: =SUM(I38:AJ38) -> 2 | AL38: 2662 | AM38: 0.85 | AN38: =AL38*(1-AM38) -> 399.3 | AO38: =AN38*AK38 -> 798.6 | AP38: =AO38*0.8 -> 638.88 | AR38: 0.1 | AS38: =AR38*AK38 -> 0.2 | AT38: =IFERROR(AP38/AS38,0) -> 3194.4 | AV38: BANDEIRANTES | AW38: =SUM(I38:AJ38) -> 2 | AX38: =AW38*AN38*0.8 -> 638.88 | AY38: =SUM(AX38)=AP38 -> TRUE
D39: NOVELA II | E39: SEG-SEX | F39: 0.85416667 | G39: 21:25 | H39: 60 | U39: 1 | AK39: =SUM(I39:AJ39) -> 1 | AL39: 33370 | AM39: 0.85 | AN39: =AL39*(1-AM39) -> 5005.5 | AO39: =AN39*AK39 -> 5005.5 | AP39: =AO39*0.8 -> 4004.4 | AR39: 0.71 | AS39: =AR39*AK39 -> 0.71 | AT39: =IFERROR(AP39/AS39,0) -> 5640 | AV39: BANDEIRANTES | AW39: =SUM(I39:AJ39) -> 1 | AX39: =AW39*AN39*0.8 -> 4004.4 | AY39: =SUM(AX39)=AP39 -> TRUE
D40: NOVELA II | E40: SEG-SEX | F40: 0.85416667 | G40: 21:25 | H40: 30 | AB40: 1 | AK40: =SUM(I40:AJ40) -> 1 | AL40: 16685 | AM40: 0.85 | AN40: =AL40*(1-AM40) -> 2502.75 | AO40: =AN40*AK40 -> 2502.75 | AP40: =AO40*0.8 -> 2002.2 | AR40: 0.71 | AS40: =AR40*AK40 -> 0.71 | AT40: =IFERROR(AP40/AS40,0) -> 2820 | AV40: BANDEIRANTES | AW40: =SUM(I40:AJ40) -> 1 | AX40: =AW40*AN40*0.8 -> 2002.2 | AY40: =SUM(AX40)=AP40 -> TRUE
D41: SABADAO DE TODOS | E41: SÁB | F41: 0.85416667 | G41: 22:30 | H41: 60 | AK41: =SUM(I41:AJ41) -> 0 | AL41: 23684 | AM41: 0.85 | AN41: =AL41*(1-AM41) -> 3552.6 | AO41: =AN41*AK41 -> 0 | AP41: =AO41*0.8 -> 0 | AR41: 0.54 | AS41: =AR41*AK41 -> 0 | AT41: =IFERROR(AP41/AS41,0) -> 0 | AV41: BANDEIRANTES | AW41: =SUM(I41:AJ41) -> 0 | AX41: =AW41*AN41*0.8 -> 0 | AY41: =SUM(AX41)=AP41 -> TRUE
D42: SABADAO DE TODOS | E42: SÁB | F42: 0.85416667 | G42: 22:30 | H42: 30 | V42: 1 | AC42: 1 | AK42: =SUM(I42:AJ42) -> 2 | AL42: 11842 | AM42: 0.85 | AN42: =AL42*(1-AM42) -> 1776.3 | AO42: =AN42*AK42 -> 3552.6 | AP42: =AO42*0.8 -> 2842.08 | AR42: 0.54 | AS42: =AR42*AK42 -> 1.08 | AT42: =IFERROR(AP42/AS42,0) -> 2631.5556 | AV42: BANDEIRANTES | AW42: =SUM(I42:AJ42) -> 2 | AX42: =AW42*AN42*0.8 -> 2842.08 | AY42: =SUM(AX42)=AP42 -> TRUE
AV43: TT | AW43: =SUM(AW31:AW42) -> 14 | AX43: =SUM(AX31:AX42) -> 16559.16 | AY43: =SUM(AP31:AP42)=AX43 -> TRUE
C44: RECORD | D44: CIDADE ALERTA | E44: SEG-SEX | F44: 0.6875 | G44: 19:55 | H44: 60 | U44: 1 | AK44: =SUM(I44:AJ44) -> 1 | AL44: 10374 | AM44: 0.78 | AN44: =AL44*(1-AM44) -> 2282.28 | AO44: =AN44*AK44 -> 2282.28 | AP44: =AO44*0.8 -> 1825.824 | AR44: 2.19 | AS44: =AR44*AK44 -> 2.19 | AT44: =IFERROR(AP44/AS44,0) -> 833.70959 | AV44: RECORD | AW44: =SUM(I44:AJ44) -> 1 | AX44: =AW44*AN44*0.8 -> 1825.824 | AY44: =SUM(AX44)=AP44 -> TRUE
D45: CIDADE ALERTA | E45: SEG-SEX | F45: 0.6875 | G45: 19:55 | H45: 30 | Y45: 1 | AA45: 1 | AF45: 1 | AK45: =SUM(I45:AJ45) -> 3 | AL45: 5187 | AM45: 0.78 | AN45: =AL45*(1-AM45) -> 1141.14 | AO45: =AN45*AK45 -> 3423.42 | AP45: =AO45*0.8 -> 2738.736 | AR45: 2.19 | AS45: =AR45*AK45 -> 6.57 | AT45: =IFERROR(AP45/AS45,0) -> 416.85479 | AV45: RECORD | AW45: =SUM(I45:AJ45) -> 3 | AX45: =AW45*AN45*0.8 -> 2738.736 | AY45: =SUM(AX45)=AP45 -> TRUE
D46: DOMINGO ESPETACULAR | E46: DOM | F46: 0.75 | G46: 20:00 | H46: 60 | AK46: =SUM(I46:AJ46) -> 0 | AL46: 50240 | AM46: 0.78 | AN46: =AL46*(1-AM46) -> 11052.8 | AO46: =AN46*AK46 -> 0 | AP46: =AO46*0.8 -> 0 | AR46: 3.05 | AS46: =AR46*AK46 -> 0 | AT46: =IFERROR(AP46/AS46,0) -> 0 | AV46: RECORD | AW46: =SUM(I46:AJ46) -> 0 | AX46: =AW46*AN46*0.8 -> 0 | AY46: =SUM(AX46)=AP46 -> TRUE
D47: DOMINGO ESPETACULAR | E47: DOM | F47: 0.75 | G47: 20:00 | H47: 30 | W47: 1 | AD47: 1 | AK47: =SUM(I47:AJ47) -> 2 | AL47: 25120 | AM47: 0.78 | AN47: =AL47*(1-AM47) -> 5526.4 | AO47: =AN47*AK47 -> 11052.8 | AP47: =AO47*0.8 -> 8842.24 | AR47: 3.05 | AS47: =AR47*AK47 -> 6.1 | AT47: =IFERROR(AP47/AS47,0) -> 1449.5475 | AV47: RECORD | AW47: =SUM(I47:AJ47) -> 2 | AX47: =AW47*AN47*0.8 -> 8842.24 | AY47: =SUM(AX47)=AP47 -> TRUE
D48: FALA BRASIL | E48: SEG-SEX | F48: 0.35416667 | G48: 09:35 | H48: 30 | Z48: 1 | AB48: 1 | AE48: 1 | AG48: 1 | AK48: =SUM(I48:AJ48) -> 4 | AL48: 5113 | AM48: 0.78 | AN48: =AL48*(1-AM48) -> 1124.86 | AO48: =AN48*AK48 -> 4499.44 | AP48: =AO48*0.8 -> 3599.552 | AR48: 1.95 | AS48: =AR48*AK48 -> 7.8 | AT48: =IFERROR(AP48/AS48,0) -> 461.48103 | AV48: RECORD | AW48: =SUM(I48:AJ48) -> 4 | AX48: =AW48*AN48*0.8 -> 3599.552 | AY48: =SUM(AX48)=AP48 -> TRUE
D49: HOJE EM DIA | E49: SEG-SEX | F49: 0.39930556 | G49: 11:30 | H49: 60 | T49: 1 | AK49: =SUM(I49:AJ49) -> 1 | AL49: 12230 | AM49: 0.78 | AN49: =AL49*(1-AM49) -> 2690.6 | AO49: =AN49*AK49 -> 2690.6 | AP49: =AO49*0.8 -> 2152.48 | AR49: 2.01 | AS49: =AR49*AK49 -> 2.01 | AT49: =IFERROR(AP49/AS49,0) -> 1070.8856 | AV49: RECORD | AW49: =SUM(I49:AJ49) -> 1 | AX49: =AW49*AN49*0.8 -> 2152.48 | AY49: =SUM(AX49)=AP49 -> TRUE
D50: HOJE EM DIA | E50: SEG-SEX | F50: 0.39930556 | G50: 11:30 | H50: 30 | X50: 1 | AA50: 1 | AF50: 1 | AK50: =SUM(I50:AJ50) -> 3 | AL50: 6115 | AM50: 0.78 | AN50: =AL50*(1-AM50) -> 1345.3 | AO50: =AN50*AK50 -> 4035.9 | AP50: =AO50*0.8 -> 3228.72 | AR50: 2 | AS50: =AR50*AK50 -> 6 | AT50: =IFERROR(AP50/AS50,0) -> 538.12 | AV50: RECORD | AW50: =SUM(I50:AJ50) -> 3 | AX50: =AW50*AN50*0.8 -> 3228.72 | AY50: =SUM(AX50)=AP50 -> TRUE
D51: NOVELA 22H | E51: SEG-SEX | F51: 0.91666667 | G51: 22:30 | H51: 30 | Z51: 1 | AE51: 1 | AK51: =SUM(I51:AJ51) -> 2 | AL51: 17866 | AM51: 0.78 | AN51: =AL51*(1-AM51) -> 3930.52 | AO51: =AN51*AK51 -> 7861.04 | AP51: =AO51*0.8 -> 6288.832 | AR51: 2.27 | AS51: =AR51*AK51 -> 4.54 | AT51: =IFERROR(AP51/AS51,0) -> 1385.2053 | AV51: RECORD | AW51: =SUM(I51:AJ51) -> 2 | AX51: =AW51*AN51*0.8 -> 6288.832 | AY51: =SUM(AX51)=AP51 -> TRUE
D52: NOVELA 3 | E52: SEG-SEX | F52: 0.875 | G52: 22:00 | H52: 60 | T52: 1 | AK52: =SUM(I52:AJ52) -> 1 | AL52: 44392 | AM52: 0.78 | AN52: =AL52*(1-AM52) -> 9766.24 | AO52: =AN52*AK52 -> 9766.24 | AP52: =AO52*0.8 -> 7812.992 | AR52: 2.56 | AS52: =AR52*AK52 -> 2.56 | AT52: =IFERROR(AP52/AS52,0) -> 3051.95 | AV52: RECORD | AW52: =SUM(I52:AJ52) -> 1 | AX52: =AW52*AN52*0.8 -> 7812.992 | AY52: =SUM(AX52)=AP52 -> TRUE
D53: NOVELA 3 | E53: SEG-SEX | F53: 0.875 | G53: 22:00 | H53: 30 | AB53: 1 | AE53: 1 | AK53: =SUM(I53:AJ53) -> 2 | AL53: 22196 | AM53: 0.78 | AN53: =AL53*(1-AM53) -> 4883.12 | AO53: =AN53*AK53 -> 9766.24 | AP53: =AO53*0.8 -> 7812.992 | AR53: 2.56 | AS53: =AR53*AK53 -> 5.12 | AT53: =IFERROR(AP53/AS53,0) -> 1525.975 | AV53: RECORD | AW53: =SUM(I53:AJ53) -> 2 | AX53: =AW53*AN53*0.8 -> 7812.992 | AY53: =SUM(AX53)=AP53 -> TRUE
D54: NOVELA DA TARDE 1 | E54: SEG-SEX | F54: 0.64583333 | G54: 16:30 | H54: 60 | U54: 1 | AK54: =SUM(I54:AJ54) -> 1 | AL54: =AL55* 2 -> 15770 | AM54: 0.78 | AN54: =AL54*(1-AM54) -> 3469.4 | AO54: =AN54*AK54 -> 3469.4 | AP54: =AO54*0.8 -> 2775.52 | AR54: 2.39 | AS54: =AR54*AK54 -> 2.39 | AT54: =IFERROR(AP54/AS54,0) -> 1161.3054 | AV54: RECORD | AW54: =SUM(I54:AJ54) -> 1 | AX54: =AW54*AN54*0.8 -> 2775.52 | AY54: =SUM(AX54)=AP54 -> TRUE
D55: NOVELA DA TARDE 1 | E55: SEG-SEX | F55: 0.64583333 | G55: 16:30 | H55: 30 | Y55: 1 | AA55: 1 | AK55: =SUM(I55:AJ55) -> 2 | AL55: 7885 | AM55: 0.78 | AN55: =AL55*(1-AM55) -> 1734.7 | AO55: =AN55*AK55 -> 3469.4 | AP55: =AO55*0.8 -> 2775.52 | AR55: 2.39 | AS55: =AR55*AK55 -> 4.78 | AT55: =IFERROR(AP55/AS55,0) -> 580.65272 | AV55: RECORD | AW55: =SUM(I55:AJ55) -> 2 | AX55: =AW55*AN55*0.8 -> 2775.52 | AY55: =SUM(AX55)=AP55 -> TRUE
D56: SUPER TELA | E56: SÁB | F56: 0.9375 | G56: 00:15 | H56: 60 | AK56: =SUM(I56:AJ56) -> 0 | AL56: 23922 | AM56: 0.78 | AN56: =AL56*(1-AM56) -> 5262.84 | AO56: =AN56*AK56 -> 0 | AP56: =AO56*0.8 -> 0 | AR56: 1.7 | AS56: =AR56*AK56 -> 0 | AT56: =IFERROR(AP56/AS56,0) -> 0 | AV56: RECORD | AW56: =SUM(I56:AJ56) -> 0 | AX56: =AW56*AN56*0.8 -> 0 | AY56: =SUM(AX56)=AP56 -> TRUE
D57: SUPER TELA | E57: SÁB | F57: 0.9375 | G57: 00:15 | H57: 30 | V57: 1 | AC57: 1 | AK57: =SUM(I57:AJ57) -> 2 | AL57: 11961 | AM57: 0.78 | AN57: =AL57*(1-AM57) -> 2631.42 | AO57: =AN57*AK57 -> 5262.84 | AP57: =AO57*0.8 -> 4210.272 | AR57: 1.7 | AS57: =AR57*AK57 -> 3.4 | AT57: =IFERROR(AP57/AS57,0) -> 1238.3153 | AV57: RECORD | AW57: =SUM(I57:AJ57) -> 2 | AX57: =AW57*AN57*0.8 -> 4210.272 | AY57: =SUM(AX57)=AP57 -> TRUE
AV58: TT | AW58: =SUM(AW44:AW57) -> 24 | AX58: =SUM(AX44:AX57) -> 54063.68 | AY58: =SUM(AP44:AP57)=AX58 -> TRUE
B59: CAMPINAS/SANTOS | C59: SBT | D59: AQUI AGORA | E59: SEG-SEX | F59: 18:30 | G59: 19:45 | H59: 60 | U59: 1 | AK59: =SUM(I59:AJ59) -> 1 | AL59: 34582 | AM59: 0.75 | AN59: =AL59*(1-AM59) -> 8645.5 | AO59: =AN59*AK59 -> 8645.5 | AP59: =AO59*0.8 -> 6916.4 | AR59: 1.38 | AS59: =AR59*AK59 -> 1.38 | AT59: =IFERROR(AP59/AS59,0) -> 5011.8841 | AV59: SBT | AW59: =SUM(I59:AJ59) -> 1 | AX59: =AW59*AN59*0.8 -> 6916.4 | AY59: =SUM(AX59)=AP59 -> TRUE
D60: AQUI AGORA | E60: SEG-SEX | F60: 18:30 | G60: 19:45 | H60: 30 | X60: 1 | AK60: =SUM(I60:AJ60) -> 1 | AL60: 17291 | AM60: 0.75 | AN60: =AL60*(1-AM60) -> 4322.75 | AO60: =AN60*AK60 -> 4322.75 | AP60: =AO60*0.8 -> 3458.2 | AR60: 1.38 | AS60: =AR60*AK60 -> 1.38 | AT60: =IFERROR(AP60/AS60,0) -> 2505.942 | AV60: SBT | AW60: =SUM(I60:AJ60) -> 1 | AX60: =AW60*AN60*0.8 -> 3458.2 | AY60: =SUM(AX60)=AP60 -> TRUE
D61: DOMINGO LEGAL 1 | E61: DOM | F61: 0.46875 | G61: 15:15 | H61: 60 | AK61: =SUM(I61:AJ61) -> 0 | AL61: 32536 | AM61: 0.75 | AN61: =AL61*(1-AM61) -> 8134 | AO61: =AN61*AK61 -> 0 | AP61: =AO61*0.8 -> 0 | AR61: 3 | AS61: =AR61*AK61 -> 0 | AT61: =IFERROR(AP61/AS61,0) -> 0 | AV61: SBT | AW61: =SUM(I61:AJ61) -> 0 | AX61: =AW61*AN61*0.8 -> 0 | AY61: =SUM(AX61)=AP61 -> TRUE
D62: DOMINGO LEGAL 1 | E62: DOM | F62: 0.46875 | G62: 15:15 | H62: 30 | AK62: =SUM(I62:AJ62) -> 0 | AL62: 16268 | AM62: 0.75 | AN62: =AL62*(1-AM62) -> 4067 | AO62: =AN62*AK62 -> 0 | AP62: =AO62*0.8 -> 0 | AR62: 3 | AS62: =AR62*AK62 -> 0 | AT62: =IFERROR(AP62/AS62,0) -> 0 | AV62: SBT | AW62: =SUM(I62:AJ62) -> 0 | AX62: =AW62*AN62*0.8 -> 0 | AY62: =SUM(AX62)=AP62 -> TRUE
D63: NOVELA NOITE 2 | E63: SEG-SEX | F63: 0.875 | G63: 21:45 | H63: 60 | T63: 1 | AK63: =SUM(I63:AJ63) -> 1 | AL63: 34076 | AM63: 0.75 | AN63: =AL63*(1-AM63) -> 8519 | AO63: =AN63*AK63 -> 8519 | AP63: =AO63*0.8 -> 6815.2 | AR63: 2.1 | AS63: =AR63*AK63 -> 2.1 | AT63: =IFERROR(AP63/AS63,0) -> 3245.3333 | AV63: SBT | AW63: =SUM(I63:AJ63) -> 1 | AX63: =AW63*AN63*0.8 -> 6815.2 | AY63: =SUM(AX63)=AP63 -> TRUE
D64: NOVELA NOITE 2 | E64: SEG-SEX | F64: 0.875 | G64: 21:45 | H64: 30 | AA64: 1 | AK64: =SUM(I64:AJ64) -> 1 | AL64: 17038 | AM64: 0.75 | AN64: =AL64*(1-AM64) -> 4259.5 | AO64: =AN64*AK64 -> 4259.5 | AP64: =AO64*0.8 -> 3407.6 | AR64: 2.1 | AS64: =AR64*AK64 -> 2.1 | AT64: =IFERROR(AP64/AS64,0) -> 1622.6667 | AV64: SBT | AW64: =SUM(I64:AJ64) -> 1 | AX64: =AW64*AN64*0.8 -> 3407.6 | AY64: =SUM(AX64)=AP64 -> TRUE
D65: NOVELA TARDE 14H | E65: SEG-SEX | F65: 0.60416667 | G65: 15:30 | H65: 30 | Y65: 1 | AK65: =SUM(I65:AJ65) -> 1 | AL65: 11151 | AM65: 0.75 | AN65: =AL65*(1-AM65) -> 2787.75 | AO65: =AN65*AK65 -> 2787.75 | AP65: =AO65*0.8 -> 2230.2 | AR65: 1.6 | AS65: =AR65*AK65 -> 1.6 | AT65: =IFERROR(AP65/AS65,0) -> 1393.875 | AV65: SBT | AW65: =SUM(I65:AJ65) -> 1 | AX65: =AW65*AN65*0.8 -> 2230.2 | AY65: =SUM(AX65)=AP65 -> TRUE
D66: PRIMEIRO IMPACTO | E66: SEG-SEX | F66: 0.35416667 | G66: 11:00 | H66: 30 | Z66: 1 | AK66: =SUM(I66:AJ66) -> 1 | AL66: 8902 | AM66: 0.75 | AN66: =AL66*(1-AM66) -> 2225.5 | AO66: =AN66*AK66 -> 2225.5 | AP66: =AO66*0.8 -> 1780.4 | AR66: 1.4 | AS66: =AR66*AK66 -> 1.4 | AT66: =IFERROR(AP66/AS66,0) -> 1271.7143 | AV66: SBT | AW66: =SUM(I66:AJ66) -> 1 | AX66: =AW66*AN66*0.8 -> 1780.4 | AY66: =SUM(AX66)=AP66 -> TRUE
D67: SBT MANHA | E67: SEG-SEX | F67: 0.3125 | G67: 08:30 | H67: 60 | AK67: =SUM(I67:AJ67) -> 0 | AL67: 17804 | AM67: 0.75 | AN67: =AL67*(1-AM67) -> 4451 | AO67: =AN67*AK67 -> 0 | AP67: =AO67*0.8 -> 0 | AR67: 1.3 | AS67: =AR67*AK67 -> 0 | AT67: =IFERROR(AP67/AS67,0) -> 0 | AV67: SBT | AW67: =SUM(I67:AJ67) -> 0 | AX67: =AW67*AN67*0.8 -> 0 | AY67: =SUM(AX67)=AP67 -> TRUE
D68: SBT MANHA | E68: SEG-SEX | F68: 0.3125 | G68: 08:30 | H68: 30 | AB68: 1 | AK68: =SUM(I68:AJ68) -> 1 | AL68: 8902 | AM68: 0.75 | AN68: =AL68*(1-AM68) -> 2225.5 | AO68: =AN68*AK68 -> 2225.5 | AP68: =AO68*0.8 -> 1780.4 | AR68: 1.3 | AS68: =AR68*AK68 -> 1.3 | AT68: =IFERROR(AP68/AS68,0) -> 1369.5385 | AV68: SBT | AW68: =SUM(I68:AJ68) -> 1 | AX68: =AW68*AN68*0.8 -> 1780.4 | AY68: =SUM(AX68)=AP68 -> TRUE
D69: SBT NOTICIAS 1A ED | E69: SÁB | F69: 0.45833333 | G69: 15:00 | H69: 60 | AK69: =SUM(I69:AJ69) -> 0 | AL69: 17804 | AM69: 0.75 | AN69: =AL69*(1-AM69) -> 4451 | AO69: =AN69*AK69 -> 0 | AP69: =AO69*0.8 -> 0 | AR69: 1.2 | AS69: =AR69*AK69 -> 0 | AT69: =IFERROR(AP69/AS69,0) -> 0 | AV69: SBT | AW69: =SUM(I69:AJ69) -> 0 | AX69: =AW69*AN69*0.8 -> 0 | AY69: =SUM(AX69)=AP69 -> TRUE
D70: SBT NOTICIAS 1A ED | E70: SÁB | F70: 0.45833333 | G70: 15:00 | H70: 30 | V70: 1 | AC70: 1 | AK70: =SUM(I70:AJ70) -> 2 | AL70: 8902 | AM70: 0.75 | AN70: =AL70*(1-AM70) -> 2225.5 | AO70: =AN70*AK70 -> 4451 | AP70: =AO70*0.8 -> 3560.8 | AR70: 1.2 | AS70: =AR70*AK70 -> 2.4 | AT70: =IFERROR(AP70/AS70,0) -> 1483.6667 | AV70: SBT | AW70: =SUM(I70:AJ70) -> 2 | AX70: =AW70*AN70*0.8 -> 3560.8 | AY70: =SUM(AX70)=AP70 -> TRUE
D71: A VOZ DA POPULACAO | E71: SEG-SEX | F71: 0.54513889 | G71: 0.5625 | H71: 30 | AE71: 1 | AG71: 1 | AK71: =SUM(I71:AJ71) -> 2 | AL71: 4634 | AM71: 0.75 | AN71: =AL71*(1-AM71) -> 1158.5 | AO71: =AN71*AK71 -> 2317 | AP71: =AO71*0.8 -> 1853.6 | AR71: 1.2 | AS71: =AR71*AK71 -> 2.4 | AT71: =IFERROR(AP71/AS71,0) -> 772.33333 | AV71: SBT | AW71: =SUM(I71:AJ71) -> 2 | AX71: =AW71*AN71*0.8 -> 1853.6 | AY71: =SUM(AX71)=AP71 -> TRUE
D72: TUDO PODE REAP | E72: DOM | F72: 0.41319444 | G72: 0.43402778 | H72: 30 | AD72: 1 | AK72: =SUM(I72:AJ72) -> 1 | AL72: 12357 | AM72: 0.75 | AN72: =AL72*(1-AM72) -> 3089.25 | AO72: =AN72*AK72 -> 3089.25 | AP72: =AO72*0.8 -> 2471.4 | AR72: 1.2 | AS72: =AR72*AK72 -> 1.2 | AT72: =IFERROR(AP72/AS72,0) -> 2059.5 | AV72: SBT | AW72: =SUM(I72:AJ72) -> 1 | AX72: =AW72*AN72*0.8 -> 2471.4 | AY72: =SUM(AX72)=AP72 -> TRUE
D73: VTV DA GENTE | E73: SEG-SEX | F73: 0.47916667 | G73: 0.54513889 | H73: 30 | AF73: 1 | AH73: 1 | AI73: 1 | AK73: =SUM(I73:AJ73) -> 3 | AL73: 5011 | AM73: 0.75 | AN73: =AL73*(1-AM73) -> 1252.75 | AO73: =AN73*AK73 -> 3758.25 | AP73: =AO73*0.8 -> 3006.6 | AR73: 1.2 | AS73: =AR73*AK73 -> 3.6 | AT73: =IFERROR(AP73/AS73,0) -> 835.16667 | AV73: SBT | AW73: =SUM(I73:AJ73) -> 3 | AX73: =AW73*AN73*0.8 -> 3006.6 | AY73: =SUM(AX73)=AP73 -> TRUE
D74: SABORES DA VILLA | E74: SÁB | F74: 0.54166667 | G74: 0.5625 | H74: 30 | AK74: =SUM(I74:AJ74) -> 0 | AL74: 20162 | AM74: 0.75 | AN74: =AL74*(1-AM74) -> 5040.5 | AO74: =AN74*AK74 -> 0 | AP74: =AO74*0.8 -> 0 | AR74: 1.2 | AS74: =AR74*AK74 -> 0 | AT74: =IFERROR(AP74/AS74,0) -> 0 | AV74: SBT | AW74: =SUM(I74:AJ74) -> 0 | AX74: =AW74*AN74*0.8 -> 0 | AY74: =SUM(AX74)=AP74 -> TRUE
AV75: TT | AW75: =SUM(AW59:AW74) -> 15 | AX75: =SUM(AX59:AX74) -> 37280.8 | AY75: =SUM(AP59:AP74)=AX75 -> TRUE
B76: SOROCABA | C76: GLOBO | D76: CALDEIRAO | E76: SÁB | F76: 0.67708333 | G76: 18:40 | H76: 60 | AK76: =SUM(I76:AJ76) -> 0 | AL76: 6946 | AM76: 0.1 | AN76: =AL76*(1-AM76) -> 6251.4 | AO76: =AN76*AK76 -> 0 | AP76: =AO76*0.8 -> 0 | AR76: 5.59 | AS76: =AR76*AK76 -> 0 | AT76: =IFERROR(AP76/AS76,0) -> 0 | AV76: TV GLOBO | AW76: =SUM(I76:AJ76) -> 0 | AX76: =AW76*AN76*0.8 -> 0 | AY76: =SUM(AX76)=AP76 -> TRUE
B77: SOROCABA | C77: GLOBO | D77: CALDEIRAO | E77: SÁB | F77: 0.67708333 | G77: 18:40 | H77: 30 | V77: 1 | AK77: =SUM(I77:AJ77) -> 1 | AL77: 3473 | AM77: 0.1 | AN77: =AL77*(1-AM77) -> 3125.7 | AO77: =AN77*AK77 -> 3125.7 | AP77: =AO77*0.8 -> 2500.56 | AR77: 5.59 | AS77: =AR77*AK77 -> 5.59 | AT77: =IFERROR(AP77/AS77,0) -> 447.32737 | AV77: TV GLOBO | AW77: =SUM(I77:AJ77) -> 1 | AX77: =AW77*AN77*0.8 -> 2500.56 | AY77: =SUM(AX77)=AP77 -> TRUE
D78: DOMINGAO COM HUCK | E78: DOM | F78: 0.625 | G78: 17:40 | H78: 60 | AK78: =SUM(I78:AJ78) -> 0 | AL78: 12726 | AM78: 0.1 | AN78: =AL78*(1-AM78) -> 11453.4 | AO78: =AN78*AK78 -> 0 | AP78: =AO78*0.8 -> 0 | AR78: 8.57 | AS78: =AR78*AK78 -> 0 | AT78: =IFERROR(AP78/AS78,0) -> 0 | AV78: TV GLOBO | AW78: =SUM(I78:AJ78) -> 0 | AX78: =AW78*AN78*0.8 -> 0 | AY78: =SUM(AX78)=AP78 -> TRUE
D79: DOMINGAO COM HUCK | E79: DOM | F79: 0.625 | G79: 17:40 | H79: 30 | W79: 1 | AD79: 1 | AK79: =SUM(I79:AJ79) -> 2 | AL79: 6363 | AM79: 0.1 | AN79: =AL79*(1-AM79) -> 5726.7 | AO79: =AN79*AK79 -> 11453.4 | AP79: =AO79*0.8 -> 9162.72 | AR79: 8.57 | AS79: =AR79*AK79 -> 17.14 | AT79: =IFERROR(AP79/AS79,0) -> 534.5811 | AV79: TV GLOBO | AW79: =SUM(I79:AJ79) -> 2 | AX79: =AW79*AN79*0.8 -> 9162.72 | AY79: =SUM(AX79)=AP79 -> TRUE
D80: ENCONTRO | E80: SEG-SEX | F80: 0.39583333 | G80: 10:35 | H80: 30 | Z80: 1 | AF80: 1 | AK80: =SUM(I80:AJ80) -> 2 | AL80: 1623 | AM80: 0.1 | AN80: =AL80*(1-AM80) -> 1460.7 | AO80: =AN80*AK80 -> 2921.4 | AP80: =AO80*0.8 -> 2337.12 | AR80: 3.89 | AS80: =AR80*AK80 -> 7.78 | AT80: =IFERROR(AP80/AS80,0) -> 300.40103 | AV80: TV GLOBO | AW80: =SUM(I80:AJ80) -> 2 | AX80: =AW80*AN80*0.8 -> 2337.12 | AY80: =SUM(AX80)=AP80 -> TRUE
D81: JORNAL HOJE | E81: SEG-SÁB | F81: 0.55902778 | G81: 14:45 | H81: 30 | X81: 1 | AE81: 1 | AK81: =SUM(I81:AJ81) -> 2 | AL81: 3794 | AM81: 0.1 | AN81: =AL81*(1-AM81) -> 3414.6 | AO81: =AN81*AK81 -> 6829.2 | AP81: =AO81*0.8 -> 5463.36 | AR81: 5.92 | AS81: =AR81*AK81 -> 11.84 | AT81: =IFERROR(AP81/AS81,0) -> 461.43243 | AV81: TV GLOBO | AW81: =SUM(I81:AJ81) -> 2 | AX81: =AW81*AN81*0.8 -> 5463.36 | AY81: =SUM(AX81)=AP81 -> TRUE
D82: JORNAL NACIONAL | E82: SEG-SEX | F82: 0.85416667 | G82: 21:20 | H82: 60 | S82: 1 | AK82: =SUM(I82:AJ82) -> 1 | AL82: 27362 | AM82: 0.1 | AN82: =AL82*(1-AM82) -> 24625.8 | AO82: =AN82*AK82 -> 24625.8 | AP82: =AO82*0.8 -> 19700.64 | AR82: 13.07 | AS82: =AR82*AK82 -> 13.07 | AT82: =IFERROR(AP82/AS82,0) -> 1507.3175 | AV82: TV GLOBO | AW82: =SUM(I82:AJ82) -> 1 | AX82: =AW82*AN82*0.8 -> 19700.64 | AY82: =SUM(AX82)=AP82 -> TRUE
D83: JORNAL NACIONAL | E83: SEG-SEX | F83: 0.85416667 | G83: 21:20 | H83: 30 | AK83: =SUM(I83:AJ83) -> 0 | AL83: 13681 | AM83: 0.1 | AN83: =AL83*(1-AM83) -> 12312.9 | AO83: =AN83*AK83 -> 0 | AP83: =AO83*0.8 -> 0 | AR83: 13.07 | AS83: =AR83*AK83 -> 0 | AT83: =IFERROR(AP83/AS83,0) -> 0 | AV83: TV GLOBO | AW83: =SUM(I83:AJ83) -> 0 | AX83: =AW83*AN83*0.8 -> 0 | AY83: =SUM(AX83)=AP83 -> TRUE
D84: MAIS VOCE | E84: SEG-SEX | F84: 0.44097222 | G84: 11:45 | H84: 60 | AK84: =SUM(I84:AJ84) -> 0 | AL84: 3870 | AM84: 0.1 | AN84: =AL84*(1-AM84) -> 3483 | AO84: =AN84*AK84 -> 0 | AP84: =AO84*0.8 -> 0 | AR84: 3.79 | AS84: =AR84*AK84 -> 0 | AT84: =IFERROR(AP84/AS84,0) -> 0 | AV84: TV GLOBO | AW84: =SUM(I84:AJ84) -> 0 | AX84: =AW84*AN84*0.8 -> 0 | AY84: =SUM(AX84)=AP84 -> TRUE
D85: MAIS VOCE | E85: SEG-SEX | F85: 0.44097222 | G85: 11:45 | H85: 30 | U85: 1 | Y85: 1 | AG85: 1 | AK85: =SUM(I85:AJ85) -> 3 | AL85: 1935 | AM85: 0.1 | AN85: =AL85*(1-AM85) -> 1741.5 | AO85: =AN85*AK85 -> 5224.5 | AP85: =AO85*0.8 -> 4179.6 | AR85: 3.79 | AS85: =AR85*AK85 -> 11.37 | AT85: =IFERROR(AP85/AS85,0) -> 367.59894 | AV85: TV GLOBO | AW85: =SUM(I85:AJ85) -> 3 | AX85: =AW85*AN85*0.8 -> 4179.6 | AY85: =SUM(AX85)=AP85 -> TRUE
D86: NOVELA DA TARDE ED E | E86: SEG-SÁB | F86: 0.61458333 | G86: 15:25 | H86: 30 | Y86: 1 | AK86: =SUM(I86:AJ86) -> 1 | AL86: 2636 | AM86: 0.1 | AN86: =AL86*(1-AM86) -> 2372.4 | AO86: =AN86*AK86 -> 2372.4 | AP86: =AO86*0.8 -> 1897.92 | AR86: 6.47 | AS86: =AR86*AK86 -> 6.47 | AT86: =IFERROR(AP86/AS86,0) -> 293.34158 | AV86: TV GLOBO | AW86: =SUM(I86:AJ86) -> 1 | AX86: =AW86*AN86*0.8 -> 1897.92 | AY86: =SUM(AX86)=AP86 -> TRUE
D87: NOVELA I | E87: SEG-SEX | F87: 0.76736111 | G87: 19:10 | H87: 30 | AA87: 1 | AK87: =SUM(I87:AJ87) -> 1 | AL87: 6402 | AM87: 0.1 | AN87: =AL87*(1-AM87) -> 5761.8 | AO87: =AN87*AK87 -> 5761.8 | AP87: =AO87*0.8 -> 4609.44 | AR87: 8.5 | AS87: =AR87*AK87 -> 8.5 | AT87: =IFERROR(AP87/AS87,0) -> 542.28706 | AV87: TV GLOBO | AW87: =SUM(I87:AJ87) -> 1 | AX87: =AW87*AN87*0.8 -> 4609.44 | AY87: =SUM(AX87)=AP87 -> TRUE
D88: NOVELA II | E88: SEG-SEX | F88: 0.81944444 | G88: 20:30 | H88: 60 | AK88: =SUM(I88:AJ88) -> 0 | AL88: 15284 | AM88: 0.1 | AN88: =AL88*(1-AM88) -> 13755.6 | AO88: =AN88*AK88 -> 0 | AP88: =AO88*0.8 -> 0 | AR88: 12.33 | AS88: =AR88*AK88 -> 0 | AT88: =IFERROR(AP88/AS88,0) -> 0 | AV88: TV GLOBO | AW88: =SUM(I88:AJ88) -> 0 | AX88: =AW88*AN88*0.8 -> 0 | AY88: =SUM(AX88)=AP88 -> TRUE
D89: NOVELA II | E89: SEG-SEX | F89: 0.81944444 | G89: 20:30 | H89: 30 | U89: 1 | AB89: 1 | AK89: =SUM(I89:AJ89) -> 2 | AL89: 7642 | AM89: 0.1 | AN89: =AL89*(1-AM89) -> 6877.8 | AO89: =AN89*AK89 -> 13755.6 | AP89: =AO89*0.8 -> 11004.48 | AR89: 12.33 | AS89: =AR89*AK89 -> 24.66 | AT89: =IFERROR(AP89/AS89,0) -> 446.24818 | AV89: TV GLOBO | AW89: =SUM(I89:AJ89) -> 2 | AX89: =AW89*AN89*0.8 -> 11004.48 | AY89: =SUM(AX89)=AP89 -> TRUE
D90: NOVELA III | E90: SEG-SEX | F90: 0.88888889 | G90: 22:25 | H90: 60 | T90: 1 | AK90: =SUM(I90:AJ90) -> 1 | AL90: 28836 | AM90: 0.1 | AN90: =AL90*(1-AM90) -> 25952.4 | AO90: =AN90*AK90 -> 25952.4 | AP90: =AO90*0.8 -> 20761.92 | AR90: 13.4 | AS90: =AR90*AK90 -> 13.4 | AT90: =IFERROR(AP90/AS90,0) -> 1549.397 | AV90: TV GLOBO | AW90: =SUM(I90:AJ90) -> 1 | AX90: =AW90*AN90*0.8 -> 20761.92 | AY90: =SUM(AX90)=AP90 -> TRUE
D91: NOVELA III | E91: SEG-SEX | F91: 0.88888889 | G91: 22:25 | H91: 30 | AF91: 1 | AK91: =SUM(I91:AJ91) -> 1 | AL91: 14418 | AM91: 0.1 | AN91: =AL91*(1-AM91) -> 12976.2 | AO91: =AN91*AK91 -> 12976.2 | AP91: =AO91*0.8 -> 10380.96 | AR91: 13.4 | AS91: =AR91*AK91 -> 13.4 | AT91: =IFERROR(AP91/AS91,0) -> 774.69851 | AV91: TV GLOBO | AW91: =SUM(I91:AJ91) -> 1 | AX91: =AW91*AN91*0.8 -> 10380.96 | AY91: =SUM(AX91)=AP91 -> TRUE
D92: VALE A PENA VER DE N | E92: SEG-SEX | F92: 0.71180556 | G92: 18:25 | H92: 30 | X92: 1 | AG92: 1 | AK92: =SUM(I92:AJ92) -> 2 | AL92: 2601 | AM92: 0.1 | AN92: =AL92*(1-AM92) -> 2340.9 | AO92: =AN92*AK92 -> 4681.8 | AP92: =AO92*0.8 -> 3745.44 | AR92: 9.21 | AS92: =AR92*AK92 -> 18.42 | AT92: =IFERROR(AP92/AS92,0) -> 203.3355 | AV92: TV GLOBO | AW92: =SUM(I92:AJ92) -> 2 | AX92: =AW92*AN92*0.8 -> 3745.44 | AY92: =SUM(AX92)=AP92 -> TRUE
AS93: =AR93*AK93 -> 0 | AT93: =IFERROR(AP93/AS93,0) -> 0 | AV93: TT | AW93: =SUM(AW76:AW92) -> 19 | AX93: =SUM(AX76:AX92) -> 95744.16 | AY93: =SUM(AP76:AP92)=AX93 -> TRUE
C94: SBT | D94: AQUI AGORA | E94: SEG-SEX | F94: 18:30 | G94: 19:45 | H94: 60 | AK94: =SUM(I94:AJ94) -> 0 | AL94: 12450 | AM94: 0.75 | AN94: =AL94*(1-AM94) -> 3112.5 | AO94: =AN94*AK94 -> 0 | AP94: =AO94*0.8 -> 0 | AR94: 1.38 | AS94: =AR94*AK94 -> 0 | AT94: =IFERROR(AP94/AS94,0) -> 0 | AV94: SBT | AW94: =SUM(I94:AJ94) -> 0 | AX94: =AW94*AN94*0.8 -> 0 | AY94: =SUM(AX94)=AP94 -> TRUE
D95: AQUI AGORA | E95: SEG-SEX | F95: 18:30 | G95: 19:45 | H95: 30 | AK95: =SUM(I95:AJ95) -> 0 | AL95: 6225 | AM95: 0.75 | AN95: =AL95*(1-AM95) -> 1556.25 | AO95: =AN95*AK95 -> 0 | AP95: =AO95*0.8 -> 0 | AR95: 1.38 | AS95: =AR95*AK95 -> 0 | AT95: =IFERROR(AP95/AS95,0) -> 0 | AV95: SBT | AW95: =SUM(I95:AJ95) -> 0 | AX95: =AW95*AN95*0.8 -> 0 | AY95: =SUM(AX95)=AP95 -> TRUE
D96: DOMINGO LEGAL 1 | E96: DOM | F96: 0.46875 | G96: 15:15 | H96: 60 | AK96: =SUM(I96:AJ96) -> 0 | AL96: 15904 | AM96: 0.75 | AN96: =AL96*(1-AM96) -> 3976 | AO96: =AN96*AK96 -> 0 | AP96: =AO96*0.8 -> 0 | AR96: 3 | AS96: =AR96*AK96 -> 0 | AT96: =IFERROR(AP96/AS96,0) -> 0 | AV96: SBT | AW96: =SUM(I96:AJ96) -> 0 | AX96: =AW96*AN96*0.8 -> 0 | AY96: =SUM(AX96)=AP96 -> TRUE
C97: SBT | D97: NOVELA NOITE 18H | E97: SEG-SEX | F97: 17:45 | G97: 18:30 | H97: 60 | U97: 1 | AK97: =SUM(I97:AJ97) -> 1 | AL97: 12450 | AM97: 0.75 | AN97: =AL97*(1-AM97) -> 3112.5 | AO97: =AN97*AK97 -> 3112.5 | AP97: =AO97*0.8 -> 2490 | AR97: 1.38 | AS97: =AR97*AK97 -> 1.38 | AT97: =IFERROR(AP97/AS97,0) -> 1804.3478 | AV97: SBT | AW97: =SUM(I97:AJ97) -> 1 | AX97: =AW97*AN97*0.8 -> 2490 | AY97: =SUM(AX97)=AP97 -> TRUE
D98: NOVELA NOITE 18H | E98: SEG-SEX | F98: 17:45 | G98: 18:30 | H98: 30 | X98: 1 | AE98: 1 | AK98: =SUM(I98:AJ98) -> 2 | AL98: 6225 | AM98: 0.75 | AN98: =AL98*(1-AM98) -> 1556.25 | AO98: =AN98*AK98 -> 3112.5 | AP98: =AO98*0.8 -> 2490 | AR98: 1.38 | AS98: =AR98*AK98 -> 2.76 | AT98: =IFERROR(AP98/AS98,0) -> 902.17391 | AV98: SBT | AW98: =SUM(I98:AJ98) -> 2 | AX98: =AW98*AN98*0.8 -> 2490 | AY98: =SUM(AX98)=AP98 -> TRUE
D99: DOMINGO LEGAL 1 | E99: DOM | F99: 0.46875 | G99: 15:15 | H99: 30 | AD99: 1 | AK99: =SUM(I99:AJ99) -> 1 | AL99: 7952 | AM99: 0.75 | AN99: =AL99*(1-AM99) -> 1988 | AO99: =AN99*AK99 -> 1988 | AP99: =AO99*0.8 -> 1590.4 | AR99: 3 | AS99: =AR99*AK99 -> 3 | AT99: =IFERROR(AP99/AS99,0) -> 530.13333 | AV99: SBT | AW99: =SUM(I99:AJ99) -> 1 | AX99: =AW99*AN99*0.8 -> 1590.4 | AY99: =SUM(AX99)=AP99 -> TRUE
D100: NOVELA NOITE 2 | E100: SEG-SEX | F100: 0.875 | G100: 21:45 | H100: 60 | T100: 1 | AK100: =SUM(I100:AJ100) -> 1 | AL100: 17036 | AM100: 0.75 | AN100: =AL100*(1-AM100) -> 4259 | AO100: =AN100*AK100 -> 4259 | AP100: =AO100*0.8 -> 3407.2 | AR100: 2.1 | AS100: =AR100*AK100 -> 2.1 | AT100: =IFERROR(AP100/AS100,0) -> 1622.4762 | AV100: SBT | AW100: =SUM(I100:AJ100) -> 1 | AX100: =AW100*AN100*0.8 -> 3407.2 | AY100: =SUM(AX100)=AP100 -> TRUE
D101: NOVELA NOITE 2 | E101: SEG-SEX | F101: 0.875 | G101: 21:45 | H101: 30 | AA101: 1 | AK101: =SUM(I101:AJ101) -> 1 | AL101: 8518 | AM101: 0.75 | AN101: =AL101*(1-AM101) -> 2129.5 | AO101: =AN101*AK101 -> 2129.5 | AP101: =AO101*0.8 -> 1703.6 | AR101: 2.1 | AS101: =AR101*AK101 -> 2.1 | AT101: =IFERROR(AP101/AS101,0) -> 811.2381 | AV101: SBT | AW101: =SUM(I101:AJ101) -> 1 | AX101: =AW101*AN101*0.8 -> 1703.6 | AY101: =SUM(AX101)=AP101 -> TRUE
D102: NOVELA TARDE 14H | E102: SEG-SEX | F102: 0.60416667 | G102: 15:30 | H102: 30 | Y102: 1 | AF102: 1 | AK102: =SUM(I102:AJ102) -> 2 | AL102: 4370 | AM102: 0.75 | AN102: =AL102*(1-AM102) -> 1092.5 | AO102: =AN102*AK102 -> 2185 | AP102: =AO102*0.8 -> 1748 | AR102: 1.6 | AS102: =AR102*AK102 -> 3.2 | AT102: =IFERROR(AP102/AS102,0) -> 546.25 | AV102: SBT | AW102: =SUM(I102:AJ102) -> 2 | AX102: =AW102*AN102*0.8 -> 1748 | AY102: =SUM(AX102)=AP102 -> TRUE
D103: PRIMEIRO IMPACTO | E103: SEG-SEX | F103: 0.35416667 | G103: 11:00 | H103: 30 | Z103: 1 | AG103: 1 | AK103: =SUM(I103:AJ103) -> 2 | AL103: 3205 | AM103: 0.75 | AN103: =AL103*(1-AM103) -> 801.25 | AO103: =AN103*AK103 -> 1602.5 | AP103: =AO103*0.8 -> 1282 | AR103: 1.4 | AS103: =AR103*AK103 -> 2.8 | AT103: =IFERROR(AP103/AS103,0) -> 457.85714 | AV103: SBT | AW103: =SUM(I103:AJ103) -> 2 | AX103: =AW103*AN103*0.8 -> 1282 | AY103: =SUM(AX103)=AP103 -> TRUE
D104: SBT MANHA | E104: SEG-SEX | F104: 0.3125 | G104: 08:30 | H104: 60 | AK104: =SUM(I104:AJ104) -> 0 | AL104: 6410 | AM104: 0.75 | AN104: =AL104*(1-AM104) -> 1602.5 | AO104: =AN104*AK104 -> 0 | AP104: =AO104*0.8 -> 0 | AR104: 1.3 | AS104: =AR104*AK104 -> 0 | AT104: =IFERROR(AP104/AS104,0) -> 0 | AV104: SBT | AW104: =SUM(I104:AJ104) -> 0 | AX104: =AW104*AN104*0.8 -> 0 | AY104: =SUM(AX104)=AP104 -> TRUE
D105: SBT MANHA | E105: SEG-SEX | F105: 0.3125 | G105: 08:30 | H105: 30 | AB105: 1 | AK105: =SUM(I105:AJ105) -> 1 | AL105: 3205 | AM105: 0.75 | AN105: =AL105*(1-AM105) -> 801.25 | AO105: =AN105*AK105 -> 801.25 | AP105: =AO105*0.8 -> 641 | AR105: 1.3 | AS105: =AR105*AK105 -> 1.3 | AT105: =IFERROR(AP105/AS105,0) -> 493.07692 | AV105: SBT | AW105: =SUM(I105:AJ105) -> 1 | AX105: =AW105*AN105*0.8 -> 641 | AY105: =SUM(AX105)=AP105 -> TRUE
...

Sheet TV ABERTA - SPE
B5: CLIENT: SABESP
B6: CAMPAING: ESCASSEZ HIDRICA - CRÍTICO
BW7: PLANNED
B8: MARKET | C8: CHANNEL | D8: PROGRAMM | E8: DAY | F8: START TIME | G8: END TIME | H8: SEC | I8: JANEIRO | BP8: INS. | BQ8: CUSTO TABELA UNITÁRIO (BRUTO) | BR8: DESC. % | BS8: CUSTO NEGOCIADO UNITÁRIO (BRUTO) | BT8: CUSTO TOTAL NEGOCIADO (BRUTO) | BU8: CUSTO TOTAL DESEMBOLSO SABESP | BW8: AUD. AS ABCDE 25+ | BX8: TRP | BY8: CPP | CA8: RESUMO
I9: T | J9: F | K9: S | L9: S | M9: M | N9: T | O9: W | P9: T | Q9: F | R9: S | S9: S | T9: M | U9: T | V9: W | W9: T | X9: F | Y9: S | Z9: S | AA9: M | AB9: T | AC9: W | AD9: T | AE9: F | AF9: S | AG9: S | AH9: M | AI9: T | AJ9: W | AK9: T | AL9: F | AM9: S | AN9: S | AO9: M | AP9: T | AQ9: W | AR9: T | AS9: F | AT9: S | AU9: S | AV9: M | AW9: T | AX9: W | AY9: T | AZ9: F | BA9: S | BB9: S | BC9: M | BD9: T | BE9: W | BF9: T | BG9: F | BH9: S | BI9: S | BJ9: M | BK9: T | BL9: W | BM9: T | BN9: F | BO9: S
I10: 1 | J10: 2 | K10: 3 | L10: 4 | M10: 5 | N10: 6 | O10: 7 | P10: 8 | Q10: 9 | R10: 10 | S10: 11 | T10: 12 | U10: 13 | V10: 14 | W10: 15 | X10: 16 | Y10: 17 | Z10: =Y10+1 -> 18 | AA10: =Z10+1 -> 19 | AB10: =AA10+1 -> 20 | AC10: =AB10+1 -> 21 | AD10: =AC10+1 -> 22 | AE10: =AD10+1 -> 23 | AF10: =AE10+1 -> 24 | AG10: =AF10+1 -> 25 | ... AM10: =AL10+1 -> 31 | AN10: 1 | AO10: 2 | AP10: 3 | AQ10: 4 | AR10: 5 | AS10: 6 | AT10: 7 | AU10: 8 | AV10: 9 | AW10: 10 | AX10: 11 | AY10: 12 | AZ10: 13 | BA10: 14 | BB10: 15 | BC10: 16 | BD10: 17 | BE10: =BD10+1 -> 18 | BF10: =BE10+1 -> 19 | BG10: =BF10+1 -> 20 | BH10: =BG10+1 -> 21 | BI10: =BH10+1 -> 22 | BJ10: =BI10+1 -> 23 | BK10: =BJ10+1 -> 24 | BL10: =BK10+1 -> 25 | ... BO10: =BN10+1 -> 28 | CA10: CHANNEL | CB10: JANEIRO | CD10: FEVEREIRO
CB12: INS | CC12: INVESTIMENTO $ | CD12: INS | CE12: INVESTIMENTO $
B13: SÃO PAULO ESTADO | C13: TV GLOBO | D13: NOVELA II | E13: SEG-SEX | F13: 0.81944444 | G13: 0.85416667 | H13: 30 | AJ13: 1 | BP13: =SUM(I13:BO13) -> 1 | BQ13: 217403 | BR13: 1 | BS13: =BQ13*(1-BR13) -> 0 | BT13: =BS13*BP13 -> 0 | BU13: =BT13*0.8 -> 0 | BW13: 12.33 | BX13: =BW13*BP13 -> 12.33 | BY13: =IFERROR(BU13/BX13,0) -> 0 | CA13: TV GLOBO | CB13: =COUNTA(I13:AM13) -> 1 | CC13: =CB13*BS13*0.8 -> 0 | CD13: =COUNTA(AN13:BO13) -> 0 | CE13: =CD13*BS13*0.8 -> 0 | CF13: =SUM(CC13,CE13)=BU13 -> TRUE
D14: NOVELA III | E14: SEG-SEX | F14: 0.88888889 | G14: 0.93402778 | H14: 30 | AH14: 1 | AK14: 1 | BP14: =SUM(I14:BO14) -> 2 | BQ14: 318624 | BR14: 0 | BS14: =BQ14*(1-BR14) -> 318624 | BT14: =BS14*BP14 -> 637248 | BU14: =BT14*0.8 -> 509798.4 | BW14: 13.35 | BX14: =BW14*BP14 -> 26.7 | BY14: =IFERROR(BU14/BX14,0) -> 19093.573 | CA14: TV GLOBO | CB14: =COUNTA(I14:AM14) -> 2 | CC14: =CB14*BS14*0.8 -> 509798.4 | CD14: =COUNTA(AN14:BO14) -> 0 | CE14: =CD14*BS14*0.8 -> 0 | CF14: =SUM(CC14,CE14)=BU14 -> TRUE
D16: NOVELA II | E16: SEG-SEX | F16: 0.81944444 | G16: 0.85416667 | H16: 30 | AO16: 1 | AR16: 1 | AW16: 1 | BP16: =SUM(I16:BO16) -> 3 | BQ16: 217403 | BR16: 0 | BS16: =BQ16*(1-BR16) -> 217403 | BT16: =BS16*BP16 -> 652209 | BU16: =BT16*0.8 -> 521767.2 | BW16: 12.33 | BX16: =BW16*BP16 -> 36.99 | BY16: =IFERROR(BU16/BX16,0) -> 14105.629 | CA16: TV GLOBO | CB16: =COUNTA(I16:AM16) -> 0 | CC16: =CB16*BS16*0.8 -> 0 | CD16: =COUNTA(AN16:BO16) -> 3 | CE16: =CD16*BS16*0.8 -> 521767.2 | CF16: =SUM(CC16,CE16)=BU16 -> TRUE
D17: NOVELA I | E17: SEG-SEX | F17: 0.76736111 | G17: 0.79861111 | H17: 30 | AS17: 1 | BP17: =SUM(I17:BO17) -> 1 | BQ17: 163381 | BR17: 1 | BS17: =BQ17*(1-BR17) -> 0 | BT17: =BS17*BP17 -> 0 | BU17: =BT17*0.8 -> 0 | BW17: 8.51 | BX17: =BW17*BP17 -> 8.51 | BY17: =IFERROR(BU17/BX17,0) -> 0 | CA17: TV GLOBO | CB17: =COUNTA(I17:AM17) -> 0 | CC17: =CB17*BS17*0.8 -> 0 | CD17: =COUNTA(AN17:BO17) -> 1 | CE17: =CD17*BS17*0.8 -> 0 | CF17: =SUM(CC17,CE17)=BU17 -> TRUE
D19: JORNAL NACIONAL | E19: SEG-SEX | F19: 0.85416667 | G19: 0.88888889 | H19: 30 | AV19: 1 | BP19: =SUM(I19:BO19) -> 1 | BQ19: 316309 | BR19: 0 | BS19: =BQ19*(1-BR19) -> 316309 | BT19: =BS19*BP19 -> 316309 | BU19: =BT19*0.8 -> 253047.2 | BW19: 13.07 | BX19: =BW19*BP19 -> 13.07 | BY19: =IFERROR(BU19/BX19,0) -> 19360.918 | CA19: TV GLOBO | CB19: =COUNTA(I19:AM19) -> 0 | CC19: =CB19*BS19*0.8 -> 0 | CD19: =COUNTA(AN19:BO19) -> 1 | CE19: =CD19*BS19*0.8 -> 253047.2 | CF19: =SUM(CC19,CE19)=BU19 -> TRUE
D20: FANTASTICO | E20: DOM | F20: 0.85416667 | G20: 0.96527778 | H20: 30 | AU20: 1 | BP20: =SUM(I20:BO20) -> 1 | BQ20: 252044 | BR20: 0 | BS20: =BQ20*(1-BR20) -> 252044 | BT20: =BS20*BP20 -> 252044 | BU20: =BT20*0.8 -> 201635.2 | BW20: 8.8 | BX20: =BW20*BP20 -> 8.8 | BY20: =IFERROR(BU20/BX20,0) -> 22913.091 | CA20: TV GLOBO | CB20: =COUNTA(I20:AM20) -> 0 | CC20: =CB20*BS20*0.8 -> 0 | CD20: =COUNTA(AN20:BO20) -> 1 | CE20: =CD20*BS20*0.8 -> 201635.2 | CF20: =SUM(CC20,CE20)=BU20 -> TRUE
D21: JORNAL DA GLOBO | E21: SEG-SEX | F21: 0.041666667 | G21: 0.076388889 | H21: 30 | AO21: 1 | AQ21: 1 | AW21: 1 | AY21: 1 | BP21: =SUM(I21:BO21) -> 4 | BQ21: 43682 | BR21: 1 | BS21: =BQ21*(1-BR21) -> 0 | BT21: =BS21*BP21 -> 0 | BU21: =BT21*0.8 -> 0 | BW21: 3.7 | BX21: =BW21*BP21 -> 14.8 | BY21: =IFERROR(BU21/BX21,0) -> 0 | CA21: TV GLOBO | CB21: =COUNTA(I21:AM21) -> 0 | CC21: =CB21*BS21*0.8 -> 0 | CD21: =COUNTA(AN21:BO21) -> 4 | CE21: =CD21*BS21*0.8 -> 0 | CF21: =SUM(CC21,CE21)=BU21 -> TRUE
D23: NOVELA I | E23: SEG-SEX | F23: 0.76736111 | G23: 0.79861111 | H23: 30 | AH23: 1 | AK23: 1 | BP23: =SUM(I23:BO23) -> 2 | BQ23: 163381 | BR23: 0 | BS23: =BQ23*(1-BR23) -> 163381 | BT23: =BS23*BP23 -> 326762 | BU23: =BT23*0.8 -> 261409.6 | BW23: 8.51 | BX23: =BW23*BP23 -> 17.02 | BY23: =IFERROR(BU23/BX23,0) -> 15358.966 | CA23: TV GLOBO | CB23: =COUNTA(I23:AM23) -> 2 | CC23: =CB23*BS23*0.8 -> 261409.6 | CD23: =COUNTA(AN23:BO23) -> 0 | CE23: =CD23*BS23*0.8 -> 0 | CF23: =SUM(CC23,CE23)=BU23 -> TRUE
D24: NOVELA II | E24: SEG-SEX | F24: 0.81944444 | G24: 0.85416667 | H24: 30 | AI24: 1 | AL24: 1 | BP24: =SUM(I24:BO24) -> 2 | BQ24: 217403 | BR24: 0 | BS24: =BQ24*(1-BR24) -> 217403 | BT24: =BS24*BP24 -> 434806 | BU24: =BT24*0.8 -> 347844.8 | BW24: 12.33 | BX24: =BW24*BP24 -> 24.66 | BY24: =IFERROR(BU24/BX24,0) -> 14105.629 | CA24: TV GLOBO | CB24: =COUNTA(I24:AM24) -> 2 | CC24: =CB24*BS24*0.8 -> 347844.8 | CD24: =COUNTA(AN24:BO24) -> 0 | CE24: =CD24*BS24*0.8 -> 0 | CF24: =SUM(CC24,CE24)=BU24 -> TRUE
D25: NOVELA I SAB | E25: SÁB | F25: 0.77777778 | G25: 0.80902778 | H25: 30 | AM25: 1 | AT25: 1 | BP25: =SUM(I25:BO25) -> 2 | BQ25: 172884 | BR25: 1 | BS25: =BQ25*(1-BR25) -> 0 | BT25: =BS25*BP25 -> 0 | BU25: =BT25*0.8 -> 0 | BW25: 11.08 | BX25: =BW25*BP25 -> 22.16 | BY25: =IFERROR(BU25/BX25,0) -> 0 | CA25: TV GLOBO | CB25: =COUNTA(I25:AM25) -> 1 | CC25: =CB25*BS25*0.8 -> 0 | CD25: =COUNTA(AN25:BO25) -> 1 | CE25: =CD25*BS25*0.8 -> 0 | CF25: =SUM(CC25,CE25)=BU25 -> TRUE
D27: NOVELA III | E27: SEG-SEX | F27: 0.88888889 | G27: 0.93402778 | H27: 60 | AD27: 1 | BP27: =SUM(I27:BO27) -> 1 | BQ27: =318624*2 -> 637248 | BR27: 0 | BS27: =BQ27*(1-BR27) -> 637248 | BT27: =BS27*BP27 -> 637248 | BU27: =BT27*0.8 -> 509798.4 | BW27: 13.35 | BX27: =BW27*BP27 -> 13.35 | BY27: =IFERROR(BU27/BX27,0) -> 38187.146 | CA27: TV GLOBO | CB27: =COUNTA(I27:AM27) -> 1 | CC27: =CB27*BS27*0.8 -> 509798.4 | CD27: =COUNTA(AN27:BO27) -> 0 | CE27: =CD27*BS27*0.8 -> 0 | CF27: =SUM(CC27,CE27)=BU27 -> TRUE
D28: NOVELA III SAB | E28: SÁB | F28: 0.88888889 | G28: 0.93402778 | H28: 60 | AF28: 1 | BP28: =SUM(I28:BO28) -> 1 | BQ28: =257775*2 -> 515550 | BR28: 0 | BS28: =BQ28*(1-BR28) -> 515550 | BT28: =BS28*BP28 -> 515550 | BU28: =BT28*0.8 -> 412440 | BW28: 11.18 | BX28: =BW28*BP28 -> 11.18 | BY28: =IFERROR(BU28/BX28,0) -> 36890.877 | CA28: TV GLOBO | CB28: =COUNTA(I28:AM28) -> 1 | CC28: =CB28*BS28*0.8 -> 412440 | CD28: =COUNTA(AN28:BO28) -> 0 | CE28: =CD28*BS28*0.8 -> 0 | CF28: =SUM(CC28,CE28)=BU28 -> TRUE
D29: NOVELA II | E29: SEG-SEX | F29: 0.81944444 | G29: 0.85416667 | H29: 60 | AE29: 1 | BP29: =SUM(I29:BO29) -> 1 | BQ29: =217403*2 -> 434806 | BR29: 1 | BS29: =BQ29*(1-BR29) -> 0 | BT29: =BS29*BP29 -> 0 | BU29: =BT29*0.8 -> 0 | BW29: 12.33 | BX29: =BW29*BP29 -> 12.33 | BY29: =IFERROR(BU29/BX29,0) -> 0 | CA29: TV GLOBO | CB29: =COUNTA(I29:AM29) -> 1 | CC29: =CB29*BS29*0.8 -> 0 | CD29: =COUNTA(AN29:BO29) -> 0 | CE29: =CD29*BS29*0.8 -> 0 | CF29: =SUM(CC29,CE29)=BU29 -> TRUE
D31: JORNAL NACIONAL - PRIMEIRISSIMA | E31: SEG-SEX | F31: 0.85416667 | G31: 0.88888889 | H31: 60 | AC31: 1 | BP31: =SUM(I31:BO31) -> 1 | BQ31: =(316309*2)*1.2 -> 759141.6 | BR31: 0.1 | BS31: =BQ31*(1-BR31) -> 683227.44 | BT31: =BS31*BP31 -> 683227.44 | BU31: =BT31*0.8 -> 546581.95 | BW31: 13.07 | BX31: =BW31*BP31 -> 13.07 | BY31: =IFERROR(BU31/BX31,0) -> 41819.583 | CA31: TV GLOBO | CB31: =COUNTA(I31:AM31) -> 1 | CC31: =CB31*BS31*0.8 -> 546581.95 | CD31: =COUNTA(AN31:BO31) -> 0 | CE31: =CD31*BS31*0.8 -> 0 | CF31: =SUM(CC31,CE31)=BU31 -> TRUE
CA32: TT | CB32: =SUM(CB13:CB31) -> 12 | CC32: =SUM(CC13:CC31) -> 2587873.2 | CD32: =SUM(CD13:CD31) -> 11 | CE32: =SUM(CE13:CE31) -> 976449.6
C33: BANDEIRANTES | D33: BORA BRASIL | E33: SEG-SEX | F33: 0.375 | G33: 11:00 | H33: 30 | AK33: 1 | AR33: 1 | AY33: 1 | BP33: =SUM(I33:BO33) -> 3 | BQ33: 18884 | BR33: 0.85 | BS33: =BQ33*(1-BR33) -> 2832.6 | BT33: =BS33*BP33 -> 8497.8 | BU33: =BT33*0.8 -> 6798.24 | BW33: 0.24 | BX33: =BW33*BP33 -> 0.72 | BY33: =IFERROR(BU33/BX33,0) -> 9442 | CA33: BANDEIRANTES | CB33: =COUNTA(I33:AM33) -> 1 | CC33: =CB33*BS33*0.8 -> 2266.08 | CD33: =COUNTA(AN33:BO33) -> 2 | CE33: =CD33*BS33*0.8 -> 4532.16 | CF33: =SUM(CC33,CE33)=BU33 -> TRUE
D34: BORA BRASIL | E34: SEG-SEX | F34: 0.375 | G34: 11:00 | H34: 60 | AD34: 1 | BP34: =SUM(I34:BO34) -> 1 | BQ34: 37768 | BR34: 0.85 | BS34: =BQ34*(1-BR34) -> 5665.2 | BT34: =BS34*BP34 -> 5665.2 | BU34: =BT34*0.8 -> 4532.16 | BW34: 0.24 | BX34: =BW34*BP34 -> 0.24 | BY34: =IFERROR(BU34/BX34,0) -> 18884 | CA34: BANDEIRANTES | CB34: =COUNTA(I34:AM34) -> 1 | CC34: =CB34*BS34*0.8 -> 4532.16 | CD34: =COUNTA(AN34:BO34) -> 0 | CE34: =CD34*BS34*0.8 -> 0 | CF34: =SUM(CC34,CE34)=BU34 -> TRUE
D35: BRASIL URGENTE | E35: SEG-SÁB | F35: 0.66666667 | G35: 17:30 | H35: 30 | AL35: 1 | AS35: 1 | AZ35: 1 | BP35: =SUM(I35:BO35) -> 3 | BQ35: 66878 | BR35: 0.85 | BS35: =BQ35*(1-BR35) -> 10031.7 | BT35: =BS35*BP35 -> 30095.1 | BU35: =BT35*0.8 -> 24076.08 | BW35: 1.43 | BX35: =BW35*BP35 -> 4.29 | BY35: =IFERROR(BU35/BX35,0) -> 5612.1399 | CA35: BANDEIRANTES | CB35: =COUNTA(I35:AM35) -> 1 | CC35: =CB35*BS35*0.8 -> 8025.36 | CD35: =COUNTA(AN35:BO35) -> 2 | CE35: =CD35*BS35*0.8 -> 16050.72 | CF35: =SUM(CC35,CE35)=BU35 -> TRUE
D36: BRASIL URGENTE | E36: SEG-SÁB | F36: 0.66666667 | G36: 17:30 | H36: 60 | AE36: 1 | BP36: =SUM(I36:BO36) -> 1 | BQ36: 133756 | BR36: 0.85 | BS36: =BQ36*(1-BR36) -> 20063.4 | BT36: =BS36*BP36 -> 20063.4 | BU36: =BT36*0.8 -> 16050.72 | BW36: 1.43 | BX36: =BW36*BP36 -> 1.43 | BY36: =IFERROR(BU36/BX36,0) -> 11224.28 | CA36: BANDEIRANTES | CB36: =COUNTA(I36:AM36) -> 1 | CC36: =CB36*BS36*0.8 -> 16050.72 | CD36: =COUNTA(AN36:BO36) -> 0 | CE36: =CD36*BS36*0.8 -> 0 | CF36: =SUM(CC36,CE36)=BU36 -> TRUE
D37: CANAL LIVRE | E37: DOM | F37: 0.95833333 | G37: 00:00 | H37: 30 | AU37: 1 | BP37: =SUM(I37:BO37) -> 1 | BQ37: 34546 | BR37: 0.85 | BS37: =BQ37*(1-BR37) -> 5181.9 | BT37: =BS37*BP37 -> 5181.9 | BU37: =BT37*0.8 -> 4145.52 | BW37: 0.21 | BX37: =BW37*BP37 -> 0.21 | BY37: =IFERROR(BU37/BX37,0) -> 19740.571 | CA37: BANDEIRANTES | CB37: =COUNTA(I37:AM37) -> 0 | CC37: =CB37*BS37*0.8 -> 0 | CD37: =COUNTA(AN37:BO37) -> 1 | CE37: =CD37*BS37*0.8 -> 4145.52 | CF37: =SUM(CC37,CE37)=BU37 -> TRUE
D38: CANAL LIVRE | E38: DOM | F38: 0.95833333 | G38: 00:00 | H38: 60 | AG38: 1 | BP38: =SUM(I38:BO38) -> 1 | BQ38: 69092 | BR38: 0.85 | BS38: =BQ38*(1-BR38) -> 10363.8 | BT38: =BS38*BP38 -> 10363.8 | BU38: =BT38*0.8 -> 8291.04 | BW38: 0.21 | BX38: =BW38*BP38 -> 0.21 | BY38: =IFERROR(BU38/BX38,0) -> 39481.143 | CA38: BANDEIRANTES | CB38: =COUNTA(I38:AM38) -> 1 | CC38: =CB38*BS38*0.8 -> 8291.04 | CD38: =COUNTA(AN38:BO38) -> 0 | CE38: =CD38*BS38*0.8 -> 0 | CF38: =SUM(CC38,CE38)=BU38 -> TRUE
D39: JORNAL DA NOITE | E39: SEG-SEX | F39: 0.010416667 | G39: 01:15 | H39: 30 | AJ39: 1 | AQ39: 1 | AX39: 1 | BP39: =SUM(I39:BO39) -> 3 | BQ39: 36271 | BR39: 0.85 | BS39: =BQ39*(1-BR39) -> 5440.65 | BT39: =BS39*BP39 -> 16321.95 | BU39: =BT39*0.8 -> 13057.56 | BW39: 0.34 | BX39: =BW39*BP39 -> 1.02 | BY39: =IFERROR(BU39/BX39,0) -> 12801.529 | CA39: BANDEIRANTES | CB39: =COUNTA(I39:AM39) -> 1 | CC39: =CB39*BS39*0.8 -> 4352.52 | CD39: =COUNTA(AN39:BO39) -> 2 | CE39: =CD39*BS39*0.8 -> 8705.04 | CF39: =SUM(CC39,CE39)=BU39 -> TRUE
D40: JORNAL DA NOITE | E40: SEG-SEX | F40: 0.010416667 | G40: 01:15 | H40: 60 | AD40: 1 | BP40: =SUM(I40:BO40) -> 1 | BQ40: 72542 | BR40: 0.85 | BS40: =BQ40*(1-BR40) -> 10881.3 | BT40: =BS40*BP40 -> 10881.3 | BU40: =BT40*0.8 -> 8705.04 | BW40: 0.34 | BX40: =BW40*BP40 -> 0.34 | BY40: =IFERROR(BU40/BX40,0) -> 25603.059 | CA40: BANDEIRANTES | CB40: =COUNTA(I40:AM40) -> 1 | CC40: =CB40*BS40*0.8 -> 8705.04 | CD40: =COUNTA(AN40:BO40) -> 0 | CE40: =CD40*BS40*0.8 -> 0 | CF40: =SUM(CC40,CE40)=BU40 -> TRUE
D41: NOVELA I | E41: SEG-SEX | F41: 0.29166667 | G41: 08:00 | H41: 30 | BP41: =SUM(I41:BO41) -> 0 | BQ41: 16564 | BR41: 0.85 | BS41: =BQ41*(1-BR41) -> 2484.6 | BT41: =BS41*BP41 -> 0 | BU41: =BT41*0.8 -> 0 | BW41: 0.1 | BX41: =BW41*BP41 -> 0 | BY41: =IFERROR(BU41/BX41,0) -> 0 | CA41: BANDEIRANTES | CB41: =COUNTA(I41:AM41) -> 0 | CC41: =CB41*BS41*0.8 -> 0 | CD41: =COUNTA(AN41:BO41) -> 0 | CE41: =CD41*BS41*0.8 -> 0 | CF41: =SUM(CC41,CE41)=BU41 -> TRUE
D42: NOVELA II | E42: SEG-SEX | F42: 0.85416667 | G42: 21:25 | H42: 30 | AH42: 1 | AO42: 1 | AV42: 1 | BP42: =SUM(I42:BO42) -> 3 | BQ42: 118356 | BR42: 0.85 | BS42: =BQ42*(1-BR42) -> 17753.4 | BT42: =BS42*BP42 -> 53260.2 | BU42: =BT42*0.8 -> 42608.16 | BW42: 0.71 | BX42: =BW42*BP42 -> 2.13 | BY42: =IFERROR(BU42/BX42,0) -> 20003.831 | CA42: BANDEIRANTES | CB42: =COUNTA(I42:AM42) -> 1 | CC42: =CB42*BS42*0.8 -> 14202.72 | CD42: =COUNTA(AN42:BO42) -> 2 | CE42: =CD42*BS42*0.8 -> 28405.44 | CF42: =SUM(CC42,CE42)=BU42 -> TRUE
D43: NOVELA II | E43: SEG-SEX | F43: 0.85416667 | G43: 21:25 | H43: 60 | AE43: 1 | BP43: =SUM(I43:BO43) -> 1 | BQ43: 236712 | BR43: 0.85 | BS43: =BQ43*(1-BR43) -> 35506.8 | BT43: =BS43*BP43 -> 35506.8 | BU43: =BT43*0.8 -> 28405.44 | BW43: 0.71 | BX43: =BW43*BP43 -> 0.71 | BY43: =IFERROR(BU43/BX43,0) -> 40007.662 | CA43: BANDEIRANTES | CB43: =COUNTA(I43:AM43) -> 1 | CC43: =CB43*BS43*0.8 -> 28405.44 | CD43: =COUNTA(AN43:BO43) -> 0 | CE43: =CD43*BS43*0.8 -> 0 | CF43: =SUM(CC43,CE43)=BU43 -> TRUE
CA44: TT | CB44: =SUM(CB33:CB43) -> 9 | CC44: =SUM(CC33:CC43) -> 94831.08 | CD44: =SUM(CD33:CD43) -> 9 | CE44: =SUM(CE33:CE43) -> 61838.88
C45: RECORD | D45: CIDADE ALERTA 2 SAB | E45: SÁB | F45: 0.875 | G45: 22:30 | H45: 30 | AM45: 1 | AT45: 1 | BA45: 1 | BP45: =SUM(I45:BO45) -> 3 | BQ45: 68258 | BR45: 0.8 | BS45: =BQ45*(1-BR45) -> 13651.6 | BT45: =BS45*BP45 -> 40954.8 | BU45: =BT45*0.8 -> 32763.84 | BW45: 2.19 | BX45: =BW45*BP45 -> 6.57 | BY45: =IFERROR(BU45/BX45,0) -> 4986.8858 | CA45: RECORD | CB45: =COUNTA(I45:AM45) -> 1 | CC45: =CB45*BS45*0.8 -> 10921.28 | CD45: =COUNTA(AN45:BO45) -> 2 | CE45: =CD45*BS45*0.8 -> 21842.56 | CF45: =SUM(CC45,CE45)=BU45 -> TRUE
D46: CIDADE ALERTA 2 SAB | E46: SÁB | F46: 0.875 | G46: 22:30 | H46: 60 | AF46: 1 | BP46: =SUM(I46:BO46) -> 1 | BQ46: 136516 | BR46: 0.8 | BS46: =BQ46*(1-BR46) -> 27303.2 | BT46: =BS46*BP46 -> 27303.2 | BU46: =BT46*0.8 -> 21842.56 | BW46: 2.19 | BX46: =BW46*BP46 -> 2.19 | BY46: =IFERROR(BU46/BX46,0) -> 9973.7717 | CA46: RECORD | CB46: =COUNTA(I46:AM46) -> 1 | CC46: =CB46*BS46*0.8 -> 21842.56 | CD46: =COUNTA(AN46:BO46) -> 0 | CE46: =CD46*BS46*0.8 -> 0 | CF46: =SUM(CC46,CE46)=BU46 -> TRUE
D47: DOMINGO ESPETACULAR | E47: DOM | F47: 0.75 | G47: 20:00 | H47: 30 | AN47: 1 | AU47: 1 | BB47: 1 | BP47: =SUM(I47:BO47) -> 3 | BQ47: 393224 | BR47: 0.8 | BS47: =BQ47*(1-BR47) -> 78644.8 | BT47: =BS47*BP47 -> 235934.4 | BU47: =BT47*0.8 -> 188747.52 | BW47: 3.05 | BX47: =BW47*BP47 -> 9.15 | BY47: =IFERROR(BU47/BX47,0) -> 20628.144 | CA47: RECORD | CB47: =COUNTA(I47:AM47) -> 0 | CC47: =CB47*BS47*0.8 -> 0 | CD47: =COUNTA(AN47:BO47) -> 3 | CE47: =CD47*BS47*0.8 -> 188747.52 | CF47: =SUM(CC47,CE47)=BU47 -> TRUE
D48: DOMINGO ESPETACULAR | E48: DOM | F48: 0.75 | G48: 20:00 | H48: 60 | AG48: 1 | BP48: =SUM(I48:BO48) -> 1 | BQ48: 786448 | BR48: 0.8 | BS48: =BQ48*(1-BR48) -> 157289.6 | BT48: =BS48*BP48 -> 157289.6 | BU48: =BT48*0.8 -> 125831.68 | BW48: 3.05 | BX48: =BW48*BP48 -> 3.05 | BY48: =IFERROR(BU48/BX48,0) -> 41256.289 | CA48: RECORD | CB48: =COUNTA(I48:AM48) -> 1 | CC48: =CB48*BS48*0.8 -> 125831.68 | CD48: =COUNTA(AN48:BO48) -> 0 | CE48: =CD48*BS48*0.8 -> 0 | CF48: =SUM(CC48,CE48)=BU48 -> TRUE
D49: FALA BRASIL | E49: SEG-SEX | F49: 0.35416667 | G49: 09:35 | H49: 30 | AJ49: 1 | AQ49: 1 | AX49: 1 | BP49: =SUM(I49:BO49) -> 3 | BQ49: 88342 | BR49: 0.8 | BS49: =BQ49*(1-BR49) -> 17668.4 | BT49: =BS49*BP49 -> 53005.2 | BU49: =BT49*0.8 -> 42404.16 | BW49: 1.95 | BX49: =BW49*BP49 -> 5.85 | BY49: =IFERROR(BU49/BX49,0) -> 7248.5744 | CA49: RECORD | CB49: =COUNTA(I49:AM49) -> 1 | CC49: =CB49*BS49*0.8 -> 14134.72 | CD49: =COUNTA(AN49:BO49) -> 2 | CE49: =CD49*BS49*0.8 -> 28269.44 | CF49: =SUM(CC49,CE49)=BU49 -> TRUE
D50: FALA BRASIL | E50: SEG-SEX | F50: 0.35416667 | G50: 09:35 | H50: 60 | AE50: 1 | BP50: =SUM(I50:BO50) -> 1 | BQ50: 176684 | BR50: 0.8 | BS50: =BQ50*(1-BR50) -> 35336.8 | BT50: =BS50*BP50 -> 35336.8 | BU50: =BT50*0.8 -> 28269.44 | BW50: 1.95 | BX50: =BW50*BP50 -> 1.95 | BY50: =IFERROR(BU50/BX50,0) -> 14497.149 | CA50: RECORD | CB50: =COUNTA(I50:AM50) -> 1 | CC50: =CB50*BS50*0.8 -> 28269.44 | CD50: =COUNTA(AN50:BO50) -> 0 | CE50: =CD50*BS50*0.8 -> 0 | CF50: =SUM(CC50,CE50)=BU50 -> TRUE
D51: HOJE EM DIA | E51: SEG-SEX | F51: 0.39930556 | G51: 11:30 | H51: 30 | AI51: 1 | AP51: 1 | AW51: 1 | BP51: =SUM(I51:BO51) -> 3 | BQ51: 68116 | BR51: 0.8 | BS51: =BQ51*(1-BR51) -> 13623.2 | BT51: =BS51*BP51 -> 40869.6 | BU51: =BT51*0.8 -> 32695.68 | BW51: 2.01 | BX51: =BW51*BP51 -> 6.03 | BY51: =IFERROR(BU51/BX51,0) -> 5422.1692 | CA51: RECORD | CB51: =COUNTA(I51:AM51) -> 1 | CC51: =CB51*BS51*0.8 -> 10898.56 | CD51: =COUNTA(AN51:BO51) -> 2 | CE51: =CD51*BS51*0.8 -> 21797.12 | CF51: =SUM(CC51,CE51)=BU51 -> TRUE
D52: NOVELA 22H | E52: SEG-SEX | F52: 0.91666667 | G52: 22:30 | H52: 30 | AK52: 1 | AR52: 1 | AY52: 1 | BP52: =SUM(I52:BO52) -> 3 | BQ52: 235310 | BR52: 0.8 | BS52: =BQ52*(1-BR52) -> 47062 | BT52: =BS52*BP52 -> 141186 | BU52: =BT52*0.8 -> 112948.8 | BW52: 2.27 | BX52: =BW52*BP52 -> 6.81 | BY52: =IFERROR(BU52/BX52,0) -> 16585.727 | CA52: RECORD | CB52: =COUNTA(I52:AM52) -> 1 | CC52: =CB52*BS52*0.8 -> 37649.6 | CD52: =COUNTA(AN52:BO52) -> 2 | CE52: =CD52*BS52*0.8 -> 75299.2 | CF52: =SUM(CC52,CE52)=BU52 -> TRUE
D53: NOVELA 22H | E53: SEG-SEX | F53: 0.91666667 | G53: 22:30 | H53: 60 | AD53: 1 | BP53: =SUM(I53:BO53) -> 1 | BQ53: 470620 | BR53: 0.8 | BS53: =BQ53*(1-BR53) -> 94124 | BT53: =BS53*BP53 -> 94124 | BU53: =BT53*0.8 -> 75299.2 | BW53: 2.27 | BX53: =BW53*BP53 -> 2.27 | BY53: =IFERROR(BU53/BX53,0) -> 33171.454 | CA53: RECORD | CB53: =COUNTA(I53:AM53) -> 1 | CC53: =CB53*BS53*0.8 -> 75299.2 | CD53: =COUNTA(AN53:BO53) -> 0 | CE53: =CD53*BS53*0.8 -> 0 | CF53: =SUM(CC53,CE53)=BU53 -> TRUE
D54: NOVELA 3 | E54: SEG-SEX | F54: 0.875 | G54: 22:00 | H54: 30 | AL54: 1 | AS54: 1 | AZ54: 1 | BP54: =SUM(I54:BO54) -> 3 | BQ54: 297974 | BR54: 0.8 | BS54: =BQ54*(1-BR54) -> 59594.8 | BT54: =BS54*BP54 -> 178784.4 | BU54: =BT54*0.8 -> 143027.52 | BW54: 2.56 | BX54: =BW54*BP54 -> 7.68 | BY54: =IFERROR(BU54/BX54,0) -> 18623.375 | CA54: RECORD | CB54: =COUNTA(I54:AM54) -> 1 | CC54: =CB54*BS54*0.8 -> 47675.84 | CD54: =COUNTA(AN54:BO54) -> 2 | CE54: =CD54*BS54*0.8 -> 95351.68 | CF54: =SUM(CC54,CE54)=BU54 -> TRUE
D55: NOVELA 3 | E55: SEG-SEX | F55: 0.875 | G55: 22:00 | H55: 60 | AE55: 1 | BP55: =SUM(I55:BO55) -> 1 | BQ55: 595948 | BR55: 0.8 | BS55: =BQ55*(1-BR55) -> 119189.6 | BT55: =BS55*BP55 -> 119189.6 | BU55: =BT55*0.8 -> 95351.68 | BW55: 2.56 | BX55: =BW55*BP55 -> 2.56 | BY55: =IFERROR(BU55/BX55,0) -> 37246.75 | CA55: RECORD | CB55: =COUNTA(I55:AM55) -> 1 | CC55: =CB55*BS55*0.8 -> 95351.68 | CD55: =COUNTA(AN55:BO55) -> 0 | CE55: =CD55*BS55*0.8 -> 0 | CF55: =SUM(CC55,CE55)=BU55 -> TRUE
D56: NOVELA DA TARDE 1 | E56: SEG-SEX | F56: 0.64583333 | G56: 16:30 | H56: 30 | AH56: 1 | AO56: 1 | AV56: 1 | BP56: =SUM(I56:BO56) -> 3 | BQ56: 87447 | BR56: 0.8 | BS56: =BQ56*(1-BR56) -> 17489.4 | BT56: =BS56*BP56 -> 52468.2 | BU56: =BT56*0.8 -> 41974.56 | BW56: 2.39 | BX56: =BW56*BP56 -> 7.17 | BY56: =IFERROR(BU56/BX56,0) -> 5854.1925 | CA56: RECORD | CB56: =COUNTA(I56:AM56) -> 1 | CC56: =CB56*BS56*0.8 -> 13991.52 | CD56: =COUNTA(AN56:BO56) -> 2 | CE56: =CD56*BS56*0.8 -> 27983.04 | CF56: =SUM(CC56,CE56)=BU56 -> TRUE
CA57: TT | CB57: =SUM(CB45:CB56) -> 11 | CC57: =SUM(CC45:CC56) -> 481866.08 | CD57: =SUM(CD45:CD56) -> 15 | CE57: =SUM(CE45:CE56) -> 459290.56
C58: SBT | D58: ALO VOCE | E58: SEG-SEX | F58: 0.45833333 | G58: 13:45 | H58: 30 | AH58: 1 | AO58: 1 | AV58: 1 | BP58: =SUM(I58:BO58) -> 3 | BQ58: 89256 | BR58: 0.75 | BS58: =BQ58*(1-BR58) -> 22314 | BT58: =BS58*BP58 -> 66942 | BU58: =BT58*0.8 -> 53553.6 | BW58: 1.45 | BX58: =BW58*BP58 -> 4.35 | BY58: =IFERROR(BU58/BX58,0) -> 12311.172 | CA58: SBT | CB58: =COUNTA(I58:AM58) -> 1 | CC58: =CB58*BS58*0.8 -> 17851.2 | CD58: =COUNTA(AN58:BO58) -> 2 | CE58: =CD58*BS58*0.8 -> 35702.4 | CF58: =SUM(CC58,CE58)=BU58 -> TRUE
D59: DOMINGO LEGAL 1 | E59: DOM | F59: 0.46875 | G59: 15:15 | H59: 30 | AN59: 1 | AU59: 1 | BB59: 1 | BP59: =SUM(I59:BO59) -> 3 | BQ59: 206148 | BR59: 0.75 | BS59: =BQ59*(1-BR59) -> 51537 | BT59: =BS59*BP59 -> 154611 | BU59: =BT59*0.8 -> 123688.8 | BW59: 2.99 | BX59: =BW59*BP59 -> 8.97 | BY59: =IFERROR(BU59/BX59,0) -> 13789.164 | CA59: SBT | CB59: =COUNTA(I59:AM59) -> 0 | CC59: =CB59*BS59*0.8 -> 0 | CD59: =COUNTA(AN59:BO59) -> 3 | CE59: =CD59*BS59*0.8 -> 123688.8 | CF59: =SUM(CC59,CE59)=BU59 -> TRUE
D60: DOMINGO LEGAL 1 | E60: DOM | F60: 0.46875 | G60: 15:15 | H60: 60 | AG60: 1 | BP60: =SUM(I60:BO60) -> 1 | BQ60: 412296 | BR60: 0.75 | BS60: =BQ60*(1-BR60) -> 103074 | BT60: =BS60*BP60 -> 103074 | BU60: =BT60*0.8 -> 82459.2 | BW60: 2.99 | BX60: =BW60*BP60 -> 2.99 | BY60: =IFERROR(BU60/BX60,0) -> 27578.328 | CA60: SBT | CB60: =COUNTA(I60:AM60) -> 1 | CC60: =CB60*BS60*0.8 -> 82459.2 | CD60: =COUNTA(AN60:BO60) -> 0 | CE60: =CD60*BS60*0.8 -> 0 | CF60: =SUM(CC60,CE60)=BU60 -> TRUE
D61: NOVELA NOITE | E61: SEG-SEX | F61: 0.875 | G61: 22:15 | H61: 30 | AH61: 1 | AO61: 1 | AV61: 1 | BP61: =SUM(I61:BO61) -> 3 | BQ61: 249316 | BR61: 0.75 | BS61: =BQ61*(1-BR61) -> 62329 | BT61: =BS61*BP61 -> 186987 | BU61: =BT61*0.8 -> 149589.6 | BW61: 2.14 | BX61: =BW61*BP61 -> 6.42 | BY61: =IFERROR(BU61/BX61,0) -> 23300.561 | CA61: SBT | CB61: =COUNTA(I61:AM61) -> 1 | CC61: =CB61*BS61*0.8 -> 49863.2 | CD61: =COUNTA(AN61:BO61) -> 2 | CE61: =CD61*BS61*0.8 -> 99726.4 | CF61: =SUM(CC61,CE61)=BU61 -> TRUE
D62: NOVELA NOITE | E62: SEG-SEX | F62: 0.875 | G62: 22:15 | H62: 60 | AD62: 1 | BP62: =SUM(I62:BO62) -> 1 | BQ62: 498632 | BR62: 0.75 | BS62: =BQ62*(1-BR62) -> 124658 | BT62: =BS62*BP62 -> 124658 | BU62: =BT62*0.8 -> 99726.4 | BW62: 2.14 | BX62: =BW62*BP62 -> 2.14 | BY62: =IFERROR(BU62/BX62,0) -> 46601.121 | CA62: SBT | CB62: =COUNTA(I62:AM62) -> 1 | CC62: =CB62*BS62*0.8 -> 99726.4 | CD62: =COUNTA(AN62:BO62) -> 0 | CE62: =CD62*BS62*0.8 -> 0 | CF62: =SUM(CC62,CE62)=BU62 -> TRUE
D63: NOVELA NOITE 18H | E63: SEG-SEX | F63: 0.73958333 | G63: 18:30 | H63: 30 | AK63: 1 | AR63: 1 | AY63: 1 | BP63: =SUM(I63:BO63) -> 3 | BQ63: 149464 | BR63: 0.75 | BS63: =BQ63*(1-BR63) -> 37366 | BT63: =BS63*BP63 -> 112098 | BU63: =BT63*0.8 -> 89678.4 | BW63: 1.08 | BX63: =BW63*BP63 -> 3.24 | BY63: =IFERROR(BU63/BX63,0) -> 27678.519 | CA63: SBT | CB63: =COUNTA(I63:AM63) -> 1 | CC63: =CB63*BS63*0.8 -> 29892.8 | CD63: =COUNTA(AN63:BO63) -> 2 | CE63: =CD63*BS63*0.8 -> 59785.6 | CF63: =SUM(CC63,CE63)=BU63 -> TRUE
D64: NOVELA TARDE 14H | E64: SEG-SEX | F64: 0.60416667 | G64: 15:30 | H64: 30 | AJ64: 1 | AQ64: 1 | AX64: 1 | BP64: =SUM(I64:BO64) -> 3 | BQ64: 128521 | BR64: 0.75 | BS64: =BQ64*(1-BR64) -> 32130.25 | BT64: =BS64*BP64 -> 96390.75 | BU64: =BT64*0.8 -> 77112.6 | BW64: 1.58 | BX64: =BW64*BP64 -> 4.74 | BY64: =IFERROR(BU64/BX64,0) -> 16268.481 | CA64: SBT | CB64: =COUNTA(I64:AM64) -> 1 | CC64: =CB64*BS64*0.8 -> 25704.2 | CD64: =COUNTA(AN64:BO64) -> 2 | CE64: =CD64*BS64*0.8 -> 51408.4 | CF64: =SUM(CC64,CE64)=BU64 -> TRUE
D65: PRIMEIRO IMPACTO | E65: SEG-SEX | F65: 0.35416667 | G65: 11:00 | H65: 30 | AI65: 1 | AP65: 1 | AW65: 1 | BP65: =SUM(I65:BO65) -> 3 | BQ65: 73583 | BR65: 0.75 | BS65: =BQ65*(1-BR65) -> 18395.75 | BT65: =BS65*BP65 -> 55187.25 | BU65: =BT65*0.8 -> 44149.8 | BW65: 1.38 | BX65: =BW65*BP65 -> 4.14 | BY65: =IFERROR(BU65/BX65,0) -> 10664.203 | CA65: SBT | CB65: =COUNTA(I65:AM65) -> 1 | CC65: =CB65*BS65*0.8 -> 14716.6 | CD65: =COUNTA(AN65:BO65) -> 2 | CE65: =CD65*BS65*0.8 -> 29433.2 | CF65: =SUM(CC65,CE65)=BU65 -> TRUE
D66: SBT MANHA | E66: SEG-SEX | F66: 0.3125 | G66: 08:30 | H66: 30 | AL66: 1 | AS66: 1 | AZ66: 1 | BP66: =SUM(I66:BO66) -> 3 | BQ66: 73583 | BR66: 0.75 | BS66: =BQ66*(1-BR66) -> 18395.75 | BT66: =BS66*BP66 -> 55187.25 | BU66: =BT66*0.8 -> 44149.8 | BW66: 1.25 | BX66: =BW66*BP66 -> 3.75 | BY66: =IFERROR(BU66/BX66,0) -> 11773.28 | CA66: SBT | CB66: =COUNTA(I66:AM66) -> 1 | CC66: =CB66*BS66*0.8 -> 14716.6 | CD66: =COUNTA(AN66:BO66) -> 2 | CE66: =CD66*BS66*0.8 -> 29433.2 | CF66: =SUM(CC66,CE66)=BU66 -> TRUE
D67: SBT MANHA | E67: SEG-SEX | F67: 0.3125 | G67: 08:30 | H67: 60 | AE67: 1 | BP67: =SUM(I67:BO67) -> 1 | BQ67: 147166 | BR67: 0.75 | BS67: =BQ67*(1-BR67) -> 36791.5 | BT67: =BS67*BP67 -> 36791.5 | BU67: =BT67*0.8 -> 29433.2 | BW67: 1.25 | BX67: =BW67*BP67 -> 1.25 | BY67: =IFERROR(BU67/BX67,0) -> 23546.56 | CA67: SBT | CB67: =COUNTA(I67:AM67) -> 1 | CC67: =CB67*BS67*0.8 -> 29433.2 | CD67: =COUNTA(AN67:BO67) -> 0 | CE67: =CD67*BS67*0.8 -> 0 | CF67: =SUM(CC67,CE67)=BU67 -> TRUE
D68: SBT NOTICIAS 1A ED | E68: SEG-SEX | F68: 0.45833333 | G68: 15:00 | H68: 30 | AM68: 1 | AT68: 1 | BA68: 1 | BP68: =SUM(I68:BO68) -> 3 | BQ68: 73583 | BR68: 0.75 | BS68: =BQ68*(1-BR68) -> 18395.75 | BT68: =BS68*BP68 -> 55187.25 | BU68: =BT68*0.8 -> 44149.8 | BW68: 1.17 | BX68: =BW68*BP68 -> 3.51 | BY68: =IFERROR(BU68/BX68,0) -> 12578.291 | CA68: SBT | CB68: =COUNTA(I68:AM68) -> 1 | CC68: =CB68*BS68*0.8 -> 14716.6 | CD68: =COUNTA(AN68:BO68) -> 2 | CE68: =CD68*BS68*0.8 -> 29433.2 | CF68: =SUM(CC68,CE68)=BU68 -> TRUE
D69: SBT NOTICIAS 1A ED | E69: SEG-SEX | F69: 0.45833333 | G69: 15:00 | H69: 60 | AF69: 1 | BP69: =SUM(I69:BO69) -> 1 | BQ69: 147166 | BR69: 0.75 | BS69: =BQ69*(1-BR69) -> 36791.5 | BT69: =BS69*BP69 -> 36791.5 | BU69: =BT69*0.8 -> 29433.2 | BW69: 1.17 | BX69: =BW69*BP69 -> 1.17 | BY69: =IFERROR(BU69/BX69,0) -> 25156.581 | CA69: SBT | CB69: =COUNTA(I69:AM69) -> 1 | CC69: =CB69*BS69*0.8 -> 29433.2 | CD69: =COUNTA(AN69:BO69) -> 0 | CE69: =CD69*BS69*0.8 -> 0 | CF69: =SUM(CC69,CE69)=BU69 -> TRUE
CA70: TT | CB70: =SUM(CB58:CB69) -> 11 | CC70: =SUM(CC58:CC69) -> 408513.2 | CD70: =SUM(CD58:CD69) -> 17 | CE70: =SUM(CE58:CE69) -> 458611.2
B72: TT OPEN TV | I72: =COUNTA(I12:I22) -> 0 | J72: =COUNTA(J12:J22) -> 0 | K72: =COUNTA(K12:K22) -> 0 | L72: =COUNTA(L12:L22) -> 0 | M72: =COUNTA(M12:M22) -> 0 | N72: =SUM(N12:N22) -> 0 | O72: =SUM(O12:O22) -> 0 | P72: =SUM(P12:P22) -> 0 | Q72: =SUM(Q12:Q70) -> 0 | R72: =SUM(R12:R70) -> 0 | S72: =SUM(S12:S70) -> 0 | T72: =SUM(T12:T70) -> 0 | U72: =SUM(U12:U70) -> 0 | V72: =SUM(V12:V70) -> 0 | W72: =SUM(W12:W70) -> 0 | X72: =SUM(X12:X70) -> 0 | ... BJ72: =SUM(BJ12:BJ70) -> 0 | BK72: =SUM(BK13:BK71) -> 0 | BL72: =SUM(BL13:BL71) -> 0 | BM72: =SUM(BM12:BM22) -> 0 | BN72: =SUM(BN12:BN22) -> 0 | BO72: =SUM(BO12:BO22) -> 0 | BP72: =SUM(BP13:BP70) -> 95 | BT72: =SUM(BT13:BT70) -> 6911592.2 | BU72: =SUM(BU13:BU70) -> 5529273.8 | BX72: =SUM(BX12:BX70) -> 354.22 | BY72: =BU72/BX72 -> 15609.716 | CA72: TT GERAL | CB72: =CB32+CB44+CB57+CB70 -> 43 | CC72: =CC32+CC44+CC57+CC70 -> 3573083.5 | CD72: =CD32+CD44+CD57+CD70 -> 52 | CE72: =CE32+CE44+CE57+CE70 -> 1956190.2
BT73: UTILIZAÇÃO DE PACOTE | BU73: =SUM(BU58:BU69) -> 867124.4
BT74: TOTAL FATURÁVEL | BU74: =BU72-BU73 -> 4662149.4 | BW74: TARGET AS ABCDE 25+ (32MM) | BY74: SPE: | CD74: TT | CE74: =CC72+CE72 -> 5529273.8
BW75: COBERTURA | BX75: 0.52 | BY75: 32157000 | CE75: =CE74=BU72 -> TRUE
BW76: ALCANCE | BX76: =BY75*BX75 -> 16721640
BW77: FREQUÊNCIA | BX77: 4.1
BW78: IMPACTOS | BX78: =BY75*BX72% -> 1.1390653e+08
BW79: CPM | BX79: =BU72/BX78*1000 -> 48.542204

Sheet TV ABERTA - COLCHÃO REP - SP1
B5: CLIENT: SABESP
B6: CAMPAING: ESCASSEZ HIDRICA - CRÍTICO
BW7: PLANNED
B8: MARKET | C8: CHANNEL | D8: PROGRAMM | E8: DAY | F8: START TIME | G8: END TIME | H8: SEC | I8: JANEIRO | BP8: INS. | BQ8: CUSTO TABELA UNITÁRIO (BRUTO) | BR8: DESC. % | BS8: CUSTO NEGOCIADO UNITÁRIO (BRUTO) | BT8: CUSTO TOTAL NEGOCIADO (BRUTO) | BU8: CUSTO TOTAL DESEMBOLSO SABESP | BW8: AUD. AS ABCDE 25+ | BX8: TRP | BY8: CPP | CA8: RESUMO
I9: T | J9: F | K9: S | L9: S | M9: M | N9: T | O9: W | P9: T | Q9: F | R9: S | S9: S | T9: M | U9: T | V9: W | W9: T | X9: F | Y9: S | Z9: S | AA9: M | AB9: T | AC9: W | AD9: T | AE9: F | AF9: S | AG9: S | AH9: M | AI9: T | AJ9: W | AK9: T | AL9: F | AM9: S | AN9: S | AO9: M | AP9: T | AQ9: W | AR9: T | AS9: F | AT9: S | AU9: S | AV9: M | AW9: T | AX9: W | AY9: T | AZ9: F | BA9: S | BB9: S | BC9: M | BD9: T | BE9: W | BF9: T | BG9: F | BH9: S | BI9: S | BJ9: M | BK9: T | BL9: W | BM9: T | BN9: F | BO9: S
I10: 1 | J10: 2 | K10: 3 | L10: 4 | M10: 5 | N10: 6 | O10: 7 | P10: 8 | Q10: 9 | R10: 10 | S10: 11 | T10: 12 | U10: 13 | V10: 14 | W10: 15 | X10: 16 | Y10: 17 | Z10: =Y10+1 -> 18 | AA10: =Z10+1 -> 19 | AB10: =AA10+1 -> 20 | AC10: =AB10+1 -> 21 | AD10: =AC10+1 -> 22 | AE10: =AD10+1 -> 23 | AF10: =AE10+1 -> 24 | AG10: =AF10+1 -> 25 | ... AM10: =AL10+1 -> 31 | AN10: 1 | AO10: 2 | AP10: 3 | AQ10: 4 | AR10: 5 | AS10: 6 | AT10: 7 | AU10: 8 | AV10: 9 | AW10: 10 | AX10: 11 | AY10: 12 | AZ10: 13 | BA10: 14 | BB10: 15 | BC10: 16 | BD10: 17 | BE10: =BD10+1 -> 18 | BF10: =BE10+1 -> 19 | BG10: =BF10+1 -> 20 | BH10: =BG10+1 -> 21 | BI10: =BH10+1 -> 22 | BJ10: =BI10+1 -> 23 | BK10: =BJ10+1 -> 24 | BL10: =BK10+1 -> 25 | ... BO10: =BN10+1 -> 28 | CA10: CHANNEL | CB10: JANEIRO | CD10: FEVEREIRO
CB12: INS | CC12: INVESTIMENTO $ | CD12: INS | CE12: INVESTIMENTO $
B13: SÃO PAULO CAPITAL | C13: TV GLOBO | D13: PRACA TV 1 EDICAO | E13: SEG-SEX | F13: 0.48958333 | G13: 13:00 | H13: 30 | AH13: 1 | AJ13: 1 | AL13: 1 | AP13: 1 | AR13: 1 | AV13: 1 | AX13: 1 | AZ13: 1 | BP13: =SUM(I13:BO13) -> 8 | BQ13: 27572 | BR13: 0.1 | BS13: =BQ13*(1-BR13) -> 24814.8 | BT13: =BS13*BP13 -> 198518.4 | BU13: =BT13*0.8 -> 158814.72 | BW13: 5.24 | BX13: =BW13*BP13 -> 41.92 | BY13: =IFERROR(BU13/BX13,0) -> 3788.5191 | CA13: TV GLOBO | CB13: =COUNTA(I13:AM13) -> 3 | CC13: =CB13*BS13*0.8 -> 59555.52 | CD13: =COUNTA(AN13:BO13) -> 5 | CE13: =CD13*BS13*0.8 -> 99259.2 | CF13: =SUM(CC13,CE13)=BU13 -> TRUE
E14: SEG-SEX | F14: 0.48958333 | G14: 13:00 | H14: 60 | AE14: 1 | BP14: =SUM(I14:BO14) -> 1 | BQ14: 55144 | BR14: 0.1 | BS14: =BQ14*(1-BR14) -> 49629.6 | BT14: =BS14*BP14 -> 49629.6 | BU14: =BT14*0.8 -> 39703.68 | BW14: 5.24 | BX14: =BW14*BP14 -> 5.24 | BY14: =IFERROR(BU14/BX14,0) -> 7577.0382 | CA14: TV GLOBO | CB14: =COUNTA(I14:AM14) -> 1 | CC14: =CB14*BS14*0.8 -> 39703.68 | CD14: =COUNTA(AN14:BO14) -> 0 | CE14: =CD14*BS14*0.8 -> 0 | CF14: =SUM(CC14,CE14)=BU14 -> TRUE
D15: PRACA TV 2 EDICAO | E15: SEG-SEX | F15: 0.79861111 | G15: 19:40 | H15: 30 | AK15: 1 | AO15: 1 | AS15: 1 | AY15: 1 | BP15: =SUM(I15:BO15) -> 4 | BQ15: 112324 | BR15: 0.1 | BS15: =BQ15*(1-BR15) -> 101091.6 | BT15: =BS15*BP15 -> 404366.4 | BU15: =BT15*0.8 -> 323493.12 | BW15: 12.39 | BX15: =BW15*BP15 -> 49.56 | BY15: =IFERROR(BU15/BX15,0) -> 6527.3027 | CA15: TV GLOBO | CB15: =COUNTA(I15:AM15) -> 1 | CC15: =CB15*BS15*0.8 -> 80873.28 | CD15: =COUNTA(AN15:BO15) -> 3 | CE15: =CD15*BS15*0.8 -> 242619.84 | CF15: =SUM(CC15,CE15)=BU15 -> TRUE
E16: SEG-SEX | F16: 0.79861111 | G16: 19:40 | H16: 60 | AD16: 1 | BP16: =SUM(I16:BO16) -> 1 | BQ16: 224648 | BR16: 0.1 | BS16: =BQ16*(1-BR16) -> 202183.2 | BT16: =BS16*BP16 -> 202183.2 | BU16: =BT16*0.8 -> 161746.56 | BW16: 12.39 | BX16: =BW16*BP16 -> 12.39 | BY16: =IFERROR(BU16/BX16,0) -> 13054.605 | CA16: TV GLOBO | CB16: =COUNTA(I16:AM16) -> 1 | CC16: =CB16*BS16*0.8 -> 161746.56 | CD16: =COUNTA(AN16:BO16) -> 0 | CE16: =CD16*BS16*0.8 -> 0 | CF16: =SUM(CC16,CE16)=BU16 -> TRUE
CA17: TT | CB17: =SUM(CB13:CB16) -> 6 | CC17: =SUM(CC13:CC16) -> 341879.04 | CD17: =SUM(CD13:CD16) -> 8 | CE17: =SUM(CE13:CE16) -> 341879.04
C18: BANDEIRANTES | D18: JORNAL DA BAND | E18: SEG-SEX | F18: 0.80555556 | G18: 20:30 | H18: 30 | AI18: 1 | AK18: 1 | AP18: 1 | AR18: 1 | AW18: 1 | AY18: 1 | BP18: =SUM(I18:BO18) -> 6 | BQ18: 107608 | BR18: 0.85 | BS18: =BQ18*(1-BR18) -> 16141.2 | BT18: =BS18*BP18 -> 96847.2 | BU18: =BT18*0.8 -> 77477.76 | BW18: 1.59 | BX18: =BW18*BP18 -> 9.54 | BY18: =IFERROR(BU18/BX18,0) -> 8121.3585 | CA18: BANDEIRANTES | CB18: =COUNTA(I18:AM18) -> 2 | CC18: =CB18*BS18*0.8 -> 25825.92 | CD18: =COUNTA(AN18:BO18) -> 4 | CE18: =CD18*BS18*0.8 -> 51651.84 | CF18: =SUM(CC18,CE18)=BU18 -> TRUE
E19: SEG-SEX | F19: 0.80555556 | G19: 20:30 | H19: 60 | AD19: 1 | BP19: =SUM(I19:BO19) -> 1 | BQ19: 215216 | BR19: 0.85 | BS19: =BQ19*(1-BR19) -> 32282.4 | BT19: =BS19*BP19 -> 32282.4 | BU19: =BT19*0.8 -> 25825.92 | BW19: 1.59 | BX19: =BW19*BP19 -> 1.59 | BY19: =IFERROR(BU19/BX19,0) -> 16242.717 | CA19: BANDEIRANTES | CB19: =COUNTA(I19:AM19) -> 1 | CC19: =CB19*BS19*0.8 -> 25825.92 | CD19: =COUNTA(AN19:BO19) -> 0 | CE19: =CD19*BS19*0.8 -> 0 | CF19: =SUM(CC19,CE19)=BU19 -> TRUE
CA20: TT | CB20: =SUM(CB18:CB19) -> 3 | CC20: =SUM(CC18:CC19) -> 51651.84 | CD20: =SUM(CD18:CD19) -> 4 | CE20: =SUM(CE18:CE19) -> 51651.84
C21: RECORD | D21: JORNAL DA RECORD | E21: SEG-SEX | F21: 0.82986111 | G21: 21:00 | H21: 30 | AJ21: 1 | AL21: 1 | AQ21: 1 | AS21: 1 | AX21: 1 | AZ21: 1 | BP21: =SUM(I21:BO21) -> 6 | BQ21: 335107 | BR21: 0.8 | BS21: =BQ21*(1-BR21) -> 67021.4 | BT21: =BS21*BP21 -> 402128.4 | BU21: =BT21*0.8 -> 321702.72 | BW21: 3.53 | BX21: =BW21*BP21 -> 21.18 | BY21: =IFERROR(BU21/BX21,0) -> 15188.986 | CA21: RECORD | CB21: =COUNTA(I21:AM21) -> 2 | CC21: =CB21*BS21*0.8 -> 107234.24 | CD21: =COUNTA(AN21:BO21) -> 4 | CE21: =CD21*BS21*0.8 -> 214468.48 | CF21: =SUM(CC21,CE21)=BU21 -> TRUE
E22: SEG-SEX | F22: 0.82986111 | G22: 21:00 | H22: 60 | AE22: 1 | BP22: =SUM(I22:BO22) -> 1 | BQ22: 670214 | BR22: 0.8 | BS22: =BQ22*(1-BR22) -> 134042.8 | BT22: =BS22*BP22 -> 134042.8 | BU22: =BT22*0.8 -> 107234.24 | BW22: 3.53 | BX22: =BW22*BP22 -> 3.53 | BY22: =IFERROR(BU22/BX22,0) -> 30377.972 | CA22: RECORD | CB22: =COUNTA(I22:AM22) -> 1 | CC22: =CB22*BS22*0.8 -> 107234.24 | CD22: =COUNTA(AN22:BO22) -> 0 | CE22: =CD22*BS22*0.8 -> 0 | CF22: =SUM(CC22,CE22)=BU22 -> TRUE
CA23: TT | CB23: =SUM(CB21:CB22) -> 3 | CC23: =SUM(CC21:CC22) -> 214468.48 | CD23: =SUM(CD21:CD22) -> 4 | CE23: =SUM(CE21:CE22) -> 214468.48
C24: SBT | D24: SBT BRASIL | E24: SEG-SEX | F24: 0.82291667 | G24: 21:00 | H24: 30 | AI24: 1 | AK24: 1 | AP24: 1 | AR24: 1 | AW24: 1 | AY24: 1 | BP24: =SUM(I24:BO24) -> 6 | BQ24: 155300 | BR24: 0.75 | BS24: =BQ24*(1-BR24) -> 38825 | BT24: =BS24*BP24 -> 232950 | BU24: =BT24*0.8 -> 186360 | BW24: 1.91 | BX24: =BW24*BP24 -> 11.46 | BY24: =IFERROR(BU24/BX24,0) -> 16261.78 | CA24: SBT | CB24: =COUNTA(I24:AM24) -> 2 | CC24: =CB24*BS24*0.8 -> 62120 | CD24: =COUNTA(AN24:BO24) -> 4 | CE24: =CD24*BS24*0.8 -> 124240 | CF24: =SUM(CC24,CE24)=BU24 -> TRUE
CA25: TT | CB25: =SUM(CB24) -> 2 | CC25: =SUM(CC24) -> 62120 | CD25: =SUM(CD24) -> 4 | CE25: =SUM(CE24) -> 124240
C26: REDE TV | D26: REDETV! NEWS | E26: SEG-SEX | F26: 0.82986111 | G26: 20:30 | H26: 30 | AI26: 1 | AL26: 1 | AP26: 1 | AS26: 1 | AW26: 1 | AZ26: 1 | BP26: =SUM(I26:BO26) -> 6 | BQ26: 83652 | BR26: 0.85 | BS26: =BQ26*(1-BR26) -> 12547.8 | BT26: =BS26*BP26 -> 75286.8 | BU26: =BT26*0.8 -> 60229.44 | BW26: 0.14 | BX26: =BW26*BP26 -> 0.84 | BY26: =IFERROR(BU26/BX26,0) -> 71701.714 | CA26: REDE TV | CB26: =COUNTA(I26:AM26) -> 2 | CC26: =CB26*BS26*0.8 -> 20076.48 | CD26: =COUNTA(AN26:BO26) -> 4 | CE26: =CD26*BS26*0.8 -> 40152.96 | CF26: =SUM(CC26,CE26)=BU26 -> TRUE
E27: SEG-SEX | F27: 0.82986111 | G27: 20:30 | H27: 60 | AE27: 1 | BP27: =SUM(I27:BO27) -> 1 | BQ27: 167304 | BR27: 0.85 | BS27: =BQ27*(1-BR27) -> 25095.6 | BT27: =BS27*BP27 -> 25095.6 | BU27: =BT27*0.8 -> 20076.48 | BW27: 0.14 | BX27: =BW27*BP27 -> 0.14 | BY27: =IFERROR(BU27/BX27,0) -> 143403.43 | CA27: REDE TV | CB27: =COUNTA(I27:AM27) -> 1 | CC27: =CB27*BS27*0.8 -> 20076.48 | CD27: =COUNTA(AN27:BO27) -> 0 | CE27: =CD27*BS27*0.8 -> 0 | CF27: =SUM(CC27,CE27)=BU27 -> TRUE
CA28: TT | CB28: =SUM(CB26:CB27) -> 3 | CC28: =SUM(CC26:CC27) -> 40152.96 | CD28: =SUM(CD26:CD27) -> 4 | CE28: =SUM(CE26:CE27) -> 40152.96
B30: TT OPEN TV | I30: =COUNTA(I12:I16) -> 0 | J30: =COUNTA(J12:J16) -> 0 | K30: =COUNTA(K12:K16) -> 0 | L30: =COUNTA(L12:L16) -> 0 | M30: =COUNTA(M12:M16) -> 0 | N30: =SUM(N12:N16) -> 0 | O30: =SUM(O12:O16) -> 0 | P30: =SUM(P12:P16) -> 0 | Q30: =SUM(Q12:Q28) -> 0 | R30: =SUM(R12:R28) -> 0 | S30: =SUM(S12:S28) -> 0 | T30: =SUM(T12:T28) -> 0 | U30: =SUM(U12:U28) -> 0 | V30: =SUM(V12:V28) -> 0 | W30: =SUM(W12:W28) -> 0 | X30: =SUM(X12:X28) -> 0 | ... BJ30: =SUM(BJ12:BJ28) -> 0 | BK30: =SUM(BK13:BK29) -> 0 | BL30: =SUM(BL13:BL29) -> 0 | BM30: =SUM(BM12:BM16) -> 0 | BN30: =SUM(BN12:BN16) -> 0 | BO30: =SUM(BO12:BO16) -> 0 | BP30: =SUM(BP13:BP28) -> 41 | BT30: =SUM(BT13:BT28) -> 1853330.8 | BU30: =SUM(BU13:BU28) -> 1482664.6 | BX30: =SUM(BX13:BX27) -> 157.39 | BY30: =BU30/BX30 -> 9420.323 | CA30: TT GERAL | CB30: =CB17+CB20+CB23+CB28+CB25 -> 17 | CC30: =CC17+CC20+CC23+CC28+CC25 -> 710272.32 | CD30: =CD17+CD20+CD23+CD28+CD25 -> 24 | CE30: =CE17+CE20+CE23+CE28+CE25 -> 772392.32
BT31: UTILIZAÇÃO DE PACOTE | BU31: =SUM(BU24:BU27) -> 266665.92
BT32: TOTAL FATURÁVEL | BU32: =BU30-BU31 -> 1215998.7 | CD32: TT | CE32: =CC30+CE30 -> 1482664.6
CE33: =CE32=BU30 -> TRUE

Sheet TV ABERTA - COLCHÃO REP - SPE
B5: CLIENT: SABESP
B6: CAMPAING: ESCASSEZ HIDRICA - CRÍTICO
BW7: PLANNED
B8: MARKET | C8: CHANNEL | D8: PROGRAMM | E8: DAY | F8: START TIME | G8: END TIME | H8: SEC | I8: JANEIRO | BP8: INS. | BQ8: CUSTO TABELA UNITÁRIO (BRUTO) | BR8: DESC. % | BS8: CUSTO NEGOCIADO UNITÁRIO (BRUTO) | BT8: CUSTO TOTAL NEGOCIADO (BRUTO) | BU8: CUSTO TOTAL DESEMBOLSO SABESP | BW8: AUD. AS ABCDE 25+ | BX8: TRP | BY8: CPP | CA8: RESUMO
I9: T | J9: F | K9: S | L9: S | M9: M | N9: T | O9: W | P9: T | Q9: F | R9: S | S9: S | T9: M | U9: T | V9: W | W9: T | X9: F | Y9: S | Z9: S | AA9: M | AB9: T | AC9: W | AD9: T | AE9: F | AF9: S | AG9: S | AH9: M | AI9: T | AJ9: W | AK9: T | AL9: F | AM9: S | AN9: S | AO9: M | AP9: T | AQ9: W | AR9: T | AS9: F | AT9: S | AU9: S | AV9: M | AW9: T | AX9: W | AY9: T | AZ9: F | BA9: S | BB9: S | BC9: M | BD9: T | BE9: W | BF9: T | BG9: F | BH9: S | BI9: S | BJ9: M | BK9: T | BL9: W | BM9: T | BN9: F | BO9: S
I10: 1 | J10: 2 | K10: 3 | L10: 4 | M10: 5 | N10: 6 | O10: 7 | P10: 8 | Q10: 9 | R10: 10 | S10: 11 | T10: 12 | U10: 13 | V10: 14 | W10: 15 | X10: 16 | Y10: 17 | Z10: =Y10+1 -> 18 | AA10: =Z10+1 -> 19 | AB10: =AA10+1 -> 20 | AC10: =AB10+1 -> 21 | AD10: =AC10+1 -> 22 | AE10: =AD10+1 -> 23 | AF10: =AE10+1 -> 24 | AG10: =AF10+1 -> 25 | ... AM10: =AL10+1 -> 31 | AN10: 1 | AO10: 2 | AP10: 3 | AQ10: 4 | AR10: 5 | AS10: 6 | AT10: 7 | AU10: 8 | AV10: 9 | AW10: 10 | AX10: 11 | AY10: 12 | AZ10: 13 | BA10: 14 | BB10: 15 | BC10: 16 | BD10: 17 | BE10: =BD10+1 -> 18 | BF10: =BE10+1 -> 19 | BG10: =BF10+1 -> 20 | BH10: =BG10+1 -> 21 | BI10: =BH10+1 -> 22 | BJ10: =BI10+1 -> 23 | BK10: =BJ10+1 -> 24 | BL10: =BK10+1 -> 25 | ... BO10: =BN10+1 -> 28 | CA10: CHANNEL | CB10: JANEIRO | CD10: FEVEREIRO
CB12: INS | CC12: INVESTIMENTO $ | CD12: INS | CE12: INVESTIMENTO $
B13: SÃO PAULO ESTADO | C13: TV GLOBO | D13: PRACA TV 1 EDICAO | E13: SEG-SEX | F13: 0.48958333 | G13: 13:00 | H13: 30 | AH13: 1 | AJ13: 1 | AL13: 1 | AP13: 1 | AR13: 1 | AV13: 1 | AX13: 1 | AZ13: 1 | BP13: =SUM(I13:BO13) -> 8 | BQ13: 64054 | BR13: 0.1 | BS13: =BQ13*(1-BR13) -> 57648.6 | BT13: =BS13*BP13 -> 461188.8 | BU13: =BT13*0.8 -> 368951.04 | BW13: 5.24 | BX13: =BW13*BP13 -> 41.92 | BY13: =IFERROR(BU13/BX13,0) -> 8801.313 | CA13: TV GLOBO | CB13: =COUNTA(I13:AM13) -> 3 | CC13: =CB13*BS13*0.8 -> 138356.64 | CD13: =COUNTA(AN13:BO13) -> 5 | CE13: =CD13*BS13*0.8 -> 230594.4 | CF13: =SUM(CC13,CE13)=BU13 -> TRUE
E14: SEG-SEX | F14: 0.48958333 | G14: 13:00 | H14: 60 | AE14: 1 | BP14: =SUM(I14:BO14) -> 1 | BQ14: 128108 | BR14: 0.1 | BS14: =BQ14*(1-BR14) -> 115297.2 | BT14: =BS14*BP14 -> 115297.2 | BU14: =BT14*0.8 -> 92237.76 | BW14: 5.24 | BX14: =BW14*BP14 -> 5.24 | BY14: =IFERROR(BU14/BX14,0) -> 17602.626 | CA14: TV GLOBO | CB14: =COUNTA(I14:AM14) -> 1 | CC14: =CB14*BS14*0.8 -> 92237.76 | CD14: =COUNTA(AN14:BO14) -> 0 | CE14: =CD14*BS14*0.8 -> 0 | CF14: =SUM(CC14,CE14)=BU14 -> TRUE
D15: PRACA TV 2 EDICAO | E15: SEG-SEX | F15: 0.79861111 | G15: 19:40 | H15: 30 | AK15: 1 | AO15: 1 | AS15: 1 | AY15: 1 | BP15: =SUM(I15:BO15) -> 4 | BQ15: 200802 | BR15: 0.1 | BS15: =BQ15*(1-BR15) -> 180721.8 | BT15: =BS15*BP15 -> 722887.2 | BU15: =BT15*0.8 -> 578309.76 | BW15: 12.39 | BX15: =BW15*BP15 -> 49.56 | BY15: =IFERROR(BU15/BX15,0) -> 11668.881 | CA15: TV GLOBO | CB15: =COUNTA(I15:AM15) -> 1 | CC15: =CB15*BS15*0.8 -> 144577.44 | CD15: =COUNTA(AN15:BO15) -> 3 | CE15: =CD15*BS15*0.8 -> 433732.32 | CF15: =SUM(CC15,CE15)=BU15 -> TRUE
E16: SEG-SEX | F16: 0.79861111 | G16: 19:40 | H16: 60 | AD16: 1 | BP16: =SUM(I16:BO16) -> 1 | BQ16: 401604 | BR16: 0.1 | BS16: =BQ16*(1-BR16) -> 361443.6 | BT16: =BS16*BP16 -> 361443.6 | BU16: =BT16*0.8 -> 289154.88 | BW16: 12.39 | BX16: =BW16*BP16 -> 12.39 | BY16: =IFERROR(BU16/BX16,0) -> 23337.763 | CA16: TV GLOBO | CB16: =COUNTA(I16:AM16) -> 1 | CC16: =CB16*BS16*0.8 -> 289154.88 | CD16: =COUNTA(AN16:BO16) -> 0 | CE16: =CD16*BS16*0.8 -> 0 | CF16: =SUM(CC16,CE16)=BU16 -> TRUE
CA17: TT | CB17: =SUM(CB13:CB16) -> 6 | CC17: =SUM(CC13:CC16) -> 664326.72 | CD17: =SUM(CD13:CD16) -> 8 | CE17: =SUM(CE13:CE16) -> 664326.72
C18: BANDEIRANTES | D18: JORNAL DA BAND | E18: SEG-SEX | F18: 0.80555556 | G18: 20:30 | H18: 30 | AI18: 1 | AK18: 1 | AP18: 1 | AR18: 1 | AW18: 1 | AY18: 1 | BP18: =SUM(I18:BO18) -> 6 | BQ18: 190834 | BR18: 0.85 | BS18: =BQ18*(1-BR18) -> 28625.1 | BT18: =BS18*BP18 -> 171750.6 | BU18: =BT18*0.8 -> 137400.48 | BW18: 1.59 | BX18: =BW18*BP18 -> 9.54 | BY18: =IFERROR(BU18/BX18,0) -> 14402.566 | CA18: BANDEIRANTES | CB18: =COUNTA(I18:AM18) -> 2 | CC18: =CB18*BS18*0.8 -> 45800.16 | CD18: =COUNTA(AN18:BO18) -> 4 | CE18: =CD18*BS18*0.8 -> 91600.32 | CF18: =SUM(CC18,CE18)=BU18 -> TRUE
E19: SEG-SEX | F19: 0.80555556 | G19: 20:30 | H19: 60 | AD19: 1 | BP19: =SUM(I19:BO19) -> 1 | BQ19: 381668 | BR19: 0.85 | BS19: =BQ19*(1-BR19) -> 57250.2 | BT19: =BS19*BP19 -> 57250.2 | BU19: =BT19*0.8 -> 45800.16 | BW19: 1.59 | BX19: =BW19*BP19 -> 1.59 | BY19: =IFERROR(BU19/BX19,0) -> 28805.132 | CA19: BANDEIRANTES | CB19: =COUNTA(I19:AM19) -> 1 | CC19: =CB19*BS19*0.8 -> 45800.16 | CD19: =COUNTA(AN19:BO19) -> 0 | CE19: =CD19*BS19*0.8 -> 0 | CF19: =SUM(CC19,CE19)=BU19 -> TRUE
CA20: TT | CB20: =SUM(CB18:CB19) -> 3 | CC20: =SUM(CC18:CC19) -> 91600.32 | CD20: =SUM(CD18:CD19) -> 4 | CE20: =SUM(CE18:CE19) -> 91600.32
C21: RECORD | D21: JORNAL DA RECORD | E21: SEG-SEX | F21: 0.82986111 | G21: 21:00 | H21: 30 | AJ21: 1 | AL21: 1 | AQ21: 1 | AS21: 1 | AX21: 1 | AZ21: 1 | BP21: =SUM(I21:BO21) -> 6 | BQ21: 405550 | BR21: 0.8 | BS21: =BQ21*(1-BR21) -> 81110 | BT21: =BS21*BP21 -> 486660 | BU21: =BT21*0.8 -> 389328 | BW21: 3.53 | BX21: =BW21*BP21 -> 21.18 | BY21: =IFERROR(BU21/BX21,0) -> 18381.87 | CA21: RECORD | CB21: =COUNTA(I21:AM21) -> 2 | CC21: =CB21*BS21*0.8 -> 129776 | CD21: =COUNTA(AN21:BO21) -> 4 | CE21: =CD21*BS21*0.8 -> 259552 | CF21: =SUM(CC21,CE21)=BU21 -> TRUE
E22: SEG-SEX | F22: 0.82986111 | G22: 21:00 | H22: 60 | AE22: 1 | BP22: =SUM(I22:BO22) -> 1 | BQ22: 811100 | BR22: 0.8 | BS22: =BQ22*(1-BR22) -> 162220 | BT22: =BS22*BP22 -> 162220 | BU22: =BT22*0.8 -> 129776 | BW22: 3.53 | BX22: =BW22*BP22 -> 3.53 | BY22: =IFERROR(BU22/BX22,0) -> 36763.739 | CA22: RECORD | CB22: =COUNTA(I22:AM22) -> 1 | CC22: =CB22*BS22*0.8 -> 129776 | CD22: =COUNTA(AN22:BO22) -> 0 | CE22: =CD22*BS22*0.8 -> 0 | CF22: =SUM(CC22,CE22)=BU22 -> TRUE
CA23: TT | CB23: =SUM(CB21:CB22) -> 3 | CC23: =SUM(CC21:CC22) -> 259552 | CD23: =SUM(CD21:CD22) -> 4 | CE23: =SUM(CE21:CE22) -> 259552
C24: SBT | D24: SBT BRASIL | E24: SEG-SEX | F24: 0.82291667 | G24: 21:00 | H24: 30 | AI24: 1 | AK24: 1 | AP24: 1 | AR24: 1 | AW24: 1 | AY24: 1 | BP24: =SUM(I24:BO24) -> 6 | BQ24: 201971 | BR24: 0.75 | BS24: =BQ24*(1-BR24) -> 50492.75 | BT24: =BS24*BP24 -> 302956.5 | BU24: =BT24*0.8 -> 242365.2 | BW24: 1.91 | BX24: =BW24*BP24 -> 11.46 | BY24: =IFERROR(BU24/BX24,0) -> 21148.796 | CA24: SBT | CB24: =COUNTA(I24:AM24) -> 2 | CC24: =CB24*BS24*0.8 -> 80788.4 | CD24: =COUNTA(AN24:BO24) -> 4 | CE24: =CD24*BS24*0.8 -> 161576.8 | CF24: =SUM(CC24,CE24)=BU24 -> TRUE
CA25: TT | CB25: =SUM(CB24) -> 2 | CC25: =SUM(CC24) -> 80788.4 | CD25: =SUM(CD24) -> 4 | CE25: =SUM(CE24) -> 161576.8
B27: TT OPEN TV | I27: =COUNTA(I12:I16) -> 0 | J27: =COUNTA(J12:J16) -> 0 | K27: =COUNTA(K12:K16) -> 0 | L27: =COUNTA(L12:L16) -> 0 | M27: =COUNTA(M12:M16) -> 0 | N27: =SUM(N12:N16) -> 0 | O27: =SUM(O12:O16) -> 0 | P27: =SUM(P12:P16) -> 0 | Q27: =SUM(Q12:Q25) -> 0 | R27: =SUM(R12:R25) -> 0 | S27: =SUM(S12:S25) -> 0 | T27: =SUM(T12:T25) -> 0 | U27: =SUM(U12:U25) -> 0 | V27: =SUM(V12:V25) -> 0 | W27: =SUM(W12:W25) -> 0 | X27: =SUM(X12:X25) -> 0 | ... BJ27: =SUM(BJ12:BJ25) -> 0 | BK27: =SUM(BK13:BK26) -> 0 | BL27: =SUM(BL13:BL26) -> 0 | BM27: =SUM(BM12:BM16) -> 0 | BN27: =SUM(BN12:BN16) -> 0 | BO27: =SUM(BO12:BO16) -> 0 | BP27: =SUM(BP13:BP25) -> 34 | BT27: =SUM(BT13:BT25) -> 2841654.1 | BU27: =SUM(BU13:BU25) -> 2273323.3 | BX27: =SUM(BX13:BX25) -> 156.41 | BY27: =BU27/BX27 -> 14534.386 | CA27: TT GERAL | CB27: =CB17+CB20+CB23+CB25 -> 14 | CC27: =CC17+CC20+CC23+CC25 -> 1096267.4 | CD27: =CD17+CD20+CD23+CD25 -> 20 | CE27: =CE17+CE20+CE23+CE25 -> 1177055.8
BT28: UTILIZAÇÃO DE PACOTE | BU28: =SUM(BU24:BU24) -> 242365.2
BT29: TOTAL FATURÁVEL | BU29: =BU27-BU28 -> 2030958.1 | CD29: TT | CE29: =CC27+CE27 -> 2273323.3
CE30: =CE29=BU27 -> TRUE

Sheet TV PAGA - COLCHÃO REP - SP1
B5: CLIENT: SABESP
B6: CAMPAING: ESCASSEZ HIDRICA - CRÍTICO
BW7: PLANNED
B8: MARKET | C8: CHANNEL | D8: PROGRAMM | E8: DAY | F8: START TIME | G8: END TIME | H8: SEC | I8: JANEIRO | BP8: INS. | BQ8: CUSTO TABELA UNITÁRIO (BRUTO) | BR8: DESC. % | BS8: CUSTO NEGOCIADO UNITÁRIO (BRUTO) | BT8: CUSTO TOTAL NEGOCIADO (BRUTO) | BU8: CUSTO TOTAL DESEMBOLSO SABESP | BW8: AUD. AS ABCDE 25+ | BX8: TRP | BY8: CPP | CA8: RESUMO
I9: T | J9: F | K9: S | L9: S | M9: M | N9: T | O9: W | P9: T | Q9: F | R9: S | S9: S | T9: M | U9: T | V9: W | W9: T | X9: F | Y9: S | Z9: S | AA9: M | AB9: T | AC9: W | AD9: T | AE9: F | AF9: S | AG9: S | AH9: M | AI9: T | AJ9: W | AK9: T | AL9: F | AM9: S | AN9: S | AO9: M | AP9: T | AQ9: W | AR9: T | AS9: F | AT9: S | AU9: S | AV9: M | AW9: T | AX9: W | AY9: T | AZ9: F | BA9: S | BB9: S | BC9: M | BD9: T | BE9: W | BF9: T | BG9: F | BH9: S | BI9: S | BJ9: M | BK9: T | BL9: W | BM9: T | BN9: F | BO9: S
I10: 1 | J10: 2 | K10: 3 | L10: 4 | M10: 5 | N10: 6 | O10: 7 | P10: 8 | Q10: 9 | R10: 10 | S10: 11 | T10: 12 | U10: 13 | V10: 14 | W10: 15 | X10: 16 | Y10: 17 | Z10: =Y10+1 -> 18 | AA10: =Z10+1 -> 19 | AB10: =AA10+1 -> 20 | AC10: =AB10+1 -> 21 | AD10: =AC10+1 -> 22 | AE10: =AD10+1 -> 23 | AF10: =AE10+1 -> 24 | AG10: =AF10+1 -> 25 | ... AM10: =AL10+1 -> 31 | AN10: 1 | AO10: 2 | AP10: 3 | AQ10: 4 | AR10: 5 | AS10: 6 | AT10: 7 | AU10: 8 | AV10: 9 | AW10: 10 | AX10: 11 | AY10: 12 | AZ10: 13 | BA10: 14 | BB10: 15 | BC10: 16 | BD10: 17 | BE10: =BD10+1 -> 18 | BF10: =BE10+1 -> 19 | BG10: =BF10+1 -> 20 | BH10: =BG10+1 -> 21 | BI10: =BH10+1 -> 22 | BJ10: =BI10+1 -> 23 | BK10: =BJ10+1 -> 24 | BL10: =BK10+1 -> 25 | ... BO10: =BN10+1 -> 28 | CA10: CHANNEL | CB10: JANEIRO | CD10: FEVEREIRO
CB12: INS | CC12: INVESTIMENTO $ | CD12: INS | CE12: INVESTIMENTO $
B13: SÃO PAULO CAPITAL | C13: GLOBONEWS | D13: GLOBO NEWS EM PAUTA | E13: SEG-SEX | F13: 0.83333333 | G13: 22:00 | H13: 30 | AI13: 1 | AK13: 1 | AO13: 1 | AR13: 1 | AV13: 1 | AX13: 1 | BP13: =SUM(I13:BO13) -> 6 | BQ13: 4180 | BR13: 0.4 | BS13: =BQ13*(1-BR13) -> 2508 | BT13: =BS13*BP13 -> 15048 | BU13: =BT13*0.8 -> 12038.4 | BW13: 0.05 | BX13: =BW13*BP13 -> 0.3 | BY13: =IFERROR(BU13/BX13,0) -> 40128 | CA13: GLOBONEWS | CB13: =COUNTA(I13:AM13) -> 2 | CC13: =CB13*BS13*0.8 -> 4012.8 | CD13: =COUNTA(AN13:BO13) -> 4 | CE13: =CD13*BS13*0.8 -> 8025.6 | CF13: =SUM(CC13,CE13)=BU13 -> TRUE
E14: SEG-SEX | F14: 0.83333333 | G14: 22:00 | H14: 60 | AE14: 1 | BP14: =SUM(I14:BO14) -> 1 | BQ14: 8360 | BR14: 0.4 | BS14: =BQ14*(1-BR14) -> 5016 | BT14: =BS14*BP14 -> 5016 | BU14: =BT14*0.8 -> 4012.8 | BW14: 0.05 | BX14: =BW14*BP14 -> 0.05 | BY14: =IFERROR(BU14/BX14,0) -> 80256 | CA14: GLOBONEWS | CB14: =COUNTA(I14:AM14) -> 1 | CC14: =CB14*BS14*0.8 -> 4012.8 | CD14: =COUNTA(AN14:BO14) -> 0 | CE14: =CD14*BS14*0.8 -> 0 | CF14: =SUM(CC14,CE14)=BU14 -> TRUE
D15: JORNAL DAS DEZ P | E15: SEG-SEX | F15: 0.91666667 | G15: 00:00 | H15: 30 | AH15: 1 | AJ15: 1 | AP15: 1 | AS15: 1 | AW15: 1 | AY15: 1 | BP15: =SUM(I15:BO15) -> 6 | BQ15: 5760 | BR15: 0.4 | BS15: =BQ15*(1-BR15) -> 3456 | BT15: =BS15*BP15 -> 20736 | BU15: =BT15*0.8 -> 16588.8 | BW15: 0.05 | BX15: =BW15*BP15 -> 0.3 | BY15: =IFERROR(BU15/BX15,0) -> 55296 | CA15: GLOBONEWS | CB15: =COUNTA(I15:AM15) -> 2 | CC15: =CB15*BS15*0.8 -> 5529.6 | CD15: =COUNTA(AN15:BO15) -> 4 | CE15: =CD15*BS15*0.8 -> 11059.2 | CF15: =SUM(CC15,CE15)=BU15 -> TRUE
E16: SEG-SEX | F16: 0.91666667 | G16: 00:00 | H16: 60 | AD16: 1 | BP16: =SUM(I16:BO16) -> 1 | BQ16: 11520 | BR16: 0.4 | BS16: =BQ16*(1-BR16) -> 6912 | BT16: =BS16*BP16 -> 6912 | BU16: =BT16*0.8 -> 5529.6 | BW16: 0.05 | BX16: =BW16*BP16 -> 0.05 | BY16: =IFERROR(BU16/BX16,0) -> 110592 | CA16: GLOBONEWS | CB16: =COUNTA(I16:AM16) -> 1 | CC16: =CB16*BS16*0.8 -> 5529.6 | CD16: =COUNTA(AN16:BO16) -> 0 | CE16: =CD16*BS16*0.8 -> 0 | CF16: =SUM(CC16,CE16)=BU16 -> TRUE
CA17: TT | CB17: =SUM(CB13:CB16) -> 6 | CC17: =SUM(CC13:CC16) -> 19084.8 | CD17: =SUM(CD13:CD16) -> 8 | CE17: =SUM(CE13:CE16) -> 19084.8
C18: CNN BRASIL | D18: CNN PRIME TIME P | E18: SEG-SEX | F18: 0.83333333 | G18: 22:00 | H18: 30 | AI18: 1 | AK18: 1 | AP18: 1 | AR18: 1 | AV18: 1 | AX18: 1 | BP18: =SUM(I18:BO18) -> 6 | BQ18: 11130 | BR18: 0.5 | BS18: =BQ18*(1-BR18) -> 5565 | BT18: =BS18*BP18 -> 33390 | BU18: =BT18*0.8 -> 26712 | BW18: 0.11 | BX18: =BW18*BP18 -> 0.66 | BY18: =IFERROR(BU18/BX18,0) -> 40472.727 | CA18: CNN BRASIL | CB18: =COUNTA(I18:AM18) -> 2 | CC18: =CB18*BS18*0.8 -> 8904 | CD18: =COUNTA(AN18:BO18) -> 4 | CE18: =CD18*BS18*0.8 -> 17808 | CF18: =SUM(CC18,CE18)=BU18 -> TRUE
E19: SEG-SEX | F19: 0.83333333 | G19: 22:00 | H19: 60 | AD19: 1 | BP19: =SUM(I19:BO19) -> 1 | BQ19: 22260 | BR19: 0.5 | BS19: =BQ19*(1-BR19) -> 11130 | BT19: =BS19*BP19 -> 11130 | BU19: =BT19*0.8 -> 8904 | BW19: 0.11 | BX19: =BW19*BP19 -> 0.11 | BY19: =IFERROR(BU19/BX19,0) -> 80945.455 | CA19: CNN BRASIL | CB19: =COUNTA(I19:AM19) -> 1 | CC19: =CB19*BS19*0.8 -> 8904 | CD19: =COUNTA(AN19:BO19) -> 0 | CE19: =CD19*BS19*0.8 -> 0 | CF19: =SUM(CC19,CE19)=BU19 -> TRUE
CA20: TT | CB20: =SUM(CB18:CB19) -> 3 | CC20: =SUM(CC18:CC19) -> 17808 | CD20: =SUM(CD18:CD19) -> 4 | CE20: =SUM(CE18:CE19) -> 17808
B21: SÃO PAULO ESTADO | C21: RECORD NEWS | D21: JORNAL RECORD NEWS | E21: SEG-SEX | F21: 0.875 | G21: 22:00 | H21: 30 | AI21: 1 | AL21: 1 | AR21: 1 | AS21: 1 | AW21: 1 | AZ21: 1 | BP21: =SUM(I21:BO21) -> 6 | BQ21: 22000 | BR21: 0.75 | BS21: =BQ21*(1-BR21) -> 5500 | BT21: =BS21*BP21 -> 33000 | BU21: =BT21*0.8 -> 26400 | BW21: 0.13 | BX21: =BW21*BP21 -> 0.78 | BY21: =IFERROR(BU21/BX21,0) -> 33846.154 | CA21: RECORD NEWS | CB21: =COUNTA(I21:AM21) -> 2 | CC21: =CB21*BS21*0.8 -> 8800 | CD21: =COUNTA(AN21:BO21) -> 4 | CE21: =CD21*BS21*0.8 -> 17600 | CF21: =SUM(CC21,CE21)=BU21 -> TRUE
E22: SEG-SEX | F22: 0.875 | G22: 22:00 | H22: 60 | AE22: 1 | BP22: =SUM(I22:BO22) -> 1 | BQ22: 44000 | BR22: 0.75 | BS22: =BQ22*(1-BR22) -> 11000 | BT22: =BS22*BP22 -> 11000 | BU22: =BT22*0.8 -> 8800 | BW22: 0.13 | BX22: =BW22*BP22 -> 0.13 | BY22: =IFERROR(BU22/BX22,0) -> 67692.308 | CA22: RECORD NEWS | CB22: =COUNTA(I22:AM22) -> 1 | CC22: =CB22*BS22*0.8 -> 8800 | CD22: =COUNTA(AN22:BO22) -> 0 | CE22: =CD22*BS22*0.8 -> 0 | CF22: =SUM(CC22,CE22)=BU22 -> TRUE
CA23: TT | CB23: =SUM(CB21:CB22) -> 3 | CC23: =SUM(CC21:CC22) -> 17600 | CD23: =SUM(CD21:CD22) -> 4 | CE23: =SUM(CE21:CE22) -> 17600
B24: SÃO PAULO CAPITAL | C24: BAND NEWS | D24: JOR BANDNEWS 2ED NOT | E24: SEG-SEX | F24: 0.8125 | G24: 0.85416667 | H24: 30 | AH24: 1 | AK24: 1 | AP24: 1 | AR24: 1 | AW24: 1 | AY24: 1 | BP24: =SUM(I24:BO24) -> 6 | BQ24: 9631 | BR24: 0.7 | BS24: =BQ24*(1-BR24) -> 2889.3 | BT24: =BS24*BP24 -> 17335.8 | BU24: =BT24*0.8 -> 13868.64 | BW24: 0.015 | BX24: =BW24*BP24 -> 0.09 | BY24: =IFERROR(BU24/BX24,0) -> 154096 | CA24: BAND NEWS | CB24: =COUNTA(I24:AM24) -> 2 | CC24: =CB24*BS24*0.8 -> 4622.88 | CD24: =COUNTA(AN24:BO24) -> 4 | CE24: =CD24*BS24*0.8 -> 9245.76 | CF24: =SUM(CC24,CE24)=BU24 -> TRUE
E25: SEG-SEX | F25: 0.8125 | G25: 0.85416667 | H25: 60 | AD25: 1 | BP25: =SUM(I25:BO25) -> 1 | BQ25: 19262 | BR25: 0.7 | BS25: =BQ25*(1-BR25) -> 5778.6 | BT25: =BS25*BP25 -> 5778.6 | BU25: =BT25*0.8 -> 4622.88 | BW25: 0.015 | BX25: =BW25*BP25 -> 0.015 | BY25: =IFERROR(BU25/BX25,0) -> 308192 | CA25: BAND NEWS | CB25: =COUNTA(I25:AM25) -> 1 | CC25: =CB25*BS25*0.8 -> 4622.88 | CD25: =COUNTA(AN25:BO25) -> 0 | CE25: =CD25*BS25*0.8 -> 0 | CF25: =SUM(CC25,CE25)=BU25 -> TRUE
CA26: TT | CB26: =SUM(CB24:CB25) -> 3 | CC26: =SUM(CC24:CC25) -> 9245.76 | CD26: =SUM(CD24:CD25) -> 4 | CE26: =SUM(CE24:CE25) -> 9245.76
B28: TT PAY TV | I28: =COUNTA(I12:I16) -> 0 | J28: =COUNTA(J12:J16) -> 0 | K28: =COUNTA(K12:K16) -> 0 | L28: =COUNTA(L12:L16) -> 0 | M28: =COUNTA(M12:M16) -> 0 | N28: =SUM(N12:N16) -> 0 | O28: =SUM(O12:O16) -> 0 | P28: =SUM(P12:P16) -> 0 | Q28: =SUM(Q12:Q26) -> 0 | R28: =SUM(R12:R26) -> 0 | S28: =SUM(S12:S26) -> 0 | T28: =SUM(T12:T26) -> 0 | U28: =SUM(U12:U26) -> 0 | V28: =SUM(V12:V26) -> 0 | W28: =SUM(W12:W26) -> 0 | X28: =SUM(X12:X26) -> 0 | ... BJ28: =SUM(BJ12:BJ26) -> 0 | BK28: =SUM(BK13:BK27) -> 0 | BL28: =SUM(BL13:BL27) -> 0 | BM28: =SUM(BM12:BM16) -> 0 | BN28: =SUM(BN12:BN16) -> 0 | BO28: =SUM(BO12:BO16) -> 0 | BP28: =SUM(BP13:BP26) -> 35 | BT28: =SUM(BT13:BT26) -> 159346.4 | BU28: =SUM(BU13:BU26) -> 127477.12 | BX28: =SUM(BX13:BX26) -> 2.485 | BY28: =BU28/BX28 -> 51298.64 | CA28: TT GERAL | CB28: =CB20+CB23+CB26 -> 9 | CC28: =CC17+CC20+CC23+CC26 -> 63738.56 | CD28: =CD20+CD23+CD26 -> 12 | CE28: =CE17+CE20+CE23+CE26 -> 63738.56
CD30: TT | CE30: =CC28+CE28 -> 127477.12
CE31: =CE30=BU28 -> TRUE

Sheet TV PAGA - COLCHÃO REP - SPE
B5: CLIENT: SABESP
B6: CAMPAING: ESCASSEZ HIDRICA - CRÍTICO
BW7: PLANNED
B8: MARKET | C8: CHANNEL | D8: PROGRAMM | E8: DAY | F8: START TIME | G8: END TIME | H8: SEC | I8: JANEIRO | BP8: INS. | BQ8: CUSTO TABELA UNITÁRIO (BRUTO) | BR8: DESC. % | BS8: CUSTO NEGOCIADO UNITÁRIO (BRUTO) | BT8: CUSTO TOTAL NEGOCIADO (BRUTO) | BU8: CUSTO TOTAL DESEMBOLSO SABESP | BW8: AUD. AS ABCDE 25+ | BX8: TRP | BY8: CPP | CA8: RESUMO
I9: T | J9: F | K9: S | L9: S | M9: M | N9: T | O9: W | P9: T | Q9: F | R9: S | S9: S | T9: M | U9: T | V9: W | W9: T | X9: F | Y9: S | Z9: S | AA9: M | AB9: T | AC9: W | AD9: T | AE9: F | AF9: S | AG9: S | AH9: M | AI9: T | AJ9: W | AK9: T | AL9: F | AM9: S | AN9: S | AO9: M | AP9: T | AQ9: W | AR9: T | AS9: F | AT9: S | AU9: S | AV9: M | AW9: T | AX9: W | AY9: T | AZ9: F | BA9: S | BB9: S | BC9: M | BD9: T | BE9: W | BF9: T | BG9: F | BH9: S | BI9: S | BJ9: M | BK9: T | BL9: W | BM9: T | BN9: F | BO9: S
I10: 1 | J10: 2 | K10: 3 | L10: 4 | M10: 5 | N10: 6 | O10: 7 | P10: 8 | Q10: 9 | R10: 10 | S10: 11 | T10: 12 | U10: 13 | V10: 14 | W10: 15 | X10: 16 | Y10: 17 | Z10: =Y10+1 -> 18 | AA10: =Z10+1 -> 19 | AB10: =AA10+1 -> 20 | AC10: =AB10+1 -> 21 | AD10: =AC10+1 -> 22 | AE10: =AD10+1 -> 23 | AF10: =AE10+1 -> 24 | AG10: =AF10+1 -> 25 | ... AM10: =AL10+1 -> 31 | AN10: 1 | AO10: 2 | AP10: 3 | AQ10: 4 | AR10: 5 | AS10: 6 | AT10: 7 | AU10: 8 | AV10: 9 | AW10: 10 | AX10: 11 | AY10: 12 | AZ10: 13 | BA10: 14 | BB10: 15 | BC10: 16 | BD10: 17 | BE10: =BD10+1 -> 18 | BF10: =BE10+1 -> 19 | BG10: =BF10+1 -> 20 | BH10: =BG10+1 -> 21 | BI10: =BH10+1 -> 22 | BJ10: =BI10+1 -> 23 | BK10: =BJ10+1 -> 24 | BL10: =BK10+1 -> 25 | ... BO10: =BN10+1 -> 28 | CA10: CHANNEL | CB10: JANEIRO | CD10: FEVEREIRO
CB12: INS | CC12: INVESTIMENTO $ | CD12: INS | CE12: INVESTIMENTO $
B13: SÃO PAULO ESTADO | C13: GLOBONEWS | D13: GLOBO NEWS EM PAUTA | E13: SEG-SEX | F13: 0.83333333 | G13: 22:00 | H13: 30 | AI13: 1 | AK13: 1 | AO13: 1 | AR13: 1 | AV13: 1 | AX13: 1 | BP13: =SUM(I13:BO13) -> 6 | BQ13: 4180 | BR13: 0.4 | BS13: =BQ13*(1-BR13) -> 2508 | BT13: =BS13*BP13 -> 15048 | BU13: =BT13*0.8 -> 12038.4 | BW13: 0.05 | BX13: =BW13*BP13 -> 0.3 | BY13: =IFERROR(BU13/BX13,0) -> 40128 | CA13: GLOBONEWS | CB13: =COUNTA(I13:AM13) -> 2 | CC13: =CB13*BS13*0.8 -> 4012.8 | CD13: =COUNTA(AN13:BO13) -> 4 | CE13: =CD13*BS13*0.8 -> 8025.6 | CF13: =SUM(CC13,CE13)=BU13 -> TRUE
C14: SP1 | E14: SEG-SEX | F14: 0.83333333 | G14: 22:00 | H14: 60 | AE14: 1 | BP14: =SUM(I14:BO14) -> 1 | BQ14: 8360 | BR14: 0.4 | BS14: =BQ14*(1-BR14) -> 5016 | BT14: =BS14*BP14 -> 5016 | BU14: =BT14*0.8 -> 4012.8 | BW14: 0.05 | BX14: =BW14*BP14 -> 0.05 | BY14: =IFERROR(BU14/BX14,0) -> 80256 | CA14: GLOBONEWS | CB14: =COUNTA(I14:AM14) -> 1 | CC14: =CB14*BS14*0.8 -> 4012.8 | CD14: =COUNTA(AN14:BO14) -> 0 | CE14: =CD14*BS14*0.8 -> 0 | CF14: =SUM(CC14,CE14)=BU14 -> TRUE
D15: JORNAL DAS DEZ P | E15: SEG-SEX | F15: 0.91666667 | G15: 00:00 | H15: 30 | AH15: 1 | AJ15: 1 | AP15: 1 | AS15: 1 | AW15: 1 | AY15: 1 | BP15: =SUM(I15:BO15) -> 6 | BQ15: 5760 | BR15: 0.4 | BS15: =BQ15*(1-BR15) -> 3456 | BT15: =BS15*BP15 -> 20736 | BU15: =BT15*0.8 -> 16588.8 | BW15: 0.05 | BX15: =BW15*BP15 -> 0.3 | BY15: =IFERROR(BU15/BX15,0) -> 55296 | CA15: GLOBONEWS | CB15: =COUNTA(I15:AM15) -> 2 | CC15: =CB15*BS15*0.8 -> 5529.6 | CD15: =COUNTA(AN15:BO15) -> 4 | CE15: =CD15*BS15*0.8 -> 11059.2 | CF15: =SUM(CC15,CE15)=BU15 -> TRUE
E16: SEG-SEX | F16: 0.91666667 | G16: 00:00 | H16: 60 | AD16: 1 | BP16: =SUM(I16:BO16) -> 1 | BQ16: 11520 | BR16: 0.4 | BS16: =BQ16*(1-BR16) -> 6912 | BT16: =BS16*BP16 -> 6912 | BU16: =BT16*0.8 -> 5529.6 | BW16: 0.05 | BX16: =BW16*BP16 -> 0.05 | BY16: =IFERROR(BU16/BX16,0) -> 110592 | CA16: GLOBONEWS | CB16: =COUNTA(I16:AM16) -> 1 | CC16: =CB16*BS16*0.8 -> 5529.6 | CD16: =COUNTA(AN16:BO16) -> 0 | CE16: =CD16*BS16*0.8 -> 0 | CF16: =SUM(CC16,CE16)=BU16 -> TRUE
C18: GLOBONEWS | D18: GLOBO NEWS EM PAUTA | E18: SEG-SEX | F18: 0.83333333 | G18: 22:00 | H18: 30 | AI18: 1 | AK18: 1 | AO18: 1 | AR18: 1 | AV18: 1 | AX18: 1 | BP18: =SUM(I18:BO18) -> 6 | BQ18: 640 | BR18: 0.4 | BS18: =BQ18*(1-BR18) -> 384 | BT18: =BS18*BP18 -> 2304 | BU18: =BT18*0.8 -> 1843.2 | BW18: 0.05 | BX18: =BW18*BP18 -> 0.3 | BY18: =IFERROR(BU18/BX18,0) -> 6144 | CA18: GLOBONEWS | CB18: =COUNTA(I18:AM18) -> 2 | CC18: =CB18*BS18*0.8 -> 614.4 | CD18: =COUNTA(AN18:BO18) -> 4 | CE18: =CD18*BS18*0.8 -> 1228.8 | CF18: =SUM(CC18,CE18)=BU18 -> TRUE
C19: SANTOS | E19: SEG-SEX | F19: 0.83333333 | G19: 22:00 | H19: 60 | AE19: 1 | BP19: =SUM(I19:BO19) -> 1 | BQ19: 1280 | BR19: 0.4 | BS19: =BQ19*(1-BR19) -> 768 | BT19: =BS19*BP19 -> 768 | BU19: =BT19*0.8 -> 614.4 | BW19: 0.05 | BX19: =BW19*BP19 -> 0.05 | BY19: =IFERROR(BU19/BX19,0) -> 12288 | CA19: GLOBONEWS | CB19: =COUNTA(I19:AM19) -> 1 | CC19: =CB19*BS19*0.8 -> 614.4 | CD19: =COUNTA(AN19:BO19) -> 0 | CE19: =CD19*BS19*0.8 -> 0 | CF19: =SUM(CC19,CE19)=BU19 -> TRUE
D20: JORNAL DAS DEZ P | E20: SEG-SEX | F20: 0.91666667 | G20: 00:00 | H20: 30 | AH20: 1 | AJ20: 1 | AP20: 1 | AS20: 1 | AW20: 1 | AY20: 1 | BP20: =SUM(I20:BO20) -> 6 | BQ20: 860 | BR20: 0.4 | BS20: =BQ20*(1-BR20) -> 516 | BT20: =BS20*BP20 -> 3096 | BU20: =BT20*0.8 -> 2476.8 | BW20: 0.05 | BX20: =BW20*BP20 -> 0.3 | BY20: =IFERROR(BU20/BX20,0) -> 8256 | CA20: GLOBONEWS | CB20: =COUNTA(I20:AM20) -> 2 | CC20: =CB20*BS20*0.8 -> 825.6 | CD20: =COUNTA(AN20:BO20) -> 4 | CE20: =CD20*BS20*0.8 -> 1651.2 | CF20: =SUM(CC20,CE20)=BU20 -> TRUE
E21: SEG-SEX | F21: 0.91666667 | G21: 00:00 | H21: 60 | AD21: 1 | BP21: =SUM(I21:BO21) -> 1 | BQ21: 1720 | BR21: 0.4 | BS21: =BQ21*(1-BR21) -> 1032 | BT21: =BS21*BP21 -> 1032 | BU21: =BT21*0.8 -> 825.6 | BW21: 0.05 | BX21: =BW21*BP21 -> 0.05 | BY21: =IFERROR(BU21/BX21,0) -> 16512 | CA21: GLOBONEWS | CB21: =COUNTA(I21:AM21) -> 1 | CC21: =CB21*BS21*0.8 -> 825.6 | CD21: =COUNTA(AN21:BO21) -> 0 | CE21: =CD21*BS21*0.8 -> 0 | CF21: =SUM(CC21,CE21)=BU21 -> TRUE
C23: GLOBONEWS | D23: GLOBO NEWS EM PAUTA | E23: SEG-SEX | F23: 0.83333333 | G23: 22:00 | H23: 30 | AI23: 1 | AK23: 1 | AO23: 1 | AR23: 1 | AV23: 1 | AX23: 1 | BP23: =SUM(I23:BO23) -> 6 | BQ23: 1140 | BR23: 0.4 | BS23: =BQ23*(1-BR23) -> 684 | BT23: =BS23*BP23 -> 4104 | BU23: =BT23*0.8 -> 3283.2 | BW23: 0.05 | BX23: =BW23*BP23 -> 0.3 | BY23: =IFERROR(BU23/BX23,0) -> 10944 | CA23: GLOBONEWS | CB23: =COUNTA(I23:AM23) -> 2 | CC23: =CB23*BS23*0.8 -> 1094.4 | CD23: =COUNTA(AN23:BO23) -> 4 | CE23: =CD23*BS23*0.8 -> 2188.8 | CF23: =SUM(CC23,CE23)=BU23 -> TRUE
C24: CAMPINAS | E24: SEG-SEX | F24: 0.83333333 | G24: 22:00 | H24: 60 | AE24: 1 | BP24: =SUM(I24:BO24) -> 1 | BQ24: 2280 | BR24: 0.4 | BS24: =BQ24*(1-BR24) -> 1368 | BT24: =BS24*BP24 -> 1368 | BU24: =BT24*0.8 -> 1094.4 | BW24: 0.05 | BX24: =BW24*BP24 -> 0.05 | BY24: =IFERROR(BU24/BX24,0) -> 21888 | CA24: GLOBONEWS | CB24: =COUNTA(I24:AM24) -> 1 | CC24: =CB24*BS24*0.8 -> 1094.4 | CD24: =COUNTA(AN24:BO24) -> 0 | CE24: =CD24*BS24*0.8 -> 0 | CF24: =SUM(CC24,CE24)=BU24 -> TRUE
D25: JORNAL DAS DEZ P | E25: SEG-SEX | F25: 0.91666667 | G25: 00:00 | H25: 30 | AH25: 1 | AJ25: 1 | AP25: 1 | AS25: 1 | AW25: 1 | AY25: 1 | BP25: =SUM(I25:BO25) -> 6 | BQ25: 1550 | BR25: 0.4 | BS25: =BQ25*(1-BR25) -> 930 | BT25: =BS25*BP25 -> 5580 | BU25: =BT25*0.8 -> 4464 | BW25: 0.05 | BX25: =BW25*BP25 -> 0.3 | BY25: =IFERROR(BU25/BX25,0) -> 14880 | CA25: GLOBONEWS | CB25: =COUNTA(I25:AM25) -> 2 | CC25: =CB25*BS25*0.8 -> 1488 | CD25: =COUNTA(AN25:BO25) -> 4 | CE25: =CD25*BS25*0.8 -> 2976 | CF25: =SUM(CC25,CE25)=BU25 -> TRUE
E26: SEG-SEX | F26: 0.91666667 | G26: 00:00 | H26: 60 | AD26: 1 | BP26: =SUM(I26:BO26) -> 1 | BQ26: 3100 | BR26: 0.4 | BS26: =BQ26*(1-BR26) -> 1860 | BT26: =BS26*BP26 -> 1860 | BU26: =BT26*0.8 -> 1488 | BW26: 0.05 | BX26: =BW26*BP26 -> 0.05 | BY26: =IFERROR(BU26/BX26,0) -> 29760 | CA26: GLOBONEWS | CB26: =COUNTA(I26:AM26) -> 1 | CC26: =CB26*BS26*0.8 -> 1488 | CD26: =COUNTA(AN26:BO26) -> 0 | CE26: =CD26*BS26*0.8 -> 0 | CF26: =SUM(CC26,CE26)=BU26 -> TRUE
C28: GLOBONEWS | D28: GLOBO NEWS EM PAUTA | E28: SEG-SEX | F28: 0.83333333 | G28: 22:00 | H28: 30 | AI28: 1 | AK28: 1 | AO28: 1 | AR28: 1 | AV28: 1 | AX28: 1 | BP28: =SUM(I28:BO28) -> 6 | BQ28: 440 | BR28: 0.4 | BS28: =BQ28*(1-BR28) -> 264 | BT28: =BS28*BP28 -> 1584 | BU28: =BT28*0.8 -> 1267.2 | BW28: 0.05 | BX28: =BW28*BP28 -> 0.3 | BY28: =IFERROR(BU28/BX28,0) -> 4224 | CA28: GLOBONEWS | CB28: =COUNTA(I28:AM28) -> 2 | CC28: =CB28*BS28*0.8 -> 422.4 | CD28: =COUNTA(AN28:BO28) -> 4 | CE28: =CD28*BS28*0.8 -> 844.8 | CF28: =SUM(CC28,CE28)=BU28 -> TRUE
C29: RIBEIRÃO PRETO | E29: SEG-SEX | F29: 0.83333333 | G29: 22:00 | H29: 60 | AE29: 1 | BP29: =SUM(I29:BO29) -> 1 | BQ29: 880 | BR29: 0.4 | BS29: =BQ29*(1-BR29) -> 528 | BT29: =BS29*BP29 -> 528 | BU29: =BT29*0.8 -> 422.4 | BW29: 0.05 | BX29: =BW29*BP29 -> 0.05 | BY29: =IFERROR(BU29/BX29,0) -> 8448 | CA29: GLOBONEWS | CB29: =COUNTA(I29:AM29) -> 1 | CC29: =CB29*BS29*0.8 -> 422.4 | CD29: =COUNTA(AN29:BO29) -> 0 | CE29: =CD29*BS29*0.8 -> 0 | CF29: =SUM(CC29,CE29)=BU29 -> TRUE
D30: JORNAL DAS DEZ P | E30: SEG-SEX | F30: 0.91666667 | G30: 00:00 | H30: 30 | AH30: 1 | AJ30: 1 | AP30: 1 | AS30: 1 | AW30: 1 | AY30: 1 | BP30: =SUM(I30:BO30) -> 6 | BQ30: 600 | BR30: 0.4 | BS30: =BQ30*(1-BR30) -> 360 | BT30: =BS30*BP30 -> 2160 | BU30: =BT30*0.8 -> 1728 | BW30: 0.05 | BX30: =BW30*BP30 -> 0.3 | BY30: =IFERROR(BU30/BX30,0) -> 5760 | CA30: GLOBONEWS | CB30: =COUNTA(I30:AM30) -> 2 | CC30: =CB30*BS30*0.8 -> 576 | CD30: =COUNTA(AN30:BO30) -> 4 | CE30: =CD30*BS30*0.8 -> 1152 | CF30: =SUM(CC30,CE30)=BU30 -> TRUE
E31: SEG-SEX | F31: 0.91666667 | G31: 00:00 | H31: 60 | AD31: 1 | BP31: =SUM(I31:BO31) -> 1 | BQ31: 1200 | BR31: 0.4 | BS31: =BQ31*(1-BR31) -> 720 | BT31: =BS31*BP31 -> 720 | BU31: =BT31*0.8 -> 576 | BW31: 0.05 | BX31: =BW31*BP31 -> 0.05 | BY31: =IFERROR(BU31/BX31,0) -> 11520 | CA31: GLOBONEWS | CB31: =COUNTA(I31:AM31) -> 1 | CC31: =CB31*BS31*0.8 -> 576 | CD31: =COUNTA(AN31:BO31) -> 0 | CE31: =CD31*BS31*0.8 -> 0 | CF31: =SUM(CC31,CE31)=BU31 -> TRUE
C33: GLOBONEWS | D33: GLOBO NEWS EM PAUTA | E33: SEG-SEX | F33: 0.83333333 | G33: 22:00 | H33: 30 | AI33: 1 | AK33: 1 | AO33: 1 | AR33: 1 | AV33: 1 | AX33: 1 | BP33: =SUM(I33:BO33) -> 6 | BQ33: 440 | BR33: 0.4 | BS33: =BQ33*(1-BR33) -> 264 | BT33: =BS33*BP33 -> 1584 | BU33: =BT33*0.8 -> 1267.2 | BW33: 0.05 | BX33: =BW33*BP33 -> 0.3 | BY33: =IFERROR(BU33/BX33,0) -> 4224 | CA33: GLOBONEWS | CB33: =COUNTA(I33:AM33) -> 2 | CC33: =CB33*BS33*0.8 -> 422.4 | CD33: =COUNTA(AN33:BO33) -> 4 | CE33: =CD33*BS33*0.8 -> 844.8 | CF33: =SUM(CC33,CE33)=BU33 -> TRUE
C34: SÃO JOSÉ DOS CAMPOS | E34: SEG-SEX | F34: 0.83333333 | G34: 22:00 | H34: 60 | AE34: 1 | BP34: =SUM(I34:BO34) -> 1 | BQ34: 880 | BR34: 0.4 | BS34: =BQ34*(1-BR34) -> 528 | BT34: =BS34*BP34 -> 528 | BU34: =BT34*0.8 -> 422.4 | BW34: 0.05 | BX34: =BW34*BP34 -> 0.05 | BY34: =IFERROR(BU34/BX34,0) -> 8448 | CA34: GLOBONEWS | CB34: =COUNTA(I34:AM34) -> 1 | CC34: =CB34*BS34*0.8 -> 422.4 | CD34: =COUNTA(AN34:BO34) -> 0 | CE34: =CD34*BS34*0.8 -> 0 | CF34: =SUM(CC34,CE34)=BU34 -> TRUE
D35: JORNAL DAS DEZ P | E35: SEG-SEX | F35: 0.91666667 | G35: 00:00 | H35: 30 | AH35: 1 | AJ35: 1 | AP35: 1 | AS35: 1 | AW35: 1 | AY35: 1 | BP35: =SUM(I35:BO35) -> 6 | BQ35: 600 | BR35: 0.4 | BS35: =BQ35*(1-BR35) -> 360 | BT35: =BS35*BP35 -> 2160 | BU35: =BT35*0.8 -> 1728 | BW35: 0.05 | BX35: =BW35*BP35 -> 0.3 | BY35: =IFERROR(BU35/BX35,0) -> 5760 | CA35: GLOBONEWS | CB35: =COUNTA(I35:AM35) -> 2 | CC35: =CB35*BS35*0.8 -> 576 | CD35: =COUNTA(AN35:BO35) -> 4 | CE35: =CD35*BS35*0.8 -> 1152 | CF35: =SUM(CC35,CE35)=BU35 -> TRUE
D36: JORNAL DAS DEZ P | E36: SEG-SEX | F36: 0.91666667 | G36: 00:00 | H36: 60 | AD36: 1 | BP36: =SUM(I36:BO36) -> 1 | BQ36: 1200 | BR36: 0.4 | BS36: =BQ36*(1-BR36) -> 720 | BT36: =BS36*BP36 -> 720 | BU36: =BT36*0.8 -> 576 | BW36: 0.05 | BX36: =BW36*BP36 -> 0.05 | BY36: =IFERROR(BU36/BX36,0) -> 11520 | CA36: GLOBONEWS | CB36: =COUNTA(I36:AM36) -> 1 | CC36: =CB36*BS36*0.8 -> 576 | CD36: =COUNTA(AN36:BO36) -> 0 | CE36: =CD36*BS36*0.8 -> 0 | CF36: =SUM(CC36,CE36)=BU36 -> TRUE
CA37: TT | CB37: =SUM(CB13:CB36) -> 30 | CC37: =SUM(CC13:CC36) -> 31123.2 | CD37: =SUM(CD13:CD36) -> 40 | CE37: =SUM(CE13:CE36) -> 31123.2
C38: CNN BRASIL | D38: CNN PRIME TIME P | E38: SEG-SEX | F38: 0.83333333 | G38: 22:00 | H38: 30 | AI38: 1 | AK38: 1 | AP38: 1 | AR38: 1 | AV38: 1 | AX38: 1 | BP38: =SUM(I38:BO38) -> 6 | BQ38: 11130 | BR38: 0.5 | BS38: =BQ38*(1-BR38) -> 5565 | BT38: =BS38*BP38 -> 33390 | BU38: =BT38*0.8 -> 26712 | BW38: 0.11 | BX38: =BW38*BP38 -> 0.66 | BY38: =IFERROR(BU38/BX38,0) -> 40472.727 | CA38: CNN BRASIL | CB38: =COUNTA(I38:AM38) -> 2 | CC38: =CB38*BS38*0.8 -> 8904 | CD38: =COUNTA(AN38:BO38) -> 4 | CE38: =CD38*BS38*0.8 -> 17808 | CF38: =SUM(CC38,CE38)=BU38 -> TRUE
E39: SEG-SEX | F39: 0.83333333 | G39: 22:00 | H39: 60 | AD39: 1 | BP39: =SUM(I39:BO39) -> 1 | BQ39: 22260 | BR39: 0.5 | BS39: =BQ39*(1-BR39) -> 11130 | BT39: =BS39*BP39 -> 11130 | BU39: =BT39*0.8 -> 8904 | BW39: 0.11 | BX39: =BW39*BP39 -> 0.11 | BY39: =IFERROR(BU39/BX39,0) -> 80945.455 | CA39: CNN BRASIL | CB39: =COUNTA(I39:AM39) -> 1 | CC39: =CB39*BS39*0.8 -> 8904 | CD39: =COUNTA(AN39:BO39) -> 0 | CE39: =CD39*BS39*0.8 -> 0 | CF39: =SUM(CC39,CE39)=BU39 -> TRUE
CA40: TT | CB40: =SUM(CB38:CB39) -> 3 | CC40: =SUM(CC38:CC39) -> 17808 | CD40: =SUM(CD38:CD39) -> 4 | CE40: =SUM(CE38:CE39) -> 17808
C41: RECORD NEWS | D41: JORNAL RECORD NEWS | E41: SEG-SEX | F41: 0.875 | G41: 22:00 | H41: 30 | AI41: 1 | AL41: 1 | AR41: 1 | AS41: 1 | AW41: 1 | AZ41: 1 | BP41: =SUM(I41:BO41) -> 6 | BQ41: 22000 | BR41: 0.75 | BS41: =BQ41*(1-BR41) -> 5500 | BT41: =BS41*BP41 -> 33000 | BU41: =BT41*0.8 -> 26400 | BW41: 0.13 | BX41: =BW41*BP41 -> 0.78 | BY41: =IFERROR(BU41/BX41,0) -> 33846.154 | CA41: RECORD NEWS | CB41: =COUNTA(I41:AM41) -> 2 | CC41: =CB41*BS41*0.8 -> 8800 | CD41: =COUNTA(AN41:BO41) -> 4 | CE41: =CD41*BS41*0.8 -> 17600 | CF41: =SUM(CC41,CE41)=BU41 -> TRUE
E42: SEG-SEX | F42: 0.875 | G42: 22:00 | H42: 60 | AE42: 1 | BP42: =SUM(I42:BO42) -> 1 | BQ42: 44000 | BR42: 0.75 | BS42: =BQ42*(1-BR42) -> 11000 | BT42: =BS42*BP42 -> 11000 | BU42: =BT42*0.8 -> 8800 | BW42: 0.13 | BX42: =BW42*BP42 -> 0.13 | BY42: =IFERROR(BU42/BX42,0) -> 67692.308 | CA42: RECORD NEWS | CB42: =COUNTA(I42:AM42) -> 1 | CC42: =CB42*BS42*0.8 -> 8800 | CD42: =COUNTA(AN42:BO42) -> 0 | CE42: =CD42*BS42*0.8 -> 0 | CF42: =SUM(CC42,CE42)=BU42 -> TRUE
CA43: TT | CB43: =SUM(CB41:CB42) -> 3 | CC43: =SUM(CC41:CC42) -> 17600 | CD43: =SUM(CD41:CD42) -> 4 | CE43: =SUM(CE41:CE42) -> 17600
B44: SÃO PAULO CAPITAL | C44: BAND NEWS | D44: JOR BANDNEWS 2ED NOT | E44: SEG-SEX | F44: 0.8125 | G44: 0.85416667 | H44: 30 | AH44: 1 | AK44: 1 | AP44: 1 | AR44: 1 | AW44: 1 | AY44: 1 | BP44: =SUM(I44:BO44) -> 6 | BQ44: 9631 | BR44: 0.7 | BS44: =BQ44*(1-BR44) -> 2889.3 | BT44: =BS44*BP44 -> 17335.8 | BU44: =BT44*0.8 -> 13868.64 | BW44: 0.015 | BX44: =BW44*BP44 -> 0.09 | BY44: =IFERROR(BU44/BX44,0) -> 154096 | CA44: BAND NEWS | CB44: =COUNTA(I44:AM44) -> 2 | CC44: =CB44*BS44*0.8 -> 4622.88 | CD44: =COUNTA(AN44:BO44) -> 4 | CE44: =CD44*BS44*0.8 -> 9245.76 | CF44: =SUM(CC44,CE44)=BU44 -> TRUE
E45: SEG-SEX | F45: 0.8125 | G45: 0.85416667 | H45: 60 | AD45: 1 | BP45: =SUM(I45:BO45) -> 1 | BQ45: 19262 | BR45: 0.7 | BS45: =BQ45*(1-BR45) -> 5778.6 | BT45: =BS45*BP45 -> 5778.6 | BU45: =BT45*0.8 -> 4622.88 | BW45: 0.015 | BX45: =BW45*BP45 -> 0.015 | BY45: =IFERROR(BU45/BX45,0) -> 308192 | CA45: BAND NEWS | CB45: =COUNTA(I45:AM45) -> 1 | CC45: =CB45*BS45*0.8 -> 4622.88 | CD45: =COUNTA(AN45:BO45) -> 0 | CE45: =CD45*BS45*0.8 -> 0 | CF45: =SUM(CC45,CE45)=BU45 -> TRUE
CA46: TT | CB46: =SUM(CB44:CB45) -> 3 | CC46: =SUM(CC44:CC45) -> 9245.76 | CD46: =SUM(CD44:CD45) -> 4 | CE46: =SUM(CE44:CE45) -> 9245.76
B48: TT PAY TV | I48: =COUNTA(I12:I16) -> 0 | J48: =COUNTA(J12:J16) -> 0 | K48: =COUNTA(K12:K16) -> 0 | L48: =COUNTA(L12:L16) -> 0 | M48: =COUNTA(M12:M16) -> 0 | N48: =SUM(N12:N16) -> 0 | O48: =SUM(O12:O16) -> 0 | P48: =SUM(P12:P16) -> 0 | Q48: =SUM(Q12:Q46) -> 0 | R48: =SUM(R12:R46) -> 0 | S48: =SUM(S12:S46) -> 0 | T48: =SUM(T12:T46) -> 0 | U48: =SUM(U12:U46) -> 0 | V48: =SUM(V12:V46) -> 0 | W48: =SUM(W12:W46) -> 0 | X48: =SUM(X12:X46) -> 0 | ... BJ48: =SUM(BJ12:BJ46) -> 0 | BK48: =SUM(BK13:BK47) -> 0 | BL48: =SUM(BL13:BL47) -> 0 | BM48: =SUM(BM12:BM16) -> 0 | BN48: =SUM(BN12:BN16) -> 0 | BO48: =SUM(BO12:BO16) -> 0 | BP48: =SUM(BP13:BP46) -> 91 | BT48: =SUM(BT13:BT46) -> 189442.4 | BU48: =SUM(BU13:BU46) -> 151553.92 | BX48: =SUM(BX13:BX45) -> 5.285 | BY48: =BU48/BX48 -> 28676.238 | CA48: TT GERAL | CB48: =CB17+CB40+CB43+CB46 -> 9 | CC48: =CC37+CC40+CC43+CC46 -> 75776.96 | CD48: =CD17+CD40+CD43+CD46 -> 12 | CE48: =CE37+CE40+CE43+CE46 -> 75776.96
CD50: TT | CE50: =CC48+CE48 -> 151553.92
CE51: =CE50=BU48 -> TRUE

Sheet RÁDIO versão completa
B5: CLIENT: SABESP
B6: CAMPAING: VERÃO 25/26
B8: MARKET | C8: CHANNEL | D8: PROPERTY | E8: FORMAT: LOCUÇÃO DE CABINE | F8: OUTUBRO | AK8: NOVEMBRO | BD8: DEZEMBRO | BH8: JANEIRO | BO8: INS. | BP8: CUSTO TABELA UNITÁRIO (BRUTO) | BQ8: DESC. % | BR8: CUSTO NEGOCIADO UNITÁRIO (BRUTO) | BS8: CUSTO TOTAL NEGOCIADO (BRUTO) | BT8: CUSTO TOTAL DESEMBOLSO CLIENTE | BV8: SHARE DE INVESTIMENTO % | BW8: SHARE DE AUDIÊNCIA % | BY8: IA% | BZ8: IA# | CA8: TRP | CB8: POPULAÇÃO TT. | CC8: UNIV. RÁDIO AS ABCDE 18+ | CD8: IMPACTOS ESTIMADOS | CE8: CPM | CG8: RÁDIO | CH8: VALOR UNITÁRIO LIQUIDO | CI8: DEZEMBRO | CK8: JANEIRO
F9: W | G9: T | H9: F | I9: S | J9: S | K9: M | L9: T | M9: W | N9: T | O9: F | P9: S | Q9: S | R9: M | S9: T | T9: W | U9: T | V9: F | W9: S | X9: S | Y9: M | Z9: T | AA9: W | AB9: T | AC9: F | AD9: S | AE9: S | AF9: M | AG9: T | AH9: W | AI9: T | AJ9: F | AK9: S | AL9: S | AM9: M | AN9: T | AO9: W | AP9: T | AQ9: F | AR9: S | AS9: S | AT9: M | AU9: T | AV9: W | AW9: T | AX9: F | AY9: S | AZ9: S | BA9: M | BB9: T | BC9: W | BD9: S | BE9: M | BF9: T | BG9: W | BH9: T | BI9: F | BJ9: S | BK9: S | BL9: F | BM9: S | BN9: S
F10: 1 | G10: 2 | H10: 3 | I10: 4 | J10: 5 | K10: 6 | L10: 7 | M10: 8 | N10: 9 | O10: 10 | P10: 11 | Q10: 12 | R10: 13 | S10: 14 | T10: 15 | U10: 16 | V10: 17 | W10: 18 | X10: 19 | Y10: 20 | Z10: 21 | AA10: 22 | AB10: 23 | AC10: 24 | AD10: 25 | AE10: 26 | AF10: 27 | AG10: 28 | AH10: 29 | AI10: 30 | AJ10: 31 | AK10: 1 | AL10: 2 | AM10: 3 | AN10: 4 | AO10: 5 | AP10: 6 | AQ10: 7 | AR10: 8 | AS10: 9 | AT10: 10 | AU10: 11 | AV10: 12 | AW10: 13 | AX10: 14 | AY10: 15 | AZ10: 16 | BA10: 17 | BB10: 18 | BC10: 19 | BD10: 28 | BE10: =BD10+1 -> 29 | BF10: =BE10+1 -> 30 | BG10: =BF10+1 -> 31 | BH10: 1 | BI10: =BH10+1 -> 2 | BJ10: =BI10+1 -> 3 | BK10: =BJ10+1 -> 4 | BL10: =BK10+1 -> 5 | BM10: =BL10+1 -> 6 | BN10: =BM10+1 -> 7 | CI10: INS. | CJ10: INV. LIQUIDO | CK10: INS. | CL10: INV. LIQUIDO
B13: RÁDIO JORNALISMO | C13: JOVEM PAN
B14: SÃO PAULO - CAPITAL | C14: ROTATIVO | D14: SEG À SEX 06H00-19H00 | E14: 30'' | BE14: 3 | BF14: 3 | BG14: 3 | BH14: 3 | BI14: 3 | BJ14: 3 | BK14: 3 | BL14: 3 | BO14: =SUM(F14:BN14) -> 24 | BP14: =13891.5 -> 13891.5 | BQ14: 0.6599 | BR14: =BP14*(1-BQ14) -> 4724.4991 | BS14: =BR14*BO14 -> 113387.98 | BT14: =BS14*0.8 -> 90710.384 | BV14: {=SUM(BT14:BT15/$BT$29)} -> 0.31554698 | BW14: 0.31796335 | BY14: 0.97 | BZ14: 97631 | CA14: =BY14*BO14 -> 23.28 | CB14: 11451245 | CC14: 16255139 | CD14: =CC14*CA14/100 -> 3784196.4 | CE14: =SUM(BT14:BT15)/SUM(CD14:CD15)*1000 -> 19.997899 | CG14: JOVEM PAN | CH14: =BR14*0.8 -> 3779.5993 | CI14: =SUM(AK14:BG14) -> 9 | CJ14: =CH14*CI14 -> 34016.394 | CK14: =SUM(BH14:BN14) -> 15 | CL14: =CK14*CH14 -> 56693.99 | CM14: =(CJ14+CL14)=BT14 -> TRUE
C15: FAIXA MUSICAL | D15: SEG À SEX 14H00-24H00 | E15: 30'' | BE15: 1 | BF15: 1 | BG15: 1 | BH15: 1 | BI15: 1 | BJ15: 1 | BK15: 1 | BL15: 1 | BO15: =SUM(F15:BN15) -> 8 | BP15: =4681.95 -> 4681.95 | BQ15: 0.6599 | BR15: =BP15*(1-BQ15) -> 1592.3312 | BS15: =BR15*BO15 -> 12738.65 | BT15: =BS15*0.8 -> 10190.92 | BY15: 0.97 | BZ15: 97631 | CA15: =BY15*BO15 -> 7.76 | CB15: 11451245 | CC15: 16255139 | CD15: =CC15*CA15/100 -> 1261398.8 | CH15: =BR15*0.8 -> 1273.865 | CI15: =SUM(AK15:BG15) -> 3 | CJ15: =CH15*CI15 -> 3821.5949 | CK15: =SUM(BH15:BN15) -> 5 | CL15: =CK15*CH15 -> 6369.3248 | CM15: =(CJ15+CL15)=BT15 -> TRUE
C18: BAND NEWS FM | D18: SEG À SEX 06H00-19H00 | E18: 30'' | BE18: 5 | BF18: 5 | BG18: 5 | BH18: 4 | BI18: 4 | BJ18: 4 | BK18: 4 | BL18: 4 | BO18: =SUM(F18:BN18) -> 35 | BP18: =7604 -> 7604 | BQ18: 0.65 | BR18: =BP18*(1-BQ18) -> 2661.4 | BS18: =BR18*BO18 -> 93149 | BT18: =BS18*0.8 -> 74519.2 | BV18: =SUM(BT18:BT19)/$BT$29 -> 0.23304266 | BW18: 0.26616162 | BY18: 0.92 | BZ18: 81725 | CA18: =BY18*BO18 -> 32.2 | CB18: 11451245 | CC18: 16255139 | CD18: =CC18*CA18/100 -> 5234154.8 | CE18: =BT18/CD18*1000 -> 14.237103 | CG18: BAND NEWS FM | CH18: =BR18*0.8 -> 2129.12 | CI18: =SUM(AK18:BG18) -> 15 | CJ18: =CH18*CI18 -> 31936.8 | CK18: =SUM(BH18:BN18) -> 20 | CL18: =CK18*CH18 -> 42582.4 | CM18: =(CJ18+CL18)=BT18 -> TRUE
C19: ROTATIVO | E19: 30'' | BO19: =SUM(F19:BN19) -> 0 | BP19: =7604 -> 7604 | BQ19: 1 | BR19: =BP19*(1-BQ19) -> 0 | BS19: =BR19*BO19 -> 0 | BT19: =BS19*0.8 -> 0 | BY19: 0.92 | BZ19: 81725 | CA19: =BY19*BO19 -> 0 | CB19: 11451245 | CC19: 17116728 | CD19: =CC19*CA19/100 -> 0 | CE19: =BT19/CD19*1000 -> #DIV/0! | CH19: =BR19*0.8 -> 0 | CI19: =SUM(AK19:BN19) -> 0 | CJ19: =CH19*CI19 -> 0 | CK19: =SUM(AM19:BP19) -> 7604 | CL19: =CJ19*CK19 -> 0 | CM19: =SUM(#REF!,CJ19,#REF!)=BT19 -> #REF!
C22: BANDEIRANTES FM | D22: SEG À SEX 06H00-09H00 | E22: 30'' | BE22: 4 | BF22: 4 | BG22: 4 | BH22: 3 | BI22: 3 | BJ22: 3 | BK22: 3 | BL22: 3 | BO22: =SUM(F22:BN22) -> 27 | BP22: =8190 -> 8190 | BQ22: 0.65 | BR22: =BP22*(1-BQ22) -> 2866.5 | BS22: =BR22*BO22 -> 77395.5 | BT22: =BS22*0.8 -> 61916.4 | BV22: {=SUM(BT22:BT23/$BT$29)} -> 0.19363013 | BW22: 0.1968604 | BY22: 0.89 | BZ22: 60446 | CA22: =BY22*BO22 -> 24.03 | CB22: 11451245 | CC22: 16255139 | CD22: =CC22*(CA22+CA24)/100 -> 3906109.9 | CE22: =BT22/CD22*1000 -> 15.851167 | CG22: BANDEIRANTES FM | CH22: =BR22*0.8 -> 2293.2 | CI22: =SUM(AK22:BG22) -> 12 | CJ22: =CH22*CI22 -> 27518.4 | CK22: =SUM(BH22:BN22) -> 15 | CL22: =CK22*CH22 -> 34398 | CM22: =(CJ22+CL22)=BT22 -> TRUE
C23: ROTATIVO | E23: 30'' | BO23: =SUM(F23:BN23) -> 0 | BP23: =8190 -> 8190 | BQ23: 1 | BR23: =BP23*(1-BQ23) -> 0 | BS23: =BR23*BO23 -> 0 | BT23: =BS23*0.8 -> 0 | BY23: 0.89 | BZ23: 60446 | CA23: =BY23*BO23 -> 0 | CB23: 11451245 | CC23: 17116728 | CD23: =CC23*(CA23+CA25)/100 -> 0 | CE23: =BT23/CD23*1000 -> #DIV/0! | CH23: =BR23*0.8 -> 0 | CI23: =SUM(AK23:BN23) -> 0 | CJ23: =CH23*CI23 -> 0 | CK23: =SUM(AM23:BP23) -> 8190 | CL23: =CJ23*CK23 -> 0
C26: CBN | D26: SEG À SEX 06H00-19H00 | E26: 30'' | BE26: 2 | BF26: 2 | BG26: 2 | BH26: 2 | BI26: 2 | BJ26: 2 | BK26: 2 | BL26: 2 | BO26: =SUM(F26:BN26) -> 16 | BP26: =10733 -> 10733 | BQ26: 0.4 | BR26: =BP26*(1-BQ26) -> 6439.8 | BS26: =BR26*BO26 -> 103036.8 | BT26: =BS26*0.8 -> 82429.44 | BV26: =SUM(BT26:BT27)/$BT$29 -> 0.25778023 | BW26: 0.25901462 | BY26: 0.87 | BZ26: 67249 | CA26: =BY26*BO26 -> 13.92 | CB26: 11451245 | CC26: 16255139 | CD26: =CC26*CA26/100 -> 2262715.3 | CE26: =BT26/CD26*1000 -> 36.429434 | CG26: CBN | CH26: =BR26*0.8 -> 5151.84 | CI26: =SUM(AK26:BG26) -> 6 | CJ26: =CH26*CI26 -> 30911.04 | CK26: =SUM(BH26:BN26) -> 10 | CL26: =CK26*CH26 -> 51518.4 | CM26: =(CJ26+CL26)=BT26 -> TRUE
C27: ROTATIVO | E27: 30'' | BO27: =SUM(F27:BN27) -> 0 | BP27: =10733 -> 10733 | BQ27: 1 | BR27: =BP27*(1-BQ27) -> 0 | BS27: =BR27*BO27 -> 0 | BT27: =BS27*0.8 -> 0 | BY27: 0.87 | BZ27: 67249 | CA27: =BY27*BO27 -> 0 | CB27: 11451245 | CC27: 21515727 | CD27: =CC27*CA27/100 -> 0 | CE27: =BT27/CD27*1000 -> #DIV/0! | CH27: =BR27*0.8 -> 0 | CI27: =SUM(AK27:BN27) -> 0 | CJ27: =CH27*CI27 -> 0 | CK27: =SUM(AM27:BP27) -> 10733 | CL27: =CJ27*CK27 -> 0
B29: TOTAL RADIO SP CAPITAL - JORNALISMO | F29: =SUM(F12:F28) -> 0 | G29: =SUM(G12:G28) -> 0 | H29: =SUM(H12:H28) -> 0 | I29: =SUM(I12:I28) -> 0 | J29: =SUM(J12:J28) -> 0 | K29: =SUM(K12:K28) -> 0 | L29: =SUM(L12:L28) -> 0 | M29: =SUM(M12:M28) -> 0 | ... Z29: =SUM(Z12:Z28) -> 0 | AA29: =SUM(AA12:AA27) -> 0 | AB29: =SUM(AB12:AB28) -> 0 | AC29: =SUM(AC12:AC28) -> 0 | AD29: =SUM(AD12:AD28) -> 0 | AE29: =SUM(AE12:AE28) -> 0 | AF29: =SUM(AF12:AF28) -> 0 | AG29: =SUM(AG12:AG28) -> 0 | AH29: =SUM(AH12:AH28) -> 0 | AI29: =SUM(AI12:AI28) -> 0 | ... BO29: =SUM(BO12:BO28) -> 110 | BS29: =SUM(BS12:BS28) -> 399707.93 | BT29: =SUM(BT12:BT28) -> 319766.34 | CB29: =CB26 -> 11451245 | CD29: =SUM(CD12:CD28) -> 16448575 | CE29: =BT29/CD29*1000 -> 19.440367 | CI29: =SUM(CI12:CI28) -> 45 | CJ29: =SUM(CJ12:CJ28) -> 128204.23 | CK29: =SUM(CK12:CK28) -> 26592 | CL29: =SUM(CL12:CL28) -> 191562.11 | CM29: =(CJ29+CL29)=BT29 -> TRUE
B31: MARKET | C31: CHANNEL | D31: PROPERTY | E31: FORMAT: SPOT | F31: OUTUBRO | BD31: DEZEMBRO | BH31: JANEIRO | BO31: INS. | BP31: CUSTO TABELA UNITÁRIO (BRUTO) | BQ31: DESC. % | BR31: CUSTO NEGOCIADO UNITÁRIO (BRUTO) | BS31: CUSTO TOTAL NEGOCIADO (BRUTO) | BT31: CUSTO TOTAL DESEMBOLSO CLIENTE | BV31: SHARE DE INVESTIMENTO % | BW31: SHARE DE AUDIÊNCIA % | BY31: IA% | BZ31: IA# | CA31: TRP | CB31: POPULAÇÃO TT. | CC31: UNIV. RÁDIO AS ABCDE 18+ | CD31: IMPACTOS ESTIMADOS | CE31: CPM | CG31: RÁDIO | CH31: VALOR UNITÁRIO LIQUIDO | CI31: DEZEMBRO | CK31: JANEIRO
F32: W | G32: T | H32: F | I32: S | J32: S | K32: M | L32: T | M32: W | N32: T | O32: F | P32: S | Q32: S | R32: M | S32: T | T32: W | U32: T | V32: F | W32: S | X32: S | Y32: M | Z32: T | AA32: W | AB32: T | AC32: F | AD32: S | AE32: S | AF32: M | AG32: T | AH32: W | AI32: T | AJ32: F | AK32: S | AL32: S | AM32: M | AN32: T | AO32: W | AP32: T | AQ32: F | AR32: S | AS32: S | AT32: M | AU32: T | AV32: W | AW32: T | AX32: F | AY32: S | AZ32: S | BA32: M | BB32: T | BC32: W | BD32: S | BE32: M | BF32: T | BG32: W | BH32: T | BI32: F | BJ32: S | BK32: S | BL32: F | BM32: S | BN32: S
F33: 1 | G33: 2 | H33: 3 | I33: 4 | J33: 5 | K33: 6 | L33: 7 | M33: 8 | N33: 9 | O33: 10 | P33: 11 | Q33: 12 | R33: 13 | S33: 14 | T33: 15 | U33: 16 | V33: 17 | W33: 18 | X33: 19 | Y33: 20 | Z33: 21 | AA33: 22 | AB33: 23 | AC33: 24 | AD33: 25 | AE33: 26 | AF33: 27 | AG33: 28 | AH33: 29 | AI33: 30 | AJ33: 31 | AK33: 1 | AL33: 2 | AM33: 3 | AN33: 4 | AO33: 5 | AP33: 6 | AQ33: 7 | AR33: 8 | AS33: 9 | AT33: 10 | AU33: 11 | AV33: 12 | AW33: 13 | AX33: 14 | AY33: 15 | AZ33: 16 | BA33: 17 | BB33: 18 | BC33: 19 | BD33: 28 | BE33: =BD33+1 -> 29 | BF33: =BE33+1 -> 30 | BG33: =BF33+1 -> 31 | BH33: 1 | BI33: =BH33+1 -> 2 | BJ33: =BI33+1 -> 3 | BK33: =BJ33+1 -> 4 | BL33: =BK33+1 -> 5 | BM33: =BL33+1 -> 6 | BN33: =BM33+1 -> 7 | CI33: INS. | CJ33: INV. LIQUIDO | CK33: INS. | CL33: INV. LIQUIDO
B35: RÁDIO MUSICAL | C35: NATIVA FM | D35: SEG À DOM 06H00-19H00 | E35: 30'' | BE35: 3 | BF35: 3 | BG35: 3 | BH35: 3 | BI35: 3 | BJ35: 3 | BK35: 3 | BL35: 3 | BO35: =SUM(F35:BN35) -> 24 | BP35: =3624 -> 3624 | BQ35: 0.63 | BR35: =BP35*(1-BQ35) -> 1340.88 | BS35: =BR35*BO35 -> 32181.12 | BT35: =BS35*0.8 -> 25744.896 | BV35: =BT35/$BT$81 -> 0.062819327 | BW35: 0.055898255 | BY35: =BZ35/CC35*100 -> 0.49702669 | BZ35: 80792.38 | CA35: =BY35*BO35 -> 11.928641 | CB35: 11451245 | CC35: 16255139 | CD35: =CC35*CA35/100 -> 1939017.1 | CE35: =BT35/CD35*1000 -> 13.277292 | CG35: NATIVA | CH35: =BR35*0.8 -> 1072.704 | CI35: =SUM(AK35:BG35) -> 9 | CJ35: =CH35*CI35 -> 9654.336 | CK35: =SUM(BH35:BN35) -> 15 | CL35: =CK35*CH35 -> 16090.56 | CM35: =(CJ35+CL35)=BT35 -> TRUE
B36: SÃO PAULO - CAPITAL | E36: 30'' | BO36: =SUM(F36:BN36) -> 0 | BP36: =3624 -> 3624 | BQ36: 1 | BR36: =BP36*(1-BQ36) -> 0 | BS36: =BR36*BO36 -> 0 | BT36: =BS36*0.8 -> 0 | BY36: =BZ36/CC36*100 -> 0.47200832 | BZ36: 80792.38 | CA36: =BY36*BO36 -> 0 | CB36: 11451245 | CC36: 17116728 | CD36: =CC36*CA36/100 -> 0 | CE36: =BT36/CD36*1000 -> #DIV/0! | CH36: =BR36*0.8 -> 0 | CI36: =SUM(AK36:BN36) -> 0 | CJ36: =CH36*CI36 -> 0 | CK36: =SUM(AM36:BP36) -> 3624 | CL36: =CJ36*CK36 -> 0 | CM36: =SUM(#REF!,CJ36,#REF!)=BT36 -> #REF!
B37: SÃO PAULO - CAPITAL
C39: BAND FM | D39: SEG À DOM 06H00-19H00 | E39: 30'' | BE39: 4 | BF39: 4 | BG39: 4 | BH39: 4 | BI39: 4 | BJ39: 4 | BK39: 4 | BL39: 4 | BO39: =SUM(F39:BN39) -> 32 | BP39: =4270 -> 4270 | BQ39: 0.65 | BR39: =BP39*(1-BQ39) -> 1494.5 | BS39: =BR39*BO39 -> 47824 | BT39: =BS39*0.8 -> 38259.2 | BV39: =BT39/$BT$81 -> 0.093355094 | BW39: 0.08560711 | BY39: =BZ39/CC39*100 -> 0.76557863 | BZ39: 124445.87 | CA39: =BY39*BO39 -> 24.498516 | CB39: 11451245 | CC39: 16255139 | CD39: =CC39*CA39/100 -> 3982267.8 | CE39: =BT39/CD39*1000 -> 9.6073899 | CG39: BAND FM | CH39: =BR39*0.8 -> 1195.6 | CI39: =SUM(AK39:BG39) -> 12 | CJ39: =CH39*CI39 -> 14347.2 | CK39: =SUM(BH39:BN39) -> 20 | CL39: =CK39*CH39 -> 23912 | CM39: =(CJ39+CL39)=BT39 -> TRUE
E40: 30'' | BO40: =SUM(F40:BN40) -> 0 | BP40: =4270 -> 4270 | BQ40: 1 | BR40: =BP40*(1-BQ40) -> 0 | BS40: =BR40*BO40 -> 0 | BT40: =BS40*0.8 -> 0 | BY40: =BZ40/CC40*100 -> 0.7270424 | BZ40: 124445.87 | CA40: =BY40*BO40 -> 0 | CB40: 11451245 | CC40: 17116728 | CD40: =CC40*CA40/100 -> 0 | CE40: =BT40/CD40*1000 -> #DIV/0! | CH40: =BR40*0.8 -> 0 | CI40: =SUM(AK40:BN40) -> 0 | CJ40: =CH40*CI40 -> 0 | CK40: =SUM(AM40:BP40) -> 4270 | CL40: =CJ40*CK40 -> 0 | CM40: =SUM(#REF!,CJ40,#REF!)=BT40 -> #REF!
C43: 89 ROCK FM | D43: SEG À DOM 06H00-19H00 | E43: 30'' | BE43: 4 | BF43: 4 | BG43: 4 | BH43: 4 | BI43: 4 | BJ43: 4 | BK43: 4 | BL43: 4 | BO43: =SUM(F43:BN43) -> 32 | BP43: =4448 -> 4448 | BQ43: 0.7 | BR43: =BP43*(1-BQ43) -> 1334.4 | BS43: =BR43*BO43 -> 42700.8 | BT43: =BS43*0.8 -> 34160.64 | BV43: =BT43/$BT$81 -> 0.083354324 | BW43: 0.076893333 | BY43: =BZ43/CC43*100 -> 0.56035731 | BZ43: 91086.86 | CA43: =BY43*BO43 -> 17.931434 | CB43: 11451245 | CC43: 16255139 | CD43: =CC43*CA43/100 -> 2914779.5 | CE43: =BT43/CD43*1000 -> 11.719802 | CG43: 89 ROCK FM | CH43: =BR43*0.8 -> 1067.52 | CI43: =SUM(AK43:BG43) -> 12 | CJ43: =CH43*CI43 -> 12810.24 | CK43: =SUM(BH43:BN43) -> 20 | CL43: =CK43*CH43 -> 21350.4 | CM43: =(CJ43+CL43)=BT43 -> TRUE
C46: ALPHA FM | D46: SEG À DOM 06H00-19H00 | E46: 30'' | BE46: 4 | BF46: 4 | BG46: 4 | BH46: 3 | BI46: 3 | BJ46: 3 | BK46: 3 | BL46: 3 | BO46: =SUM(F46:BN46) -> 27 | BP46: =4800 -> 4800 | BQ46: 0.58 | BR46: =BP46*(1-BQ46) -> 2016 | BS46: =BR46*BO46 -> 54432 | BT46: =BS46*0.8 -> 43545.6 | BV46: =BT46/$BT$81 -> 0.10625428 | BW46: 0.09770284 | BY46: =BZ46/CC46*100 -> 0.88456217 | BZ46: 143786.81 | CA46: =BY46*BO46 -> 23.883179 | CB46: 11451245 | CC46: 16255139 | CD46: =CC46*CA46/100 -> 3882243.9 | CE46: =BT46/CD46*1000 -> 11.216606 | CG46: ALPHA FM | CH46: =BR46*0.8 -> 1612.8 | CI46: =SUM(AK46:BG46) -> 12 | CJ46: =CH46*CI46 -> 19353.6 | CK46: =SUM(BH46:BN46) -> 15 | CL46: =CK46*CH46 -> 24192 | CM46: =(CJ46+CL46)=BT46 -> TRUE
C49: DISNEY FM | D49: SEG À DOM 06H00-19H00 | E49: 30'' | BE49: 3 | BF49: 3 | BG49: 3 | BH49: 3 | BI49: 3 | BL49: 3 | BO49: =SUM(F49:BN49) -> 18 | BP49: =3700 -> 3700 | BQ49: 0.61 | BR49: =BP49*(1-BQ49) -> 1443 | BS49: =BR49*BO49 -> 25974 | BT49: =BS49*0.8 -> 20779.2 | BV49: =BT49/$BT$81 -> 0.050702685 | BW49: 0.051110058 | BY49: =BZ49/CC49*100 -> 0.28165794 | BZ49: 45783.89 | CA49: =BY49*BO49 -> 5.069843 | CB49: 11451245 | CC49: 16255139 | CD49: =CC49*(CA49+CA51)/100 -> 824110.02 | CE49: =BT49/CD49*1000 -> 25.214109 | CG49: DISNEY FM | CH49: =BR49*0.8 -> 1154.4 | CI49: =SUM(AK49:BG49) -> 9 | CJ49: =CH49*CI49 -> 10389.6 | CK49: =SUM(BH49:BN49) -> 9 | CL49: =CK49*CH49 -> 10389.6 | CM49: =(CJ49+CL49)=BT49 -> TRUE
C52: ENERGIA 97 FM | D52: SEG À DOM 06H00-19H00 | E52: 30'' | BE52: 4 | BF52: 4 | BG52: 4 | BH52: 4 | BI52: 4 | BJ52: 4 | BK52: 4 | BL52: 4 | BO52: =SUM(F52:BN52) -> 32 | BP52: 990.99 | BQ52: 0.5 | BR52: =BP52*(1-BQ52) -> 495.495 | BS52: =BR52*BO52 -> 15855.84 | BT52: =BS52*0.8 -> 12684.672 | BV52: =BT52/$BT$81 -> 0.030951477 | BW52: 0.031110058 | BY52: =BZ52/CC52*100 -> 0.29396027 | BZ52: 47783.65 | CA52: =BY52*BO52 -> 9.4067285 | CB52: 11451245 | CC52: 16255139 | CD52: =CC52*CA52/100 -> 1529076.8 | CE52: =BT52/CD52*1000 -> 8.2956409 | CG52: ENERGIA 97 FM | CH52: =BR52*0.8 -> 396.396 | CI52: =SUM(AK52:BG52) -> 12 | CJ52: =CH52*CI52 -> 4756.752 | CK52: =SUM(BH52:BN52) -> 20 | CL52: =CK52*CH52 -> 7927.92 | CM52: =(CJ52+CL52)=BT52 -> TRUE
C55: KISS FM | D55: SEG À DOM 06H00-19H00 | E55: 30'' | BE55: 3 | BF55: 3 | BG55: 3 | BH55: 3 | BI55: 3 | BJ55: 3 | BK55: 3 | BL55: 3 | BO55: =SUM(F55:BN55) -> 24 | BP55: =3900 -> 3900 | BQ55: 0.7011 | BR55: =BP55*(1-BQ55) -> 1165.71 | BS55: =BP55*BO55*(1-BQ55) -> 27977.04 | BT55: =BS55*0.8 -> 22381.632 | BV55: =BT55/$BT$81 -> 0.05461273 | BW55: 0.047536391 | BY55: =BZ55/CC55*100 -> 0.43037534 | BZ55: 69958.11 | CA55: =BY55*BO55 -> 10.329008 | CB55: 11451245 | CC55: 16255139 | CD55: =CC55*(CA55+CA57)/100 -> 1678994.6 | CE55: =BT55/CD55*1000 -> 13.330377 | CG55: KISS FM | CH55: =BR55*0.8 -> 932.568 | CI55: =SUM(AK55:BG55) -> 9 | CJ55: =CH55*CI55 -> 8393.112 | CK55: =SUM(BH55:BN55) -> 15 | CL55: =CK55*CH55 -> 13988.52 | CM55: =(CJ55+CL55)=BT55 -> TRUE
C58: GAZETA FM | D58: SEG À DOM 06H00-19H00 | E58: 30'' | BE58: 4 | BF58: 4 | BG58: 4 | BH58: 4 | BI58: 4 | BJ58: 4 | BK58: 4 | BL58: 4 | BO58: =SUM(F58:BN58) -> 32 | BP58: =2968 -> 2968 | BQ58: 0.62 | BR58: =BP58*(1-BQ58) -> 1127.84 | BS58: =BR58*BO58 -> 36090.88 | BT58: =BS58*0.8 -> 28872.704 | BV58: =BT58/$BT$81 -> 0.070451395 | BW58: 0.068857471 | BY58: =BZ58/CC58*100 -> 0.44233587 | BZ58: 71902.31 | CA58: =BY58*BO58 -> 14.154748 | CB58: 11451245 | CC58: 16255139 | CD58: =CC58*CA58/100 -> 2300873.9 | CE58: =BT58/CD58*1000 -> 12.548582 | CG58: GAZETA FM | CH58: =BR58*0.8 -> 902.272 | CI58: =SUM(AK58:BG58) -> 12 | CJ58: =CH58*CI58 -> 10827.264 | CK58: =SUM(BH58:BN58) -> 20 | CL58: =CK58*CH58 -> 18045.44 | CM58: =(CJ58+CL58)=BT58 -> TRUE
C61: 105 FM | D61: SEG À DOM 05H00-18H00 | E61: 30'' | BE61: 4 | BF61: 4 | BG61: 4 | BH61: 4 | BI61: 4 | BJ61: 4 | BK61: 4 | BL61: 4 | BO61: =SUM(F61:BN61) -> 32 | BP61: =1610 -> 1610 | BQ61: 0.55 | BR61: =BP61*(1-BQ61) -> 724.5 | BS61: =BR61*BO61 -> 23184 | BT61: =BS61*0.8 -> 18547.2 | BV61: =BT61/$BT$81 -> 0.045256451 | BW61: 0.048388488 | BY61: =BZ61/CC61*100 -> 0.43808989 | BZ61: 71212.12 | CA61: =BY61*BO61 -> 14.018876 | CB61: 11451245 | CC61: 16255139 | CD61: =CC61*CA61/100 -> 2278787.8 | CE61: =BT61/CD61*1000 -> 8.139064 | CG61: 105 FM | CH61: =BR61*0.8 -> 579.6 | CI61: =SUM(AK61:BG61) -> 12 | CJ61: =CH61*CI61 -> 6955.2 | CK61: =SUM(BH61:BN61) -> 20 | CL61: =CK61*CH61 -> 11592 | CM61: =(CJ61+CL61)=BT61 -> TRUE | EO61: =SUM(F61:EN61) -> 30119696
C64: RÁDIO MIX | D64: SEG À DOM 06H00-19H00 | E64: 30'' | BE64: 3 | BF64: 3 | BG64: 3 | BH64: 3 | BI64: 3 | BJ64: 3 | BK64: 3 | BL64: 3 | BO64: =SUM(F64:BN64) -> 24 | BP64: =5205 -> 5205 | BQ64: 0.75 | BR64: =BP64*(1-BQ64) -> 1301.25 | BS64: =BR64*BO64 -> 31230 | BT64: =BS64*0.8 -> 24984 | BV64: =BT64/$BT$81 -> 0.060962688 | BW64: 0.057246938 | BY64: =BZ64/CC64*100 -> 0.42775475 | BZ64: 69532.13 | CA64: =BY64*BO64 -> 10.266114 | CB64: 11451245 | CC64: 16255139 | CD64: =CC64*CA64/100 -> 1668771.1 | CE64: =BT64/CD64*1000 -> 14.971496 | CG64: RÁDIO MIX | CH64: =BR64*0.8 -> 1041 | CI64: =SUM(AK64:BG64) -> 9 | CJ64: =CH64*CI64 -> 9369 | CK64: =SUM(BH64:BN64) -> 15 | CL64: =CK64*CH64 -> 15615 | CM64: =(CJ64+CL64)=BT64 -> TRUE
C67: TRANSAMÉRICA FM | D67: SEG À SEX 06H00-19H00 | E67: 30'' | BE67: 4 | BF67: 4 | BG67: 4 | BH67: 4 | BI67: 4 | BJ67: 4 | BK67: 4 | BL67: 4 | BO67: =SUM(F67:BN67) -> 32 | BP67: =3877 -> 3877 | BQ67: 0.8 | BR67: =BP67*(1-BQ67) -> 775.4 | BS67: =BR67*BO67 -> 24812.8 | BT67: =BS67*0.8 -> 19850.24 | BV67: =BT67/$BT$81 -> 0.048435959 | BW67: 0.045629449 | BY67: =BZ67/CC67*100 -> 0.22298511 | BZ67: 36246.54 | CA67: =BY67*BO67 -> 7.1355236 | CB67: 11451245 | CC67: 16255139 | CD67: =CC67*(CA67+CA69)/100 -> 1159889.3 | CE67: =BT67/CD67*1000 -> 17.113909 | CG67: TRANSAMÉRICA FM | CH67: =BR67*0.8 -> 620.32 | CI67: =SUM(AK67:BG67) -> 12 | CJ67: =CH67*CI67 -> 7443.84 | CK67: =SUM(BH67:BN67) -> 20 | CL67: =CK67*CH67 -> 12406.4 | CM67: =(CJ67+CL67)=BT67 -> TRUE
C70: MASSA FM | D70: SEG À DOM 06H00-19H00 | E70: 30'' | BE70: 4 | BF70: 4 | BG70: 4 | BH70: 4 | BI70: 4 | BJ70: 4 | BK70: 4 | BL70: 4 | BO70: =SUM(F70:BN70) -> 32 | BP70: =2166 -> 2166 | BQ70: 0.73 | BR70: =BP70*(1-BQ70) -> 584.82 | BS70: =BR70*BO70 -> 18714.24 | BT70: =BS70*0.8 -> 14971.392 | BV70: =BT70/$BT$81 -> 0.036531232 | BW70: 0.036231217 | BY70: =BZ70/CC70*100 -> 0.30991565 | BZ70: 50377.22 | CA70: =BY70*BO70 -> 9.9173009 | CB70: 11451245 | CC70: 16255139 | CD70: =CC70*CA70/100 -> 1612071 | CE70: =BT70/CD70*1000 -> 9.2870547 | CG70: MASSA FM | CH70: =BR70*0.8 -> 467.856 | CI70: =SUM(AK70:BG70) -> 12 | CJ70: =CH70*CI70 -> 5614.272 | CK70: =SUM(BH70:BN70) -> 20 | CL70: =CK70*CH70 -> 9357.12 | CM70: =(CJ70+CL70)=BT70 -> TRUE
C73: ANTENA 1 | D73: SEG À SEX 06H00-19H00 | E73: 30'' | BE73: 4 | BF73: 4 | BG73: 4 | BH73: 4 | BI73: 4 | BJ73: 4 | BK73: 4 | BL73: 4 | BO73: =SUM(F73:BN73) -> 32 | BP73: =6617 -> 6617 | BQ73: 0.75 | BR73: =BP73*(1-BQ73) -> 1654.25 | BS73: =BR73*BO73 -> 52936 | BT73: =BS73*0.8 -> 42348.8 | BV73: =BT73/$BT$81 -> 0.103334 | BW73: 0.099775299 | BY73: =BZ73/CC73*100 -> 0.72225344 | BZ73: 117403.3 | CA73: =BY73*BO73 -> 23.11211 | CB73: 11451245 | CC73: 16255139 | CD73: =CC73*CA73/100 -> 3756905.6 | CE73: =BT73/CD73*1000 -> 11.272256 | CG73: ANTENA 1 | CH73: =BR73*0.8 -> 1323.4 | CI73: =SUM(AK73:BG73) -> 12 | CJ73: =CH73*CI73 -> 15880.8 | CK73: =SUM(BH73:BN73) -> 20 | CL73: =CK73*CH73 -> 26468 | CM73: =(CJ73+CL73)=BT73 -> TRUE
C76: NOVABRASIL | D76: SEG À DOM 09H00-20H00 | E76: 30'' | BE76: 4 | BF76: 4 | BG76: 4 | BH76: 4 | BI76: 4 | BJ76: 4 | BK76: 4 | BL76: 4 | BO76: =SUM(F76:BN76) -> 32 | BP76: =5275.6 -> 5275.6 | BQ76: 0.8 | BR76: =BP76*(1-BQ76) -> 1055.12 | BS76: =BR76*BO76 -> 33763.84 | BT76: =BS76*0.8 -> 27011.072 | BV76: =BT76/$BT$81 -> 0.065908884 | BW76: 0.065906448 | BY76: =BZ76/CC76*100 -> 0.37035051 | BZ76: 60200.99 | CA76: =BY76*BO76 -> 11.851216 | CB76: 11451245 | CC76: 16255139 | CD76: =CC76*(CA76+CA78)/100 -> 1926431.7 | CE76: =BT76/CD76*1000 -> 14.021298 | CG76: NOVABRASIL | CH76: =BR76*0.8 -> 844.096 | CI76: =SUM(AK76:BG76) -> 12 | CJ76: =CH76*CI76 -> 10129.152 | CK76: =SUM(BH76:BN76) -> 20 | CL76: =CK76*CH76 -> 16881.92 | CM76: =(CJ76+CL76)=BT76 -> TRUE
C79: TRANSCONTINENTAL | D79: SEG À DOM 06H00-19H00 | E79: 30'' | BE79: 3 | BF79: 3 | BG79: 3 | BH79: 3 | BI79: 3 | BJ79: 3 | BK79: 3 | BL79: 3 | BO79: =SUM(F79:BN79) -> 24 | BP79: =3717 -> 3717 | BQ79: 0.5 | BR79: =BP79*(1-BQ79) -> 1858.5 | BS79: =BR79*BO79 -> 44604 | BT79: =BS79*0.8 -> 35683.2 | BV79: =BT79/$BT$81 -> 0.087069476 | BW79: 0.086909353 | BY79: =BZ79/CC79*100 -> 0.60577034 | BZ79: 98468.81 | CA79: =BY79*BO79 -> 14.538488 | CB79: 11451245 | CC79: 16255139 | CD79: =CC79*(CA79+CA81)/100 -> 2363251.4 | CE79: =BT79/CD79*1000 -> 15.099197 | CG79: TRANSCONTINENTAL | CH79: =BR79*0.8 -> 1486.8 | CI79: =SUM(AK79:BG79) -> 9 | CJ79: =CH79*CI79 -> 13381.2 | CK79: =SUM(BH79:BN79) -> 15 | CL79: =CK79*CH79 -> 22302 | CM79: =(CJ79+CL79)=BT79 -> TRUE
B81: TOTAL RADIO SP CAPITAL | F81: =SUM(F34:F80) -> 0 | G81: =SUM(G34:G80) -> 0 | H81: =SUM(H34:H80) -> 0 | I81: =SUM(I34:I80) -> 0 | J81: =SUM(J34:J80) -> 0 | K81: =SUM(K34:K80) -> 0 | L81: =SUM(L34:L80) -> 0 | M81: =SUM(M34:M80) -> 0 | ... BO81: =SUM(BO34:BO80) -> 429 | BS81: =SUM(BS34:BS80) -> 512280.56 | BT81: =SUM(BT34:BT80) -> 409824.45 | CB81: =CB79 -> 11451245 | CD81: =SUM(CD34:CD80) -> 33817472 | CE81: =BT81/CD81*1000 -> 12.118719 | CI81: =SUM(CI34:CI80) -> 165 | CJ81: =SUM(CJ34:CJ80) -> 159305.57 | CK81: =SUM(CK34:CK80) -> 8158 | CL81: =SUM(CL34:CL80) -> 250518.88 | CM81: =(CJ81+CL81)=BT81 -> TRUE
B83: CARAGUATATUBA | SÃO SABASTIÃO | UBATUBA - LITORAL NORTE | C83: CARAGUA FM | D83: 07h00 as 19h00 | E83: 30" | BO83: =SUM(F83:AI83) -> 0 | BP83: 165 | BQ83: 0.58 | BR83: =BP83*(1-BQ83) -> 69.3 | BS83: =BR83*BO83 -> 0 | BT83: =BR83*0.8 -> 55.44 | BV83: =BS83*0.8 -> 0 | BY83: =BZ83/CC83*100 -> 3.8168405 | BZ83: 2351 | CA83: =BY83*BO83 -> 0 | CB83: 125194 | CC83: 61595.448 | CD83: 188080 | CE83: =BV83/CD83*1000 -> 0 | CG83: CARAGUA FM | CI83: =SUM(#REF!) -> #REF! | CJ83: =#REF!*CI83 -> #REF! | CK83: =SUM(#REF!) -> #REF! | CL83: =#REF!*CK83 -> #REF!
C84: (via Caraguatatuba)
C86: BEIRA MAR FM | D86: 07h00 as 19h00 | E86: 30" | BO86: =SUM(F86:AI86) -> 0 | BP86: 310 | BQ86: 0.3 | BR86: =BP86*(1-BQ86) -> 217 | BS86: =BR86*BO86 -> 0 | BT86: =BR86*0.8 -> 173.6 | BV86: =BS86*0.8 -> 0 | BY86: =BZ86/CC86*100 -> 3.0700541 | BZ86: 1402 | CA86: =BY86*BO86 -> 0 | CB86: 92819 | CC86: 45666.948 | CD86: 112160 | CE86: =BV86/CD86*1000 -> 0 | CG86: =C86 -> BEIRA MAR FM | CI86: =SUM(#REF!) -> #REF! | CJ86: =#REF!*CI86 -> #REF! | CK86: =SUM(#REF!) -> #REF! | CL86: =#REF!*CK86 -> #REF!
C87: (via Ubatuba)
C89: MORADA FM | D89: 07h00 as 19h00 | E89: 30" | BO89: =SUM(F89:AI89) -> 0 | BP89: 800 | BQ89: 0.8 | BR89: =BP89*(1-BQ89) -> 160 | BS89: =BR89*BO89 -> 0 | BT89: =BR89*0.8 -> 128 | BV89: =BS89*0.8 -> 0 | BY89: =BZ89/CC89*100 -> #DIV/0! | CA89: =BY89*BO89 -> #DIV/0! | CE89: =BV89/CD89*1000 -> #DIV/0! | CG89: =C89 -> MORADA FM | CI89: =SUM(#REF!) -> #REF! | CJ89: =#REF!*CI89 -> #REF! | CK89: =SUM(#REF!) -> #REF! | CL89: =#REF!*CK89 -> #REF!
C90: (via São Sebastião)
C92: ANTENA 1 | D92: 07h00 as 19h00 | E92: 30" | BO92: =SUM(F92:AI92) -> 0 | BP92: 178 | BQ92: 0.78 | BR92: =BP92*(1-BQ92) -> 39.16 | BS92: =BR92*BO92 -> 0 | BT92: =BR92*0.8 -> 31.328 | BV92: =BS92*0.8 -> 0 | BY92: =BZ92/CC92*100 -> #DIV/0! | CA92: =BY92*BO92 -> #DIV/0! | CE92: =BV92/CD92*1000 -> #DIV/0! | CG92: =C92 -> ANTENA 1 | CI92: =SUM(#REF!) -> #REF! | CJ92: =#REF!*CI92 -> #REF! | CK92: =SUM(#REF!) -> #REF! | CL92: =#REF!*CK92 -> #REF!
C93: (via Ilha Bela - São Sebastião)
C95: RÁDIO PRAIA FM | D95: 07h00 as 19h00 | E95: 30" | BO95: =SUM(#REF!) -> #REF! | BQ95: 0.4 | BR95: =BP95*(1-BQ95) -> 0 | BS95: =BR95*BO95 -> #REF! | BT95: =BR95*0.8 -> 0 | BV95: =BS95*0.8 -> #REF! | CA95: =BY95*BO95 -> #REF! | CE95: =BV95/CD95*1000 -> #REF! | CG95: =C95 -> RÁDIO PRAIA FM | CI95: =SUM(#REF!) -> #REF! | CJ95: =#REF!*CI95 -> #REF! | CK95: =SUM(#REF!) -> #REF! | CL95: =#REF!*CK95 -> #REF!
C98: RÁDIO ANTENA 8 | D98: 07h00 as 19h00 | E98: 30" | BO98: =SUM(F98:AI98) -> 0 | BP98: 120 | BQ98: 0.3 | BR98: =BP98*(1-BQ98) -> 84 | BS98: =BR98*BO98 -> 0 | BT98: =BR98*0.8 -> 67.2 | BV98: =BS98*0.8 -> 0 | CA98: =BY98*BO98 -> 0 | CE98: =BV98/CD98*1000 -> #DIV/0! | CG98: =C98 -> RÁDIO ANTENA 8 | CI98: =SUM(#REF!) -> #REF! | CJ98: =#REF!*CI98 -> #REF! | CK98: =SUM(#REF!) -> #REF! | CL98: =#REF!*CK98 -> #REF!
C99: (via Caraguatatuba)
C101: ROCK NEWS LITORAL | D101: 07h00 as 19h00 | E101: 30" | BO101: =SUM(#REF!) -> #REF! | BQ101: 0.4 | BR101: =BP101*(1-BQ101) -> 0 | BS101: =BR101*BO101 -> #REF! | BT101: =BR101*0.8 -> 0 | BV101: =BS101*0.8 -> #REF! | CA101: =BY101*BO101 -> #REF! | CE101: =BV101/CD101*1000 -> #REF! | CG101: =C101 -> ROCK NEWS LITORAL | CI101: =SUM(#REF!) -> #REF! | CJ101: =#REF!*CI101 -> #REF! | CK101: =SUM(#REF!) -> #REF! | CL101: =#REF!*CK101 -> #REF!
C102: (via São Sebastião)
C104: ONDA 101.1 | D104: 07h00 as 19h00 | E104: 30" | BO104: =SUM(#REF!) -> #REF! | BQ104: 0.4 | BR104: =BP104*(1-BQ104) -> 0 | BS104: =BR104*BO104 -> #REF! | BT104: =BR104*0.8 -> 0 | BV104: =BS104*0.8 -> #REF! | CA104: =BY104*BO104 -> #REF! | CE104: =BV104/CD104*1000 -> #REF! | CG104: =C104 -> ONDA 101.1 | CI104: =SUM(#REF!) -> #REF! | CJ104: =#REF!*CI104 -> #REF! | CK104: =SUM(#REF!) -> #REF! | CL104: =#REF!*CK104 -> #REF!
C105: (via São Sebastião)
C107: COSTA AZUL | D107: 07h00 as 19h00 | E107: 30" | BO107: =SUM(#REF!) -> #REF! | BQ107: 0.4 | BR107: =BP107*(1-BQ107) -> 0 | BS107: =BR107*BO107 -> #REF! | BT107: =BR107*0.8 -> 0 | BV107: =BS107*0.8 -> #REF! | CA107: =BY107*BO107 -> #REF! | CE107: =BV107/CD107*1000 -> #REF! | CG107: =C107 -> COSTA AZUL | CI107: =SUM(#REF!) -> #REF! | CJ107: =#REF!*CI107 -> #REF! | CK107: =SUM(#REF!) -> #REF! | CL107: =#REF!*CK107 -> #REF!
B110: TOTAL RÁDIO LITORAL NORTE | F110: =SUM(F82:F109) -> 0 | G110: =SUM(G82:G109) -> 0 | H110: =SUM(H82:H109) -> 0 | I110: =SUM(I82:I109) -> 0 | J110: =SUM(J82:J109) -> 0 | K110: =SUM(K82:K109) -> 0 | L110: =SUM(L82:L109) -> 0 | M110: =SUM(M82:M109) -> 0 | N110: =SUM(N82:N84) -> 0 | O110: =SUM(O82:O84) -> 0 | P110: =SUM(P82:P84) -> 0 | Q110: =SUM(Q82:Q84) -> 0 | R110: =SUM(R82:R84) -> 0 | S110: =SUM(S82:S84) -> 0 | T110: =SUM(T82:T84) -> 0 | U110: =SUM(U82:U84) -> 0 | ... AJ110: =SUM(AJ82:AJ84) -> 0 | AK110: =SUM(AK82:AK109) -> 0 | AL110: =SUM(AL82:AL109) -> 0 | AM110: =SUM(AM82:AM109) -> 0 | AN110: =SUM(AN82:AN109) -> 0 | AO110: =SUM(AO82:AO109) -> 0 | AP110: =SUM(AP82:AP109) -> 0 | AQ110: =SUM(AQ82:AQ109) -> 0 | AR110: =SUM(AR82:AR109) -> 0 | AS110: =SUM(AS82:AS84) -> 0 | AT110: =SUM(AT82:AT84) -> 0 | AU110: =SUM(AU82:AU84) -> 0 | AV110: =SUM(AV82:AV84) -> 0 | AW110: =SUM(AW82:AW84) -> 0 | AX110: =SUM(AX82:AX84) -> 0 | AY110: =SUM(AY82:AY84) -> 0 | AZ110: =SUM(AZ82:AZ84) -> 0 | ... BN110: =SUM(BN82:BN84) -> 0 | BO110: =SUM(BO82:BO109) -> #REF! | BS110: =SUM(BS82:BS109) -> #REF! | BT110: =SUM(BT82:BT109) -> 455.568 | BV110: =SUM(BV82:BV109) -> #REF! | CD110: =SUM(CD82:CD109) -> 300240 | CE110: =BV110/CD110*1000 -> #REF!
B112: SANTOS - BAIXADA SANTISTA | C112: TRI FM | D112: 06h00 as 19h00 | E112: 30" | BO112: =SUM(F112:S112) -> 0 | BP112: 0 | BQ112: 0 | BR112: 0 | BS112: =BR112*BO112 -> 0 | BT112: =BR112*0.8 -> 0 | BV112: =BS112*0.8 -> 0 | BY112: =BZ112/CC112*100 -> 12.336811 | BZ112: 26342 | CA112: =BY112*BO112 -> 0 | CB112: 433991 | CC112: 213523.57 | CD112: =CC112*CA112% -> 0 | CE112: =BV112/CD112*1000 -> #DIV/0! | CG112: TRI FM | CI112: =SUM(#REF!) -> #REF! | CJ112: =#REF!*CI112 -> #REF! | CK112: =SUM(#REF!) -> #REF! | CL112: =#REF!*CK112 -> #REF!
C115: GUARUJA FM | D115: 07h00 as 19h00 | E115: 30" | BO115: =SUM(F115:S115) -> 0 | BP115: 500 | BQ115: 0.5 | BR115: =BP115*(1-BQ115) -> 250 | BS115: =BR115*BO115 -> 0 | BT115: =BR115*0.8 -> 200 | BV115: =BS115*0.8 -> 0 | BY115: =BZ115/CC115*100 -> 9.7492749 | BZ115: 20817 | CA115: =BY115*BO115 -> 0 | CB115: 433991 | CC115: 213523.57 | CD115: =CC115*CA115% -> 0 | CE115: =BV115/CD115*1000 -> #DIV/0! | CG115: GUARUJA FM | CI115: =SUM(#REF!) -> #REF! | CJ115: =#REF!*CI115 -> #REF! | CK115: =SUM(#REF!) -> #REF! | CL115: =#REF!*CK115 -> #REF!
C118: SAUDADE FM | D118: 07h00 as 19h00 | E118: 30" | BO118: =SUM(F118:S118) -> 0 | BP118: 580 | BQ118: 0.5 | BR118: =BP118*(1-BQ118) -> 290 | BS118: =BR118*BO118 -> 0 | BT118: =BR118*0.8 -> 232 | BV118: =BS118*0.8 -> 0 | BY118: =BZ118/CC118*100 -> 12.888507 | BZ118: 27520 | CA118: =BY118*BO118 -> 0 | CB118: 433991 | CC118: 213523.57 | CD118: =CC118*CA118% -> 0 | CE118: =BV118/CD118*1000 -> #DIV/0! | CG118: SAUDADE FM | CI118: =SUM(#REF!) -> #REF! | CJ118: =#REF!*CI118 -> #REF! | CK118: =SUM(#REF!) -> #REF! | CL118: =#REF!*CK118 -> #REF!
C121: SANTA CECILIA FM | D121: 07h00 as 19h00 | E121: 30" | BO121: =SUM(F121:S121) -> 0 | BP121: 568.83 | BQ121: 0.75 | BR121: =BP121*(1-BQ121) -> 142.2075 | BS121: =BR121*BO121 -> 0 | BT121: =BR121*0.8 -> 113.766 | BV121: =BS121*0.8 -> 0 | BY121: =BZ121/CC121*100 -> 4.86129 | BZ121: 10380 | CA121: =BY121*BO121 -> 0 | CB121: 433991 | CC121: 213523.57 | CD121: =CC121*CA121% -> 0 | CE121: =BV121/CD121*1000 -> #DIV/0! | CG121: =C121 -> SANTA CECILIA FM | CI121: =SUM(#REF!) -> #REF! | CJ121: =#REF!*CI121 -> #REF! | CK121: =SUM(#REF!) -> #REF! | CL121: =#REF!*CK121 -> #REF!
C124: JOVEM PAN FM | D124: 07h00 as 19h00 | E124: 30" | BO124: =SUM(F124:S124) -> 0 | BP124: 330 | BQ124: 0.5 | BR124: =BP124*(1-BQ124) -> 165 | BS124: =BR124*BO124 -> 0 | BT124: =BR124*0.8 -> 132 | BV124: =BS124*0.8 -> 0 | BY124: =BZ124/CC124*100 -> 3.4399012 | BZ124: 7345 | CA124: =BY124*BO124 -> 0 | CB124: 433991 | CC124: 213523.57 | CD124: =CC124*CA124% -> 0 | CE124: =BV124/CD124*1000 -> #DIV/0! | CG124: =C124 -> JOVEM PAN FM | CI124: =SUM(#REF!) -> #REF! | CJ124: =#REF!*CI124 -> #REF! | CK124: =SUM(#REF!) -> #REF! | CL124: =#REF!*CK124 -> #REF!
C127: MIX FM | D127: 07h00 as 19h00 | E127: 30" | BO127: =SUM(F127:S127) -> 0 | BP127: 505 | BQ127: 0.6 | BR127: =BP127*(1-BQ127) -> 202 | BS127: =BR127*BO127 -> 0 | BT127: =BR127*0.8 -> 161.6 | BV127: =BS127*0.8 -> 0 | BY127: =BZ127/CC127*100 -> 2.1426206 | BZ127: 4575 | CA127: =BY127*BO127 -> 0 | CB127: 433991 | CC127: 213523.57 | CD127: =CC127*CA127% -> 0 | CE127: =BV127/CD127*1000 -> #DIV/0! | CG127: =C127 -> MIX FM | CI127: =SUM(#REF!) -> #REF! | CJ127: =#REF!*CI127 -> #REF! | CK127: =SUM(#REF!) -> #REF! | CL127: =#REF!*CK127 -> #REF!
C130: BOA NOVA FM | D130: 07h00 as 19h00 | E130: 30" | BO130: =SUM(F130:S130) -> 0 | BP130: =87.5*1.3 -> 113.75 | BQ130: 0.5 | BR130: =BP130*(1-BQ130) -> 56.875 | BS130: =BR130*BO130 -> 0 | BT130: =BR130*0.8 -> 45.5 | BV130: =BS130*0.8 -> 0 | BY130: =BZ130/CC130*100 -> 0.1114631 | BZ130: 238 | CA130: =BY130*BO130 -> 0 | CB130: 433991 | CC130: 213523.57 | CD130: =CC130*CA130% -> 0 | CE130: =BV130/CD130*1000 -> #DIV/0! | CG130: =C130 -> BOA NOVA FM | CI130: =SUM(#REF!) -> #REF! | CJ130: =#REF!*CI130 -> #REF! | CK130: =SUM(#REF!) -> #REF! | CL130: =#REF!*CK130 -> #REF!
C133: KISS FM | D133: 07h00 as 19h00 | E133: 30" | BO133: =SUM(F133:S133) -> 0 | BP133: 1058 | BQ133: 0.7 | BR133: =BP133*(1-BQ133) -> 317.4 | BS133: =BR133*BO133 -> 0 | BT133: =BR133*0.8 -> 253.92 | BV133: =BS133*0.8 -> 0 | BY133: =BZ133/CC133*100 -> 0.58635212 | BZ133: 1252 | CA133: =BY133*BO133 -> 0 | CB133: 433991 | CC133: 213523.57 | CD133: =CC133*(CA133+CA134)% -> 0 | CE133: =BV133/CD133*1000 -> #DIV/0! | CG133: =C133 -> KISS FM | CI133: =SUM(#REF!) -> #REF! | CJ133: =#REF!*CI133 -> #REF! | CK133: =SUM(#REF!) -> #REF! | CL133: =#REF!*CK133 -> #REF!
BO134: =SUM(F134:S134) -> 0 | BP134: 847.8 | BQ134: 1 | BR134: =BP134*(1-BQ134) -> 0 | BS134: =BR134*BO134 -> 0 | BT134: =BR134*0.8 -> 0 | BV134: =BS134*0.8 -> 0 | CA134: =BY133*BO134 -> 0
B136: TOTAL RÁDIO SANTOS - BAIXADA SANTISTA | F136: =SUM(F111:F135) -> 0 | G136: =SUM(G111:G135) -> 0 | H136: =SUM(H111:H135) -> 0 | I136: =SUM(I111:I135) -> 0 | J136: =SUM(J111:J135) -> 0 | K136: =SUM(K111:K135) -> 0 | L136: =SUM(L111:L135) -> 0 | M136: =SUM(M111:M135) -> 0 | ... BO136: =SUM(BO111:BO135) -> 0 | BS136: =SUM(BS111:BS135) -> 0 | BT136: =SUM(BT111:BT135) -> 1138.786 | BV136: =SUM(BV111:BV135) -> 0 | CD136: =SUM(CD111:CD135) -> 0 | CE136: =BV136/CD136*1000 -> #DIV/0!
C138: METROPOLITANA FM | D138: 07h00 as 19h00 | E138: 30" | BO138: =SUM(#REF!) -> #REF! | BQ138: 0.4 | BR138: =BP138*(1-BQ138) -> 0 | BS138: =BR138*BO138 -> #REF! | BT138: =BR138*0.8 -> 0 | BV138: =BS138*0.8 -> #REF! | BY138: =BZ138/CC138*100 -> 2.4049146 | BZ138: 3796 | CA138: 192.39317 | CB138: 320820 | CC138: 157843.44 | CE138: =BV138/CD138*1000 -> #REF! | CG138: METROPOLITANA FM | CI138: =SUM(#REF!) -> #REF! | CJ138: =#REF!*CI138 -> #REF! | CK138: =SUM(#REF!) -> #REF! | CL138: =#REF!*CK138 -> #REF!
B140: TAUBATE E SÃO JOSE DOS CAMPOS | C140: BAND VALE | D140: 07h00 as 19h00 | E140: 30" | BO140: =SUM(F140:AI140) -> 0 | BP140: 197.36842 | BQ140: 0 | BR140: =BP140*(1-BQ140) -> 197.36842 | BS140: 15000 | BT140: =BR140*0.8 -> 157.89474 | BV140: =BS140*0.8 -> 12000 | BY140: =BZ140/CC140*100 -> 3.4401176 | BZ140: 5430 | CA140: =BY140*BO140 -> 0 | CB140: 320820 | CC140: 157843.44 | CD140: =CC140*CA140% -> 0 | CE140: =BV140/CD140*1000 -> #DIV/0! | CG140: BAND VALE | CI140: =SUM(#REF!) -> #REF! | CJ140: =BX140/2 -> 0 | CK140: =SUM(#REF!) -> #REF! | CL140: =BZ140/2 -> 2715
C141: (via S.J.Campos)
C143: STEREO VALE | D143: 07h00 as 19h00 | E143: 30" | BO143: =SUM(F143:AI143) -> 0 | BP143: 131.57895 | BQ143: 0 | BR143: =BP143*(1-BQ143) -> 131.57895 | BS143: 10000 | BT143: =BR143*0.8 -> 105.26316 | BV143: =BS143*0.8 -> 8000 | BY143: =BZ143/CC143*100 -> 2.5183182 | BZ143: 3975 | CA143: =BY143*BO143 -> 0 | CB143: 320820 | CC143: 157843.44 | CD143: =CC143*CA143% -> 0 | CE143: =BV143/CD143*1000 -> #DIV/0! | CG143: =C143 -> STEREO VALE | CI143: =SUM(#REF!) -> #REF! | CJ143: =BX143/2 -> 0 | CK143: =SUM(#REF!) -> #REF! | CL143: =BZ143/2 -> 1987.5
C144: (via S.J.Campos)
C146: NATIVA FM | D146: 07h00 as 19h00 | E146: 30" | BO146: =SUM(F146:AI146) -> 0 | BP146: 157.89474 | BQ146: 0 | BR146: =BP146*(1-BQ146) -> 157.89474 | BS146: 12000 | BT146: =BR146*0.8 -> 126.31579 | BV146: =BS146*0.8 -> 9600 | BY146: =BZ146/CC146*100 -> 5.2780147 | BZ146: 8331 | CA146: =BY146*BO146 -> 0 | CB146: 320820 | CC146: 157843.44 | CD146: =CC146*CA146% -> 0 | CE146: =BV146/CD146*1000 -> #DIV/0! | CG146: =C146 -> NATIVA FM | CI146: =SUM(#REF!) -> #REF! | CJ146: =BX146/2 -> 0 | CK146: =SUM(#REF!) -> #REF! | CL146: =BZ146/2 -> 4165.5
C147: (via S.J.Campos)
C149: ÓTIMA FM | D149: 07h00 as 19h00 | E149: 30" | BO149: =SUM(F149:AI149) -> 0 | BP149: 255 | BQ149: =(BP149-BR149)/BP149 -> 0.4 | BR149: 153 | BS149: =BR149*BO149 -> 0 | BT149: =BR149*0.8 -> 122.4 | BV149: =BS149*0.8 -> 0 | BY149: =BZ149/CC149*100 -> 7.6189419 | BZ149: 12026 | CA149: =BY149*BO149 -> 0 | CB149: 320820 | CC149: 157843.44 | CD149: =CC149*CA149% -> 0 | CE149: =BV149/CD149*1000 -> #DIV/0! | CG149: =C149 -> ÓTIMA FM | CI149: =SUM(#REF!) -> #REF! | CJ149: =#REF!*CI149 -> #REF! | CK149: =SUM(#REF!) -> #REF! | CL149: =#REF!*CK149 -> #REF!
C150: (via S.J.Campos)
C152: ANTENA 1 FM | D152: 07h00 as 19h00 | E152: 30" | BO152: =SUM(F152:AI152) -> 0 | BP152: 331 | BQ152: 0.78 | BR152: =BP152*(1-BQ152) -> 72.82 | BS152: =BR152*BO152 -> 0 | BT152: =BR152*0.8 -> 58.256 | BV152: =BS152*0.8 -> 0 | BY152: =BZ152/CC152*100 -> 3.5161423 | BZ152: 5550 | CA152: =BY152*BO152 -> 0 | CB152: 320820 | CC152: 157843.44 | CD152: =CC152*CA152% -> 0 | CE152: =BV152/CD152*1000 -> #DIV/0! | CG152: =C152 -> ANTENA 1 FM | CI152: =SUM(#REF!) -> #REF! | CJ152: =#REF!*CI152 -> #REF! | CK152: =SUM(#REF!) -> #REF! | CL152: =#REF!*CK152 -> #REF!
C153: (via S.J.Campos)
C155: JOVEM PAN FM | D155: 07h00 as 19h00 | E155: 30" | BO155: =SUM(F155:AI155) -> 0 | BP155: 325 | BQ155: 0.5 | BR155: =BP155*(1-BQ155) -> 162.5 | BS155: =BR155*BO155 -> 0 | BT155: =BR155*0.8 -> 130 | BV155: =BS155*0.8 -> 0 | BY155: =BZ155/CC155*100 -> 2.4087159 | BZ155: 3802 | CA155: =BY155*BO155 -> 0 | CB155: 320820 | CC155: 157843.44 | CD155: =CC155*CA155% -> 0 | CE155: =BV155/CD155*1000 -> #DIV/0! | CG155: =C155 -> JOVEM PAN FM | CI155: =SUM(#REF!) -> #REF! | CJ155: =#REF!*CI155 -> #REF! | CK155: =SUM(#REF!) -> #REF! | CL155: =#REF!*CK155 -> #REF!
C156: (via Taubaté)
C158: CANÇÃO NOVA FM | D158: 07h00 as 19h00 | E158: 30" | BO158: =SUM(F158:AI158) -> 0 | BP158: 184 | BQ158: 0.4 | BR158: =BP158*(1-BQ158) -> 110.4 | BS158: =BR158*BO158 -> 0 | BT158: =BR158*0.8 -> 88.32 | BV158: =BS158*0.8 -> 0 | BY158: =BZ158/CC158*100 -> 1.7206924 | BZ158: 2716 | CA158: =BY158*BO158 -> 0 | CB158: 320820 | CC158: 157843.44 | CD158: =CC158*CA158% -> 0 | CE158: =BV158/CD158*1000 -> #DIV/0! | CG158: =C158 -> CANÇÃO NOVA FM | CI158: =SUM(#REF!) -> #REF! | CJ158: =#REF!*CI158 -> #REF! | CK158: =SUM(#REF!) -> #REF! | CL158: =#REF!*CK158 -> #REF!
C159: (via S.J.Campos)
C161: MIX FM | D161: 07h00 as 19h00 | E161: 30" | BO161: =SUM(F161:AI161) -> 0 | BP161: 160 | BQ161: 0.4 | BR161: =BP161*(1-BQ161) -> 96 | BS161: =BR161*BO161 -> 0 | BT161: =BR161*0.8 -> 76.8 | BV161: =BS161*0.8 -> 0 | BY161: =BZ161/CC161*100 -> 1.6966179 | BZ161: 2678 | CA161: =BY161*BO161 -> 0 | CB161: 320820 | CC161: 157843.44 | CD161: 324862 | CE161: =BV161/CD161*1000 -> 0 | CG161: =C161 -> MIX FM | CI161: =SUM(#REF!) -> #REF! | CJ161: =#REF!*CI161 -> #REF! | CK161: =SUM(#REF!) -> #REF! | CL161: =#REF!*CK161 -> #REF!
C162: (via S.J.Campos)
B164: TOTAL RÁDIO TAUBATE E SÃO JOSÉ DOS CAMPOS | F164: =SUM(F137:F163) -> 0 | G164: =SUM(G137:G163) -> 0 | H164: =SUM(H137:H163) -> 0 | I164: =SUM(I137:I163) -> 0 | J164: =SUM(J137:J163) -> 0 | K164: =SUM(K137:K163) -> 0 | L164: =SUM(L137:L163) -> 0 | M164: =SUM(M137:M163) -> 0 | ... BO164: =SUM(BO137:BO163) -> #REF! | BS164: =SUM(BS137:BS163) -> #REF! | BT164: =SUM(BT137:BT163) -> 865.24968 | BV164: =SUM(BV137:BV163) -> #REF! | CD164: =SUM(CD137:CD163) -> 324862 | CE164: =BV164/CD164*1000 -> #REF!
B166: BOTUCATU | C166: CLUBE FM | D166: 06h00 as 19h00 | E166: 30" | BO166: =SUM(F166:AI166) -> 0 | BP166: 200 | BQ166: 0.6 | BR166: =BP166*(1-BQ166) -> 80 | BS166: =BR166*BO166 -> 0 | BT166: =BR166*0.8 -> 64 | BV166: =BS166*0.8 -> 0 | CB166: 145155 | CE166: =BV166/CD166*1000 -> #DIV/0! | CG166: =C166 -> CLUBE FM | CI166: =SUM(#REF!) -> #REF! | CJ166: =#REF!*CI166 -> #REF! | CK166: =SUM(#REF!) -> #REF! | CL166: =#REF!*CK166 -> #REF!
B168: TOTAL RÁDIO BOTUCATU | F168: =SUM(F165:F167) -> 0 | G168: =SUM(G165:G167) -> 0 | H168: =SUM(H165:H167) -> 0 | I168: =SUM(I165:I167) -> 0 | J168: =SUM(J165:J167) -> 0 | K168: =SUM(K165:K167) -> 0 | L168: =SUM(L165:L167) -> 0 | M168: =SUM(M165:M167) -> 0 | ... BO168: =SUM(BO165:BO167) -> 0 | BS168: =SUM(BS165:BS167) -> 0 | BT168: =SUM(BT165:BT167) -> 64 | BV168: =SUM(BV165:BV167) -> 0 | CD168: =SUM(CD165:CD167) -> 0 | CE168: =BV168/CD168*1000 -> #DIV/0!
B170: LINS | C170: CLUBE FM | D170: 06h00 as 19h00 | E170: 30" | BO170: =SUM(F170:AI170) -> 0 | BP170: =21*1.25 -> 26.25 | BQ170: 0.3 | BR170: =BP170*(1-BQ170) -> 18.375 | BS170: =BR170*BO170 -> 0 | BT170: =BR170*0.8 -> 14.7 | BV170: =BS170*0.8 -> 0 | CA170: =BY170*BO170 -> 0 | CB170: 74779 | CD170: =CC170*CA170% -> 0 | CE170: =BV170/CD170*1000 -> #DIV/0! | CG170: =C170 -> CLUBE FM | CI170: =SUM(#REF!) -> #REF! | CJ170: =#REF!*CI170 -> #REF! | CK170: =SUM(#REF!) -> #REF! | CL170: =#REF!*CK170 -> #REF!
CI171: =SUM(#REF!) -> #REF! | CK171: =SUM(#REF!) -> #REF!
C172: RÁDIO AMIGA FM | D172: 06h00 as 19h00 | E172: 30" | BO172: =SUM(F172:AI172) -> 0 | BP172: =BR172/0.64 -> 121.5625 | BQ172: 0.36 | BR172: 77.8 | BS172: =BR172*BO172 -> 0 | BT172: =BR172*0.8 -> 62.24 | BV172: =BS172*0.8 -> 0 | CA172: =BY172*BO172 -> 0 | CB172: 74779 | CD172: =CC172*CA172% -> 0 | CE172: =BV172/CD172*1000 -> #DIV/0! | CG172: =C172 -> RÁDIO AMIGA FM | CJ172: =#REF!*CI171 -> #REF! | CL172: =#REF!*CK171 -> #REF!
B174: TOTAL RÁDIO LINS | F174: =SUM(F169:F173) -> 0 | G174: =SUM(G169:G173) -> 0 | H174: =SUM(H169:H173) -> 0 | I174: =SUM(I169:I173) -> 0 | J174: =SUM(J169:J173) -> 0 | K174: =SUM(K169:K173) -> 0 | L174: =SUM(L169:L173) -> 0 | M174: =SUM(M169:M173) -> 0 | ... BO174: =SUM(BO169:BO173) -> 0 | BS174: =SUM(BS169:BS173) -> 0 | BT174: =SUM(BT169:BT173) -> 76.94 | BV174: =SUM(BV169:BV173) -> 0 | CD174: =SUM(CD169:CD173) -> 0 | CE174: =BV174/CD174*1000 -> #DIV/0!
B176: PRESIDENTE PRUDENTE | C176: FRONTEIRA FM | D176: 06h00 as 19h00 | E176: 30" | BO176: =SUM(F176:AI176) -> 0 | BP176: 121 | BQ176: 0.5 | BR176: =BP176*(1-BQ176) -> 60.5 | BS176: =BR176*BO176 -> 0 | BT176: =BR176*0.8 -> 48.4 | BV176: =BS176*0.8 -> 0 | CA176: =BY176*BO176 -> 0 | CB176: 225668 | CD176: =CC176*CA176% -> 0 | CE176: =BV176/CD176*1000 -> #DIV/0! | CG176: =C176 -> FRONTEIRA FM | CI176: =SUM(#REF!) -> #REF! | CJ176: =#REF!*CI176 -> #REF! | CK176: =SUM(#REF!) -> #REF! | CL176: =#REF!*CK176 -> #REF!
C178: RÁDIO 98,1 | D178: 06h00 as 19h00 | E178: 30" | BO178: =SUM(F178:AI178) -> 0 | BP178: 218.5 | BQ178: 0.5 | BR178: =BP178*(1-BQ178) -> 109.25 | BS178: =BR178*BO178 -> 0 | BT178: =BR178*0.8 -> 87.4 | BV178: =BS178*0.8 -> 0 | CA178: =BY178*BO178 -> 0 | CB178: 225668 | CD178: =CC178*CA178% -> 0 | CE178: =BV178/CD178*1000 -> #DIV/0! | CG178: =C178 -> RÁDIO 98,1 | CI178: =SUM(#REF!) -> #REF! | CJ178: =#REF!*CI178 -> #REF! | CK178: =SUM(#REF!) -> #REF! | CL178: =#REF!*CK178 -> #REF!
C180: 101 FM | D180: 06h00 as 19h00 | E180: 30" | BO180: =SUM(F180:AI180) -> 0 | BP180: 427 | BQ180: 0.45 | BR180: =BP180*(1-BQ180) -> 234.85 | BS180: =BR180*BO180 -> 0 | BT180: =BR180*0.8 -> 187.88 | BV180: =BS180*0.8 -> 0 | CA180: =BY180*BO180 -> 0 | CB180: 225668 | CD180: =CC180*CA180% -> 0 | CE180: =BV180/CD180*1000 -> #DIV/0! | CG180: =C180 -> 101 FM | CI180: =SUM(#REF!) -> #REF! | CJ180: =#REF!*CI180 -> #REF! | CK180: =SUM(#REF!) -> #REF! | CL180: =#REF!*CK180 -> #REF!
B182: TOTAL RÁDIO PRESIDENTE PRUDENTE | F182: =SUM(F175:F181) -> 0 | G182: =SUM(G175:G181) -> 0 | H182: =SUM(H175:H181) -> 0 | I182: =SUM(I175:I181) -> 0 | J182: =SUM(J175:J181) -> 0 | K182: =SUM(K175:K181) -> 0 | L182: =SUM(L175:L181) -> 0 | M182: =SUM(M175:M181) -> 0 | ... BO182: =SUM(BO175:BO181) -> 0 | BS182: =SUM(BS175:BS181) -> 0 | BT182: =SUM(BT175:BT181) -> 323.68 | BV182: =SUM(BV175:BV181) -> 0 | CD182: =SUM(CD175:CD181) -> 0 | CE182: =BV182/CD182*1000 -> #DIV/0!
B184: MARKET | C184: CHANNEL | D184: PROPERTY | E184: FORMAT: SPOT | F184: OUTUBRO | BD184: DEZEMBRO | BH184: JANEIRO | BO184: INS. | BP184: CUSTO TABELA UNITÁRIO (BRUTO) | BQ184: DESC. % | BR184: CUSTO NEGOCIADO UNITÁRIO (BRUTO) | BS184: CUSTO TOTAL NEGOCIADO (BRUTO) | BT184: CUSTO TOTAL DESEMBOLSO CLIENTE | BV184: SHARE DE INVESTIMENTO % | BW184: SHARE DE AUDIÊNCIA % | BY184: IA% | BZ184: IA# | CA184: TRP | CB184: POPULAÇÃO TT. | CC184: UNIV. RÁDIO AS ABCDE 18+ | CD184: IMPACTOS ESTIMADOS | CE184: CPM | CG184: RÁDIO | CH184: VALOR UNITÁRIO LIQUIDO | CI184: DEZEMBRO | CK184: JANEIRO
F185: W | G185: T | H185: F | I185: S | J185: S | K185: M | L185: T | M185: W | N185: T | O185: F | P185: S | Q185: S | R185: M | S185: T | T185: W | U185: T | V185: F | W185: S | X185: S | Y185: M | Z185: T | AA185: W | AB185: T | AC185: F | AD185: S | AE185: S | AF185: M | AG185: T | AH185: W | AI185: T | AJ185: F | AK185: S | AL185: S | AM185: M | AN185: T | AO185: W | AP185: T | AQ185: F | AR185: S | AS185: S | AT185: M | AU185: T | AV185: W | AW185: T | AX185: F | AY185: S | AZ185: S | BA185: M | BB185: T | BC185: W | BD185: S | BE185: M | BF185: T | BG185: W | BH185: T | BI185: F | BJ185: S | BK185: S | BL185: F | BM185: S | BN185: S
F186: 1 | G186: 2 | H186: 3 | I186: 4 | J186: 5 | K186: 6 | L186: 7 | M186: 8 | N186: 9 | O186: 10 | P186: 11 | Q186: 12 | R186: 13 | S186: 14 | T186: 15 | U186: 16 | V186: 17 | W186: 18 | X186: 19 | Y186: 20 | Z186: 21 | AA186: 22 | AB186: 23 | AC186: 24 | AD186: 25 | AE186: 26 | AF186: 27 | AG186: 28 | AH186: 29 | AI186: 30 | AJ186: 31 | AK186: 1 | AL186: 2 | AM186: 3 | AN186: 4 | AO186: 5 | AP186: 6 | AQ186: 7 | AR186: 8 | AS186: 9 | AT186: 10 | AU186: 11 | AV186: 12 | AW186: 13 | AX186: 14 | AY186: 15 | AZ186: 16 | BA186: 17 | BB186: 18 | BC186: 19 | BD186: 28 | BE186: =BD186+1 -> 29 | BF186: =BE186+1 -> 30 | BG186: =BF186+1 -> 31 | BH186: 1 | BI186: =BH186+1 -> 2 | BJ186: =BI186+1 -> 3 | BK186: =BJ186+1 -> 4 | BL186: =BK186+1 -> 5 | BM186: =BL186+1 -> 6 | BN186: =BM186+1 -> 7 | CI186: INS. | CJ186: INV. LIQUIDO | CK186: INS. | CL186: INV. LIQUIDO
B188: BOTUCATU | C188: CLUBE FM | D188: 06h00 as 19h00 | E188: 30" | BE188: 4 | BF188: 4 | BG188: 4 | BH188: 4 | BI188: 4 | BJ188: 4 | BK188: 4 | BL188: 4 | BO188: =SUM(AK188:BN188) -> 32 | BP188: 200 | BQ188: 0.6 | BR188: =BP188*(1-BQ188) -> 80 | BS188: =BR188*BO188 -> 2560 | BT188: =BS188*0.8 -> 2048 | BV188: =BT188/BT191 -> 1 | BW188: - | CB188: 145155 | CG188: =C188 -> CLUBE FM | CH188: =BR188*0.8 -> 64 | CI188: =SUM(AK188:BG188) -> 12 | CJ188: =CH188*CI188 -> 768 | CK188: =SUM(BH188:BN188) -> 20 | CL188: =CK188*CH188 -> 1280 | CM188: =(CJ188+CL188)=BT188 -> TRUE
B191: TOTAL BOTUCATU | F191: =SUM(F144:F190) -> 1 | G191: =SUM(G144:G190) -> 2 | H191: =SUM(H144:H190) -> 3 | I191: =SUM(I144:I190) -> 4 | J191: =SUM(J144:J190) -> 5 | K191: =SUM(K144:K190) -> 6 | L191: =SUM(L144:L190) -> 7 | M191: =SUM(M144:M190) -> 8 | ... BC191: =SUM(BC144:BC190) -> 19 | BD191: =SUM(BD187:BD190) -> 0 | BE191: =SUM(BE187:BE190) -> 4 | BF191: =SUM(BF187:BF190) -> 4 | BG191: =SUM(BG187:BG190) -> 4 | BH191: =SUM(BH187:BH190) -> 4 | BI191: =SUM(BI187:BI190) -> 4 | BJ191: =SUM(BJ187:BJ190) -> 4 | BK191: =SUM(BK187:BK190) -> 4 | ... BT191: =SUM(BT187:BT190) -> 2048 | CB191: =SUM(CB187:CB190) -> 145155 | CC191: =SUM(CC187:CC190) -> 0 | CD191: =SUM(CD187:CD190) -> 0 | CE191: =SUM(CE187:CE190) -> 0 | CG191: =SUM(CG187:CG190) -> 0 | CH191: =SUM(CH187:CH190) -> 64 | CI191: =SUM(CI187:CI190) -> 12 | CJ191: =SUM(CJ187:CJ190) -> 768 | CK191: =SUM(CK187:CK190) -> 20 | CL191: =SUM(CL187:CL190) -> 1280 | CM191: =(CJ191+CL191)=BT191 -> TRUE
B193: LINS | C193: CLUBE FM | D193: 06h00 as 19h00 | E193: 30" | BE193: 4 | BF193: 4 | BG193: 4 | BH193: 4 | BI193: 4 | BJ193: 4 | BK193: 4 | BL193: 4 | BO193: =SUM(AK193:BN193) -> 32 | BP193: =21*1.25 -> 26.25 | BQ193: 0.3 | BR193: =BP193*(1-BQ193) -> 18.375 | BS193: =BR193*BO193 -> 588 | BT193: =BS193*0.8 -> 470.4 | BV193: =BT193/BT198 -> 0.19105797 | BW193: - | CB193: 74779 | CG193: =C193 -> CLUBE FM | CH193: =BR193*0.8 -> 14.7 | CI193: =SUM(AK193:BG193) -> 12 | CJ193: =CH193*CI193 -> 176.4 | CK193: =SUM(BH193:BN193) -> 20 | CL193: =CK193*CH193 -> 294 | CM193: =(CJ193+CL193)=BT193 -> TRUE
C196: RÁDIO AMIGA FM | D196: 06h00 as 19h00 | E196: 30" | BE196: 4 | BF196: 4 | BG196: 4 | BH196: 4 | BI196: 4 | BJ196: 4 | BK196: 4 | BL196: 4 | BO196: =SUM(AK196:BN196) -> 32 | BP196: 121.5625 | BQ196: 0.36 | BR196: =BP196*(1-BQ196) -> 77.8 | BS196: =BR196*BO196 -> 2489.6 | BT196: =BS196*0.8 -> 1991.68 | BV196: =BT196/BT198 -> 0.80894203 | BW196: - | CB196: 74779 | CG196: =C196 -> RÁDIO AMIGA FM | CH196: =BR196*0.8 -> 62.24 | CI196: =SUM(AK196:BG196) -> 12 | CJ196: =CH196*CI196 -> 746.88 | CK196: =SUM(BH196:BN196) -> 20 | CL196: =CK196*CH196 -> 1244.8 | CM196: =(CJ196+CL196)=BT196 -> TRUE
B198: TOTAL LINS | F198: =SUM(F153:F197) -> 2 | G198: =SUM(G153:G197) -> 4 | H198: =SUM(H153:H197) -> 6 | I198: =SUM(I153:I197) -> 8 | J198: =SUM(J153:J197) -> 10 | K198: =SUM(K153:K197) -> 12 | L198: =SUM(L153:L197) -> 14 | M198: =SUM(M153:M197) -> 16 | ... BC198: =SUM(BC153:BC197) -> 38 | BD198: =SUM(BD192:BD197) -> 0 | BE198: =SUM(BE192:BE197) -> 8 | BF198: =SUM(BF192:BF197) -> 8 | BG198: =SUM(BG192:BG197) -> 8 | BH198: =SUM(BH192:BH197) -> 8 | BI198: =SUM(BI192:BI197) -> 8 | BJ198: =SUM(BJ192:BJ197) -> 8 | BK198: =SUM(BK192:BK197) -> 8 | ... BT198: =SUM(BT192:BT197) -> 2462.08 | BV198: =SUM(BV192:BV197) -> 1 | CB198: =CB193 -> 74779 | CC198: =SUM(CC192:CC197) -> 0 | CD198: =SUM(CD192:CD197) -> 0 | CE198: =SUM(CE192:CE197) -> 0 | CG198: =SUM(CG192:CG197) -> 0 | CH198: =SUM(CH192:CH197) -> 76.94 | CI198: =SUM(CI192:CI197) -> 24 | CJ198: =SUM(CJ192:CJ197) -> 923.28 | CK198: =SUM(CK192:CK197) -> 40 | CL198: =SUM(CL192:CL197) -> 1538.8 | CM198: =(CJ198+CL198)=BT198 -> TRUE
...

Sheet CUSTO GERAÇÃO SPE
B2: CLIENT: SABESP
B3: CAMPAING: ESCASSEZ HIDRICA - CRÍTICO
B5: VEICULO | C5: DESCRIÇÃO | D5: DESTINO | E5: UF | F5: MATERIAL | G5: CUSTO UNITÁRIO | H5: QTD FILMES | I5: CUSTO LIQUIDO
B6: GLOBO | C6: ENVIO DE MATERIAL | D6: BAU | E6: SP | F6: 30'' | G6: 415 | H6: 1 | I6: =G6*H6 -> 415
B7: GLOBO | C7: ENVIO DE MATERIAL | D7: CAM | E7: SP | F7: 30'' | G7: 415 | H7: 1 | I7: =G7*H7 -> 415
B8: GLOBO | C8: ENVIO DE MATERIAL | D8: ITP | E8: SP | F8: 30'' | G8: 415 | H8: 1 | I8: =G8*H8 -> 415
B9: GLOBO | C9: ENVIO DE MATERIAL | D9: MOC | E9: SP | F9: 30'' | G9: 415 | H9: 1 | I9: =G9*H9 -> 415
B10: GLOBO | C10: ENVIO DE MATERIAL | D10: RIB | E10: SP | F10: 30'' | G10: 415 | H10: 1 | I10: =G10*H10 -> 415
B11: GLOBO | C11: ENVIO DE MATERIAL | D11: SAN | E11: SP | F11: 30'' | G11: 415 | H11: 1 | I11: =G11*H11 -> 415
B12: GLOBO | C12: ENVIO DE MATERIAL | D12: SCA | E12: SP | F12: 30'' | G12: 415 | H12: 1 | I12: =G12*H12 -> 415
B13: GLOBO | C13: ENVIO DE MATERIAL | D13: SJC | E13: SP | F13: 30'' | G13: 415 | H13: 1 | I13: =G13*H13 -> 415
B14: GLOBO | C14: ENVIO DE MATERIAL | D14: SJRP | E14: SP | F14: 30'' | G14: 415 | H14: 1 | I14: =G14*H14 -> 415
B15: GLOBO | C15: ENVIO DE MATERIAL | D15: SOR | E15: SP | F15: 30'' | G15: 415 | H15: 1 | I15: =G15*H15 -> 415
B16: GLOBO | C16: ENVIO DE MATERIAL | D16: SP1 | E16: SP | F16: 30'' | G16: 255 | H16: 1 | I16: =G16*H16 -> 255
B17: GLOBO | C17: ENVIO DE MATERIAL | D17: TAU | E17: SP | F17: 30'' | G17: 415 | H17: 1 | I17: =G17*H17 -> 415
... B29: GLOBO | C29: ENVIO DE MATERIAL | D29: TAU | E29: SP | F29: 60" | G29: 415 | H29: 1 | I29: =G29*H29 -> 415
H30: 1 | I30: =SUM(I6:I29) -> 9640
B31: BANDEIRANTES | C31: ENVIO DE MATERIAL | D31: SAÕ PAULO CAPITAL | E31: SP | F31: 30'' | G31: 255 | H31: 1 | I31: =G31*H31 -> 255
B32: BANDEIRANTES | C32: ENVIO DE MATERIAL | D32: BAND CAMPINAS | E32: SP | F32: 30'' | G32: 415 | H32: 1 | I32: =G32*H32 -> 415
B33: BANDEIRANTES | C33: ENVIO DE MATERIAL | D33: BAND PAULISTA | E33: SP | F33: 30'' | G33: 415 | H33: 1 | I33: =G33*H33 -> 415
B34: BANDEIRANTES | C34: ENVIO DE MATERIAL | D34: BAND VALE TAUBATÉ | E34: SP | F34: 30'' | G34: 415 | H34: 1 | I34: =G34*H34 -> 415
B35: BANDEIRANTES | C35: ENVIO DE MATERIAL | D35: RIBEIRÃO PRETO | E35: SP | F35: 30'' | G35: 415 | H35: 1 | I35: =G35*H35 -> 415
B36: BANDEIRANTES | C36: ENVIO DE MATERIAL | D36: SANTOS | E36: SP | F36: 30'' | G36: 415 | H36: 1 | I36: =G36*H36 -> 415
B37: BANDEIRANTES | C37: ENVIO DE MATERIAL | D37: SAÕ PAULO CAPITAL | E37: SP | F37: 60" | G37: 255 | H37: 1 | I37: =G37*H37 -> 255
B38: BANDEIRANTES | C38: ENVIO DE MATERIAL | D38: BAND CAMPINAS | E38: SP | F38: 60" | G38: 415 | H38: 1 | I38: =G38*H38 -> 415
B39: BANDEIRANTES | C39: ENVIO DE MATERIAL | D39: BAND PAULISTA | E39: SP | F39: 60" | G39: 415 | H39: 1 | I39: =G39*H39 -> 415
B40: BANDEIRANTES | C40: ENVIO DE MATERIAL | D40: BAND VALE TAUBATÉ | E40: SP | F40: 60" | G40: 415 | H40: 1 | I40: =G40*H40 -> 415
B41: BANDEIRANTES | C41: ENVIO DE MATERIAL | D41: RIBEIRÃO PRETO | E41: SP | F41: 60" | G41: 415 | H41: 1 | I41: =G41*H41 -> 415
B42: BANDEIRANTES | C42: ENVIO DE MATERIAL | D42: SANTOS | E42: SP | F42: 60" | G42: 415 | H42: 1 | I42: =G42*H42 -> 415
H43: 1 | I43: =SUM(I31:I42) -> 4660
B44: SBT | C44: ENVIO DE MATERIAL | D44: SP1 - SBT SÃO PAULO | E44: SP | F44: 30'' | G44: 255 | H44: 1 | I44: =G44*H44 -> 255
B45: SBT | C45: ENVIO DE MATERIAL | D45: SP3 - SBT RIBEIRÃO PRETO | E45: SP | F45: 30'' | G45: 415 | H45: 1 | I45: =G45*H45 -> 415
B46: SBT | C46: ENVIO DE MATERIAL | D46: SP5 - TV SOROCABA - SBT SOROCABA | E46: SP | F46: 30'' | G46: 415 | H46: 1 | I46: =G46*H46 -> 415
B47: SBT | C47: ENVIO DE MATERIAL | D47: SP2 - SBT JAÚ | E47: SP | F47: 30'' | G47: 415 | H47: 1 | I47: =G47*H47 -> 415
B48: SBT | C48: ENVIO DE MATERIAL | D48: SP6 - TV I ARAÇATUBA - SBT ARAÇATUBA | E48: SP | F48: 30'' | G48: 415 | H48: 1 | I48: =G48*H48 -> 415
B49: SBT | C49: ENVIO DE MATERIAL | D49: SP7 - SBT SÃO JOSÉ DOS CAMPOS | E49: SP | F49: 30'' | G49: 415 | H49: 1 | I49: =G49*H49 -> 415
B50: SBT | C50: ENVIO DE MATERIAL | D50: SP9 - REDE VTV - SBT SANTOS/CAMPINAS | E50: SP | F50: 30'' | G50: 415 | H50: 1 | I50: =G50*H50 -> 415
B51: SBT | C51: ENVIO DE MATERIAL | D51: SP1 - SBT SÃO PAULO | E51: SP | F51: 60" | G51: 255 | H51: 1 | I51: =G51*H51 -> 255
B52: SBT | C52: ENVIO DE MATERIAL | D52: SP3 - SBT RIBEIRÃO PRETO | E52: SP | F52: 60" | G52: 415 | H52: 1 | I52: =G52*H52 -> 415
B53: SBT | C53: ENVIO DE MATERIAL | D53: SP5 - TV SOROCABA - SBT SOROCABA | E53: SP | F53: 60" | G53: 415 | H53: 1 | I53: =G53*H53 -> 415
B54: SBT | C54: ENVIO DE MATERIAL | D54: SP2 - SBT JAÚ | E54: SP | F54: 60" | G54: 415 | H54: 1 | I54: =G54*H54 -> 415
B55: SBT | C55: ENVIO DE MATERIAL | D55: SP6 - TV I ARAÇATUBA - SBT ARAÇATUBA | E55: SP | F55: 60" | G55: 415 | H55: 1 | I55: =G55*H55 -> 415
... B57: SBT | C57: ENVIO DE MATERIAL | D57: SP9 - REDE VTV - SBT SANTOS/CAMPINAS | E57: SP | F57: 60" | G57: 415 | H57: 1 | I57: =G57*H57 -> 415
H58: 1 | I58: =SUM(I44:I57) -> 5490
B59: RECORD | C59: ENVIO DE MATERIAL | D59: SÃO PAULO CAPITAL | E59: SP | F59: 30'' | G59: 255 | H59: 1 | I59: =G59*H59 -> 255
B60: RECORD | C60: ENVIO DE MATERIAL | D60: FRANCA | E60: SP | F60: 30'' | G60: 415 | H60: 1 | I60: =G60*H60 -> 415
B61: RECORD | C61: ENVIO DE MATERIAL | D61: SANTOS | E61: SP | F61: 30'' | G61: 415 | H61: 1 | I61: =G61*H61 -> 415
B62: RECORD | C62: ENVIO DE MATERIAL | D62: BAURU | E62: SP | F62: 30'' | G62: 415 | H62: 1 | I62: =G62*H62 -> 415
B63: RECORD | C63: ENVIO DE MATERIAL | D63: SÃO JOSÉ DO RIO PRETO | E63: SP | F63: 30'' | G63: 415 | H63: 1 | I63: =G63*H63 -> 415
B64: RECORD | C64: ENVIO DE MATERIAL | D64: CAMPINAS | E64: SP | F64: 30'' | G64: 415 | H64: 1 | I64: =G64*H64 -> 415
B65: RECORD | C65: ENVIO DE MATERIAL | D65: SÃO PAULO CAPITAL | E65: SP | F65: 60" | G65: 255 | H65: 1 | I65: =G65*H65 -> 255
B66: RECORD | C66: ENVIO DE MATERIAL | D66: FRANCA | E66: SP | F66: 60" | G66: 415 | H66: 1 | I66: =G66*H66 -> 415
B67: RECORD | C67: ENVIO DE MATERIAL | D67: SANTOS | E67: SP | F67: 60" | G67: 415 | H67: 1 | I67: =G67*H67 -> 415
B68: RECORD | C68: ENVIO DE MATERIAL | D68: BAURU | E68: SP | F68: 60" | G68: 415 | H68: 1 | I68: =G68*H68 -> 415
B69: RECORD | C69: ENVIO DE MATERIAL | D69: SÃO JOSÉ DO RIO PRETO | E69: SP | F69: 60" | G69: 415 | H69: 1 | I69: =G69*H69 -> 415
B70: RECORD | C70: ENVIO DE MATERIAL | D70: CAMPINAS | E70: SP | F70: 60" | G70: 415 | H70: 1 | I70: =G70*H70 -> 415
H71: 1 | I71: =SUM(I59:I70) -> 4660
B72: REDE TV | C72: ENVIO DE MATERIAL | D72: SÃO PAULO | E72: SP | F72: 30'' | G72: 255 | H72: 1 | I72: =G72*H72 -> 255
B73: REDE TV | C73: ENVIO DE MATERIAL | D73: SÃO PAULO | E73: SP | F73: 60" | G73: 255 | H73: 1 | I73: =G73*H73 -> 255
H74: 1 | I74: =SUM(I72:I73) -> 510
B75: ADSTREAM | C75: ENVIO DE MATERIAL | D75: TV CULTURA | E75: SP | F75: 30'' | G75: 240 | H75: 1 | I75: =G75*H75 -> 240
B76: ADSTREAM | C76: ENVIO DE MATERIAL | D76: TV CULTURA | E76: SP | F76: 60" | G76: 480 | H76: 1 | I76: =G76*H76 -> 480
B77: ADSTREAM | C77: ENVIO DE MATERIAL | D77: TV GAZETA | E77: SP | F77: 30'' | G77: 240 | H77: 1 | I77: =G77*H77 -> 240
B78: ADSTREAM | C78: ENVIO DE MATERIAL | D78: TV GAZETA | E78: SP | F78: 60" | G78: 480 | H78: 1 | I78: =G78*H78 -> 480
B79: ADSTREAM | C79: ENVIO DE MATERIAL | D79: RECORD NEWS | E79: SP | F79: 30'' | G79: 240 | H79: 1 | I79: =G79*H79 -> 240
B80: ADSTREAM | C80: ENVIO DE MATERIAL | D80: RECORD NEWS | E80: SP | F80: 60" | G80: 480 | H80: 1 | I80: =G80*H80 -> 480
B81: ADSTREAM | C81: ENVIO DE MATERIAL | D81: CNN BRASIL | E81: SP | F81: 30'' | G81: 240 | H81: 1 | I81: =G81*H81 -> 240
B82: ADSTREAM | C82: ENVIO DE MATERIAL | D82: CNN BRASIL | E82: SP | F82: 60" | G82: 480 | H82: 1 | I82: =G82*H82 -> 480
B83: ADSTREAM | C83: ENVIO DE MATERIAL | D83: JOVEM PAN | E83: SP | F83: 30'' | G83: 240 | H83: 1 | I83: =G83*H83 -> 240
B84: ADSTREAM | C84: ENVIO DE MATERIAL | D84: JOVEM PAN | E84: SP | F84: 60" | G84: 480 | H84: 1 | I84: =G84*H84 -> 480
H85: 1 | I85: =SUM(I75:I84) -> 3600
B86: GLOBONEWS | C86: ENVIO DE MATERIAL | D86: SÃO PAULO | E86: SP | F86: 30'' | G86: 255 | H86: 1 | I86: =G86*H86 -> 255
B87: GLOBONEWS | C87: ENVIO DE MATERIAL | D87: SÃO PAULO | E87: SP | F87: 60" | G87: 255 | H87: 1 | I87: =G87*H87 -> 255
H88: 1 | I88: =SUM(I86:I87) -> 510
B89: BANDNEWS | C89: ENVIO DE MATERIAL | D89: SÃO PAULO | E89: SP | F89: 30'' | G89: 255 | H89: 1 | I89: =G89*H89 -> 255
B90: BANDNEWS | C90: ENVIO DE MATERIAL | D90: SÃO PAULO | E90: SP | F90: 60" | G90: 255 | H90: 1 | I90: =G90*H90 -> 255
H91: 1 | I91: =SUM(I89:I90) -> 510
F93: TT GERAL | I93: =SUM(I85,I74,I71,I58,I43,I30,I91,I88) -> 29580

Sheet RÁDIO 
B5: CLIENT: SABESP
B6: CAMPAING: ESCASSESZ HIDRICA PCJ
B9: MARKET | C9: CHANNEL | D9: PROGRAM | E9: PROPERTY | F9: FORMAT: SPOT | G9: DEZEMBRO_2025 | Z9: FEVEREIRO | BB9: INS. | BC9: CUSTO TABELA UNITÁRIO (BRUTO) | BD9: DESC. % | BE9: CUSTO NEGOCIADO UNITÁRIO (BRUTO) | BF9: CUSTO TOTAL NEGOCIADO (BRUTO) | BG9: CUSTO TOTAL DESEMBOLSO CLIENTE | BI9: FEVEREIRO
G10: M | H10: T | I10: W | J10: T | K10: F | L10: S | M10: S | N10: M | O10: T | P10: W | Q10: T | R10: F | S10: S | T10: S | U10: M | V10: T | W10: W | X10: T | Y10: F | Z10: S | AA10: M | AB10: T | AC10: W | AD10: T | AE10: F | AF10: S | AG10: S | AH10: M | AI10: T | AJ10: W | AK10: T | AL10: F | AM10: S | AN10: S | AO10: M | AP10: T | AQ10: W | AR10: T | AS10: F | AT10: S | AU10: S | AV10: M | AW10: T | AX10: W | AY10: T | AZ10: F | BA10: S
G11: 1 | H11: 2 | I11: 3 | J11: 4 | K11: 5 | L11: 6 | M11: 7 | N11: 8 | O11: 9 | P11: 10 | Q11: 11 | R11: 12 | S11: 13 | T11: 14 | U11: 15 | V11: 16 | W11: 17 | X11: 18 | Y11: 19 | Z11: 1 | AA11: =Z11+1 -> 2 | AB11: =AA11+1 -> 3 | AC11: =AB11+1 -> 4 | AD11: =AC11+1 -> 5 | AE11: =AD11+1 -> 6 | AF11: =AE11+1 -> 7 | AG11: =AF11+1 -> 8 | AH11: =AG11+1 -> 9 | ... BA11: =AZ11+1 -> 28 | BI11: INS. | BJ11: INV LIQUIDO
B14: BAIXA MOGIANA | C14: BAND FM | D14: ROTATIVO | E14: 07h00 as 19h00 | F14: 30" | AO14: 4 | AP14: 4 | AQ14: 4 | AR14: 4 | AS14: 4 | AT14: 4 | AU14: 4 | AV14: 4 | AW14: 4 | AX14: 4 | BB14: =SUM(Z14:BA14) -> 40 | BC14: 188 | BD14: 0.45 | BE14: =BC14*(1-BD14) -> 103.4 | BF14: =BE14*BB14 -> 4136 | BG14: =BF14*0.8 -> 3308.8 | BI14: =BB14 -> 40 | BJ14: =BG14 -> 3308.8
F15: 60" | AK15: 3 | AL15: 3 | AM15: 2 | AN15: 2 | BB15: =SUM(Z15:BA15) -> 10 | BC15: =BC14*2 -> 376 | BD15: 0.45 | BE15: =BC15*(1-BD15) -> 206.8 | BF15: =BE15*BB15 -> 2068 | BG15: =BF15*0.8 -> 1654.4 | BI15: =BB15 -> 10 | BJ15: =BG15 -> 1654.4
BI16: =SUM(BI14:BI15) -> 50 | BJ16: =SUM(BJ14:BJ15) -> 4963.2
B18: CAMPINAS | C18: BAND FM | D18: ROTATIVO | E18: 07h00 as 19h00 | F18: 30" | AO18: 4 | AP18: 4 | AQ18: 4 | AR18: 4 | AS18: 4 | AT18: 4 | AU18: 4 | AV18: 4 | AW18: 4 | AX18: 4 | BB18: =SUM(Z18:BA18) -> 40 | BC18: 1863 | BD18: 0.55 | BE18: =BC18*(1-BD18) -> 838.35 | BF18: =BE18*BB18 -> 33534 | BG18: =BF18*0.8 -> 26827.2 | BI18: =BB18 -> 40 | BJ18: =BG18 -> 26827.2
F19: 60" | AK19: 3 | AL19: 3 | AM19: 2 | AN19: 2 | BB19: =SUM(Z19:BA19) -> 10 | BC19: =BC18*2 -> 3726 | BD19: 0.55 | BE19: =BC19*(1-BD19) -> 1676.7 | BF19: =BE19*BB19 -> 16767 | BG19: =BF19*0.8 -> 13413.6 | BI19: =BB19 -> 10 | BJ19: =BG19 -> 13413.6
BI20: =SUM(BI18:BI19) -> 50 | BJ20: =SUM(BJ18:BJ19) -> 40240.8
C22: NATIVA | D22: ROTATIVO | E22: 07h00 as 19h00 | F22: 30" | AO22: 4 | AP22: 4 | AQ22: 4 | AR22: 4 | AS22: 4 | AT22: 4 | AU22: 4 | AV22: 4 | AW22: 4 | AX22: 4 | BB22: =SUM(Z22:BA22) -> 40 | BC22: 1568 | BD22: 0.4 | BE22: =BC22*(1-BD22) -> 940.8 | BF22: =BE22*BB22 -> 37632 | BG22: =BF22*0.8 -> 30105.6 | BI22: =BB22 -> 40 | BJ22: =BG22 -> 30105.6
F23: 60" | AK23: 3 | AL23: 3 | AM23: 2 | AN23: 2 | BB23: =SUM(Z23:BA23) -> 10 | BC23: =BC22*2 -> 3136 | BD23: 0.4 | BE23: =BC23*(1-BD23) -> 1881.6 | BF23: =BE23*BB23 -> 18816 | BG23: =BF23*0.8 -> 15052.8 | BI23: =BB23 -> 10 | BJ23: =BG23 -> 15052.8
BI24: =SUM(BI22:BI23) -> 50 | BJ24: =SUM(BJ22:BJ23) -> 45158.4
C26: EDUCADORA | D26: ROTATIVO | E26: 07h00 as 19h00 | F26: 30" | AO26: 2 | AP26: 2 | AQ26: 2 | AR26: 2 | AS26: 2 | AT26: 2 | AU26: 2 | BB26: =SUM(Z26:BA26) -> 14 | BC26: 1676 | BD26: 0.5 | BE26: =BC26*(1-BD26) -> 838 | BF26: =BE26*BB26 -> 11732 | BG26: =BF26*0.8 -> 9385.6 | BI26: =BB26 -> 14 | BJ26: =BG26 -> 9385.6
F27: 60" | AL27: 1 | AM27: 1 | AN27: 1 | BB27: =SUM(Z27:BA27) -> 3 | BC27: =BC26*1.9 -> 3184.4 | BD27: 0.5 | BE27: =BC27*(1-BD27) -> 1592.2 | BF27: =BE27*BB27 -> 4776.6 | BG27: =BF27*0.8 -> 3821.28 | BI27: =BB27 -> 3 | BJ27: =BG27 -> 3821.28
BI28: =SUM(BI26:BI27) -> 17 | BJ28: =SUM(BJ26:BJ27) -> 13206.88
B30: MOCOCA | C30: BAND FM | D30: ROTATIVO | E30: 07h00 as 19h00 | F30: 30" | AO30: 4 | AP30: 4 | AQ30: 4 | AR30: 4 | AS30: 4 | AT30: 4 | AU30: 4 | AV30: 4 | AW30: 4 | AX30: 4 | BB30: =SUM(Z30:BA30) -> 40 | BC30: 73 | BD30: 0.45 | BE30: =BC30*(1-BD30) -> 40.15 | BF30: =BE30*BB30 -> 1606 | BG30: =BF30*0.8 -> 1284.8 | BI30: =BB30 -> 40 | BJ30: =BG30 -> 1284.8
F31: 60" | AK31: 3 | AL31: 3 | AM31: 2 | AN31: 2 | BB31: =SUM(Z31:BA31) -> 10 | BC31: =BC30*2 -> 146 | BD31: 0.45 | BE31: =BC31*(1-BD31) -> 80.3 | BF31: =BE31*BB31 -> 803 | BG31: =BF31*0.8 -> 642.4 | BI31: =BB31 -> 10 | BJ31: =BG31 -> 642.4
BI32: =SUM(BI30:BI31) -> 50 | BJ32: =SUM(BJ30:BJ31) -> 1927.2
B33: TOTAL RÁDIO ESCASSEZ HIDRICA PCJ | G33: =SUM(G13:G32) -> 0 | H33: =SUM(H13:H32) -> 0 | I33: =SUM(I13:I32) -> 0 | J33: =SUM(J13:J32) -> 0 | K33: =SUM(K13:K32) -> 0 | L33: =SUM(L13:L32) -> 0 | M33: =SUM(M13:M32) -> 0 | N33: =SUM(N13:N32) -> 0 | ... BB33: =SUM(BB13:BB32) -> 217 | BF33: =SUM(BF13:BF32) -> 131870.6 | BG33: =SUM(BG13:BG32) -> 105496.48 | BI33: =SUM(BI16,BI20,BI24,BI28,BI32) -> 217 | BJ33: =SUM(BJ16,BJ20,BJ24,BJ28,BJ32) -> 105496.48 | BL33: =BJ33=BG33 -> TRUE

Sheet CUSTO GERAÇÃO
B2: CLIENT: SABESP
B3: CAMPAING: ESCASSEZ HIDRICA PCJ
B5: VEICULO | C5: DESCRIÇÃO | D5: DESTINO | E5: UF | F5: MATERIAL | G5: CUSTO UNITÁRIO | H5: QTD FILMES | I5: CUSTO LIQUIDO
B6: GLOBO | C6: ENVIO DE MATERIAL | D6: CAM - CAMPINAS - EPTV CAMPINAS | E6: SP | F6: 60'' - SOLUCOES PCJ | G6: 415 | H6: 1 | I6: =G6*H6 -> 415
B7: GLOBO | C7: ENVIO DE MATERIAL | D7: SOROCABA | E7: SP | F7: 60'' - SOLUCOES PCJ | G7: 415 | H7: 1 | I7: =G7*H7 -> 415
B8: GLOBO | C8: ENVIO DE MATERIAL | D8: RIB - RIBEIRAO PRETO - EPTV RIBEIRÃO | E8: SP | F8: 60'' - SOLUCOES PCJ | G8: 415 | H8: 1 | I8: =G8*H8 -> 415
B9: GLOBO | C9: ENVIO DE MATERIAL | D9: SÃO JOSÉ DOS CAMPOS | E9: SP | F9: 60'' - SOLUCOES PCJ | G9: 415 | H9: 1 | I9: =G9*H9 -> 415
B10: GLOBO | C10: ENVIO DE MATERIAL | D10: SÃO CARLOS | E10: SP | F10: 60'' - SOLUCOES PCJ | G10: 415 | H10: 1 | I10: =G10*H10 -> 415
B11: GLOBO | C11: ENVIO DE MATERIAL | D11: CAM - CAMPINAS - EPTV CAMPINAS | E11: SP | F11: 30'' - SOLUCOES PCJ 01 DE 05 | G11: 415 | H11: 1 | I11: =G11*H11 -> 415
B12: GLOBO | C12: ENVIO DE MATERIAL | D12: SOROCABA | E12: SP | F12: 30'' - SOLUCOES PCJ 01 DE 05 | G12: 415 | H12: 1 | I12: =G12*H12 -> 415
B13: GLOBO | C13: ENVIO DE MATERIAL | D13: RIB - RIBEIRAO PRETO - EPTV RIBEIRÃO | E13: SP | F13: 30'' - SOLUCOES PCJ 01 DE 05 | G13: 415 | H13: 1 | I13: =G13*H13 -> 415
B14: GLOBO | C14: ENVIO DE MATERIAL | D14: SÃO JOSÉ DOS CAMPOS | E14: SP | F14: 30'' - SOLUCOES PCJ 01 DE 05 | G14: 415 | H14: 1 | I14: =G14*H14 -> 415
B15: GLOBO | C15: ENVIO DE MATERIAL | D15: SÃO CARLOS | E15: SP | F15: 30'' - SOLUCOES PCJ 01 DE 05 | G15: 415 | H15: 1 | I15: =G15*H15 -> 415
H16: =SUM(H6:H15) -> 10 | I16: =SUM(I6:I15) -> 4150
B17: BANDEIRANTES | C17: ENVIO DE MATERIAL | D17: CAMPINAS | E17: SP | F17: 60'' - SOLUCOES PCJ | G17: 415 | H17: 1 | I17: =G17*H17 -> 415
B18: BANDEIRANTES | C18: ENVIO DE MATERIAL | D18: RIBEIRÃO PRETO | E18: SP | F18: 60'' - SOLUCOES PCJ | G18: 415 | H18: 1 | I18: =G18*H18 -> 415
B19: BANDEIRANTES | C19: ENVIO DE MATERIAL | D19: CAMPINAS | E19: SP | F19: 30'' - SOLUCOES PCJ 01 DE 05 | G19: 415 | H19: 1 | I19: =G19*H19 -> 415
B20: BANDEIRANTES | C20: ENVIO DE MATERIAL | D20: RIBEIRÃO PRETO | E20: SP | F20: 30'' - SOLUCOES PCJ 01 DE 05 | G20: 415 | H20: 1 | I20: =G20*H20 -> 415
H21: =SUM(H17:H20) -> 4 | I21: =SUM(I17:I20) -> 1660
B22: SBT | C22: ENVIO DE MATERIAL | D22: CAMPINAS | E22: SP | F22: 60'' - SOLUCOES PCJ | G22: 415 | H22: 1 | I22: =G22*H22 -> 415
B23: SBT | C23: ENVIO DE MATERIAL | D23: SOROCABA | E23: SP | F23: 60'' - SOLUCOES PCJ | G23: 415 | H23: 1 | I23: =G23*H23 -> 415
B24: SBT | C24: ENVIO DE MATERIAL | D24: RIBEIRÃO PRETO | E24: SP | F24: 60'' - SOLUCOES PCJ | G24: 415 | H24: 1 | I24: =G24*H24 -> 415
B25: SBT | C25: ENVIO DE MATERIAL | D25: SÃO JOSÉ DOS CAMPOS | E25: SP | F25: 60'' - SOLUCOES PCJ | G25: 415 | H25: 1 | I25: =G25*H25 -> 415
B26: SBT | C26: ENVIO DE MATERIAL | D26: CAMPINAS | E26: SP | F26: 30'' - SOLUCOES PCJ 01 DE 05 | G26: 415 | H26: 1 | I26: =G26*H26 -> 415
B27: SBT | C27: ENVIO DE MATERIAL | D27: SOROCABA | E27: SP | F27: 30'' - SOLUCOES PCJ 01 DE 05 | G27: 415 | H27: 1 | I27: =G27*H27 -> 415
B28: SBT | C28: ENVIO DE MATERIAL | D28: RIBEIRÃO PRETO | E28: SP | F28: 30'' - SOLUCOES PCJ 01 DE 05 | G28: 415 | H28: 1 | I28: =G28*H28 -> 415
B29: SBT | C29: ENVIO DE MATERIAL | D29: SÃO JOSÉ DOS CAMPOS | E29: SP | F29: 30'' - SOLUCOES PCJ 01 DE 05 | G29: 415 | H29: 1 | I29: =G29*H29 -> 415
H30: =SUM(H22:H29) -> 8 | I30: =SUM(I22:I29) -> 3320
B31: RECORD | C31: ENVIO DE MATERIAL | D31: CAMPINAS | E31: SP | F31: 60'' - SOLUCOES PCJ | G31: 415 | H31: 1 | I31: =G31*H31 -> 415
B32: RECORD | C32: ENVIO DE MATERIAL | D32: FRANCA | E32: SP | F32: 60'' - SOLUCOES PCJ | G32: 415 | H32: 1 | I32: =G32*H32 -> 415
B33: RECORD | C33: ENVIO DE MATERIAL | D33: CAMPINAS | E33: SP | F33: 30'' - SOLUCOES PCJ 01 DE 05 | G33: 415 | H33: 1 | I33: =G33*H33 -> 415
B34: RECORD | C34: ENVIO DE MATERIAL | D34: FRANCA | E34: SP | F34: 30'' - SOLUCOES PCJ 01 DE 05 | G34: 415 | H34: 1 | I34: =G34*H34 -> 415
H35: =SUM(H31:H34) -> 4 | I35: =SUM(I31:I34) -> 1660
B36: GLOBONEWS | C36: ENVIO DE MATERIAL | D36: SÃO PAULO | E36: SP | F36: 30'' | G36: 255 | H36: 0 | I36: =G36*H36 -> 0
B37: GLOBONEWS | C37: ENVIO DE MATERIAL | D37: SÃO PAULO | E37: SP | F37: 60" | G37: 255 | H37: 0 | I37: =G37*H37 -> 0
H38: =SUM(H36:H37) -> 0 | I38: =SUM(I36:I37) -> 0
B39: BANDNEWS | C39: ENVIO DE MATERIAL | D39: SÃO PAULO | E39: SP | F39: 30'' | G39: 255 | H39: 0 | I39: =G39*H39 -> 0
B40: BANDNEWS | C40: ENVIO DE MATERIAL | D40: SÃO PAULO | E40: SP | F40: 60" | G40: 255 | H40: 0 | I40: =G40*H40 -> 0
H41: =SUM(H39:H40) -> 0 | I41: =SUM(I39:I40) -> 0
H43: TT GERAL | I43: =SUM(I35,I30,I21,I16,I41,I38) -> 10790

Sheet COBERTURA
B2: MUNICIPIOS | C2: COBERTURA DAS EMISSORAS
C3: GLOBO | D3: RECORD | E3: SBT | F3: BANDEIRANTES | G3: RÁDIO
B4: Aguaí | C4: São Carlos | D4: Franca | E4: Ribeirão Preto | F4: Campinas | G4: BAND / NATIVA
B5: Águas de São Pedro | C5: Campinas | D5: Campinas | E5: Campinas/Santos | F5: Campinas | G5: BAND / NATIVA / EDUCADORA
B6: Campo Limpo Paulista | C6: Sorocaba | D6: Campinas | E6: Sorocaba | F6: Campinas | G6: BAND / NATIVA / EDUCADORA
B7: Charqueada | C7: Campinas | D7: Campinas | E7: Sorocaba | F7: Campinas | G7: BAND / NATIVA / EDUCADORA
B8: Divinolândia | C8: São Carlos | D8: Franca | E8: Ribeirão Preto | F8: Campinas | G8: BAND (MOCOCA)
B9: Elias Fausto | C9: Campinas | D9: Campinas | E9: Campinas/Santos | F9: Campinas | G9: BAND / NATIVA / EDUCADORA
B10: Franca | C10: Ribeirão Preto | D10: Franca | E10: Ribeirão Preto | F10: Ribeirão Preto | G10: -
B11: Hortolândia | C11: Campinas | D11: Campinas | E11: Campinas/Santos | F11: Campinas | G11: BAND / NATIVA / EDUCADORA
B12: Itatiba | C12: Sorocaba | D12: Campinas | E12: Campinas/Santos | F12: Campinas | G12: BAND / NATIVA / EDUCADORA
B13: Itupeva | C13: Sorocaba | D13: Campinas | E13: Sorocaba | F13: Campinas | G13: BAND / NATIVA / EDUCADORA
B14: Joanópolis | C14: São Jose Campos | D14: Campinas | E14: São Jose dos Campos | F14: - | G14: NATIVA
B15: Miguelópolis | C15: Ribeirão Preto | D15: Franca | E15: Ribeirão Preto | F15: - | G15: -
... B26: Tapiratiba | C26: São Carlos | D26: Franca | E26: - | F26: Campinas | G26: BAND (MOCOCA)
